Workbook

Sheet 1. DB_Experiment_VER1
C1: SABIC | D1: KRICT (5.8%) | E1: KRICT (10%) | F1: KRICT (20%) | G1: KRICT (30%) | H1: KRICT (업데이트 실험결과)
A2: Reference | C2: PCT/US2018/012064
C3: US 7,919,431 B2
A4: Preheating | J4: lb | K4: g
A5: Temp (oC) | C5: 500 | D5: - | J5: 1 | K5: 453.592
A7: CH4 pyrolysis | J7: 43.5
A8: Temp (oC) | C8: 2500 | D8: 1114 | E8: 1114 | F8: 1114 | G8: 1114 | H8: 1230
A9: CH4 feed (lb/h) | C9: 43.5
A10: CH4 feed (g/h) | C10: =C9*K5 -> 19731.252
A11: CH4 feed (ml/min) | D11: 20 | E11: 20 | F11: 20 | G11: 20 | H11: 14.4
A12: CH4 feed (mol/h) | C12: =C10/16 -> 1233.2033 | D12: =D11*60/22400 -> 0.053571429 | E12: =E11*60/22400 -> 0.053571429 | F12: =F11*60/22400 -> 0.053571429 | G12: =G11*60/22400 -> 0.053571429 | H12: =H11*60/22400 -> 0.038571429
A13: H2 feed (ml/min) | D13: 60 | E13: 60 | F13: 60 | G13: 60 | H13: 64
A14: H2 feed (mol/h) | D14: =D13*60/22400 -> 0.16071429 | E14: =E13*60/22400 -> 0.16071429 | F14: =F13*60/22400 -> 0.16071429 | G14: =G13*60/22400 -> 0.16071429 | H14: =H13*60/22400 -> 0.17142857 | I14: H2/CH4 | J14: =H14/H12 -> 4.4444444
A15: CH4 fuel (lb/h) | C15: 55.6
A16: CH4 fuel (g/h) | C16: =C15*K5 -> 25219.715
A17: CH4 fuel (mol/h) | C17: =C16/16 -> 1576.2322
A18: Pure O2 (lb/h) | C18: 182.8
A19: O2 fuel (g/h) | C19: =C18*K5 -> 82916.618
A20: O2 fuel (mol/h) | C20: =C19/32 -> 2591.1443
A21: Duty (Mbtu/h) | C21: 1114
A22: O2 stoichometry (%) | C22: 88.4
A27: Methane conversion (%) | C27: 51.3 | D27: 5.8 | E27: 10 | F27: 20 | G27: 30 | H27: 30.353963
A29: Product composition (C%)
A30: C2H6 | D30: 5.5 | E30: 5.5 | F30: 5.5 | G30: 5.5 | H30: 1.9832376
A31: C2H4 | D31: 60.3 | E31: 60.3 | F31: 60.3 | G31: 60.3 | H31: 35.180966
A32: C2H2 | D32: 2.9 | E32: 2.9 | F32: 2.9 | G32: 2.9 | H32: 41.411786
A33: C3-C5 | D33: 1.3 | E33: 1.3 | F33: 1.3 | G33: 1.3 | H33: 0
A34: Benzene | D34: 4.3 | E34: 4.3 | F34: 4.3 | G34: 4.3 | H34: 7.4789878
A35: Naphthalene | D35: 25.6 | E35: 25.6 | F35: 25.6 | G35: 25.6 | H35: 2.6768978
A36: Coke | H36: 11.268125
A37: Total | D37: =SUM(D30:D35) -> 99.9 | E37: =SUM(E30:E35) -> 99.9 | F37: =SUM(F30:F35) -> 99.9 | G37: =SUM(G30:G35) -> 99.9 | H37: =SUM(H30:H36) -> 100
L38: -253 | M38: Hydrogen in hydrocarbon | N38: 1 CASE | O38: 2 CASE | P38: 3 CASE | Q38: 4 CASE | R38: KRICT (업데이트 실험결과)
A39: Product composition (mol/h) (1) | L39: -164 | M39: CH4 | N39: =D12*D27/100*2 -> 0.0062142857 | O39: =E12*E27/100*2 -> 0.010714286 | P39: =F12*F27/100*2 -> 0.021428571 | Q39: =G12*G27/100*2 -> 0.032142857 | R39: =H12*H27/100*2 -> 0.023415914 | S39: =Q39/$Q$48*100 -> 48.056122
A40: H2 | C40: =$C$42*C54/$C$56 -> 1544.3952 | D40: =D14+N47 -> 0.1643282 | E40: =E14+O47 -> 0.1688282 | F40: =F14+P47 -> 0.17954249 | G40: =G14+Q47 -> 0.19025678 | H40: =H14+R47 -> 0.1873898 | I40: =H40*10000 -> 1873.898 | L40: -89 | M40: C2H6 | N40: =D43*3 -> 0.00025633929 | O40: =E43*3 -> 0.00025633929 | P40: =F43*3 -> 0.00025633929 | Q40: =G43*3 -> 0.00025633929 | R40: =H43*3 -> 0.0003482949 | S40: =Q40/$Q$48*100 -> 0.38324757
A41: CO2 | C41: =$C$42*C55/$C$56 -> 859.26123 | I41: =H41*10000 -> 0 | L41: -104 | M41: C2H4 | N41: =D44*2 -> 0.0018736071 | O41: =E44*2 -> 0.0018736071 | P41: =F44*2 -> 0.0018736071 | Q41: =G44*2 -> 0.0018736071 | R41: =H44*2 -> 0.0041189724 | S41: =Q41/$Q$48*100 -> 2.8011913
A42: CH4 | C42: =C12*C27/100 -> 632.63327 | D42: =D12*(100-D27)/100 -> 0.050464286 | E42: =E12*(100-E27)/100 -> 0.048214286 | F42: =F12*(100-F27)/100 -> 0.042857143 | G42: =G12*(100-G27)/100 -> 0.0375 | H42: =H12*(100-H27)/100 -> 0.026863472 | I42: =H42*10000 -> 268.63472 | L42: -84 | M42: C2H2 | N42: =D45*1 -> 4.5053571e-05 | O42: =E45*1 -> 4.5053571e-05 | P42: =F45*1 -> 4.5053571e-05 | Q42: =G45*1 -> 4.5053571e-05 | R42: =H45*1 -> 0.002424237 | S42: =Q42/$Q$48*100 -> 0.067358664
A43: C2H6 | D43: =($D$12-$D$42)*D30/100/2 -> 8.5446429e-05 | E43: =($D$12-$D$42)*E30/100/2 -> 8.5446429e-05 | F43: =($D$12-$D$42)*F30/100/2 -> 8.5446429e-05 | G43: =($D$12-$D$42)*G30/100/2 -> 8.5446429e-05 | H43: =($H$12-$H$42)*H30/100/2 -> 0.0001160983 | I43: =H43*10000 -> 1.160983 | L43: -84 | M43: C3-C5 | N43: =D46*3 -> 4.0392857e-05 | O43: =E46*3 -> 4.0392857e-05 | P43: =F46*3 -> 4.0392857e-05 | Q43: =G46*3 -> 4.0392857e-05 | R43: =H46*3 -> 0 | S43: =Q43/$Q$48*100 -> 0.060390526
A44: C2H4 | C44: =$C$42*C58/$C$56 -> 21.000274 | D44: =($D$12-$D$42)*D31/100/2 -> 0.00093680357 | E44: =($D$12-$D$42)*E31/100/2 -> 0.00093680357 | F44: =($D$12-$D$42)*F31/100/2 -> 0.00093680357 | G44: =($D$12-$D$42)*G31/100/2 -> 0.00093680357 | H44: =($H$12-$H$42)*H31/100/2 -> 0.0020594862 | I44: =H44*10000 -> 20.594862 | L44: -47 -> 36 | M44: Benzene | N44: =D47*3 -> 6.6803571e-05 | O44: =E47*3 -> 6.6803571e-05 | P44: =F47*3 -> 6.6803571e-05 | Q44: =G47*3 -> 6.6803571e-05 | R44: =H47*3 -> 0.00043781834 | S44: =Q44/$Q$48*100 -> 0.09987664
A45: C2H2 | C45: =$C$42*C59/$C$56 -> 200.37762 | D45: =($D$12-$D$42)*D32/100/2 -> 4.5053571e-05 | E45: =($D$12-$D$42)*E32/100/2 -> 4.5053571e-05 | F45: =($D$12-$D$42)*F32/100/2 -> 4.5053571e-05 | G45: =($D$12-$D$42)*G32/100/2 -> 4.5053571e-05 | H45: =($H$12-$H$42)*H32/100/2 -> 0.002424237 | I45: =H45*10000 -> 24.24237 | L45: 80 | M45: Naphthalene | N45: =D48*4 -> 0.00031817143 | O45: =E48*4 -> 0.00031817143 | P45: =F48*4 -> 0.00031817143 | Q45: =G48*4 -> 0.00031817143 | R45: =H48*4 -> 0.00012536402 | S45: =Q45/$Q$48*100 -> 0.47569153
A46: C3-C5 | D46: =($D$12-$D$42)*D33/100/3 -> 1.3464286e-05 | E46: =($D$12-$D$42)*E33/100/3 -> 1.3464286e-05 | F46: =($D$12-$D$42)*F33/100/3 -> 1.3464286e-05 | G46: =($D$12-$D$42)*G33/100/3 -> 1.3464286e-05 | H46: =($H$12-$H$42)*H33/100/3 -> 0 | I46: =H46*10000 -> 0 | L46: 218 | M46: H2 | N46: =SUM(N40:N45) -> 0.0026003679 | O46: =SUM(O40:O45) -> 0.0026003679 | P46: =SUM(P40:P45) -> 0.0026003679 | Q46: =SUM(Q40:Q45) -> 0.0026003679 | R46: =SUM(R40:R45) -> 0.0074546866 | S46: =(Q46+Q47)/Q48*100 -> 48.056122
A47: Benzene | D47: =($D$12-$D$42)*D34/100/6 -> 2.2267857e-05 | E47: =($D$12-$D$42)*E34/100/6 -> 2.2267857e-05 | F47: =($D$12-$D$42)*F34/100/6 -> 2.2267857e-05 | G47: =($D$12-$D$42)*G34/100/6 -> 2.2267857e-05 | H47: =($H$12-$H$42)*H34/100/6 -> 0.00014593945 | I47: =H47*10000 -> 1.4593945 | M47: Produced hydrogen | N47: =N39-N46 -> 0.0036139179 | O47: =O39-O46 -> 0.0081139179 | P47: =P39-P46 -> 0.018828204 | Q47: =Q39-Q46 -> 0.029542489 | R47: =R39-R46 -> 0.015961227 | S47: =SUM(S39:S46) -> 100
A48: Naphthalene | D48: =($D$12-$D$42)*D35/100/10 -> 7.9542857e-05 | E48: =($D$12-$D$42)*E35/100/10 -> 7.9542857e-05 | F48: =($D$12-$D$42)*F35/100/10 -> 7.9542857e-05 | G48: =($D$12-$D$42)*G35/100/10 -> 7.9542857e-05 | H48: =($H$12-$H$42)*H35/100/10 -> 3.1341004e-05 | I48: =H48*10000 -> 0.31341004 | Q48: =SUM(Q39:Q47) -> 0.066886082
A49: CO | C49: =$C$42*C63/$C$56 -> 1053.9513 | I49: =H49*10000 -> 0
A50: C | H50: =($H$12-$H$42)*H36/100/2 -> 0.00065963364 | I50: =H50*10000 -> 6.5963364
A51: Total | C51: =SUM(C40:C49) -> 4311.6188 | D51: =SUM(D42:D49) -> 0.051646864 | E51: =SUM(E42:E49) -> 0.049396864 | F51: =SUM(F42:F49) -> 0.044039721 | G51: =SUM(G42:G49) -> 0.038682579 | H51: =SUM(H42:H50) -> 0.032300207
A53: Effluent composition (vol%) (1)
A54: H2 | C54: 35.3 | D54: =D40/D51*100 -> 318.17654 | E54: =E40/E51*100 -> 341.77919 | F54: =F40/F51*100 -> 407.68307 | G54: =G40/G51*100 -> 491.84098 | H54: =H40/H51*100 -> 580.15046
A55: CO2 | C55: 19.64
A56: CH4 | C56: 14.46 | D56: =D42/D51*100 -> 97.710261 | E56: =E42/E51*100 -> 97.605964 | F56: =F42/F51*100 -> 97.314746 | G56: =G42/G51*100 -> 96.942865 | H56: =H42/H51*100 -> 83.168109
A57: C2H6 | D57: =D43/D51*100 -> 0.16544359 | E57: =E43/E51*100 -> 0.17297946 | F57: =F43/F51*100 -> 0.19402127 | G57: =G43/G51*100 -> 0.22089124 | H57: =H43/H51*100 -> 0.35943516
A58: C2H4 | C58: 0.48 | D58: =D44/D51*100 -> 1.8138634 | E58: =E44/E51*100 -> 1.8964839 | F58: =F44/F51*100 -> 2.1271787 | G58: =G44/G51*100 -> 2.4217713 | H58: =H44/H51*100 -> 6.3760773
A59: C2H2 | C59: 4.58 | D59: =D45/D51*100 -> 0.087233895 | E59: =E45/E51*100 -> 0.091207351 | F59: =F45/F51*100 -> 0.10230213 | G59: =G45/G51*100 -> 0.11646993 | H59: =H45/H51*100 -> 7.5053297
A60: C3-C5 | D60: =D46/D51*100 -> 0.0260699 | E60: =E46/E51*100 -> 0.027257369 | F60: =F46/F51*100 -> 0.030573049 | G60: =G46/G51*100 -> 0.034807105 | H60: =H46/H51*100 -> 0
A61: Benzene | D61: =D47/D51*100 -> 0.043115603 | E61: =E47/E51*100 -> 0.045079495 | F61: =F47/F51*100 -> 0.05056312 | G61: =G47/G51*100 -> 0.057565597 | H61: =H47/H51*100 -> 0.45182202
A62: Naphthalene | D62: =D48/D51*100 -> 0.15401295 | E62: =E48/E51*100 -> 0.16102815 | F62: =F48/F51*100 -> 0.18061617 | G62: =G48/G51*100 -> 0.20562967 | H62: =H48/H51*100 -> 0.097030351
A63: CO | C63: 24.09
A64: C | H64: =H50/H51*100 -> 2.0421963
A65: Total | C65: =SUM(C54:C63) -> 98.55 | D65: =SUM(D54:D63) -> 418.17654 | E65: =SUM(E54:E63) -> 441.77919 | F65: =SUM(F54:F63) -> 507.68307 | G65: =SUM(G54:G63) -> 591.84098 | H65: =SUM(H54:H64) -> 680.15046
A67: Coolant quenching
A68: Temp (oC) | C68: 300
A69: Water
A71: Quenched product composition (mol/h) (2)
A72: H2 | C72: =C40 -> 1544.3952
A73: CO2 | C73: =C41 -> 859.26123
A74: CH4 | C74: =C42 -> 632.63327
A75: C2H6
A76: C2H4 | C76: =C44 -> 21.000274
A77: C2H2
A78: C3-C5
A79: Benzene
A80: Naphthalene
A81: CO | C81: =C49 -> 1053.9513
A82: Total | C82: =SUM(C72:C81) -> 4111.2412
A84: Liquid phase hydrogenation | C84: n-methyl-2-pyrrolidone (NMP)
A85: Temp (oC) | C85: 111
A86: Press (psig) | C86: 150
A87: 1.5 wt% acetylene in Liquid NMP flow rate (ml/min) | C87: 18
A88: (1) gaseous flow rate (ml/min) | C88: 30
A90: Quenched product composition (mol/h) (3)
A91: H2 | C91: =$C$51*C104/$C$114 -> 1544.4526
A92: CO2 | C92: =$C$51*C105/$C$114 -> 859.29318
A93: CH4 | C93: =$C$51*C106/$C$114 -> 632.65679
A94: C2H6 | C94: =$C$51*C107/$C$114 -> 4.0477784
A95: C2H4 | C95: =$C$51*C108/$C$114 -> 216.3765
A96: C2H2 | C96: =$C$51*C109/$C$114 -> 0.80154027
A97: C3-C5
A98: Benzene
A99: Naphthalene
A100: CO | C100: =$C$51*C113/$C$114 -> 1053.9905
A101: Total | C101: =SUM(C91:C100) -> 4311.6188
A103: Effluent composition (vol%) (3)
A104: H2 | C104: 35.3
A105: CO2 | C105: 19.64
A106: CH4 | C106: 14.46
A107: C2H6 | C107: =C59*2.02/100 -> 0.092516
A108: C2H4 | C108: =C58+C59*97.5/100 -> 4.9455
A109: C2H2 | C109: =C59*0.4/100 -> 0.01832
A110: C3-C5
A111: Benzene
A112: Naphthalene
...

Sheet 1. DB_Experiment_VER2
C1: KRICT (previous data) | D1: KRICT (current data)
A2: Reference
A4: Preheating | J4: lb | K4: g
A5: Temp (oC) | J5: 1 | K5: 453.592
A7: CH4 pyrolysis | C7: O | D7: O | E7: O | F7: O | G7: O | J7: 43.5
A8: Temp (oC) | C8: 1230 | D8: 1230 | E8: 1230 | F8: 1230 | G8: 1230 | H8: 1150
A9: CH4 feed (lb/h)
A10: CH4 feed (g/h)
A11: CH4 feed (ml/min) | C11: 14.4 | D11: 14.4 | E11: 22.5 | F11: 45 | G11: 162
A12: CH4 feed (mol/h) | C12: =C11*60/22400 -> 0.038571429 | D12: =D11*60/22400 -> 0.038571429 | E12: =E11*60/22400 -> 0.060267857 | F12: =F11*60/22400 -> 0.12053571 | G12: =G11*60/22400 -> 0.43392857
A13: H2 feed (ml/min) | C13: 64 | D13: 65.6 | E13: 77.5 | F13: 105 | G13: 198
A14: H2 feed (mol/h) | C14: =C13*60/22400 -> 0.17142857 | D14: =D13*60/22400 -> 0.17571429 | E14: =E13*60/22400 -> 0.20758929 | F14: =F13*60/22400 -> 0.28125 | G14: =G13*60/22400 -> 0.53035714 | I14: H2/CH4 | J14: =C14/C12 -> 4.4444444 | K14: =D14/D12 -> 4.5555556 | L14: =E14/E12 -> 3.4444444 | M14: =F14/F12 -> 2.3333333 | N14: =G14/G12 -> 1.2222222 | O14: 2.5
A15: CH4 fuel (lb/h) | J15: =J14*3663 -> 16280 | K15: =K14*3663 -> 16687
A16: CH4 fuel (g/h)
A17: CH4 fuel (mol/h) | I17: [Carbon]
A18: Pure O2 (lb/h) | I18: CH4 | J18: =C45 -> 0.026863472 | K18: =D45 -> 0.027989396 | L18: =E45 -> 0.041616556 | M18: =F45 -> 0.082340326 | N18: =G45 -> 0.31211678
A19: O2 fuel (g/h) | I19: C2H6 | J19: =C46*2 -> 0.0002321966 | K19: =D46*2 -> 0.00063791607 | L19: =E46*2 -> 0.00081582931 | M19: =F46*2 -> 0.0013307041 | N19: =G46*2 -> 0.0036049504
A20: O2 fuel (mol/h) | I20: C2H4 | J20: =C47*2 -> 0.0041189724 | K20: =D47*2 -> 0.0084717494 | L20: =E47*2 -> 0.013754806 | M20: =F47*2 -> 0.026454735 | N20: =G47*2 -> 0.076315145
A21: Duty (Mbtu/h) | I21: C2H2 | J21: =C48*2 -> 0.0048484741 | K21: =D48*2 -> 0 | L21: =E48*2 -> 0 | M21: =F48*2 -> 0 | N21: =G48*2 -> 0.00034907813
A22: O2 stoichometry (%) | I22: C3-C5 | J22: =C49*3 -> 0 | K22: =D49*3 -> 0.00011935238 | L22: =E49*3 -> 0.0002325979 | M22: =F49*3 -> 0.00063994831 | N22: =G49*3 -> 0.0029762308
I23: Benzene | J23: =C50*6 -> 0.00087563668 | K23: =D50*6 -> 0.00087970214 | L23: =E50*6 -> 0.0020476513 | M23: =F50*6 -> 0.005455672 | N23: =G50*6 -> 0.02146341
A24: Low temp hydrogenation (temperature control by thermal gradient of CH4 pyrolysis zone in a single tube reactor) | C24: X | D24: O | E24: O | F24: O | G24: O | H24: O | I24: Toluene | J24: =C51*7 -> 0 | K24: =D51*7 -> 1.1922658e-05 | L24: =E51*7 -> 3.2852261e-05 | M24: =F51*7 -> 0.00011618638 | N24: =G51*7 -> 0.00083245596
A25: Temp (oC) | D25: 200 | E25: 200 | F25: 200 | G25: 200 | H25: 200 | I25: Naphthalene | J25: =C52*10 -> 0.00031341004 | K25: =D52*10 -> 0.00010564422 | L25: =E52*10 -> 0.00030244964 | M25: =F52*10 -> 0.00096099069 | N25: =G52*10 -> 0.0043561429
A26: Catalyst (Pd content on wall coated (umol) | D26: 1.532 | E26: 1.532 | F26: 1.532 | G26: 1.532 | H26: 1.532 | I26: C | J26: =C53 -> 0.00065963364 | K26: =D53 -> 0.00031596139 | L26: =E53 -> 0.0013875819 | M26: =F53 -> 0.0030238356 | N26: =G53 -> 0.010922306
I27: Total CH4 reacted | J27: =SUM(J19:J26) -> 0.011048323 | K27: =SUM(K19:K26) -> 0.010542248 | L27: =SUM(L19:L26) -> 0.018573768 | M27: =SUM(M19:M26) -> 0.037982072 | N27: =SUM(N19:N26) -> 0.12081972
J29: Previous (2019) | K29: Current data (2021)
A30: Methane conversion (%) | C30: 30.353963 | D30: 27.434899 | E30: 30.947344 | F30: 31.688026 | G30: 28.071854 | H30: 20 | I30: Selectivity(Carbon%) | J30: 4.4444444 | K30: 4.5555556 | L30: 3.4444444 | M30: 2.3333333 | N30: 1.2222222
I31: C2H6 | J31: =J19/J$27 -> 0.021016456 | K31: =K19/K$27 -> 0.06051044 | L31: =L19/L$27 -> 0.043923737 | M31: =M19/M$27 -> 0.035035058 | N31: =N19/N$27 -> 0.029837434 | P31: Ethylene yield
A32: Product composition (C%) | I32: C2H4 | J32: =J20/J$27 -> 0.37281425 | K32: =K20/K$27 -> 0.80359988 | L32: =L20/L$27 -> 0.7405501 | M32: =M20/M$27 -> 0.69650584 | N32: =N20/N$27 -> 0.63164478 | P32: =D30*K32 -> 22.046681 | Q32: =E30*L32 -> 22.918059 | R32: =F30*M32 -> 22.070895 | S32: =G30*N32 -> 17.73144
A33: C2H6 | C33: 1.9832376 | D33: 6.0282945 | E33: 4.3741148 | F33: 3.4839392 | G33: 2.9594428 | H33: 3.4839392 | I33: C2H2 | J33: =J21/J$27 -> 0.43884252 | K33: =K21/K$27 -> 0 | L33: =L21/L$27 -> 0 | M33: =M21/M$27 -> 0 | N33: =N21/N$27 -> 0.002889248
A34: C2H4 | C34: 35.180966 | D34: 80.057867 | E34: 73.747167 | F34: 69.261595 | G34: 62.650045 | H34: 69.261595 | I34: C3-C5 | J34: =J22/J$27 -> 0 | K34: =K22/K$27 -> 0.01132134 | L34: =L22/L$27 -> 0.012522924 | M34: =M22/M$27 -> 0.016848694 | N34: =N22/N$27 -> 0.024633651
A35: C2H2 | C35: 41.411786 | D35: 0 | E35: 0 | F35: 0 | G35: 0.28657169 | H35: 0 | I35: Benzene | J35: =J23/J$27 -> 0.079255164 | K35: =K23/K$27 -> 0.083445402 | L35: =L23/L$27 -> 0.11024426 | M35: =M23/M$27 -> 0.14363808 | N35: =N23/N$27 -> 0.17764824
A36: C3-C5 | C36: 0 | D36: 1.5038369 | E36: 1.6627823 | F36: 2.2339462 | G36: 3.2577369 | H36: 2.2339462 | I36: Toluene | J36: =J24/J$27 -> 0 | K36: =K24/K$27 -> 0.0011309408 | L36: =L24/L$27 -> 0.0017687451 | M36: =M24/M$27 -> 0.0030589796 | N36: =N24/N$27 -> 0.006890067
A37: Benzene | C37: 7.4789878 | D37: 8.3131681 | E37: 10.978598 | F37: 14.283588 | G37: 17.620141 | H37: 14.283588 | I37: Naphthalene | J37: =J25/J$27 -> 0.028367204 | K37: =K25/K$27 -> 0.010021033 | L37: =L25/L$27 -> 0.016283698 | M37: =M25/M$27 -> 0.025301166 | N37: =N25/N$27 -> 0.0360549
A38: Toluene | D38: 0.11266889 | E38: 0.17613925 | F38: 0.30418956 | G38: 0.68339519 | H38: 0.30418956 | I38: C | J38: =J26/J$27 -> 0.059704411 | K38: =K26/K$27 -> 0.029970969 | L38: =L26/L$27 -> 0.074706536 | M38: =M26/M$27 -> 0.079612183 | N38: =N26/N$27 -> 0.090401681
A39: Naphthalene | C39: 2.6768978 | D39: 0.9983358 | E39: 1.6216007 | F39: 2.5159862 | G39: 3.5761256 | H39: 2.5159862 | I39: Conversion | J39: =C30/100 -> 0.30353963 | K39: =D30/100 -> 0.27434899 | L39: =E30/100 -> 0.30947344 | M39: =F30/100 -> 0.31688026 | N39: =G30/100 -> 0.28071854
A40: Coke | C40: 11.268125 | D40: 2.985829 | E40: 7.4395984 | F40: 7.9167559 | G40: 8.9665419 | H40: 7.9167559
A41: Total | C41: =SUM(C33:C40) -> 100 | D41: =SUM(D33:D40) -> 100 | E41: =SUM(E33:E40) -> 100 | F41: =SUM(F33:F40) -> 100 | G41: =SUM(G33:G40) -> 100 | H41: =SUM(H33:H40) -> 100
M42: Hydrogen in hydrocarbon | N42: KRICT (previous data) | O42: KRICT (current data)
A43: Product composition (mol/h) (1) | M43: CH4 | N43: =C12*C30/100*2 -> 0.023415914 | O43: =D12*D30/100*2 -> 0.021164065 | P43: =E12*E30/100*2 -> 0.037302602 | Q43: =F12*F30/100*2 -> 0.076390776 | R43: =G12*G30/100*2 -> 0.24362359
A44: H2 | C44: =C14+N52 -> 0.1873898 | D44: =D14+O52 -> 0.18680167 | E44: =E14+P52 -> 0.22843963 | F44: =F14+Q52 -> 0.3251581 | G44: =G14+R52 -> 0.67516547 | H44: =H14+S52 -> 0.52387777 | M44: C2H6 | N44: =C46*3 -> 0.0003482949 | O44: =D46*3 -> 0.00095687411 | P44: =E46*3 -> 0.001223744 | Q44: =F46*3 -> 0.0019960561 | R44: =G46*3 -> 0.0054074256
A45: CH4 | C45: =C12*(100-C30)/100 -> 0.026863472 | D45: =D12*(100-D30)/100 -> 0.027989396 | E45: =E12*(100-E30)/100 -> 0.041616556 | F45: =F12*(100-F30)/100 -> 0.082340326 | G45: =G12*(100-G30)/100 -> 0.31211678 | M45: C2H4 | N45: =C47*2 -> 0.0041189724 | O45: =D47*2 -> 0.0084717494 | P45: =E47*2 -> 0.013754806 | Q45: =F47*2 -> 0.026454735 | R45: =G47*2 -> 0.076315145
A46: C2H6 | C46: =($C$12-$C$45)*C33/100/2 -> 0.0001160983 | D46: =(D12-D45)*D33/100/2 -> 0.00031895804 | E46: =(E12-E45)*E33/100/2 -> 0.00040791465 | F46: =(F12-F45)*F33/100/2 -> 0.00066535204 | G46: =(G12-G45)*G33/100/2 -> 0.0018024752 | M46: C2H2 | N46: =C48*1 -> 0.002424237 | O46: =D48*1 -> 0 | P46: =E48*1 -> 0 | Q46: =F48*1 -> 0 | R46: =G48*1 -> 0.00017453906
A47: C2H4 | C47: =($C$12-$C$45)*C34/100/2 -> 0.0020594862 | D47: =(D12-D45)*D34/100/2 -> 0.0042358747 | E47: =(E12-E45)*E34/100/2 -> 0.0068774031 | F47: =(F12-F45)*F34/100/2 -> 0.013227367 | G47: =(G12-G45)*G34/100/2 -> 0.038157573 | M47: C3-C5 | N47: =C49*4 -> 0 | O47: =D49*4 -> 0.0001591365 | P47: =E49*4 -> 0.00031013053 | Q47: =F49*4 -> 0.00085326441 | R47: =G49*4 -> 0.0039683078
A48: C2H2 | C48: =($C$12-$C$45)*C35/100/2 -> 0.002424237 | D48: =(D12-D45)*D35/100/2 -> 0 | E48: =(E12-E45)*E35/100/2 -> 0 | F48: =(F12-F45)*F35/100/2 -> 0 | G48: =(G12-G45)*G35/100/2 -> 0.00017453906 | M48: Benzene | N48: =C50*3 -> 0.00043781834 | O48: =D50*3 -> 0.00043985107 | P48: =E50*3 -> 0.0010238256 | Q48: =F50*3 -> 0.002727836 | R48: =G50*3 -> 0.010731705
A49: C3-C5 | C49: =($C$12-$C$45)*C36/100/3 -> 0 | D49: =(D12-D45)*D36/100/4 -> 3.9784126e-05 | E49: =(E12-E45)*E36/100/4 -> 7.7532632e-05 | F49: =(F12-F45)*F36/100/4 -> 0.0002133161 | G49: =(G12-G45)*G36/100/4 -> 0.00099207694 | M49: Toluene | N49: =C51*4 -> 0 | O49: =D51*4 -> 6.8129476e-06 | P49: =E51*4 -> 1.8772721e-05 | Q49: =F51*4 -> 6.6392218e-05 | R49: =G51*4 -> 0.00047568912
A50: Benzene | C50: =($C$12-$C$45)*C37/100/6 -> 0.00014593945 | D50: =(D12-D45)*D37/100/6 -> 0.00014661702 | E50: =(E12-E45)*E37/100/6 -> 0.00034127521 | F50: =(F12-F45)*F37/100/6 -> 0.00090927867 | G50: =(G12-G45)*G37/100/6 -> 0.003577235 | M50: Naphthalene | N50: =C52*4 -> 0.00012536402 | O50: =D52*4 -> 4.2257687e-05 | P50: =E52*4 -> 0.00012097985 | Q50: =F52*4 -> 0.00038439628 | R50: =G52*4 -> 0.0017424572
A51: Toluene | D51: =(D12-D45)*D38/100/7 -> 1.7032369e-06 | E51: =(E12-E45)*E38/100/7 -> 4.6931802e-06 | F51: =(F12-F45)*F38/100/7 -> 1.6598055e-05 | G51: =(G12-G45)*G38/100/7 -> 0.00011892228 | M51: H2 | N51: =SUM(N44:N50) -> 0.0074546866 | O51: =SUM(O44:O50) -> 0.010076682 | P51: =SUM(P44:P50) -> 0.016452259 | Q51: =SUM(Q44:Q50) -> 0.03248268 | R51: =SUM(R44:R50) -> 0.098815269
A52: Naphthalene | C52: =($C$12-$C$45)*C39/100/10 -> 3.1341004e-05 | D52: =(D12-D45)*D39/100/10 -> 1.0564422e-05 | E52: =(E12-E45)*E39/100/10 -> 3.0244964e-05 | F52: =(F12-F45)*F39/100/10 -> 9.6099069e-05 | G52: =(G12-G45)*G39/100/10 -> 0.00043561429 | M52: Produced hydrogen | N52: =N43-N51 -> 0.015961227 | O52: =O43-O51 -> 0.011087383 | P52: =P43-P51 -> 0.020850343 | Q52: =Q43-Q51 -> 0.043908096 | R52: =R43-R51 -> 0.14480832 | S52: =O52/O43 -> 0.52387777 | T52: =P52/P43 -> 0.55895144 | U52: =Q52/Q43 -> 0.5747827 | V52: =R52/R43 -> 0.59439368
A53: C | C53: =($C$12-$C$45)*C40/100/2 -> 0.00065963364 | D53: =(D12-D45)*D40/100 -> 0.00031596139 | E53: =(E12-E45)*E40/100 -> 0.0013875819 | F53: =(F12-F45)*F40/100 -> 0.0030238356 | G53: =(G12-G45)*G40/100 -> 0.010922306
A54: Total | C54: =SUM(C44:C53) -> 0.21969001 | D54: =SUM(D44:D53) -> 0.21986053 | E54: =SUM(E44:E53) -> 0.27918283 | F54: =SUM(F44:F53) -> 0.42565027 | G54: =SUM(G44:G53) -> 1.043463 | K54: Case 1 | L54: Case 2 | M54: Case 3 | N54: Case 4
J55: Temperature (oC) | K55: 1230 | L55: 1230 | M55: 1230 | N55: 1230
A56: Effluent composition (vol%) (1) | J56: H2/CH4 ratio | K56: 4.5555556 | L56: 3.4444444 | M56: 2.3333333 | N56: 1.2222222
A57: H2 | C57: =C44/C54*100 -> 85.297371 | D57: =D44/D54*100 -> 84.963713 | E57: =E44/E54*100 -> 81.824383 | F57: =F44/F54*100 -> 76.390906 | G57: =G44/G54*100 -> 64.704305 | J57: Selectivity(Carbon%)
A58: CO2 | J58: C2H6 | K58: 0.06051044 | L58: 0.043923737 | M58: 0.035035058 | N58: 0.029837434 | P58: 0.027989396 | Q58: 0.041616556 | R58: 0.082340326 | S58: 0.31211678
A59: CH4 | C59: =C45/C54*100 -> 12.227899 | D59: =D45/D54*100 -> 12.730524 | E59: =E45/E54*100 -> 14.90656 | F59: =F45/F54*100 -> 19.344596 | G59: =G45/G54*100 -> 29.911629 | J59: C2H4 | K59: 0.80359988 | L59: 0.7405501 | M59: 0.69650584 | N59: 0.63164478 | P59: 0.00031895804 | Q59: 0.00040791465 | R59: 0.00066535204 | S59: 0.0018024752
A60: C2H6 | C60: =C46/C54*100 -> 0.052846419 | D60: =D46/D54*100 -> 0.1450729 | E60: =E46/E54*100 -> 0.14611022 | F60: =F46/F54*100 -> 0.15631425 | G60: =G46/G54*100 -> 0.17273973 | J60: C2H2 | K60: 0 | L60: 0 | M60: 0 | N60: 0.002889248 | P60: 0.0042358747 | Q60: 0.0068774031 | R60: 0.013227367 | S60: 0.038157573
A61: C2H4 | C61: =C47/C54*100 -> 0.93745101 | D61: =D47/D54*100 -> 1.926619 | E61: =E47/E54*100 -> 2.4634047 | F61: =F47/F54*100 -> 3.107567 | G61: =G47/G54*100 -> 3.6568209 | J61: C3-C5 | K61: 0.01132134 | L61: 0.012522924 | M61: 0.016848694 | N61: 0.024633651 | P61: 0 | Q61: 0 | R61: 0 | S61: 0.00017453906
A62: C2H2 | C62: =C48/C54*100 -> 1.1034808 | D62: =D48/D54*100 -> 0 | E62: =E48/E54*100 -> 0 | F62: =F48/F54*100 -> 0 | G62: =G48/G54*100 -> 0.016726905 | J62: Benzene | K62: 0.083445402 | L62: 0.11024426 | M62: 0.14363808 | N62: 0.17764824 | P62: 3.9784126e-05 | Q62: 7.7532632e-05 | R62: 0.0002133161 | S62: 0.00099207694
A63: C3-C5 | C63: =C49/C54*100 -> 0 | D63: =D49/D54*100 -> 0.018095165 | E63: =E49/E54*100 -> 0.027771275 | F63: =F49/F54*100 -> 0.050115345 | G63: =G49/G54*100 -> 0.095075433 | J63: Toluene | K63: 0.0011309408 | L63: 0.0017687451 | M63: 0.0030589796 | N63: 0.006890067 | P63: 0.00014661702 | Q63: 0.00034127521 | R63: 0.00090927867 | S63: 0.003577235
A64: Benzene | C64: =C50/C54*100 -> 0.066429716 | D64: =D50/D54*100 -> 0.066686378 | E64: =E50/E54*100 -> 0.12224076 | F64: =F50/F54*100 -> 0.21362107 | G64: =G50/G54*100 -> 0.34282337 | J64: Naphthalene | K64: 0.010021033 | L64: 0.016283698 | M64: 0.025301166 | N64: 0.0360549 | P64: 1.7032369e-06 | Q64: 4.6931802e-06 | R64: 1.6598055e-05 | S64: 0.00011892228
A65: Naphthalene | C65: =C52/C54*100 -> 0.014266013 | D65: =D52/D54*100 -> 0.0048050561 | E65: =E52/E54*100 -> 0.01083339 | F65: =F52/F54*100 -> 0.022577002 | G65: =G52/G54*100 -> 0.041746981 | J65: C | K65: 0.029970969 | L65: 0.074706536 | M65: 0.079612183 | N65: 0.090401681 | P65: 1.0564422e-05 | Q65: 3.0244964e-05 | R65: 9.6099069e-05 | S65: 0.00043561429
A66: CO | J66: Conversion | K66: 0.27434899 | L66: 0.30947344 | M66: 0.31688026 | N66: 0.28071854 | P66: 0.00031596139 | Q66: 0.0013875819 | R66: 0.0030238356 | S66: 0.010922306
A67: C | C67: =C53/C54*100 -> 0.30025655 | D67: =D53/D54*100 -> 0.14370992 | E67: =E53/E54*100 -> 0.49701548 | F67: =F53/F54*100 -> 0.71040379 | G67: =G53/G54*100 -> 1.0467363 | P67: 0.011087383 | Q67: 0.020850343 | R67: 0.043908096 | S67: 0.14480832
A68: Total | C68: =SUM(C57:C67) -> 100 | D68: =SUM(D57:D67) -> 99.999225 | E68: =SUM(E57:E67) -> 99.998319 | F68: =SUM(F57:F67) -> 99.996101 | G68: =SUM(G57:G67) -> 99.988603 | P68: =SUM(P58:P67) -> 0.044146242 | Q68: =SUM(Q58:Q67) -> 0.071593545 | R68: =SUM(R58:R67) -> 0.14440027 | S68: =SUM(S58:S67) -> 0.51310584
A70: Coolant quenching | P70: =P67/P68 -> 0.25115123 | Q70: =Q67/Q68 -> 0.29123217 | R70: =R67/R68 -> 0.30407212 | S70: =S67/S68 -> 0.28221921
A71: Temp (oC)
A72: Water | C72: C2H6 | D72: =D33*D$30/10000 -> 0.016538565 | E72: =E33*E$30/10000 -> 0.013536723 | F72: =F33*F$30/10000 -> 0.011039915 | G72: =G33*G$30/10000 -> 0.0083077045 | H72: =H33*H$30/10000 -> 0.0069678783
C73: C2H4 | D73: =D34*D$30/10000 -> 0.21963795 | E73: =E34*E$30/10000 -> 0.22822789 | F73: =F34*F$30/10000 -> 0.21947632 | G73: =G34*G$30/10000 -> 0.17587029 | H73: =H34*H$30/10000 -> 0.13852319
A74: Quenched product composition (mol/h) (2) | C74: C2H2 | D74: =D35*D$30/10000 -> 0 | E74: =E35*E$30/10000 -> 0 | F74: =F35*F$30/10000 -> 0 | G74: =G35*G$30/10000 -> 0.00080445988 | H74: =H35*H$30/10000 -> 0
A75: H2 | C75: C3-C5 | D75: =D36*D$30/10000 -> 0.0041257612 | E75: =E36*E$30/10000 -> 0.0051458695 | F75: =F36*F$30/10000 -> 0.0070789344 | G75: =G36*G$30/10000 -> 0.0091450714 | H75: =H36*H$30/10000 -> 0.0044678924
A76: CO2 | C76: Benzene | D76: =D37*D$30/10000 -> 0.022807093 | E76: =E37*E$30/10000 -> 0.033975844 | F76: =F37*F$30/10000 -> 0.045261871 | G76: =G37*G$30/10000 -> 0.049463002 | H76: =H37*H$30/10000 -> 0.028567177
A77: CH4 | C77: Toluene | D77: =D38*D$30/10000 -> 0.00030910596 | E77: =E38*E$30/10000 -> 0.00054510419 | F77: =F38*F$30/10000 -> 0.00096391665 | G77: =G38*G$30/10000 -> 0.001918417 | H77: =H38*H$30/10000 -> 0.00060837912
A78: C2H6 | C78: Naphthalene | D78: =D39*D$30/10000 -> 0.0027389241 | E78: =E39*E$30/10000 -> 0.0050184236 | F78: =F39*F$30/10000 -> 0.0079726635 | G78: =G39*G$30/10000 -> 0.010038848 | H78: =H39*H$30/10000 -> 0.0050319724
A79: C2H4 | C79: Coke | D79: =D40*D$30/10000 -> 0.0081915917 | E79: =E40*E$30/10000 -> 0.023023581 | F79: =F40*F$30/10000 -> 0.025086636 | G79: =G40*G$30/10000 -> 0.025170746 | H79: =H40*H$30/10000 -> 0.015833512
A80: C2H2 | C80: SUM | D80: =SUM(D72:D79) -> 0.27434899 | E80: =SUM(E72:E79) -> 0.30947344 | F80: =SUM(F72:F79) -> 0.31688026 | G80: =SUM(G72:G79) -> 0.28071854 | H80: =SUM(H72:H79) -> 0.2
A81: C3-C5
A82: Benzene | C82: product distribution(vol%)
A83: Naphthalene | C83: C2H6 | D83: =D72/D$80 -> 0.060282945 | E83: =E72/E$80 -> 0.043741148 | F83: =F72/F$80 -> 0.034839392 | G83: =G72/G$80 -> 0.029594428 | H83: =H72/H$80 -> 0.034839392
A84: CO | C84: C2H4 | D84: =D73/D$80 -> 0.80057867 | E84: =E73/E$80 -> 0.73747167 | F84: =F73/F$80 -> 0.69261595 | G84: =G73/G$80 -> 0.62650045 | H84: =H73/H$80 -> 0.69261595
A85: Total | C85: C2H2 | D85: =D74/D$80 -> 0 | E85: =E74/E$80 -> 0 | F85: =F74/F$80 -> 0 | G85: =G74/G$80 -> 0.0028657169 | H85: =H74/H$80 -> 0
C86: C3-C5 | D86: =D75/D$80 -> 0.015038369 | E86: =E75/E$80 -> 0.016627823 | F86: =F75/F$80 -> 0.022339462 | G86: =G75/G$80 -> 0.032577369 | H86: =H75/H$80 -> 0.022339462
A87: Liquid phase hydrogenation | C87: Benzene | D87: =D76/D$80 -> 0.083131681 | E87: =E76/E$80 -> 0.10978598 | F87: =F76/F$80 -> 0.14283588 | G87: =G76/G$80 -> 0.17620141 | H87: =H76/H$80 -> 0.14283588
A88: Temp (oC) | C88: Toluene | D88: =D77/D$80 -> 0.0011266889 | E88: =E77/E$80 -> 0.0017613925 | F88: =F77/F$80 -> 0.0030418956 | G88: =G77/G$80 -> 0.0068339519 | H88: =H77/H$80 -> 0.0030418956
A89: Press (psig) | C89: Naphthalene | D89: =D78/D$80 -> 0.009983358 | E89: =E78/E$80 -> 0.016216007 | F89: =F78/F$80 -> 0.025159862 | G89: =G78/G$80 -> 0.035761256 | H89: =H78/H$80 -> 0.025159862
A90: 1.5 wt% acetylene in Liquid NMP flow rate (ml/min) | C90: Coke | D90: =D79/D$80 -> 0.02985829 | E90: =E79/E$80 -> 0.074395984 | F90: =F79/F$80 -> 0.079167559 | G90: =G79/G$80 -> 0.089665419 | H90: =H79/H$80 -> 0.079167559
A91: (1) gaseous flow rate (ml/min) | C91: SUM | D91: =SUM(D83:D90) -> 1 | E91: =SUM(E83:E90) -> 1 | F91: =SUM(F83:F90) -> 1 | G91: =SUM(G83:G90) -> 1 | H91: =SUM(H83:H90) -> 1
A93: Quenched product composition (mol/h) (3)
A94: H2
A95: CO2
A96: CH4
A97: C2H6
A98: C2H4
A99: C2H2
A100: C3-C5 | J100: Recycle ratio
A101: Benzene | E101: Case 1 | F101: Case 2 | G101: Case 3 | H101: Case 4 | J101: 13186.8 | K101: 3.6e-08 | L101: 220482.14 | M101: 21743.202 | N101: 5284.8719 | O101: 1602.2014
A102: Naphthalene | E102: 18.891043 | F102: 13.111256 | G102: 9.3292035 | H102: 6.7396577 | L102: =SUM(L101:O101) -> 249112.41
A103: CO | J103: =L102/J101 -> 18.891043
A104: Total
J105: 13186.8 | K105: 3.6e-08 | L105: 147171.92 | M105: 17606.909 | N105: 6405.2974 | O105: 1711.3791 | P105: 186082.31
...

Sheet 5. HEN_equip
A1: EQUIP.ICS (Equipment)
A3: Area Name | B3: Component Name | C3: Component Type | D3: Total Direct Cost | E3: Equipment Cost | F3: Equipment Weight | G3: Installed Weight
D4: (USD) | E4: (USD) | F4: LBS | G4: LBS
A11: R1 | B11: R1.RADIANT1 | C11: DHE TEMA EXCH
A12: R1 | B12: R1.M5 | C12: C | D12: 0 | E12: 0 | F12: 0 | G12: 0
A13: R1 | B13: R1.M402 | C13: C | D13: 0 | E13: 0 | F13: 0 | G13: 0
A14: R1 | B14: R1.DECOKING | C14: DAT REACTOR
A15: R1 | B15: R1.CONVECT2 | C15: DHE TEMA EXCH
A16: R1 | B16: R1.CONVECT1 | C16: DHE TEMA EXCH
A17: R1 | B17: R1.COMBUST | C17: DAT REACTOR
A18: R1 | B18: R1.B6 | C18: C | D18: 0 | E18: 0 | F18: 0 | G18: 0
A19: R1 | B19: R1.B1 | C19: DVT CYLINDER
A21: Miscellaneous Flowsheet Area | B21: VAL1 | C21: C | D21: 0 | E21: 0 | F21: 0 | G21: 0
A22: Miscellaneous Flowsheet Area | B22: V5-flash vessel | C22: DVT CYLINDER | D22: 449600 | E22: 165100 | F22: 77400 | G22: 123720
A23: Miscellaneous Flowsheet Area | B23: V4-flash vessel | C23: DVT CYLINDER | D23: 827300 | E23: 465200 | F23: 201800 | G23: 260882
A24: Miscellaneous Flowsheet Area | B24: V3-flash vessel | C24: DVT CYLINDER | D24: 812700 | E24: 583200 | F24: 245600 | G24: 284078
A25: Miscellaneous Flowsheet Area | B25: V2-flash vessel | C25: DVT CYLINDER | D25: 879100 | E25: 674200 | F25: 288900 | G25: 324361
A26: Miscellaneous Flowsheet Area | B26: V1-flash vessel | C26: DVT CYLINDER | D26: 3166900 | E26: 2366000 | F26: 1062700 | G26: 1216094
A27: Miscellaneous Flowsheet Area | B27: T3-bottoms split | C27: C | D27: 0 | E27: 0 | F27: 0 | G27: 0
A28: Miscellaneous Flowsheet Area | B28: T3-cond | C28: DHE TEMA EXCH | D28: 897800 | E28: 785600 | F28: 251000 | G28: 267561
A29: Miscellaneous Flowsheet Area | B29: T3-cond acc | C29: DHT HORIZ DRUM | D29: 348500 | E29: 58600 | F29: 17500 | G29: 60908
A30: Miscellaneous Flowsheet Area | B30: T3-overhead split | C30: C | D30: 0 | E30: 0 | F30: 0 | G30: 0
A31: Miscellaneous Flowsheet Area | B31: T3-reb | C31: DRB U TUBE | D31: 955000 | E31: 777800 | F31: 224700 | G31: 251939
A32: Miscellaneous Flowsheet Area | B32: T3-reflux pump | C32: DCP CENTRIF | D32: 116200 | E32: 33900 | F32: 2500 | G32: 15774
... A47: Miscellaneous Flowsheet Area | B47: T1-tower | C47: DTW TOWER | D47: 359100 | E47: 158600 | F47: 56300 | G47: 83523
A48: Miscellaneous Flowsheet Area | B48: MCOMP2 | C48: DGC CENTRIF
A49: Miscellaneous Flowsheet Area | B49: MCOMP1 | C49: DGC CENTRIF
A50: Miscellaneous Flowsheet Area | B50: M4 | C50: C | D50: 0 | E50: 0 | F50: 0 | G50: 0
A51: Miscellaneous Flowsheet Area | B51: M3 | C51: C | D51: 0 | E51: 0 | F51: 0 | G51: 0
A52: Miscellaneous Flowsheet Area | B52: M2 | C52: C | D52: 0 | E52: 0 | F52: 0 | G52: 0
A53: Miscellaneous Flowsheet Area | B53: M1 | C53: C | D53: 0 | E53: 0 | F53: 0 | G53: 0
A54: Miscellaneous Flowsheet Area | B54: HX1 | C54: DHE TEMA EXCH
A55: Miscellaneous Flowsheet Area | B55: E9 | C55: DHE TEMA EXCH | D55: 799000 | E55: 770000 | F55: 245500 | G55: 249322
A56: Miscellaneous Flowsheet Area | B56: E8 | C56: DHE TEMA EXCH | D56: 667300 | E56: 646300 | F56: 180000 | G56: 182261
A57: Miscellaneous Flowsheet Area | B57: E7 | C57: DHE TEMA EXCH | D57: 1435300 | E57: 1316700 | F57: 373600 | G57: 391318
A58: Miscellaneous Flowsheet Area | B58: E6 | C58: DHE TEMA EXCH | D58: 1191300 | E58: 1112400 | F58: 314800 | G58: 327046
A59: Miscellaneous Flowsheet Area | B59: E5 | C59: DHE TEMA EXCH | D59: 970300 | E59: 949000 | F59: 272400 | G59: 274711
A60: Miscellaneous Flowsheet Area | B60: E4 | C60: DHE TEMA EXCH | D60: 252900 | E60: 236100 | F60: 66900 | G60: 68962
A61: Miscellaneous Flowsheet Area | B61: E3 | C61: DHE TEMA EXCH
A62: Miscellaneous Flowsheet Area | B62: E2 | C62: DHE TEMA EXCH | D62: 17682200 | E62: 7976800 | F62: 1048800 | G62: 1675328
A63: Miscellaneous Flowsheet Area | B63: E10 | C63: DHE TEMA EXCH | D63: 3472500 | E63: 3419400 | F63: 981200 | G63: 988913
A64: Miscellaneous Flowsheet Area | B64: B1 | C64: C | D64: 0 | E64: 0 | F64: 0 | G64: 0

Sheet 3. UPC & MSP (fixed)
A1: 1. Assumption and parameters
B3: ASSUMPTION AND PARAMETERS
B4: Location | E4: North America
B5: System Cost Base Date | E5: 1Q 16
B6: Project Type | E6: Grass roots/Clear field
B7: Plant lifetime (y) | E7: 30
B8: Annual operating hours (h) | E8: 8000
B9: Depreciation method | E9: Straight line
B10: Interest rate (%) | E10: 0.08
B11: Tax rate (%) | E11: 0.35
B12: Operating charges [% of operating labor cost] | E12: 0.15
B13: Plant overhead [% of labor and maintenance costs] | E13: 0.25
B14: G&A [% of fixed-operating cost] | E14: 0.06
B15: Capital charge factor | E15: =E10*POWER(1+E10,E7)/(POWER(1+E10,E7)-1) -> 0.088827433
A18: 2. Production Costs, UPC, and MSP
E20: Previous | F20: Case 1 | G20: Case 2 | H20: Case 3 | I20: Case 4
B21: 1. Total capital investment cost (TCI) ($) | D21: =SUBTOTAL(9,D22:D36) -> 5.04 | E21: =SUBTOTAL(9,E22:E36) -> 2.5298291e+09 | F21: =SUBTOTAL(9,F22:F36) -> 3.0959305e+09 | G21: =SUBTOTAL(9,G22:G36) -> 2.2739022e+09 | H21: =SUBTOTAL(9,H22:H36) -> 1.9751287e+09 | I21: =SUBTOTAL(9,I22:I36) -> 1.7921087e+09
B22: 1.1. Direct plan cost | D22: =SUBTOTAL(9,D23:D30) -> 3.6 | E22: =SUBTOTAL(9,E23:E30) -> 1.8070208e+09 | F22: =SUBTOTAL(9,F23:F30) -> 2.2113789e+09 | G22: =SUBTOTAL(9,G23:G30) -> 1.6242158e+09 | H22: =SUBTOTAL(9,H23:H30) -> 1.4108062e+09 | I22: =SUBTOTAL(9,I23:I30) -> 1.2800776e+09
B23: Purchased equipment (PE) | D23: 1 | E23: 5.0195021e+08 | F23: 6.1427193e+08 | G23: 4.5117106e+08 | H23: 3.9189061e+08 | I23: 3.5557711e+08
B24: Equipment setting | D24: 0.47 | E24: =$D24*E$23/$D$23 -> 2.359166e+08 | F24: =$D24*F$23/$D$23 -> 2.8870781e+08 | G24: =$D24*G$23/$D$23 -> 2.120504e+08 | H24: =$D24*H$23/$D$23 -> 1.8418859e+08 | I24: =$D24*I$23/$D$23 -> 1.6712124e+08
B25: Instrumentation and control | D25: 0.36 | E25: =$D25*E$23/$D$23 -> 1.8070208e+08 | F25: =$D25*F$23/$D$23 -> 2.2113789e+08 | G25: =$D25*G$23/$D$23 -> 1.6242158e+08 | H25: =$D25*H$23/$D$23 -> 1.4108062e+08 | I25: =$D25*I$23/$D$23 -> 1.2800776e+08
B26: Piping | D26: 0.68 | E26: =$D26*E$23/$D$23 -> 3.4132614e+08 | F26: =$D26*F$23/$D$23 -> 4.1770491e+08 | G26: =$D26*G$23/$D$23 -> 3.0679632e+08 | H26: =$D26*H$23/$D$23 -> 2.6648561e+08 | I26: =$D26*I$23/$D$23 -> 2.4179244e+08
B27: Electrical installation | D27: 0.11 | E27: =$D27*E$23/$D$23 -> 55214523 | F27: =$D27*F$23/$D$23 -> 67569912 | G27: =$D27*G$23/$D$23 -> 49628817 | H27: =$D27*H$23/$D$23 -> 43107967 | I27: =$D27*I$23/$D$23 -> 39113483
B28: Building and building services | D28: 0.18 | E28: =$D28*E$23/$D$23 -> 90351038 | F28: =$D28*F$23/$D$23 -> 1.1056895e+08 | G28: =$D28*G$23/$D$23 -> 81210792 | H28: =$D28*H$23/$D$23 -> 70540310 | I28: =$D28*I$23/$D$23 -> 64003881
B29: Yard improvements | D29: 0.1 | E29: =$D29*E$23/$D$23 -> 50195021 | F29: =$D29*F$23/$D$23 -> 61427193 | G29: =$D29*G$23/$D$23 -> 45117106 | H29: =$D29*H$23/$D$23 -> 39189061 | I29: =$D29*I$23/$D$23 -> 35557711
B30: Services facilities | D30: 0.7 | E30: =$D30*E$23/$D$23 -> 3.5136515e+08 | F30: =$D30*F$23/$D$23 -> 4.2999035e+08 | G30: =$D30*G$23/$D$23 -> 3.1581975e+08 | H30: =$D30*H$23/$D$23 -> 2.7432343e+08 | I30: =$D30*I$23/$D$23 -> 2.4890398e+08
B31: 1.2. Indirect plant cost | D31: =SUBTOTAL(9,D32:D36) -> 1.44 | E31: =SUBTOTAL(9,E32:E36) -> 7.2280831e+08 | F31: =SUBTOTAL(9,F32:F36) -> 8.8455158e+08 | G31: =SUBTOTAL(9,G32:G36) -> 6.4968633e+08 | H31: =SUBTOTAL(9,H32:H36) -> 5.6432248e+08 | I31: =SUBTOTAL(9,I32:I36) -> 5.1203104e+08
B32: Engineering | D32: 0.33 | E32: =$D32*E$23/$D$23 -> 1.6564357e+08 | F32: =$D32*F$23/$D$23 -> 2.0270974e+08 | G32: =$D32*G$23/$D$23 -> 1.4888645e+08 | H32: =$D32*H$23/$D$23 -> 1.293239e+08 | I32: =$D32*I$23/$D$23 -> 1.1734045e+08
B33: Construction expenses | D33: 0.41 | E33: =$D33*E$23/$D$23 -> 2.0579959e+08 | F33: =$D33*F$23/$D$23 -> 2.5185149e+08 | G33: =$D33*G$23/$D$23 -> 1.8498014e+08 | H33: =$D33*H$23/$D$23 -> 1.6067515e+08 | I33: =$D33*I$23/$D$23 -> 1.4578662e+08
B34: Legal expenses | D34: 0.04 | E34: =$D34*E$23/$D$23 -> 20078008 | F34: =$D34*F$23/$D$23 -> 24570877 | G34: =$D34*G$23/$D$23 -> 18046843 | H34: =$D34*H$23/$D$23 -> 15675624 | I34: =$D34*I$23/$D$23 -> 14223085
B35: Contractor's fee | D35: 0.22 | E35: =$D35*E$23/$D$23 -> 1.1042905e+08 | F35: =$D35*F$23/$D$23 -> 1.3513982e+08 | G35: =$D35*G$23/$D$23 -> 99257634 | H35: =$D35*H$23/$D$23 -> 86215934 | I35: =$D35*I$23/$D$23 -> 78226965
B36: Contingency | D36: 0.44 | E36: =$D36*E$23/$D$23 -> 2.2085809e+08 | F36: =$D36*F$23/$D$23 -> 2.7027965e+08 | G36: =$D36*G$23/$D$23 -> 1.9851527e+08 | H36: =$D36*H$23/$D$23 -> 1.7243187e+08 | I36: =$D36*I$23/$D$23 -> 1.5645393e+08
B37: Annualized TCI | E37: =E21*$E$15 -> 2.2471822e+08 | F37: =F21*$E$15 -> 2.7500356e+08 | G37: =G21*$E$15 -> 2.0198489e+08 | H37: =H21*$E$15 -> 1.7544561e+08 | I37: =I21*$E$15 -> 1.5918841e+08
B39: 2. Total perationg cost ($) | E39: =SUBTOTAL(9,E40:E54) -> 1.2502726e+09 | F39: =SUBTOTAL(9,F40:F54) -> 1.5037352e+09 | G39: =SUBTOTAL(9,G40:G54) -> 1.1987966e+09 | H39: =SUBTOTAL(9,H40:H54) -> 1.004324e+09 | I39: =SUBTOTAL(9,I40:I54) -> 8.5671061e+08 | K39: Assumption | O39: Yeraly consumprtion (8000 hr/y) | V39: lb | W39: kg
B40: 2.1. Variable operating cost | E40: =SUBTOTAL(9,E41:E48) -> 1.2401759e+09 | F40: =SUBTOTAL(9,F41:F48) -> 1.4916324e+09 | G40: =SUBTOTAL(9,G41:G48) -> 1.1896068e+09 | H40: =SUBTOTAL(9,H41:H48) -> 9.9619288e+08 | I40: =SUBTOTAL(9,I41:I48) -> 8.4922809e+08 | L40: Value | M40: Unit price | N40: Weight factor | O40: Unit | P40: Previous | Q40: Case 1 | R40: Case 2 | S40: Case 3 | T40: Case 4 | V40: 1 | W40: 0.45359237
B41: Natural gas feedstock | E41: =P41*$L41*$N41 -> 3.0306628e+08 | F41: =Q41*$L41*$N41 -> 3.0306628e+08 | G41: =R41*$L41*$N41 -> 3.0306628e+08 | H41: =S41*$L41*$N41 -> 3.0306628e+08 | I41: =T41*$L41*$N41 -> 3.0306628e+08 | K41: Natural gas feedstock | L41: 3.27 | M41: $/MMBTU | N41: 1 | O41: MMBTU | P41: 92680819 | Q41: 92680819 | R41: =327437.649716956/28.263682*8000 -> 92680819 | S41: =327437.649716956/28.263682*8000 -> 92680819 | T41: =327437.649716956/28.263682*8000 -> 92680819 | V41: 1 MMBTU = 28.263682 m3 NG
B42: Fuel gas | E42: =P42*$L42*$N42 -> 1.4326561e+08 | F42: =Q42*$L42*$N42 -> 2.431001e+08 | G42: =R42*$L42*$N42 -> 1.8710409e+08 | H42: =S42*$L42*$N42 -> 1.5613069e+08 | I42: =T42*$L42*$N42 -> 1.3639264e+08 | K42: Fuel gas | L42: =L41 -> 3.27 | M42: $/MMBTU | N42: 1 | O42: MMBTU | P42: 43812113 | Q42: =262649.228386354/28.263682*8000 -> 74342537 | R42: =202150.247312389/28.263682*8000 -> 57218376 | S42: =168686.087475501/28.263682*8000 -> 47746387 | T42: =147360.785925464/28.263682*8000 -> 41710287 | V42: 1MMBTU=1055MJ, 4251 MMBTU, 0.85 ef by Gavin Towler book
B43: O2 | E43: =P43*$L43*$N43 -> 14335462 | F43: =Q43*$L43*$N43 -> 2.2096061e+08 | G43: =R43*$L43*$N43 -> 1.700659e+08 | H43: =S43*$L43*$N43 -> 1.419142e+08 | I43: =T43*$L43*$N43 -> 1.2397431e+08 | K43: O2 | L43: 40 | M43: $/ton | N43: 1 | O43: ton | P43: 358386.56 | Q43: =690501.918117916/1000*8000 -> 5524015.3 | R43: =531455.927757318/1000*8000 -> 4251647.4 | S43: =443481.876816915/1000*8000 -> 3547855 | T43: =387419.714371281/1000*8000 -> 3099357.7
B44: CW | E44: =P44*$L44*$N44 -> 1.0188414e+08 | F44: =Q44*$L44*$N44 -> 1.0007561e+08 | G44: =R44*$L44*$N44 -> 70529292 | H44: =S44*$L44*$N44 -> 53760234 | I44: =T44*$L44*$N44 -> 44886792 | K44: CW | L44: 0.03 | M44: $/ton | N44: 1 | O44: ton | P44: 3396138120 | Q44: 3335853552 | R44: 2350976388 | S44: 1792007796 | T44: 1496226396
B45: Electricity | E45: =P45*$L45*$N45 -> 5.7882009e+08 | F45: =Q45*$L45*$N45 -> 5.693438e+08 | G45: =R45*$L45*$N45 -> 4.1372467e+08 | H45: =S45*$L45*$N45 -> 2.994831e+08 | I45: =T45*$L45*$N45 -> 1.9299286e+08 | K45: Electricity | L45: 0.069 | M45: $/kWh | N45: 1 | O45: kWh | P45: 8388696888 | Q45: 8251359360 | R45: 5996009760 | S45: 4340334720 | T45: 2796997920
B46: HPS | E46: =P46*$L46*$N46 -> 572343.23 | F46: =Q46*$L46*$N46 -> 0 | G46: =R46*$L46*$N46 -> 0 | H46: =S46*$L46*$N46 -> 0 | I46: =T46*$L46*$N46 -> 0 | K46: HPS | L46: 14.5 | M46: $/ton | N46: 1 | O46: ton | P46: 39471.947 | Q46: 0 | R46: 0 | S46: 0 | T46: 0
B47: LPS | E47: =P47*$L47*$N47 -> 12053565 | F47: =Q47*$L47*$N47 -> 0 | G47: =R47*$L47*$N47 -> 0 | H47: =S47*$L47*$N47 -> 0 | I47: =T47*$L47*$N47 -> 0 | K47: LPS | L47: 10.5 | M47: $/ton | N47: 1 | O47: ton | P47: 1147958.6 | Q47: 0 | R47: 0 | S47: 0 | T47: 0
B48: Refrigeration | E48: =P48*$L48*$N48 -> 86178385 | F48: =Q48*$L48*$N48 -> 55085994 | G48: =R48*$L48*$N48 -> 45116572 | H48: =S48*$L48*$N48 -> 41838381 | I48: =T48*$L48*$N48 -> 47915218 | K48: Refrigeration | L48: 0.032 | M48: $/kWh | N48: 1 | O48: kWh | P48: 2.6930745e+09 | Q48: 1.7214373e+09 | R48: 1.4098929e+09 | S48: 1.3074494e+09 | T48: 1.4973506e+09
B49: Fixed operating costs | E49: =SUBTOTAL(9,E50:E54) -> 10096738 | F49: =SUBTOTAL(9,F50:F54) -> 12102802 | G49: =SUBTOTAL(9,G50:G54) -> 9189824.3 | H49: =SUBTOTAL(9,H50:H54) -> 8131077.8 | I49: =SUBTOTAL(9,I50:I54) -> 7482520.9
B50: Operating labor cost | E50: 760000 | F50: 760000 | G50: 760001 | H50: 760002 | I50: 760003 | N50: Natural gas feedstock | P50: =E41/E$39 -> 0.24240016 | Q50: =F41/F$39 -> 0.20154232 | R50: =G41/G$39 -> 0.25280875 | S50: =H41/H$39 -> 0.30176148 | T50: =I41/I$39 -> 0.35375572
B51: Maintenance cost | E51: =0.03*E75 -> 6741546.7 | F51: =0.03*F75 -> 8250106.9 | G51: =0.03*G75 -> 6059546.8 | H51: =0.03*H75 -> 5263368.3 | I51: =0.03*I75 -> 4775652.4 | N51: Fuel gas | P51: =E42/E$39 -> 0.1145875 | Q51: =F42/F$39 -> 0.16166417 | R51: =G42/G$39 -> 0.15607659 | S51: =H42/H$39 -> 0.15545849 | T51: =I42/I$39 -> 0.15920503
B52: Operating charges | E52: =0.15*E50 -> 114000 | F52: =0.15*F50 -> 114000 | G52: =0.15*G50 -> 114000.15 | H52: =0.15*H50 -> 114000.3 | I52: =0.15*I50 -> 114000.45 | N52: O2 | P52: =E43/E$39 -> 0.011465869 | Q52: =F43/F$39 -> 0.14694117 | R52: =G43/G$39 -> 0.14186384 | S52: =H43/H$39 -> 0.14130321 | T52: =I43/I$39 -> 0.14470967
B53: Plant overhead | E53: =0.25*(E50+E51) -> 1875386.7 | F53: =0.25*(F50+F51) -> 2252526.7 | G53: =0.25*(G50+G51) -> 1704886.9 | H53: =0.25*(H50+H51) -> 1505842.6 | I53: =0.25*(I50+I51) -> 1383913.8 | N53: CW | P53: =E44/E$39 -> 0.081489543 | Q53: =F44/F$39 -> 0.06655135 | R53: =G44/G$39 -> 0.058833409 | S53: =H44/H$39 -> 0.053528778 | T53: =I44/I$39 -> 0.052394346
B54: G&A cost | E54: =SUM(E50:E53)/0.94*0.06 -> 605804.26 | F54: =SUM(F50:F53)/0.94*0.06 -> 726168.1 | G54: =SUM(G50:G53)/0.94*0.06 -> 551389.46 | H54: =SUM(H50:H53)/0.94*0.06 -> 487864.67 | I54: =SUM(I50:I53)/0.94*0.06 -> 448951.25 | N54: Electricity | P54: =E45/E$39 -> 0.4629551 | Q54: =F45/F$39 -> 0.37861972 | R54: =G45/G$39 -> 0.34511665 | S54: =H45/H$39 -> 0.29819372 | T54: =I45/I$39 -> 0.22527193
N55: HPS | P55: =E46/E$39 -> 0.00045777475 | Q55: =F46/F$39 -> 0 | R55: =G46/G$39 -> 0 | S55: =H46/H$39 -> 0 | T55: =I46/I$39 -> 0
B56: Production amount (kg/y) | N56: LPS | P56: =E47/E$39 -> 0.0096407495 | Q56: =F47/F$39 -> 0 | R56: =G47/G$39 -> 0 | S56: =H47/H$39 -> 0 | T56: =I47/I$39 -> 0
B57: Ethylene (99.9% vol) | D57: kg/y | E57: =P65 -> 4.8694133e+08 | F57: =Q65 -> 9.9704611e+08 | G57: =R65 -> 9.5257016e+08 | H57: =S65 -> 9.23201e+08 | I57: =T65 -> 8.5601968e+08 | N57: Refrigeration | P57: =E48/E$39 -> 0.068927676 | Q57: =F48/F$39 -> 0.036632776 | R57: =G48/G$39 -> 0.037634884 | S57: =H48/H$39 -> 0.041658253 | T57: =I48/I$39 -> 0.055929292
B58: Hydrogen (96 %vol) | D58: kg/y | E58: =P66 -> 3.503607e+08 | F58: =Q66 -> 2.7474281e+08 | G58: =R66 -> 2.9320363e+08 | H58: =S66 -> 3.0101806e+08 | I58: =T66 -> 3.1024314e+08 | N58: Fixed operating costs | P58: =E49/E$39 -> 0.0080756289 | Q58: =F49/F$39 -> 0.0080484927 | R58: =G49/G$39 -> 0.0076658744 | S58: =H49/H$39 -> 0.0080960708 | T58: =I49/I$39 -> 0.0087340122
B59: Crude Naphthalene (95.7 %wt) | D59: kg/y | E59: =P67 -> 34503790 | F59: =Q67 -> 12756501 | G59: =R67 -> 21305721 | H59: =S67 -> 32966567 | I59: =T67 -> 47398147
B60: Benzene (99 %wt) | D60: kg/y | E60: =P68 -> 91327939 | F60: =Q68 -> 1.0528551e+08 | G60: =R68 -> 1.4167665e+08 | H60: =S68 -> 1.8677811e+08 | I60: =T68 -> 2.3403433e+08
B61: C2-C5 hydrocarbon | D61: kg/y | E61: =P69 -> 0 | F61: =Q69 -> 1.1342609e+08 | G61: =R69 -> 88112436 | H61: =S69 -> 78865736 | I61: =T69 -> 85277185
B62: Raw Acethylene (95.1 %vol) | D62: kg/y | E62: =P70 -> 5.6637178e+08 | F62: =Q70 -> 0 | G62: =R70 -> 0 | H62: =S70 -> 0 | I62: =T70 -> 0
B64: Total production cost ($/y) | E64: =E39+E37 -> 1.4749908e+09 | F64: =F39+F37 -> 1.7787387e+09 | G64: =G39+G37 -> 1.4007815e+09 | H64: =H39+H37 -> 1.1797696e+09 | I64: =I39+I37 -> 1.015899e+09 | K64: Product | L64: Value | M64: Unit price | N64: Weight factor | O64: Unit | P64: Previous | Q64: Case 1 | R64: Case 2 | S64: Case 3 | T64: Case 4 | V64: H2 price in correlation to NG gas H2=0.1515NG+0.9287 ($/kg)
B65: Ethylene (99.9% vol) | D65: $/y | E65: =E64-SUM(E66:E70) -> 5.5059714e+08 | F65: =F64-SUM(F66:F70) -> 1.2968527e+09 | G65: =G64-SUM(G66:G70) -> 8.6980483e+08 | H65: =H64-SUM(H66:H70) -> 6.0528563e+08 | I65: =I64-SUM(I66:I70) -> 3.9066008e+08 | K65: Ethylene (99.9% vol) | L65: - | M65: $/kg | N65: 1 | O65: kg/y | P65: 4.8694133e+08 | Q65: 9.9704611e+08 | R65: 9.5257016e+08 | S65: 9.23201e+08 | T65: 8.5601968e+08 | V65: Naphthalene and benzene price in correlation to ethylene price
B66: Hydrogen (96 %vol) | D66: $/y | E66: =$L66*$N66*P66 -> 4.9895042e+08 | F66: =$L66*$N66*Q66 -> 3.9126261e+08 | G66: =$L66*$N66*R66 -> 4.1755276e+08 | H66: =$L66*$N66*S66 -> 4.2868132e+08 | I66: =$L66*$N66*T66 -> 4.418188e+08 | K66: Hydrogen (96 %vol) | L66: =0.1515*L41+0.9287 -> 1.424105 | M66: $/kg | N66: 1 | O66: kg/y | P66: 3.503607e+08 | Q66: 2.7474281e+08 | R66: 2.9320363e+08 | S66: 3.0101806e+08 | T66: 3.1024314e+08 | V66: Ben=0.695ethylene - 37.031/1000 ($/kg), Nap=0.5/0.65*Ben ($/kg)
B67: Crude Naphthalene (95.7 %wt) | D67: $/y | E67: =$L67*$N67*P67 -> 16633322 | F67: =$L67*$N67*Q67 -> 6149555.9 | G67: =$L67*$N67*R67 -> 10270898 | H67: =$L67*$N67*S67 -> 15892269 | I67: =$L67*$N67*T67 -> 22849334 | K67: Crude Naphthalene (95.7 %wt) | L67: =L68*0.5/0.65 -> 0.48207231 | M67: $/kg | N67: 1 | O67: kg/y | P67: 34503790 | Q67: 12756501 | R67: 21305721 | S67: 32966567 | T67: 47398147 | V67: Acetylene = 0.65 ethylene
B68: Benzene (99 %wt) | D68: $/y | E68: =$L68*$N68*P68 -> 57234671 | F68: =$L68*$N68*Q68 -> 65981797 | G68: =$L68*$N68*R68 -> 88787903 | H68: =$L68*$N68*S68 -> 1.1705272e+08 | I68: =$L68*$N68*T68 -> 1.4666791e+08 | K68: Benzene (99 %wt) | L68: =0.695*0.955-37.031/1000 -> 0.626694 | M68: $/kg | N68: 1 | O68: kg/y | P68: 91327939 | Q68: 1.0528551e+08 | R68: 1.4167665e+08 | S68: 1.8677811e+08 | T68: 2.3403433e+08 | V68: 0.955 $/kg ethylene (korean market 2020 - https://www.fibre2fashion.com/market-intelligence/textile-market-watch/ethylene-price-trends-industry-reports/16/?gcode=1)
B69: C2-C5 hydrocarbon | D69: $/y | E69: =$L69*$N69*P69 -> 0 | F69: =$L69*$N69*Q69 -> 18492064 | G69: =$L69*$N69*R69 -> 14365133 | H69: =$L69*$N69*S69 -> 12857626 | I69: =$L69*$N69*T69 -> 13902897 | K69: C2-C5 hydrocarbon (85%vol C2, 15% C3-C5) | L69: =(8.7/100/0.45359237)*0.85 -> 0.16303184 | M69: $/kg | N69: 1 | O69: kg/y | P69: 0 | Q69: 1.1342609e+08 | R69: 88112436 | S69: 78865736 | T69: 85277185 | V69: etrhane 8.7 cent/lb (https://investors.westlake.com/industry-pricing/default.aspx)
B70: Raw Acethylene (95.1 %vol) | D70: $/y | E70: =$L70*$N70*P70 -> 3.5157528e+08 | F70: =$L70*$N70*Q70 -> 0 | G70: =$L70*$N70*R70 -> 0 | H70: =$L70*$N70*S70 -> 0 | I70: =$L70*$N70*T70 -> 0 | K70: Raw Acethylene (95.1 %vol) | L70: =0.955*0.65 -> 0.62075 | M70: $/kg | N70: 1 | O70: kg/y | P70: 5.6637178e+08 | Q70: 0 | R70: 0 | S70: 0 | T70: 0
B71: UPC_Ethylene | D71: $/kg | E71: =E65/E57 -> 1.1307258 | F71: =F65/F57 -> 1.3006948 | G71: =G65/G57 -> 0.91311367 | H71: =H65/H57 -> 0.65563797 | I71: =I65/I57 -> 0.4563681
B74: Expenditure ($) | E74: =(E75-$E$11*E76+(1-$E$11)*E80)/(1-$E$11) -> 1.5505858e+09 | F74: =(F75-$E$11*F76+(1-$E$11)*F80)/(1-$E$11) -> 1.8712496e+09 | G74: =(G75-$E$11*G76+(1-$E$11)*G80)/(1-$E$11) -> 1.468729e+09 | H74: =(H75-$E$11*H76+(1-$E$11)*H80)/(1-$E$11) -> 1.2387892e+09 | I74: =(I75-$E$11*I76+(1-$E$11)*I80)/(1-$E$11) -> 1.0694498e+09
B75: Annualized TCI | D75: $/y | E75: =E21*$E$15 -> 2.2471822e+08 | F75: =F21*$E$15 -> 2.7500356e+08 | G75: =G21*$E$15 -> 2.0198489e+08 | H75: =H21*$E$15 -> 1.7544561e+08 | I75: =I21*$E$15 -> 1.5918841e+08
B76: Depreciation = TPI / Life time | D76: $/y | E76: =E21/$E$7 -> 84327636 | F76: =F21/$E$7 -> 1.0319768e+08 | G76: =G21/$E$7 -> 75796739 | H76: =H21/$E$7 -> 65837622 | I76: =I21/$E$7 -> 59736955
B77: Tax = (Profit - Depreciation)* Tax rate | D77: $/y | E77: =(E79-E76)*$E$11 -> 75594932 | F77: =(F79-F76)*$E$11 -> 92510857 | G77: =(G79-G76)*$E$11 -> 67947468 | H77: =(H79-H76)*$E$11 -> 59019686 | I77: =(I79-I76)*$E$11 -> 53550785
B78: ROI = Profit - Tax | D78: $/y | E78: =E79-E77 -> 2.2471822e+08 | F78: =F79-F77 -> 2.7500356e+08 | G78: =G79-G77 -> 2.0198489e+08 | H78: =H79-H77 -> 1.7544561e+08 | I78: =I79-I77 -> 1.5918841e+08
B79: Profit = Revenue - Expenses | D79: $/y | E79: =E74-E80 -> 3.0031315e+08 | F79: =F74-F80 -> 3.6751442e+08 | G79: =G74-G80 -> 2.6993236e+08 | H79: =H74-H80 -> 2.344653e+08 | I79: =I74-I80 -> 2.127392e+08
B80: Expense (OPEX) = Variable + Fixed costs | D80: $/y | E80: =E39 -> 1.2502726e+09 | F80: =F39 -> 1.5037352e+09 | G80: =G39 -> 1.1987966e+09 | H80: =H39 -> 1.004324e+09 | I80: =I39 -> 8.5671061e+08
B81: Revenue (at break-even point) ($) | E81: =E74 -> 1.5505858e+09 | F81: =F74 -> 1.8712496e+09 | G81: =G74 -> 1.468729e+09 | H81: =H74 -> 1.2387892e+09 | I81: =I74 -> 1.0694498e+09
B82: Ethylene (99.9% vol) | D82: $/y | E82: =E81-SUM(E83:E87) -> 6.2619207e+08 | F82: =F81-SUM(F83:F87) -> 1.3893636e+09 | G82: =G81-SUM(G83:G87) -> 9.377523e+08 | H82: =H81-SUM(H83:H87) -> 6.6430531e+08 | I82: =I81-SUM(I83:I87) -> 4.4421086e+08
B83: Hydrogen (96 %vol) | D83: $/y | E83: =$L66*$N66*P66 -> 4.9895042e+08 | F83: =$L66*$N66*Q66 -> 3.9126261e+08 | G83: =$L66*$N66*R66 -> 4.1755276e+08 | H83: =$L66*$N66*S66 -> 4.2868132e+08 | I83: =$L66*$N66*T66 -> 4.418188e+08
B84: Crude Naphthalene (95.7 %wt) | D84: $/y | E84: =$L67*$N67*P67 -> 16633322 | F84: =$L67*$N67*Q67 -> 6149555.9 | G84: =$L67*$N67*R67 -> 10270898 | H84: =$L67*$N67*S67 -> 15892269 | I84: =$L67*$N67*T67 -> 22849334
B85: Benzene (99 %wt) | D85: $/y | E85: =$L68*$N68*P68 -> 57234671 | F85: =$L68*$N68*Q68 -> 65981797 | G85: =$L68*$N68*R68 -> 88787903 | H85: =$L68*$N68*S68 -> 1.1705272e+08 | I85: =$L68*$N68*T68 -> 1.4666791e+08
B86: C2-C5 hydrocarbon | D86: $/y | E86: =$L69*$N69*P69 -> 0 | F86: =$L69*$N69*Q69 -> 18492064 | G86: =$L69*$N69*R69 -> 14365133 | H86: =$L69*$N69*S69 -> 12857626 | I86: =$L69*$N69*T69 -> 13902897
B87: Raw Acethylene (95.1 %vol) | D87: $/y | E87: =$L70*$N70*P70 -> 3.5157528e+08 | F87: =$L70*$N70*Q70 -> 0 | G87: =$L70*$N70*R70 -> 0 | H87: =$L70*$N70*S70 -> 0 | I87: =$L70*$N70*T70 -> 0
B88: Unit price ($/kg)
B89: MSP_Ethylene (99.9% vol) | D89: $/kg | E89: =E82/E57 -> 1.2859703 | F89: =F82/F57 -> 1.3934798 | G89: =G82/G57 -> 0.98444434 | H89: =H82/H57 -> 0.71956737 | I89: =I82/I57 -> 0.51892599
B90: Hydrogen (96 %vol) | D90: $/kg | E90: =$L$66 -> 1.424105 | F90: =$L$66 -> 1.424105 | G90: =$L$66 -> 1.424105 | H90: =$L$66 -> 1.424105 | I90: =$L$66 -> 1.424105
B91: Crude Naphthalene (95.7 %wt) | D91: $/kg | E91: =$L$67 -> 0.48207231 | F91: =$L$67 -> 0.48207231 | G91: =$L$67 -> 0.48207231 | H91: =$L$67 -> 0.48207231 | I91: =$L$67 -> 0.48207231
B92: Benzene (99 %wt) | D92: $/kg | E92: =$L$68 -> 0.626694 | F92: =$L$68 -> 0.626694 | G92: =$L$68 -> 0.626694 | H92: =$L$68 -> 0.626694 | I92: =$L$68 -> 0.626694
B93: C2-C5 hydrocarbon | D93: $/kg | E93: =$L$69 -> 0.16303184 | F93: =$L$69 -> 0.16303184 | G93: =$L$69 -> 0.16303184 | H93: =$L$69 -> 0.16303184 | I93: =$L$69 -> 0.16303184
B94: Raw Acethylene (95.1 %vol) | D94: $/kg | E94: =$L$70 -> 0.62075 | F94: =$L$70 -> 0.62075 | G94: =$L$70 -> 0.62075 | H94: =$L$70 -> 0.62075 | I94: =$L$70 -> 0.62075
D97: Production cost
E98: Previous | F98: Case 1 | G98: Case 2 | H98: Case 3 | I98: Case 4
D99: Total production cost ($/y) | E99: =E64 -> 1.4749908e+09 | F99: =F64 -> 1.7787387e+09 | G99: =G64 -> 1.4007815e+09 | H99: =H64 -> 1.1797696e+09 | I99: =I64 -> 1.015899e+09
D100: Ethylene | E100: =E65 -> 5.5059714e+08 | F100: =F65 -> 1.2968527e+09 | G100: =G65 -> 8.6980483e+08 | H100: =H65 -> 6.0528563e+08 | I100: =I65 -> 3.9066008e+08
D101: Hydrogen | E101: =-E66 -> -4.9895042e+08 | F101: =-F66 -> -3.9126261e+08 | G101: =-G66 -> -4.1755276e+08 | H101: =-H66 -> -4.2868132e+08 | I101: =-I66 -> -4.418188e+08
D102: Raw Naphthalene | E102: =-E67 -> -16633322 | F102: =-F67 -> -6149555.9 | G102: =-G67 -> -10270898 | H102: =-H67 -> -15892269 | I102: =-I67 -> -22849334
D103: Benzene | E103: =-E68 -> -57234671 | F103: =-F68 -> -65981797 | G103: =-G68 -> -88787903 | H103: =-H68 -> -1.1705272e+08 | I103: =-I68 -> -1.4666791e+08
D104: C2-C5 | E104: =-E69 -> 0 | F104: =-F69 -> -18492064 | G104: =-G69 -> -14365133 | H104: =-H69 -> -12857626 | I104: =-I69 -> -13902897
D105: Raw Acethylene | E105: =-E70 -> -3.5157528e+08 | F105: =-F70 -> 0 | G105: =-G70 -> 0 | H105: =-H70 -> 0 | I105: =-I70 -> 0
D107: UPC
E108: Previous | F108: Case 1 | G108: Case 2 | H108: Case 3 | I108: Case 4
D109: Annualized capital cost | E109: =E71/E64*E37 -> 0.17226866 | F109: =F71/F64*F37 -> 0.20109514 | G109: =G71/G64*G37 -> 0.13166591 | H109: =H71/H64*H37 -> 0.097501077 | I109: =I71/I64*I37 -> 0.07151155
D110: Raw material | E110: =E71/E64*E41 -> 0.23233017 | F110: =F71/F64*F41 -> 0.22161587 | G110: =G71/G64*G41 -> 0.19755683 | H110: =H71/H64*H41 -> 0.16842421 | I110: =I71/I64*I41 -> 0.13614521
D111: Utility | E111: =E71/E64*SUM(E42:E48) -> 0.71838685 | F111: =F71/F64*SUM(F42:F48) -> 0.8691337 | G111: =G71/G64*SUM(G42:G48) -> 0.57790045 | H111: =H71/H64*SUM(H42:H48) -> 0.38519396 | I111: =I71/I64*SUM(I42:I48) -> 0.24535
...

Sheet Previous_Technical performance
B2: Catlatyst performance (conversion, selectivity) | H2: BOILING TEMPERATURE AT 1ATM (°C)
E3: Experiment | F3: Aspen (checked) | H3: H2 | J3: -253
B4: Reactor inlet: H2/CH4 ratio | E4: ='1. DB_Experiment_VER1'!$J$14 -> 4.4444444 | F4: =F47/F48 -> 4.4443999 | H4: CH4 | J4: -164
B5: Conversion (%) | E5: 30.353963 | F5: =(F48-G48)/F48*100 -> 30.350448 | H5: C2H6 | J5: -89
B6: Selectivity (%) | E6: =SUM(E7:E12) -> 100 | F6: =SUM(F7:F12) -> 100.01719 | H6: C2H4 | J6: -104
C7: C2H6 | E7: 1.9832376 | F7: =(G49-F49)*2/($F$48-$G$48)*100 -> 1.9835724 | H7: C2H2 | J7: -84
C8: C2H4 | E8: 35.180966 | F8: =(G50-F50)*2/($F$48-$G$48)*100 -> 35.187281 | H8: C3-C5 | J8: -84
C9: C2H2 | E9: 41.411786 | F9: =(G51-F51)*2/($F$48-$G$48)*100 -> 41.418759 | H9: Benzene | J9: -47~36
C10: Benzene | E10: 7.4789878 | F10: =(G53-F53)*6/($F$48-$G$48)*100 -> 7.4802315 | H10: Naphthalene | J10: 80
C11: Naphthalene | E11: 2.6768978 | F11: =(G54-F54)*10/($F$48-$G$48)*100 -> 2.6773429
C12: Coke | E12: 11.268125 | F12: =N55/($F$48-$G$48)*100 -> 11.269999 | H12: PRODUCT STREAM (KG/H) | K12: ton/y | L12: MT/y | M12: CH4Fd ton/y | S12: Mole flowrate (kmol/h) | T12: Mass flow rate (kg/h)
B13: Yields (%) | E13: =SUM(E14:E19) -> 30.355664 | H13: Ethylene (99.9% vol) | J13: =H59 -> 60867.667 | K13: =J13*8000/1000 -> 486941.33 | L13: =J13*8000/10^9 -> 0.48694133 | M13: =D59*8 -> 1692421.3 | R13: Raw materials
C14: C2H6 | E14: =F7*$F$5/100 -> 0.60202309 | H14: Acethylene (95.1 %vol) | J14: =I59 -> 70796.472 | K14: =J14*8000/1000 -> 566371.78 | L14: =J14*8000/10^9 -> 0.56637178 | R14: Methane | S14: =D46 -> 13186.8 | T14: =D59 -> 211552.67
C15: C2H4 | E15: =F8*$F$5/100 -> 10.679497 | H15: Naphthalene (95.7 %wt) | J15: =J59 -> 4312.9738 | K15: =J15*8000/1000 -> 34503.79 | L15: =J15*8000/10^9 -> 0.03450379 | R15: Products
C16: C2H2 | E16: =F9*$F$5/100 -> 12.570779 | H16: Benzene (99 %wt) | J16: =K59 -> 11415.992 | K16: =J16*8000/1000 -> 91327.939 | L16: =J16*8000/10^9 -> 0.091327939 | R16: Ethylene (99.9% vol) | S16: =H46 -> 2170.0515 | T16: 60867.667
C17: Benzene | E17: =F10*$F$5/100 -> 2.2702838 | H17: Hydrogen (96 %vol) | J17: =L59 -> 43795.087 | K17: =J17*8000/1000 -> 350360.7 | L17: =J17*8000/10^9 -> 0.3503607 | R17: Acethylene (95.1 %vol) | S17: =I46 -> 2685.8454 | T17: 70796.472
C18: Naphthalene | E18: =F11*$F$5/100 -> 0.81258557 | R18: Naphthalene (95.7 %wt) | S18: =J46 -> 35.101909 | T18: 4312.9738
C19: Coke | E19: =F12*$F$5/100 -> 3.4204952 | R19: Benzene (99 %wt) | S19: =K46 -> 145.59242 | T19: 11415.992
R20: Hydrogen (96 %vol) | S20: =L46 -> 17390.595 | T20: 43795.087
B44: MAJOR STREAM INFORMATION
D45: ='DB_Aspen simulation_previous'!D117 -> 1-CH4 | E45: ='DB_Aspen simulation_previous'!E117 -> 50-O2 | F45: ='DB_Aspen simulation_previous'!F117 -> 6-RXNin | G45: ='DB_Aspen simulation_previous'!G117 -> 7-RXN-out | H45: ='DB_Aspen simulation_previous'!H117 -> 27-Ethylene | I45: ='DB_Aspen simulation_previous'!I117 -> 28-C2 | J45: ='DB_Aspen simulation_previous'!J117 -> 12-Naphthalene | K45: ='DB_Aspen simulation_previous'!K117 -> 20-Benzene | ... N45: ='DB_Aspen simulation_previous'!N117 -> 49-COKE
B46: ='DB_Aspen simulation_previous'!B118 -> Mole Flows | C46: ='DB_Aspen simulation_previous'!C118 -> kmol/hr | D46: ='DB_Aspen simulation_previous'!D118 -> 13186.8 | E46: ='DB_Aspen simulation_previous'!E118 -> 1400 | F46: ='DB_Aspen simulation_previous'!F118 -> 221973.91 | G46: ='DB_Aspen simulation_previous'!G118 -> 231437.85 | H46: ='DB_Aspen simulation_previous'!H118 -> 2170.0515 | I46: ='DB_Aspen simulation_previous'!I118 -> 2685.8454 | ... N46: ='DB_Aspen simulation_previous'!N118 -> 1392.0025 | R46: 13186.8 | S46: 1400 | T46: 221973.91 | U46: 231437.85 | V46: 2170.0515 | W46: 2685.8454 | X46: 35.101909 | Y46: 145.59242 | Z46: 17390.595 | AA46: 1400 | AB46: 1392.0025
B47: ='DB_Aspen simulation_previous'!B119 -> H2 | C47: ='DB_Aspen simulation_previous'!C119 -> kmol/hr | D47: ='DB_Aspen simulation_previous'!D119 -> 0 | E47: ='DB_Aspen simulation_previous'!E119 -> 0 | F47: ='DB_Aspen simulation_previous'!F119 -> 180869.01 | G47: ='DB_Aspen simulation_previous'!G119 -> 197643.84 | H47: ='DB_Aspen simulation_previous'!H119 -> 1.0538853e-09 | I47: ='DB_Aspen simulation_previous'!I119 -> 2.1702471e-39 | ... N47: ='DB_Aspen simulation_previous'!N119 -> 0 | R47: 0 | S47: 0 | T47: 180869.01 | U47: 197643.84 | V47: 1.0538853e-09 | W47: 2.1702471e-39 | X47: 0.20996271 | Y47: 5.7435524e-08 | Z47: 16767.799 | AA47: 0 | AB47: 0
B48: ='DB_Aspen simulation_previous'!B120 -> CH4 | C48: ='DB_Aspen simulation_previous'!C120 -> kmol/hr | D48: ='DB_Aspen simulation_previous'!D120 -> 13186.8 | E48: ='DB_Aspen simulation_previous'!E120 -> 0 | F48: ='DB_Aspen simulation_previous'!F120 -> 40695.935 | G48: ='DB_Aspen simulation_previous'!G120 -> 28344.536 | H48: ='DB_Aspen simulation_previous'!H120 -> 0.43146133 | I48: ='DB_Aspen simulation_previous'!I120 -> 1.1295021e-14 | ... N48: ='DB_Aspen simulation_previous'!N120 -> 0 | R48: 13186.8 | S48: 0 | T48: 40695.935 | U48: 28344.536 | V48: 0.43146133 | W48: 1.1295021e-14 | X48: 0.20312417 | Y48: 7.4918187e-06 | Z48: 622.64269 | AA48: 0 | AB48: 0
B49: ='DB_Aspen simulation_previous'!B121 -> C2H6 | C49: ='DB_Aspen simulation_previous'!C121 -> kmol/hr | D49: ='DB_Aspen simulation_previous'!D121 -> 0 | E49: ='DB_Aspen simulation_previous'!E121 -> 0 | F49: ='DB_Aspen simulation_previous'!F121 -> 3.8575921 | G49: ='DB_Aspen simulation_previous'!G121 -> 126.35705 | H49: ='DB_Aspen simulation_previous'!H121 -> 9.4418223e-13 | I49: ='DB_Aspen simulation_previous'!I121 -> 122.44253 | ... N49: ='DB_Aspen simulation_previous'!N121 -> 0 | R49: 0 | S49: 0 | T49: 3.8575921 | U49: 126.35705 | V49: 9.4418223e-13 | W49: 122.44253 | X49: 0.0063581651 | Y49: 0.00010754155 | Z49: 0.00027909048 | AA49: 0 | AB49: 0
B50: ='DB_Aspen simulation_previous'!B122 -> C2H4 | C50: ='DB_Aspen simulation_previous'!C122 -> kmol/hr | D50: ='DB_Aspen simulation_previous'!D122 -> 0 | E50: ='DB_Aspen simulation_previous'!E122 -> 0 | F50: ='DB_Aspen simulation_previous'!F122 -> 338.47624 | G50: ='DB_Aspen simulation_previous'!G122 -> 2511.5369 | H50: ='DB_Aspen simulation_previous'!H122 -> 2167.0134 | I50: ='DB_Aspen simulation_previous'!I122 -> 2.1691536 | ... N50: ='DB_Aspen simulation_previous'!N122 -> 0 | R50: 0 | S50: 0 | T50: 338.47624 | U50: 2511.5369 | V50: 2167.0134 | W50: 2.1691536 | X50: 0.084735456 | Y50: 0.0003748476 | Z50: 0.15035486 | AA50: 0 | AB50: 0
B51: ='DB_Aspen simulation_previous'!B123 -> C2H2 | C51: ='DB_Aspen simulation_previous'!C123 -> kmol/hr | D51: ='DB_Aspen simulation_previous'!D123 -> 0 | E51: ='DB_Aspen simulation_previous'!E123 -> 0 | F51: ='DB_Aspen simulation_previous'!F123 -> 66.628656 | G51: ='DB_Aspen simulation_previous'!G123 -> 2624.5266 | H51: ='DB_Aspen simulation_previous'!H123 -> 2.6065817 | I51: ='DB_Aspen simulation_previous'!I123 -> 2554.23 | ... N51: ='DB_Aspen simulation_previous'!N123 -> 0 | R51: 0 | S51: 0 | T51: 66.628656 | U51: 2624.5266 | V51: 2.6065817 | W51: 2554.23 | X51: 0.14815622 | Y51: 0.0046312008 | Z51: 0.0032250312 | AA51: 0 | AB51: 0
B52: ='DB_Aspen simulation_previous'!B124 -> C3-C5 | C52: ='DB_Aspen simulation_previous'!C124 -> kmol/hr | D52: ='DB_Aspen simulation_previous'!D124 -> 0 | E52: ='DB_Aspen simulation_previous'!E124 -> 0 | F52: ='DB_Aspen simulation_previous'!F124 -> 0 | G52: ='DB_Aspen simulation_previous'!G124 -> 0 | H52: ='DB_Aspen simulation_previous'!H124 -> 0 | I52: ='DB_Aspen simulation_previous'!I124 -> 0 | ... N52: ='DB_Aspen simulation_previous'!N124 -> 0 | R52: 0 | S52: 0 | T52: 0 | U52: 0 | V52: 0 | W52: 0 | X52: 0 | Y52: 0 | Z52: 0 | AA52: 0 | AB52: 0
B53: ='DB_Aspen simulation_previous'!B125 -> BEN | C53: ='DB_Aspen simulation_previous'!C125 -> kmol/hr | D53: ='DB_Aspen simulation_previous'!D125 -> 0 | E53: ='DB_Aspen simulation_previous'!E125 -> 0 | F53: ='DB_Aspen simulation_previous'!F125 -> 3.5999699e-07 | G53: ='DB_Aspen simulation_previous'!G125 -> 153.98553 | H53: ='DB_Aspen simulation_previous'!H125 -> 5.2571404e-239 | I53: ='DB_Aspen simulation_previous'!I125 -> 7.0036464 | ... N53: ='DB_Aspen simulation_previous'!N125 -> 0 | R53: 0 | S53: 0 | T53: 3.5999699e-07 | U53: 153.98553 | V53: 5.2571404e-239 | W53: 7.0036464 | X53: 2.2504466 | Y53: 144.71826 | Z53: 6.6589645e-18 | AA53: 0 | AB53: 0
B54: ='DB_Aspen simulation_previous'!B126 -> NAP | C54: ='DB_Aspen simulation_previous'!C126 -> kmol/hr | D54: ='DB_Aspen simulation_previous'!D126 -> 0 | E54: ='DB_Aspen simulation_previous'!E126 -> 0 | F54: ='DB_Aspen simulation_previous'!F126 -> 1.8118093e-56 | G54: ='DB_Aspen simulation_previous'!G126 -> 33.068929 | H54: ='DB_Aspen simulation_previous'!H126 -> 0 | I54: ='DB_Aspen simulation_previous'!I126 -> 7.4870779e-06 | ... N54: ='DB_Aspen simulation_previous'!N126 -> 0 | R54: 0 | S54: 0 | T54: 1.8118093e-56 | U54: 33.068929 | V54: 0 | W54: 7.4870779e-06 | X54: 32.199125 | Y54: 0.86903727 | Z54: 0 | AA54: 0 | AB54: 0
B55: ='DB_Aspen simulation_previous'!B127 -> C | C55: ='DB_Aspen simulation_previous'!C127 -> kmol/hr | D55: ='DB_Aspen simulation_previous'!D127 -> 0 | E55: ='DB_Aspen simulation_previous'!E127 -> 0 | F55: ='DB_Aspen simulation_previous'!F127 -> 0 | G55: ='DB_Aspen simulation_previous'!G127 -> 0 | H55: ='DB_Aspen simulation_previous'!H127 -> 0 | I55: ='DB_Aspen simulation_previous'!I127 -> 0 | ... N55: ='DB_Aspen simulation_previous'!N127 -> 1392.0025 | R55: 0 | S55: 0 | T55: 0 | U55: 0 | V55: 0 | W55: 0 | X55: 0 | Y55: 0 | Z55: 0 | AA55: 0 | AB55: 1392.0025
B56: ='DB_Aspen simulation_previous'!B128 -> WATER | C56: ='DB_Aspen simulation_previous'!C128 -> kmol/hr | D56: ='DB_Aspen simulation_previous'!D128 -> 0 | E56: ='DB_Aspen simulation_previous'!E128 -> 0 | F56: ='DB_Aspen simulation_previous'!F128 -> 0 | G56: ='DB_Aspen simulation_previous'!G128 -> 0 | H56: ='DB_Aspen simulation_previous'!H128 -> 0 | I56: ='DB_Aspen simulation_previous'!I128 -> 0 | ... N56: ='DB_Aspen simulation_previous'!N128 -> 0 | R56: 0 | S56: 0 | T56: 0 | U56: 0 | V56: 0 | W56: 0 | X56: 0 | Y56: 0 | Z56: 0 | AA56: 0 | AB56: 0
B57: ='DB_Aspen simulation_previous'!B129 -> O2 | C57: ='DB_Aspen simulation_previous'!C129 -> kmol/hr | D57: ='DB_Aspen simulation_previous'!D129 -> 0 | E57: ='DB_Aspen simulation_previous'!E129 -> 1400 | F57: ='DB_Aspen simulation_previous'!F129 -> 0 | G57: ='DB_Aspen simulation_previous'!G129 -> 0 | H57: ='DB_Aspen simulation_previous'!H129 -> 0 | I57: ='DB_Aspen simulation_previous'!I129 -> 0 | ... N57: ='DB_Aspen simulation_previous'!N129 -> 0 | R57: 0 | S57: 1400 | T57: 0 | U57: 0 | V57: 0 | W57: 0 | X57: 0 | Y57: 0 | Z57: 0 | AA57: 7.9975 | AB57: 0
B58: ='DB_Aspen simulation_previous'!B130 -> CO2 | C58: ='DB_Aspen simulation_previous'!C130 -> kmol/hr | D58: ='DB_Aspen simulation_previous'!D130 -> 0 | E58: ='DB_Aspen simulation_previous'!E130 -> 0 | F58: ='DB_Aspen simulation_previous'!F130 -> 0 | G58: ='DB_Aspen simulation_previous'!G130 -> 0 | H58: ='DB_Aspen simulation_previous'!H130 -> 0 | I58: ='DB_Aspen simulation_previous'!I130 -> 0 | ... N58: ='DB_Aspen simulation_previous'!N130 -> 0 | R58: 0 | S58: 0 | T58: 0 | U58: 0 | V58: 0 | W58: 0 | X58: 0 | Y58: 0 | Z58: 0 | AA58: 1392.0025 | AB58: 0
B59: ='DB_Aspen simulation_previous'!B144 -> Mass Flows | C59: ='DB_Aspen simulation_previous'!C144 -> kg/hr | D59: ='DB_Aspen simulation_previous'!D144 -> 211552.67 | E59: ='DB_Aspen simulation_previous'!E144 -> 44798.32 | F59: ='DB_Aspen simulation_previous'!F144 -> 1028831.7 | G59: ='DB_Aspen simulation_previous'!G144 -> 1012012.5 | H59: ='DB_Aspen simulation_previous'!H144 -> 60867.667 | I59: ='DB_Aspen simulation_previous'!I144 -> 70796.472 | ... N59: ='DB_Aspen simulation_previous'!N144 -> 16719.342
B60: ='DB_Aspen simulation_previous'!B145 -> H2 | C60: ='DB_Aspen simulation_previous'!C145 -> kg/hr | D60: ='DB_Aspen simulation_previous'!D145 -> 0 | E60: ='DB_Aspen simulation_previous'!E145 -> 0 | F60: ='DB_Aspen simulation_previous'!F145 -> 364610.22 | G60: ='DB_Aspen simulation_previous'!G145 -> 398426.26 | H60: ='DB_Aspen simulation_previous'!H145 -> 2.1245063e-09 | I60: ='DB_Aspen simulation_previous'!I145 -> 4.3749578e-39 | ... N60: ='DB_Aspen simulation_previous'!N145 -> 0
B61: ='DB_Aspen simulation_previous'!B146 -> CH4 | C61: ='DB_Aspen simulation_previous'!C146 -> kg/hr | D61: ='DB_Aspen simulation_previous'!D146 -> 211552.67 | E61: ='DB_Aspen simulation_previous'!E146 -> 0 | F61: ='DB_Aspen simulation_previous'!F146 -> 652875.12 | G61: ='DB_Aspen simulation_previous'!G146 -> 454724.6 | H61: ='DB_Aspen simulation_previous'!H146 -> 6.9218306 | I61: ='DB_Aspen simulation_previous'!I146 -> 1.8120331e-13 | ... N61: ='DB_Aspen simulation_previous'!N146 -> 0
B62: ='DB_Aspen simulation_previous'!B147 -> C2H6 | C62: ='DB_Aspen simulation_previous'!C147 -> kg/hr | D62: ='DB_Aspen simulation_previous'!D147 -> 0 | E62: ='DB_Aspen simulation_previous'!E147 -> 0 | F62: ='DB_Aspen simulation_previous'!F147 -> 115.9964 | G62: ='DB_Aspen simulation_previous'!G147 -> 3799.5111 | H62: ='DB_Aspen simulation_previous'!H147 -> 2.839122e-11 | I62: ='DB_Aspen simulation_previous'!I147 -> 3681.8027 | ... N62: ='DB_Aspen simulation_previous'!N147 -> 0
B63: ='DB_Aspen simulation_previous'!B148 -> C2H4 | C63: ='DB_Aspen simulation_previous'!C148 -> kg/hr | D63: ='DB_Aspen simulation_previous'!D148 -> 0 | E63: ='DB_Aspen simulation_previous'!E148 -> 0 | F63: ='DB_Aspen simulation_previous'!F148 -> 9495.5312 | G63: ='DB_Aspen simulation_previous'!G148 -> 70458.053 | H63: ='DB_Aspen simulation_previous'!H148 -> 60792.875 | I63: ='DB_Aspen simulation_previous'!I148 -> 60.852914 | ... N63: ='DB_Aspen simulation_previous'!N148 -> 0
B64: ='DB_Aspen simulation_previous'!B149 -> C2H2 | C64: ='DB_Aspen simulation_previous'!C149 -> kg/hr | D64: ='DB_Aspen simulation_previous'!D149 -> 0 | E64: ='DB_Aspen simulation_previous'!E149 -> 0 | F64: ='DB_Aspen simulation_previous'!F149 -> 1734.869 | G64: ='DB_Aspen simulation_previous'!G149 -> 68337.109 | H64: ='DB_Aspen simulation_previous'!H149 -> 67.869862 | I64: ='DB_Aspen simulation_previous'!I149 -> 66506.735 | ... N64: ='DB_Aspen simulation_previous'!N149 -> 0
B65: ='DB_Aspen simulation_previous'!B150 -> C3-C5 | C65: ='DB_Aspen simulation_previous'!C150 -> kg/hr | D65: ='DB_Aspen simulation_previous'!D150 -> 0 | E65: ='DB_Aspen simulation_previous'!E150 -> 0 | F65: ='DB_Aspen simulation_previous'!F150 -> 0 | G65: ='DB_Aspen simulation_previous'!G150 -> 0 | H65: ='DB_Aspen simulation_previous'!H150 -> 0 | I65: ='DB_Aspen simulation_previous'!I150 -> 0 | ... N65: ='DB_Aspen simulation_previous'!N150 -> 0
B66: ='DB_Aspen simulation_previous'!B151 -> BEN | C66: ='DB_Aspen simulation_previous'!C151 -> kg/hr | D66: ='DB_Aspen simulation_previous'!D151 -> 0 | E66: ='DB_Aspen simulation_previous'!E151 -> 0 | F66: ='DB_Aspen simulation_previous'!F151 -> 2.8120675e-05 | G66: ='DB_Aspen simulation_previous'!G151 -> 12028.371 | H66: ='DB_Aspen simulation_previous'!H151 -> 4.1065437e-237 | I66: ='DB_Aspen simulation_previous'!I151 -> 547.08032 | ... N66: ='DB_Aspen simulation_previous'!N151 -> 0
B67: ='DB_Aspen simulation_previous'!B152 -> NAP | C67: ='DB_Aspen simulation_previous'!C152 -> kg/hr | D67: ='DB_Aspen simulation_previous'!D152 -> 0 | E67: ='DB_Aspen simulation_previous'!E152 -> 0 | F67: ='DB_Aspen simulation_previous'!F152 -> 2.3222597e-54 | G67: ='DB_Aspen simulation_previous'!G152 -> 4238.5611 | H67: ='DB_Aspen simulation_previous'!H152 -> 0 | I67: ='DB_Aspen simulation_previous'!I152 -> 0.00095964512 | ... N67: ='DB_Aspen simulation_previous'!N152 -> 0
B68: ='DB_Aspen simulation_previous'!B153 -> C | C68: ='DB_Aspen simulation_previous'!C153 -> kg/hr | D68: ='DB_Aspen simulation_previous'!D153 -> 0 | E68: ='DB_Aspen simulation_previous'!E153 -> 0 | F68: ='DB_Aspen simulation_previous'!F153 -> 0 | G68: ='DB_Aspen simulation_previous'!G153 -> 0 | H68: ='DB_Aspen simulation_previous'!H153 -> 0 | I68: ='DB_Aspen simulation_previous'!I153 -> 0 | ... N68: ='DB_Aspen simulation_previous'!N153 -> 16719.342
B69: ='DB_Aspen simulation_previous'!B154 -> WATER | C69: ='DB_Aspen simulation_previous'!C154 -> kg/hr | D69: ='DB_Aspen simulation_previous'!D154 -> 0 | E69: ='DB_Aspen simulation_previous'!E154 -> 0 | F69: ='DB_Aspen simulation_previous'!F154 -> 0 | G69: ='DB_Aspen simulation_previous'!G154 -> 0 | H69: ='DB_Aspen simulation_previous'!H154 -> 0 | I69: ='DB_Aspen simulation_previous'!I154 -> 0 | ... N69: ='DB_Aspen simulation_previous'!N154 -> 0
B70: ='DB_Aspen simulation_previous'!B155 -> O2 | C70: ='DB_Aspen simulation_previous'!C155 -> kg/hr | D70: ='DB_Aspen simulation_previous'!D155 -> 0 | E70: ='DB_Aspen simulation_previous'!E155 -> 44798.32 | F70: ='DB_Aspen simulation_previous'!F155 -> 0 | G70: ='DB_Aspen simulation_previous'!G155 -> 0 | H70: ='DB_Aspen simulation_previous'!H155 -> 0 | I70: ='DB_Aspen simulation_previous'!I155 -> 0 | ... N70: ='DB_Aspen simulation_previous'!N155 -> 0
B71: ='DB_Aspen simulation_previous'!B156 -> CO2 | C71: ='DB_Aspen simulation_previous'!C156 -> kg/hr | D71: ='DB_Aspen simulation_previous'!D156 -> 0 | E71: ='DB_Aspen simulation_previous'!E156 -> 0 | F71: ='DB_Aspen simulation_previous'!F156 -> 0 | G71: ='DB_Aspen simulation_previous'!G156 -> 0 | H71: ='DB_Aspen simulation_previous'!H156 -> 0 | I71: ='DB_Aspen simulation_previous'!I156 -> 0 | ... N71: ='DB_Aspen simulation_previous'!N156 -> 0
B72: ='DB_Aspen simulation_previous'!B170 -> Volume Flow | C72: ='DB_Aspen simulation_previous'!C170 -> cum/hr | D72: ='DB_Aspen simulation_previous'!D170 -> 327437.65 | E72: ='DB_Aspen simulation_previous'!E170 -> 3502.9029 | F72: ='DB_Aspen simulation_previous'!F170 -> 27389526 | G72: ='DB_Aspen simulation_previous'!G170 -> 28557235 | H72: ='DB_Aspen simulation_previous'!H170 -> 98.383621 | I72: ='DB_Aspen simulation_previous'!I170 -> 109.68343 | ... N72: ='DB_Aspen simulation_previous'!N170 -> 28.555045
B74: CARBON EFFICIENCY
B75: One-pass conversion (%) | F75: =(F48-G48)/F48 -> 0.30350448
B76: Overall conversion (%)_Ethylene | F76: =H46*2/D46 -> 0.3291248
B77: Overall conversion (%)_Hydrocarbon | F77: =(SUM(H49:I51)*2+J54*10+J53*6+K53*6+K54*10)/D48 -> 0.82729831
B79: ENERGY EFFICIENCY | H79: HHV | I79: (MJ/kg) | J79: (kWh/kg)
B80: Energy efficiency (%)_For only Ethylene | F80: =F88/(F84+F94) -> 0.1452582 | H80: CH4 | I80: 55.5 | J80: =I80/3.6 -> 15.416667 | M80: 169696.1 | N80: =M80*I80 -> 9418133.6 | O80: MJ
B81: Energy efficiency (%)_For all Hydrocarbon | F81: =F87/(F84+F94) -> 0.59750678 | H81: H2 | I81: 141.7 | J81: =I81/3.6 -> 39.361111 | N81: 2250 | O81: Gcal
B82: Improve by burning coke_Hydrocarbon | F82: =F81-(F87/(F84+F94+F100)) -> 0.016735927 | H82: C2H6 | I82: 51.9 | J82: =I82/3.6 -> 14.416667
H83: C2H4 | I83: 50.3 | J83: =I83/3.6 -> 13.972222
B84: Heat flow in raw material (MJ/h) | F84: =F85 -> 11741173 | H84: C2H2 | I84: 49.9 | J84: =I84/3.6 -> 13.861111
C85: Methane | F85: =D61*I80 -> 11741173 | H85: BEN | I85: 41.8 | J85: =I85/3.6 -> 11.611111
H86: NAP | I86: =17303*2.326/1000 -> 40.246778 | J86: =I86/3.6 -> 11.179661
B87: Heat flow in production (MJ/h) | F87: =SUM(F88:F92) -> 12592257 | H87: C | I87: 32.8 | J87: =I87/3.6 -> 9.1111111
C88: Ethylene | F88: =H63*I83+H64*I84 -> 3061268.3 | H88: C2-C5 | I88: 45.75 | J88: =I88/3.6 -> 12.708333
C89: C2 (Ethane, Acethylene) | F89: =I62*I82+I63*I83+I64*I84+I66*I85 -> 3535700.5 | H89: TOL | I89: 40.589 | J89: =I89/3.6 -> 11.274722
C90: Benzene | F90: =K66*I85+K67*I86 -> 477009.85
C91: Napthalene | F91: =J61*I80+J62*I82+J63*I83+J64*I84+J66*I85+J67*I86 -> 173952.38
C92: Hydrogen | F92: =L60*I81+L61*I80+L63*I83+L64*I84 -> 5344325.6
B94: Utility consumption (MJ/h) | F94: =SUM(F95:F99) -> 9333494.4 | H94: =F94/3.6 -> 2592637.3
C95: Refrigeration | F95: ='DB_Aspen simulation_previous'!L173 -> 1106743 | G95: =F95/3.6 -> 307428.6
C96: Electicity | F96: ='DB_Aspen simulation_previous'!L182 -> 3447411 | G96: =F96/3.6 -> 957614.17
C97: Fired heat | F97: ='DB_Aspen simulation_previous'!L195 -> 4484990 | G97: =F97/3.6 -> 1245830.6
C98: High pressure steam | F98: ='DB_Aspen simulation_previous'!L200 -> 7114.45 | G98: =F98/3.6 -> 1976.2361
C99: Low pressure steam | F99: ='DB_Aspen simulation_previous'!L205 -> 287236 | G99: =F99/3.6 -> 79787.778
B100: Heat recovery by burning coke (included) (MJ) | F100: 607303.38

Sheet 5. Sensitivity
B2: -20%: | C2: Case 4_FH | D2: Case 4_efurnace | E2: Case 5_FH | F2: Case 5_efurnace | H2: +20%: | I2: Case 4_FH | J2: Case 4_efurnace | K2: Case 5_FH | L2: Case 5_efurnace | O2: -20% | P2: Based | Q2: +20%
C3: 0.011398261 | D3: 0.72559845 | E3: 0.63378365 | F3: 1.756879 | I3: 0.011398261 | J3: 0.72559845 | K3: 0.63378365 | L3: 1.756879
B4: Natural gas price ($/MMBTU) | C4: -0.091276695 | D4: 0.6547902 | E4: 0.52282631 | F4: 1.690355 | H4: Natural gas price ($/MMBTU) | I4: 0.11407322 | J4: 0.7964067 | K4: 0.744741 | L4: 1.8234031 | N4: Natural gas price ($/MMBTU) | O4: =P4*0.8 -> 2.616 | P4: 3.27 | Q4: =P4*1.2 -> 3.924
B5: By-product H2 price ($/kg) | C5: 0.20951934 | D5: 0.92371953 | E5: 0.8131482 | F5: 1.9362436 | H5: By-product H2 price ($/kg) | I5: -0.18672282 | J5: 0.52747737 | K5: 0.45441911 | L5: 1.5775145 | N5: By-product H2 price ($/kg) | O5: =P5*0.8 -> 3.16 | P5: 3.95 | Q5: =P5*1.2 -> 4.74
B6: Grid electricity ($/kWh) | C6: -0.033692491 | D6: 0.72559845 | E6: 0.5324055 | F6: 1.756879 | H6: Grid electricity ($/kWh) | I6: 0.056489013 | J6: 0.72559845 | K6: 0.73516181 | L6: 1.756879 | N6: Grid electricity ($/kWh) | O6: =P6*0.8 -> 0.0552 | P6: 0.069 | Q6: =P6*1.2 -> 0.0828
B7: Renewable electricity ($/kWh) | C7: 0.011398261 | D7: 0.47269003 | E7: 0.63378365 | F7: 1.3457684 | H7: Renewable electricity ($/kWh) | I7: 0.011398261 | J7: 0.97850688 | K7: 0.63378365 | L7: 2.1679897 | N7: Renewable electricity ($/kWh) | O7: =P7*0.8 -> 0.0768 | P7: 0.096 | Q7: =P7*1.2 -> 0.1152
B8: Interest rate (%) | C8: -0.02132741 | D8: 0.69503012 | E8: 0.59391008 | F8: 1.7172206 | H8: Interest rate (%) | I8: 0.045846189 | J8: 0.75777551 | K8: 0.67575566 | L8: 1.7986246 | N8: Interest rate (%) | O8: =P8*0.8 -> 0.064 | P8: 0.08 | Q8: =P8*1.2 -> 0.096
B12: =C2 -> Case 4_FH | C12: Based UPC | D12: =C3 -> 0.011398261
C13: Value | E13: Increase
C14: -20% | D14: +20% | E14: -20% | F14: +20%
B15: Natural gas price ($/MMBTU) | C15: =C4 -> -0.091276695 | D15: =I4 -> 0.11407322 | E15: =(C15-$D$12)/$D$12 -> -9.0079491 | F15: =(D15-$D$12)/$D$12 -> 9.0079491
B16: By-product H2 price ($/kg) | C16: =C5 -> 0.20951934 | D16: =I5 -> -0.18672282 | E16: =(C16-$D$12)/$D$12 -> 17.381694 | F16: =(D16-$D$12)/$D$12 -> -17.381694
B17: Grid electricity ($/kWh) | C17: =C6 -> -0.033692491 | D17: =I6 -> 0.056489013 | E17: =(C17-$D$12)/$D$12 -> -3.9559325 | F17: =(D17-$D$12)/$D$12 -> 3.9559325
B18: Renewable electricity ($/kWh) | C18: =C7 -> 0.011398261 | D18: =I7 -> 0.011398261 | E18: =(C18-$D$12)/$D$12 -> 0 | F18: =(D18-$D$12)/$D$12 -> 0
B19: Interest rate (%) | C19: =C8 -> -0.02132741 | D19: =I8 -> 0.045846189 | E19: =(C19-$D$12)/$D$12 -> -2.8711108 | F19: =(D19-$D$12)/$D$12 -> 3.022209
B21: =D2 -> Case 4_efurnace | C21: Based UPC | D21: =D3 -> 0.72559845
C22: Value | E22: Increase
C23: -20% | D23: +20% | E23: -20% | F23: +20%
B24: Natural gas price ($/MMBTU) | C24: =D4 -> 0.6547902 | D24: =J4 -> 0.7964067 | E24: =(C24-$D$21)/$D$21 -> -0.097585999 | F24: =(D24-$D$21)/$D$21 -> 0.097585999
B25: By-product H2 price ($/kg) | C25: =D5 -> 0.92371953 | D25: =J5 -> 0.52747737 | E25: =(C25-$D$21)/$D$21 -> 0.27304507 | F25: =(D25-$D$21)/$D$21 -> -0.27304507
B26: Grid electricity ($/kWh) | C26: =D6 -> 0.72559845 | D26: =J6 -> 0.72559845 | E26: =(C26-$D$21)/$D$21 -> 0 | F26: =(D26-$D$21)/$D$21 -> 0
B27: Renewable electricity ($/kWh) | C27: =D7 -> 0.47269003 | D27: =J7 -> 0.97850688 | E27: =(C27-$D$21)/$D$21 -> -0.3485515 | F27: =(D27-$D$21)/$D$21 -> 0.3485515
B28: Interest rate (%) | C28: =D8 -> 0.69503012 | D28: =J8 -> 0.75777551 | E28: =(C28-$D$21)/$D$21 -> -0.042128444 | F28: =(D28-$D$21)/$D$21 -> 0.044345542
B30: =E2 -> Case 5_FH | C30: Based UPC | D30: =E3 -> 0.63378365
C31: Value | E31: Increase
C32: -20% | D32: +20% | E32: -20% | F32: +20%
B33: Natural gas price ($/MMBTU) | C33: =E4 -> 0.52282631 | D33: =K4 -> 0.744741 | E33: =(C33-$D$30)/$D$30 -> -0.17507133 | F33: =(D33-$D$30)/$D$30 -> 0.17507133
B34: By-product H2 price ($/kg) | C34: =E5 -> 0.8131482 | D34: =K5 -> 0.45441911 | E34: =(C34-$D$30)/$D$30 -> 0.28300595 | F34: =(D34-$D$30)/$D$30 -> -0.28300595
B35: Grid electricity ($/kWh) | C35: =E6 -> 0.5324055 | D35: =K6 -> 0.73516181 | E35: =(C35-$D$30)/$D$30 -> -0.15995703 | F35: =(D35-$D$30)/$D$30 -> 0.15995703
B36: Renewable electricity ($/kWh) | C36: =E7 -> 0.63378365 | D36: =K7 -> 0.63378365 | E36: =(C36-$D$30)/$D$30 -> 0 | F36: =(D36-$D$30)/$D$30 -> 0
B37: Interest rate (%) | C37: =E8 -> 0.59391008 | D37: =K8 -> 0.67575566 | E37: =(C37-$D$30)/$D$30 -> -0.062913541 | F37: =(D37-$D$30)/$D$30 -> 0.066224498
B39: =F2 -> Case 5_efurnace | C39: Based UPC | D39: =F3 -> 1.756879
C40: Value | E40: Increase
C41: -20% | D41: +20% | E41: -20% | F41: +20%
B42: Natural gas price ($/MMBTU) | C42: =F4 -> 1.690355 | D42: =L4 -> 1.8234031 | E42: =(C42-$D$39)/$D$39 -> -0.037864893 | F42: =(D42-$D$39)/$D$39 -> 0.037864893
B43: By-product H2 price ($/kg) | C43: =F5 -> 1.9362436 | D43: =L5 -> 1.5775145 | E43: =(C43-$D$39)/$D$39 -> 0.10209271 | F43: =(D43-$D$39)/$D$39 -> -0.10209271
B44: Grid electricity ($/kWh) | C44: =F6 -> 1.756879 | D44: =L6 -> 1.756879 | E44: =(C44-$D$39)/$D$39 -> 0 | F44: =(D44-$D$39)/$D$39 -> 0
B45: Renewable electricity ($/kWh) | C45: =F7 -> 1.3457684 | D45: =L7 -> 2.1679897 | E45: =(C45-$D$39)/$D$39 -> -0.23400053 | F45: =(D45-$D$39)/$D$39 -> 0.23400053
B46: Interest rate (%) | C46: =F8 -> 1.7172206 | D46: =L8 -> 1.7986246 | E46: =(C46-$D$39)/$D$39 -> -0.02257324 | F46: =(D46-$D$39)/$D$39 -> 0.023761204

Sheet 5. HEN_Worksheet_Case4
C2: Heat exchanger | E2: Cold stream | F2: Cold T in | H2: Cold T out | J2: Hot stream | K2: Hot T in | M2: Hot T out | O2: Load (kJ/h) | P2: Load (MW) | Q2: Area (m2)
B3: 1 | C3: E-110 | E3: 39_To_42 | F3: -152.58127 | H3: 35 | I3: 1 | J3: 5_To_10 | K3: 1230 | M3: 697.77413 | N3: FALSE | O3: 77245002 | P3: =O3/3600000 -> 21.456945 | Q3: 2209.505 | S3: 1195 | T3: 850.3554
B4: 2 | C4: E-111 | E4: 3_To_4 | F4: 33.11567 | H4: 708.07038 | I4: 1 | J4: 5_To_10 | K4: 1230 | M4: 697.77413 | N4: FALSE | O4: 2.7153907e+09 | P4: =O4/3600000 -> 754.27521 | Q4: 231868.91 | S4: 521.92962 | T4: 664.65846
B5: 3 | C5: E-112 | E5: 31_To_35 | F5: 15 | H5: 35 | I5: 1 | J5: 5_To_10 | K5: 697.77413 | M5: 666.15607 | N5: FALSE | O5: 41005773 | P5: =O5/3600000 -> 11.390492 | Q5: 524.36286 | S5: 662.77413 | T5: 651.15607
B6: 4 | C6: E-113 | E6: 45_To_46 | F6: -124.97704 | H6: 35 | I6: 1 | J6: 5_To_10 | K6: 697.77413 | M6: 666.15607 | N6: FALSE | O6: 1.0591177e+08 | P6: =O6/3600000 -> 29.419937 | Q6: 1517.8128 | S6: 662.77413 | T6: 791.13311
B7: 5 | C7: E-114 | E7: 31_To_35 | F7: 1.663465 | H7: 15 | I7: 1 | J7: 14_To_15 | K7: 35 | M7: 27.114621 | N7: 1 | O7: 27343746 | P7: =O7/3600000 -> 7.5954851 | Q7: 2627.52 | S7: 20 | T7: 25.451156
B8: 6 | C8: E-115 | E8: CW | F8: 20 | H8: 25 | I8: FALSE | J8: 5_To_10 | K8: 666.15607 | M8: 95.001737 | N8: 1 | O8: 2.391974e+09 | P8: =O8/3600000 -> 664.43723 | Q8: 63656.534 | S8: 641.15607 | T8: 75.001737
B9: 7 | C9: E-116 | E9: 31_To_35 | F9: -119.47366 | H9: 1.663465 | I9: 1 | J9: 5_To_10 | K9: 95.001737 | M9: 30 | N9: 1 | O9: 2.4836607e+08 | P9: =O9/3600000 -> 68.990576 | Q9: 18828.978 | S9: 93.338272 | T9: 149.47366
B10: 8 | C10: E-117 | E10: To Reboiler@T3_TO_28-C2C5 | F10: -87.391501 | H10: -82.18093 | I10: FALSE | J10: 22_To_24 | K10: -60 | M10: -75.406232 | N10: 1 | O10: 52482156 | P10: =O10/3600000 -> 14.578377 | Q10: 3627.0799 | S10: 22.18093 | T10: 11.985269
B11: 9 | C11: E-118 | E11: 31_To_35 | F11: -154.96705 | H11: -119.47366 | I11: 1 | J11: To Condenser@T3_TO_27-ETHYL | K11: -104.12595 | M11: -104.19312 | N11: 1 | O11: 72771688 | P11: =O11/3600000 -> 20.214358 | Q11: 2547.8667 | S11: 15.347708 | T11: 50.773925
B12: 10 | C12: E-119 | E12: To Reboiler@T2_TO_26-C2+ | F12: -56.348231 | H12: -51.280823 | I12: 1 | J12: 17_To_18 | K12: 20 | M12: -28.567041 | N12: 1 | O12: 1.753865e+08 | P12: =O12/3600000 -> 48.718471 | Q12: 3506.0192 | S12: 71.280823 | T12: 27.781191
B13: 11 | C13: E-120 | E13: To Reboiler@T3_TO_28-C2C5 | F13: -87.391501 | H13: -82.18093 | I13: FALSE | J13: V3_heat | K13: -31.127413 | M13: -44.433369 | N13: 1 | O13: 45654056 | P13: =O13/3600000 -> 12.681682 | Q13: 1544.7447 | S13: 51.053517 | T13: 42.958132
B14: 12 | C14: E-121 | E14: CRYOTEMP | F14: -269.24253 | H14: -269 | I14: FALSE | J14: 29_To_30 | K14: -140 | M14: -159.13216 | N14: 1 | O14: 1.1640974e+08 | P14: =O14/3600000 -> 32.336038 | Q14: 452.97963 | S14: 129 | T14: 110.11037
B15: 13 | C15: E-122 | E15: CRYOTEMP | F15: -269.24253 | H15: -269 | I15: FALSE | J15: To Condenser@T1_TO_21 | K15: 38.387637 | M15: 0.89491272 | N15: 1 | O15: 323821.28 | P15: =O15/3600000 -> 0.089950357 | Q15: 1.0619544 | S15: 307.38764 | T15: 270.13744
B16: 14 | C16: E-123 | E16: CRYOTEMP | F16: -269.24253 | H16: -269 | I16: FALSE | J16: To Condenser@T2_TO_45Duplicate | K16: -124.73484 | M16: -124.97704 | N16: 1 | O16: 18896309 | P16: =O16/3600000 -> 5.2489746 | Q16: 67.131286 | S16: 144.26516 | T16: 144.26549
B17: 15 | C17: E-124 | E17: To Reboiler@T1_TO_20-BEN | F17: 250.52967 | H17: 251.23443 | I17: 1 | J17: FIRED | K17: 2000 | M17: 830 | N17: FALSE | O17: 18534905 | P17: =O17/3600000 -> 5.1485847 | Q17: 44.84747 | S17: 1748.7656 | T17: 579.47033
B18: 16 | C18: E-125 | E18: 31_To_35 | F18: -167 | H18: -154.96705 | I18: 1 | J18: 14_To_15 | K18: 27.114621 | M18: 20 | N18: 1 | O18: 24671025 | P18: =O18/3600000 -> 6.8530624 | Q18: 280.39569 | S18: 182.08167 | T18: 187
B19: 17 | C19: E-126 | E19: CRYOTEMP | F19: -270 | H19: -269.24253 | I19: FALSE | J19: V5_heat | K19: -159.13216 | M19: -167 | N19: 1 | O19: 37516725 | P19: =O19/3600000 -> 10.421313 | Q19: 564.50129 | S19: 110.11037 | T19: 103
B20: 18 | C20: E-127 | E20: CRYOTEMP | F20: -270 | H20: -269.24253 | I20: FALSE | J20: V4_heat | K20: -103.3156 | M20: -140 | N20: 1 | O20: 2.8346503e+08 | P20: =O20/3600000 -> 78.740286 | Q20: 3086.0353 | S20: 165.92693 | T20: 130
B21: 19 | C21: E-128 | E21: CRYOTEMP | F21: -270 | H21: -269.24253 | I21: FALSE | J21: 22_To_24 | K21: -75.406232 | M21: -103.3156 | N21: 1 | O21: 1.0261631e+08 | P21: =O21/3600000 -> 28.50453 | Q21: 628.58755 | S21: 193.8363 | T21: 166.6844
B22: 20 | C22: E-129 | E22: V1_heat | F22: 34.865664 | H22: 35 | I22: 1 | J22: LPS | K22: 125 | M22: 124.05067 | N22: FALSE | O22: 467559.65 | P22: =O22/3600000 -> 0.12987768 | Q22: 7.4899246 | S22: 90 | T22: 89.185005
B23: 21 | C23: E-130 | E23: To Reboiler@T3_TO_28-C2C5 | F23: -88.318585 | H23: -87.391501 | I23: FALSE | J23: 17_To_18 | K23: -28.567041 | M23: -31.141817 | N23: 1 | O23: 9298096.2 | P23: =O23/3600000 -> 2.5828045 | Q23: 135.92547 | S23: 58.82446 | T23: 57.176767
B24: 22 | C24: E-131 | E24: 39_To_42 | F24: -169.27894 | H24: -152.58127 | I24: 1 | J24: To Condenser@T3_TO_27-ETHYL | K24: -104.19312 | M24: -106.01723 | N24: 1 | O24: 1.0315914e+08 | P24: =O24/3600000 -> 28.655317 | Q24: 296.12329 | S24: 48.388147 | T24: 63.261706
B25: 23 | C25: E-132 | E25: To Reboiler@T3_TO_28-C2C5 | F25: -88.318585 | H25: -87.391501 | I25: FALSE | J25: V3_heat | K25: -44.433369 | M25: -60 | N25: 1 | O25: 53410658 | P25: =O25/3600000 -> 14.836294 | Q25: 2179.8082 | S25: 42.958132 | T25: 28.318585
B26: 24 | C26: E-133 | E26: V1_heat | F26: 34.858494 | H26: 34.865664 | I26: 1 | J26: LPS | K26: 124.05067 | M26: 124 | N26: FALSE | O26: 24954.91 | P26: =O26/3600000 -> 0.0069319196 | Q26: 0.40167801 | S26: 89.185005 | T26: 89.141506
A29: Heating requirement | C29: Heat exchanger | E29: Cold stream | F29: Cold T in | H29: Cold T out | J29: Hot stream | K29: Hot T in | M29: Hot T out | O29: Load (kJ/h) | P29: Load (MW) | Q29: Area (m2) | W29: Heating requirement | Y29: Cooling requirement
A30: Cat | B30: 1 | C30: =C4 -> E-111 | D30: =D4 -> 0 | E30: =E4 -> 3_To_4 | F30: =F4 -> 33.11567 | G30: =G4 -> 0 | H30: =H4 -> 708.07038 | I30: =I4 -> 1 | J30: =J4 -> 5_To_10 | ... Q30: =Q4 -> 231868.91 | S30: =S4 -> 521.92962 | T30: =T4 -> 664.65846 | W30: Before | X30: After | Y30: Before | Z30: After
V31: Catalytic conversion | W31: =P30 -> 754.27521 | X31: 0 | Y31: =SUM(P53:P58) -> 1549.9704 | Z31: =P57 -> 664.43723
A32: Compress & G/L sep | B32: 2 | C32: =C17 -> E-124 | D32: =D17 -> 0 | E32: =E17 -> To Reboiler@T1_TO_20-BEN | F32: =F17 -> 250.52967 | G32: =G17 -> 0 | H32: =H17 -> 251.23443 | I32: =I17 -> 1 | J32: =J17 -> FIRED | ... Q32: =Q17 -> 44.84747 | S32: =S17 -> 1748.7656 | T32: =T17 -> 579.47033 | V32: Compression and G/L separation | W32: =SUM(P32:P35) -> 20.121688 | X32: =P32+P34+P35 -> 5.2853943 | Y32: =SUM(P60:P68) -> 113.1851 | Z32: =P64+P65 -> 5.338925
B33: 3 | C33: =C25 -> E-132 | D33: =D25 -> 0 | E33: =E25 -> To Reboiler@T3_TO_28-C2C5 | F33: =F25 -> -88.318585 | G33: =G25 -> 0 | H33: =H25 -> -87.391501 | I33: =I25 -> FALSE | J33: =J25 -> V3_heat | ... Q33: =Q25 -> 2179.8082 | S33: =S25 -> 42.958132 | T33: =T25 -> 28.318585 | V33: Coldbox and cryogenic separation | W33: =SUM(P37:P49) -> 287.9738 | X33: 0 | Y33: =SUM(P70:P75) -> 197.36731 | Z33: =SUM(P71:P74) -> 148.49764
B34: 4 | C34: =C26 -> E-133 | D34: =D26 -> 0 | E34: =E26 -> V1_heat | F34: =F26 -> 34.858494 | G34: =G26 -> 0 | H34: =H26 -> 34.865664 | I34: =I26 -> 1 | J34: =J26 -> LPS | ... Q34: =Q26 -> 0.40167801 | S34: =S26 -> 89.185005 | T34: =T26 -> 89.141506 | V34: SUM | W34: =SUM(W31:W33) -> 1062.3707 | X34: =SUM(X31:X33) -> 5.2853943 | Y34: =SUM(Y31:Y33) -> 1860.5228 | Z34: =SUM(Z31:Z33) -> 818.27379
B35: 5 | C35: =C22 -> E-129 | D35: =D22 -> 0 | E35: =E22 -> V1_heat | F35: =F22 -> 34.865664 | G35: =G22 -> 0 | H35: =H22 -> 35 | I35: =I22 -> 1 | J35: =J22 -> LPS | ... Q35: =Q22 -> 7.4899246 | S35: =S22 -> 90 | T35: =T22 -> 89.185005
A37: Cryogenic separation and recovery | B37: 6 | C37: =C3 -> E-110 | D37: =D3 -> 0 | E37: =E3 -> 39_To_42 | F37: =F3 -> -152.58127 | G37: =G3 -> 0 | H37: =H3 -> 35 | I37: =I3 -> 1 | J37: =J3 -> 5_To_10 | ... Q37: =Q3 -> 2209.505 | S37: =S3 -> 1195 | T37: =T3 -> 850.3554
B38: 7 | C38: =C5 -> E-112 | D38: =D5 -> 0 | E38: =E5 -> 31_To_35 | F38: =F5 -> 15 | G38: =G5 -> 0 | H38: =H5 -> 35 | I38: =I5 -> 1 | J38: =J5 -> 5_To_10 | ... Q38: =Q5 -> 524.36286 | S38: =S5 -> 662.77413 | T38: =T5 -> 651.15607
B39: 8 | C39: =C6 -> E-113 | D39: =D6 -> 0 | E39: =E6 -> 45_To_46 | F39: =F6 -> -124.97704 | G39: =G6 -> 0 | H39: =H6 -> 35 | I39: =I6 -> 1 | J39: =J6 -> 5_To_10 | ... Q39: =Q6 -> 1517.8128 | S39: =S6 -> 662.77413 | T39: =T6 -> 791.13311
B40: 9 | C40: =C7 -> E-114 | D40: =D7 -> 0 | E40: =E7 -> 31_To_35 | F40: =F7 -> 1.663465 | G40: =G7 -> 0 | H40: =H7 -> 15 | I40: =I7 -> 1 | J40: =J7 -> 14_To_15 | ... Q40: =Q7 -> 2627.52 | S40: =S7 -> 20 | T40: =T7 -> 25.451156
B41: 10 | C41: =C9 -> E-116 | D41: =D9 -> 0 | E41: =E9 -> 31_To_35 | F41: =F9 -> -119.47366 | G41: =G9 -> 0 | H41: =H9 -> 1.663465 | I41: =I9 -> 1 | J41: =J9 -> 5_To_10 | ... Q41: =Q9 -> 18828.978 | S41: =S9 -> 93.338272 | T41: =T9 -> 149.47366
B42: 11 | C42: =C10 -> E-117 | D42: =D10 -> 0 | E42: =E10 -> To Reboiler@T3_TO_28-C2C5 | F42: =F10 -> -87.391501 | G42: =G10 -> 0 | H42: =H10 -> -82.18093 | I42: =I10 -> FALSE | J42: =J10 -> 22_To_24 | ... Q42: =Q10 -> 3627.0799 | S42: =S10 -> 22.18093 | T42: =T10 -> 11.985269
B43: 12 | C43: =C11 -> E-118 | D43: =D11 -> 0 | E43: =E11 -> 31_To_35 | F43: =F11 -> -154.96705 | G43: =G11 -> 0 | H43: =H11 -> -119.47366 | I43: =I11 -> 1 | J43: =J11 -> To Condenser@T3_TO_27-ETHYL | ... Q43: =Q11 -> 2547.8667 | S43: =S11 -> 15.347708 | T43: =T11 -> 50.773925
B44: 13 | C44: =C12 -> E-119 | D44: =D12 -> 0 | E44: =E12 -> To Reboiler@T2_TO_26-C2+ | F44: =F12 -> -56.348231 | G44: =G12 -> 0 | H44: =H12 -> -51.280823 | I44: =I12 -> 1 | J44: =J12 -> 17_To_18 | ... Q44: =Q12 -> 3506.0192 | S44: =S12 -> 71.280823 | T44: =T12 -> 27.781191
B45: 14 | C45: =C13 -> E-120 | D45: =D13 -> 0 | E45: =E13 -> To Reboiler@T3_TO_28-C2C5 | F45: =F13 -> -87.391501 | G45: =G13 -> 0 | H45: =H13 -> -82.18093 | I45: =I13 -> FALSE | J45: =J13 -> V3_heat | ... Q45: =Q13 -> 1544.7447 | S45: =S13 -> 51.053517 | T45: =T13 -> 42.958132
B46: 15 | C46: =C18 -> E-125 | D46: =D18 -> 0 | E46: =E18 -> 31_To_35 | F46: =F18 -> -167 | G46: =G18 -> 0 | H46: =H18 -> -154.96705 | I46: =I18 -> 1 | J46: =J18 -> 14_To_15 | ... Q46: =Q18 -> 280.39569 | S46: =S18 -> 182.08167 | T46: =T18 -> 187
B47: 16 | C47: =C23 -> E-130 | D47: =D23 -> 0 | E47: =E23 -> To Reboiler@T3_TO_28-C2C5 | F47: =F23 -> -88.318585 | G47: =G23 -> 0 | H47: =H23 -> -87.391501 | I47: =I23 -> FALSE | J47: =J23 -> 17_To_18 | ... Q47: =Q23 -> 135.92547 | S47: =S23 -> 58.82446 | T47: =T23 -> 57.176767
B48: 17 | C48: =C24 -> E-131 | D48: =D24 -> 0 | E48: =E24 -> 39_To_42 | F48: =F24 -> -169.27894 | G48: =G24 -> 0 | H48: =H24 -> -152.58127 | I48: =I24 -> 1 | J48: =J24 -> To Condenser@T3_TO_27-ETHYL | ... Q48: =Q24 -> 296.12329 | S48: =S24 -> 48.388147 | T48: =T24 -> 63.261706
B49: 18 | C49: =C25 -> E-132 | D49: =D25 -> 0 | E49: =E25 -> To Reboiler@T3_TO_28-C2C5 | F49: =F25 -> -88.318585 | G49: =G25 -> 0 | H49: =H25 -> -87.391501 | I49: =I25 -> FALSE | J49: =J25 -> V3_heat | ... Q49: =Q25 -> 2179.8082 | S49: =S25 -> 42.958132 | T49: =T25 -> 28.318585
A52: Cooling requirement | C52: Heat exchanger | E52: Cold stream | F52: Cold T in | H52: Cold T out | J52: Hot stream | K52: Hot T in | M52: Hot T out | O52: Load (kJ/h) | P52: Load (MW) | Q52: Area (m2)
A53: Cat | B53: 1 | C53: =C3 -> E-110 | D53: =D3 -> 0 | E53: =E3 -> 39_To_42 | F53: =F3 -> -152.58127 | G53: =G3 -> 0 | H53: =H3 -> 35 | I53: =I3 -> 1 | J53: =J3 -> 5_To_10 | ... T53: =T3 -> 850.3554
B54: 2 | C54: =C4 -> E-111 | D54: =D4 -> 0 | E54: =E4 -> 3_To_4 | F54: =F4 -> 33.11567 | G54: =G4 -> 0 | H54: =H4 -> 708.07038 | I54: =I4 -> 1 | J54: =J4 -> 5_To_10 | ... T54: =T4 -> 664.65846
B55: 3 | C55: =C5 -> E-112 | D55: =D5 -> 0 | E55: =E5 -> 31_To_35 | F55: =F5 -> 15 | G55: =G5 -> 0 | H55: =H5 -> 35 | I55: =I5 -> 1 | J55: =J5 -> 5_To_10 | ... T55: =T5 -> 651.15607
B56: 4 | C56: =C6 -> E-113 | D56: =D6 -> 0 | E56: =E6 -> 45_To_46 | F56: =F6 -> -124.97704 | G56: =G6 -> 0 | H56: =H6 -> 35 | I56: =I6 -> 1 | J56: =J6 -> 5_To_10 | ... T56: =T6 -> 791.13311
B57: 5 | C57: =C8 -> E-115 | D57: =D8 -> 0 | E57: =E8 -> CW | F57: =F8 -> 20 | G57: =G8 -> 0 | H57: =H8 -> 25 | I57: =I8 -> FALSE | J57: =J8 -> 5_To_10 | ... T57: =T8 -> 75.001737
B58: 6 | C58: =C9 -> E-116 | D58: =D9 -> 0 | E58: =E9 -> 31_To_35 | F58: =F9 -> -119.47366 | G58: =G9 -> 0 | H58: =H9 -> 1.663465 | I58: =I9 -> 1 | J58: =J9 -> 5_To_10 | ... T58: =T9 -> 149.47366
A60: Compress & G/L sep | B60: 7 | C60: =C7 -> E-114 | D60: =D7 -> 0 | E60: =E7 -> 31_To_35 | F60: =F7 -> 1.663465 | G60: =G7 -> 0 | H60: =H7 -> 15 | I60: =I7 -> 1 | J60: =J7 -> 14_To_15 | ... T60: =T7 -> 25.451156
B61: 8 | C61: =C10 -> E-117 | D61: =D10 -> 0 | E61: =E10 -> To Reboiler@T3_TO_28-C2C5 | F61: =F10 -> -87.391501 | G61: =G10 -> 0 | H61: =H10 -> -82.18093 | I61: =I10 -> FALSE | J61: =J10 -> 22_To_24 | ... T61: =T10 -> 11.985269
B62: 9 | C62: =C12 -> E-119 | D62: =D12 -> 0 | E62: =E12 -> To Reboiler@T2_TO_26-C2+ | F62: =F12 -> -56.348231 | G62: =G12 -> 0 | H62: =H12 -> -51.280823 | I62: =I12 -> 1 | J62: =J12 -> 17_To_18 | ... T62: =T12 -> 27.781191
B63: 10 | C63: =C13 -> E-120 | D63: =D13 -> 0 | E63: =E13 -> To Reboiler@T3_TO_28-C2C5 | F63: =F13 -> -87.391501 | G63: =G13 -> 0 | H63: =H13 -> -82.18093 | I63: =I13 -> FALSE | J63: =J13 -> V3_heat | ... T63: =T13 -> 42.958132
B64: 11 | C64: =C15 -> E-122 | D64: =D15 -> 0 | E64: =E15 -> CRYOTEMP | F64: =F15 -> -269.24253 | G64: =G15 -> 0 | H64: =H15 -> -269 | I64: =I15 -> FALSE | J64: =J15 -> To Condenser@T1_TO_21 | ... T64: =T15 -> 270.13744
B65: 12 | C65: =C16 -> E-123 | D65: =D16 -> 0 | E65: =E16 -> CRYOTEMP | F65: =F16 -> -269.24253 | G65: =G16 -> 0 | H65: =H16 -> -269 | I65: =I16 -> FALSE | J65: =J16 -> To Condenser@T2_TO_45Duplicate | ... T65: =T16 -> 144.26549
B66: 13 | C66: =C18 -> E-125 | D66: =D18 -> 0 | E66: =E18 -> 31_To_35 | F66: =F18 -> -167 | G66: =G18 -> 0 | H66: =H18 -> -154.96705 | I66: =I18 -> 1 | J66: =J18 -> 14_To_15 | ... T66: =T18 -> 187
B67: 14 | C67: =C23 -> E-130 | D67: =D23 -> 0 | E67: =E23 -> To Reboiler@T3_TO_28-C2C5 | F67: =F23 -> -88.318585 | G67: =G23 -> 0 | H67: =H23 -> -87.391501 | I67: =I23 -> FALSE | J67: =J23 -> 17_To_18 | ... T67: =T23 -> 57.176767
B68: 15 | C68: =C25 -> E-132 | D68: =D25 -> 0 | E68: =E25 -> To Reboiler@T3_TO_28-C2C5 | F68: =F25 -> -88.318585 | G68: =G25 -> 0 | H68: =H25 -> -87.391501 | I68: =I25 -> FALSE | J68: =J25 -> V3_heat | ... T68: =T25 -> 28.318585
A70: Cryogenic separation and recovery | B70: 16 | C70: =C11 -> E-118 | D70: =D11 -> 0 | E70: =E11 -> 31_To_35 | F70: =F11 -> -154.96705 | G70: =G11 -> 0 | H70: =H11 -> -119.47366 | I70: =I11 -> 1 | J70: =J11 -> To Condenser@T3_TO_27-ETHYL | ... T70: =T11 -> 50.773925
B71: 17 | C71: =C14 -> E-121 | D71: =D14 -> 0 | E71: =E14 -> CRYOTEMP | F71: =F14 -> -269.24253 | G71: =G14 -> 0 | H71: =H14 -> -269 | I71: =I14 -> FALSE | J71: =J14 -> 29_To_30 | ... T71: =T14 -> 110.11037
B72: 18 | C72: =C19 -> E-126 | D72: =D19 -> 0 | E72: =E19 -> CRYOTEMP | F72: =F19 -> -270 | G72: =G19 -> 0 | H72: =H19 -> -269.24253 | I72: =I19 -> FALSE | J72: =J19 -> V5_heat | ... T72: =T19 -> 103
B73: 19 | C73: =C20 -> E-127 | D73: =D20 -> 0 | E73: =E20 -> CRYOTEMP | F73: =F20 -> -270 | G73: =G20 -> 0 | H73: =H20 -> -269.24253 | I73: =I20 -> FALSE | J73: =J20 -> V4_heat | ... T73: =T20 -> 130
B74: 20 | C74: =C21 -> E-128 | D74: 21 | E74: =E21 -> CRYOTEMP | F74: 22 | G74: =G21 -> 0 | H74: 23 | I74: =I21 -> FALSE | J74: 24 | K74: =K21 -> -75.406232 | L74: 25 | M74: =M21 -> -103.3156 | N74: 26 | O74: =O21 -> 1.0261631e+08 | P74: 27 | Q74: =Q21 -> 628.58755 | R74: 28 | S74: =S21 -> 193.8363 | T74: 29
B75: 21 | C75: =C24 -> E-131 | D75: =D24 -> 0 | E75: =E24 -> 39_To_42 | F75: =F24 -> -169.27894 | G75: =G24 -> 0 | H75: =H24 -> -152.58127 | I75: =I24 -> 1 | J75: =J24 -> To Condenser@T3_TO_27-ETHYL | ... T75: =T24 -> 63.261706

Sheet Previous_Economic Analysis
A1: 1. Assumption and parameters
B3: ASSUMPTION AND PARAMETERS | H3: PURCHASED EQUIPMENT COST ($)
B4: Location | F4: North America | H4: Reactor (R1+E1)_1245MW | L4: =100.38*10^6*(1246/500)^0.67 -> 1.850693e+08 | M4: https://doi.org/10.1016/j.joule.2018.01.001
B5: System Cost Base Date | F5: 1Q 16 | H5: Flash tank
B6: Project Type | F6: Grass roots/Clear field | H6: V1 | L6: ='Previous_Equipment cost'!E48 -> 1476700
B7: Plant lifetime (y) | F7: 30 | H7: V2 | L7: ='Previous_Equipment cost'!E53 -> 1090800
B8: Annual operating hours (h) | F8: 8000 | H8: V3 | L8: ='Previous_Equipment cost'!E51 -> 949500
B9: Depreciation method | F9: Straight line | H9: V4 | L9: ='Previous_Equipment cost'!E63 -> 444700
B10: Interest rate (%) | F10: 8 | H10: V5 | L10: ='Previous_Equipment cost'!E32 -> 443200
B11: Tax rate (%) | F11: 35 | H11: Columns
H12: T1 | L12: =SUM('Previous_Equipment cost'!E20:E26) -> 125300
B13: FACTOR FOR TCI | H13: T2 | L13: =SUM('Previous_Equipment cost'!E54:E60) -> 1031800
B14: Total capital investment cost (TCI) | F14: =SUBTOTAL(9,F15:F29) -> 5.04 | H14: T3 | L14: =SUM('Previous_Equipment cost'!E37:E43) -> 3547200
B15: Direct plan cost | F15: =SUBTOTAL(9,F16:F23) -> 3.6 | H15: Heat exchanger, heater, cooler
B16: Purchased equipment (PE) | F16: 1 | H16: E2 | L16: ='Previous_Equipment cost'!E19 -> 12850900
B17: Equipment setting | F17: 0.47 | H17: E3 | L17: ='Previous_Equipment cost'!E27 -> 4429400
B18: Instrumentation and control | F18: 0.36 | H18: E4 | L18: ='Previous_Equipment cost'!E47 -> 8613900
B19: Piping | F19: 0.68 | H19: HX1 | L19: =(541.7/280)*101.3*28232^0.65*(0.8+0)*1 -> 122541.25 | M19: Douglas_KoltsegFuggvenyek estimated for HE
B20: Electrical installation | F20: 0.11 | H20: HX2 | L20: =541.7/323.8*398*(1375/1)^0.65*(1+0.52)*1 -> 110944.4
B21: Building and building services | F21: 0.18 | H21: HX3 | L21: ='Previous_Equipment cost'!E44 -> 1865400
B22: Yard improvements | F22: 0.1 | H22: HX4 | L22: ='Previous_Equipment cost'!E62 -> 409400
B23: Services facilities | F23: 0.7 | H23: HX5 | L23: ='Previous_Equipment cost'!$E$61 -> 475200
B24: Indirect plant cost | F24: =SUBTOTAL(9,F25:F29) -> 1.44 | H24: HX6 | L24: ='Previous_Equipment cost'!E29 -> 801700
B25: Engineering | F25: 0.33 | H25: Total | L25: =SUM(L4:L24) -> 2.2385788e+08
B26: Construction expenses | F26: 0.41
B27: Legal expenses | F27: 0.04
B28: Contractor's fee | F28: 0.22
B29: Contingency | F29: 0.44
A31: 2. Calculation of Production Costs and Revenue
B33: ECONOMIC CALCULATION | H33: Variable operating cost ($/year) | U33: lb | V33: kg | AE33: Value (MM$)
B34: Total capital investment cost (TCI) ($) | F34: =F14*$L$25 -> 1.1282437e+09 | K34: Weight factor | M34: Unit price | O34: Total amount (year) | Q34: Original ($) | R34: Changed | S34: % | U34: 1 | V34: 0.45359237 | AD34: Total capital investment cost (TCI) | AE34: =F34/10^6 -> 1128.2437 | AF34: 1128.2437
B35: Direct plan cost | F35: =F15*$L$25 -> 8.0588838e+08 | H35: Raw materials | Q35: =SUBTOTAL(9,Q36) -> 3.0306628e+08 | R35: =SUBTOTAL(9,R36) -> 3.0306628e+08 | S35: =(R35-Q35)/Q35 -> 0 | AD35: Direct plan cost | AE35: =F35/10^6 -> 805.88838 | AF35: 805.88838
B36: Purchased equipment (PE) | F36: =F16*$L$25 -> 2.2385788e+08 | H36: CH4 | K36: 1 | M36: 3.27 | N36: $/MMBTU | O36: ='Previous_Technical performance'!D72/28.263682*8000 -> 92680819 | P36: MMBTU | Q36: =O36*M36 -> 3.0306628e+08 | R36: =Q36*K36 -> 3.0306628e+08 | S36: =(R36-Q36)/Q36 -> 0 | T36: 1 MMBTU = 28.263682 m3 NG | AD36: Purchased equipment (PE) | AE36: =F36/10^6 -> 223.85788 | AF36: 223.85788
B37: Equipment setting | F37: =F17*$L$25 -> 1.0521321e+08 | H37: Utility | Q37: =SUBTOTAL(9,Q38:Q44) -> 9.3721732e+08 | R37: =SUBTOTAL(9,R38:R44) -> 9.3721732e+08 | S37: =(R37-Q37)/Q37 -> 0 | AD37: Equipment setting | AE37: =F37/10^6 -> 105.21321 | AF37: 105.21321
B38: Instrumentation and control | F38: =F18*$L$25 -> 80588838 | H38: O2 | K38: 1 | M38: 40 | N38: $/ton | O38: ='Previous_Technical performance'!E59/1000*8000 -> 358386.56 | P38: ton | Q38: =O38*M38 -> 14335462 | R38: =Q38*K38 -> 14335462 | S38: =(R38-Q38)/Q38 -> 0 | U38: =Q38/10^6 -> 14.335462 | AD38: Instrumentation and control | AE38: =F38/10^6 -> 80.588838 | AF38: 80.588838
B39: Piping | F39: =F19*$L$25 -> 1.5222336e+08 | H39: Refrigeration | K39: 1 | M39: 8.9e-06 | N39: $/kJ | O39: ='DB_Aspen simulation_previous'!D176*8760 -> 9.6950683e+09 | P39: MJ | Q39: =O39*1000*M39 -> 86286108 | R39: =Q39*K39 -> 86286108 | S39: =(R39-Q39)/Q39 -> 0 | U39: =Q39/10^6 -> 86.286108 | AD39: Piping | AE39: =F39/10^6 -> 152.22336 | AF39: 152.22336
B40: Electrical installation | F40: =F20*$L$25 -> 24624367 | H40: Electricity | K40: 1 | M40: 0.069 | N40: $/kWh | O40: ='DB_Aspen simulation_previous'!F177*8760 -> 8388696888 | P40: kWh | Q40: =O40*M40 -> 5.7882009e+08 | R40: =Q40*K40 -> 5.7882009e+08 | S40: =(R40-Q40)/Q40 -> 0 | U40: =Q40/10^6 -> 578.82009 | AD40: Electrical installation | AE40: =F40/10^6 -> 24.624367 | AF40: 24.624367
B41: Building and building services | F41: =F21*$L$25 -> 40294419 | H41: Cooling water | K41: 1 | M41: 0.03 | N41: $/ton | O41: ='DB_Aspen simulation_previous'!F178/1000*8760 -> 3396138120 | P41: ton | Q41: =O41*M41 -> 1.0188414e+08 | R41: =Q41*K41 -> 1.0188414e+08 | S41: =(R41-Q41)/Q41 -> 0 | U41: =Q41/10^6 -> 101.88414 | AD41: Building and building services | AE41: =F41/10^6 -> 40.294419 | AF41: 40.294419
B42: Yard improvements | F42: =F22*$L$25 -> 22385788 | H42: High pressure steam | K42: 1 | M42: 14.5 | N42: $/ton | O42: ='DB_Aspen simulation_previous'!F180/1000*8760 -> 39471.947 | P42: ton | Q42: =O42*M42 -> 572343.23 | R42: =Q42*K42 -> 572343.23 | S42: =(R42-Q42)/Q42 -> 0 | U42: =Q42/10^6 -> 0.57234323 | AD42: Yard improvements | AE42: =F42/10^6 -> 22.385788 | AF42: 22.385788
B43: Services facilities | F43: =F23*$L$25 -> 1.5670052e+08 | H43: Low pressure steam | K43: 1 | M43: 10.5 | N43: $/ton | O43: ='DB_Aspen simulation_previous'!F181/1000*8760 -> 1147958.6 | P43: ton | Q43: =O43*M43 -> 12053565 | R43: =Q43*K43 -> 12053565 | S43: =(R43-Q43)/Q43 -> 0 | U43: =Q43/10^6 -> 12.053565 | AD43: Services facilities | AE43: =F43/10^6 -> 156.70052 | AF43: 156.70052
B44: Indirect plant cost | F44: =F24*$L$25 -> 3.2235535e+08 | H44: Natural gas for Fired heat | K44: 1 | M44: =M36 -> 3.27 | N44: $/MMBTU | O44: ='DB_Aspen simulation_previous'!D179/1055/0.85*8760 -> 43812113 | P44: MMBTU | Q44: =O44*M44 -> 1.4326561e+08 | R44: =Q44*K44 -> 1.4326561e+08 | S44: =(R44-Q44)/Q44 -> 0 | T44: 1MMBTU=1055MJ, 4251 MMBTU, 0.85 ef by Gavin Towler book | U44: =Q44/10^6 -> 143.26561 | AD44: Indirect plant cost | AE44: =F44/10^6 -> 322.35535 | AF44: 322.35535
B45: Engineering | F45: =F25*$L$25 -> 73873101 | H45: Total | Q45: =SUBTOTAL(9,Q35:Q43) -> 1.097018e+09 | R45: =SUBTOTAL(9,R35:R43) -> 1.097018e+09 | S45: =(R45-Q45)/Q45 -> 0 | AD45: Engineering | AE45: =F45/10^6 -> 73.873101 | AF45: 73.873101
B46: Construction expenses | F46: =F26*$L$25 -> 91781732 | AD46: Construction expenses | AE46: =F46/10^6 -> 91.781732 | AF46: 91.781732
B47: Legal expenses | F47: =F27*$L$25 -> 8954315.3 | H47: Annualized TPI ($/year) | AD47: Legal expenses | AE47: =F47/10^6 -> 8.9543153 | AF47: 8.9543153
B48: Contractor's fee | F48: =F28*$L$25 -> 49248734 | H48: TCI | M48: =F34 -> 1.1282437e+09 | P48: =13.11/10^6 -> 1.311e-05 | AD48: Contractor's fee | AE48: =F48/10^6 -> 49.248734 | AF48: 49.248734
B49: Contingency | F49: =F29*$L$25 -> 98497469 | H49: Interest rate (r) | M49: 0.08 | AD49: Contingency | AE49: =F49/10^6 -> 98.497469 | AF49: 98.497469
B50: Operationg cost | F50: =SUBTOTAL(9,F51:F59) -> 1.273993e+09 | H50: Life time (n) | M50: =30*1 -> 30 | AD50: Operationg cost | AE50: =F50/10^6 -> 1273.993 | AF50: 1193.9256
B51: Variable operating cost | F51: =SUBTOTAL(9,F52:F53) -> 1.2402836e+09 | H51: Inter.value (1+r) n | M51: =POWER(1+M49,M50) -> 10.062657 | AD51: Variable operating cost | AE51: =F51/10^6 -> 1240.2836 | AF51: 1160.2162
B52: Raw materials | F52: =R35 -> 3.0306628e+08 | H52: Annual factor (a(r,n)) | M52: =M49*M51/(M51-1) -> 0.088827433 | AD52: Raw materials | AE52: =F52/10^6 -> 303.06628 | AF52: 303.06628
B53: Utilities | F53: =R37 -> 9.3721732e+08 | H53: Annualized TCI | M53: =M48*M52 -> 1.0021899e+08 | AD53: Utilities | AE53: =F53/10^6 -> 937.21732 | AF53: 857.14994
B54: Fixed operating costs | F54: =SUBTOTAL(9,F55:F59) -> 33709371 | H54: Tax rate | M54: =35%*1 -> 0.35 | AD54: O2 | AE54: =Q38/10^6 -> 14.335462 | AF54: 14.335462
B55: Operating labor cost | F55: 760000 | AD55: Refrigeration | AE55: =Q39/10^6 -> 86.286108 | AF55: 78.800099
B56: Maintenance cost | F56: 1980000 | H56: Annualized TCI | M56: =M53 -> 1.0021899e+08 | AD56: Electricity | AE56: =Q40/10^6 -> 578.82009 | AF56: 528.60282
B57: Operating charges | F57: 190000 | H57: Depreciation = TPI / Life time | M57: =M48/M50 -> 37608124 | R57: revenue | AD57: Cooling water | AE57: =Q41/10^6 -> 101.88414 | AF57: 93.04488
B58: Plant overhead | F58: 1370000 | H58: Tax = (Profit - Depreciation)* Tax rate | M58: =(M60-M57)*M54 -> 33713546 | R58: =S67/$S$65 -> 0.36974698 | AD58: High pressure steam | AE58: =Q42/10^6 -> 0.57234323 | AF58: 0.52268788
B59: G&A cost | F59: 29409371 | H59: ROI = Profit - Tax | M59: =M60-M58 -> 1.0021899e+08 | R59: =S69/$S$65 -> 0.012596047 | AD59: Low pressure steam | AE59: =Q43/10^6 -> 12.053565 | AF59: 11.007822
B60: Annualized TPI (Return on investment ROI) | F60: =M56 -> 1.0021899e+08 | H60: Profit = Revenue - Expenses | M60: =M62-M61 -> 1.3393254e+08 | R60: =S70/$S$65 -> 0.043342551 | AD60: Natural gas for Fired heat | AE60: =Q44/10^6 -> 143.26561 | AF60: 130.83617
B61: Depreciation | F61: =M57 -> 37608124 | H61: Expense = Variable + Fixed costs | M61: =F50 -> 1.273993e+09 | R61: =S68/$S$65 -> 0.26592186 | AD61: Fixed operating costs | AE61: =F54/10^6 -> 33.709371 | AF61: 33.709371
B62: Tax | F62: =M58 -> 33713546 | H62: Expenditure ($) = revenue at MSP | M62: =(M56-M54*M57+(1-M54)*M61)/(1-M54) -> 1.4079255e+09 | R62: =S66/$S$65 -> 0.35173511 | AD62: Annualized TCI | AE62: =F60/10^6 -> 100.21899 | AF62: 100.21899
B63: Profit | F63: =M60 -> 1.3393254e+08 | AD63: Production and credits (MM$/y) | AE63: =M62/10^6 -> 1407.9255 | AF63: 1327.8581
B64: Expense | F64: =M61 -> 1.273993e+09 | H64: Minimum selling price of ethylene - MSP ($/kg) | AD64: Ethylene (99.9% vol) | AE64: =AG81 -> 433.03511 | AF64: 433.03511
B65: Revenue (at break-even point) ($) | F65: =M62 -> 1.4079255e+09 | H65: Production | K65: Unit price | M65: Total amount (year) | Q65: Production cost | S65: =SUM(S66:S69) -> 1349.4374 | U65: H2 price in correlation to NG gas H2=0.1515NG+0.9287 ($/kg) | AD65: Hydrogen (96 %vol) | AE65: =AG77 -> 498.95042 | AF65: 498.95042
C66: Hydrogen (96 %vol) | F66: =Q67 -> 4.9895042e+08 | H66: Ethylene (99.9% vol) | K66: =(M62-Q67+37.031/1000*M70+37.031/1000*0.5/0.65*M69)/((0.65*M68+M66)+M70*0.695+M69*0.5/0.65*0.695) -> 0.97474685 | L66: $/kg | M66: ='Previous_Technical performance'!H59*8000 -> 4.8694133e+08 | N66: kg | O66: =M66/10^6 -> 486.94133 | P66: kton | Q66: =M66*K66 -> 4.7464453e+08 | R66: $/y | S66: =Q66/10^6 -> 474.64453 | T66: M$/y | U66: Naphthalene and benzene price in correlation to ethylene price | AD66: Raw Acethylene (95.1 %vol) | AE66: =AG80 -> 327.387 | AF66: 327.387
C67: Crude Naphthalene (95.7 %wt) | F67: =Q69 -> 16997577 | H67: Hydrogen (96 %vol) | K67: =0.1515*M36+0.9287 -> 1.424105 | L67: $/kg | M67: ='Previous_Technical performance'!L59*8000 -> 3.503607e+08 | N67: kg | O67: =M67/10^6 -> 350.3607 | P67: kton | Q67: =M67*K67 -> 4.9895042e+08 | R67: $/y | S67: =Q67/10^6 -> 498.95042 | T67: M$/y | U67: Ben=0.695ethylene - 37.031/1000 ($/kg), Nap=0.5/0.65*Ben ($/kg) | AD67: Crude Naphthalene (95.7 %wt) | AE67: =AG78 -> 15.421334 | AF67: 15.421334
C68: Benzene (99 %wt) | F68: =Q70 -> 58488061 | H68: Raw Acethylene (95.1 %vol) | K68: =K66*0.65 -> 0.63358545 | L68: $/kg | M68: ='Previous_Technical performance'!I59*8000 -> 5.6637178e+08 | N68: kg | O68: =M68/10^6 -> 566.37178 | P68: kton | Q68: =M68*K68 -> 3.5884492e+08 | R68: $/y | S68: =Q68/10^6 -> 358.84492 | T68: M$/y | U68: Acetylene = 0.65 ethylene | AD68: Benzene (99 %wt) | AE68: =AG79 -> 53.064264 | AF68: 53.064264
C69: Raw Acethylene (95.1 %vol) | F69: =Q68 -> 3.5884492e+08 | H69: Crude Naphthalene (95.7 %wt) | K69: =K70*0.5/0.65 -> 0.49262928 | L69: $/kg | M69: ='Previous_Technical performance'!J59*8000 -> 34503790 | N69: kg | O69: =M69/10^6 -> 34.50379 | P69: kton | Q69: =M69*K69 -> 16997577 | R69: $/y | S69: =Q69/10^6 -> 16.997577 | T69: M$/y
C70: Ethylene (99.9% vol) | F70: =Q66 -> 4.7464453e+08 | H70: Benzene (99 %wt) | K70: =0.695*K66-37.031/1000 -> 0.64041806 | L70: $/kg | M70: ='Previous_Technical performance'!K59*8000 -> 91327939 | N70: kg | O70: =M70/10^6 -> 91.327939 | P70: kton | Q70: =M70*K70 -> 58488061 | R70: $/y | S70: =Q70/10^6 -> 58.488061 | T70: M$/y
E73: Revenue | F73: Production costs
D74: DC | F74: =(F35/F34)*M56/M62 -> 0.050844307
D75: IDC | F75: =(F44/F34)*M56/M62 -> 0.020337723
D76: VOC | F76: =F51/M62 -> 0.88092984 | AE76: Capacity (kton/y) | AF76: Unit price ($/kg) | AG76: Sale credits (M$/y)
D77: FOC | F77: =F54/M62 -> 0.023942581 | AD77: Hydrogen (96 %vol) | AE77: 350.3607 | AF77: 1.424105 | AG77: 498.95042
D78: Tax | F78: =M58/M62 -> 0.023945546 | AD78: Crude Naphthalene (95.7 %wt) | AE78: 34.50379 | AF78: 0.44694608 | AG78: 15.421334
D79: Ethylene | E79: 0.32611549 | AD79: Benzene (99 %wt) | AE79: 91.327939 | AF79: 0.58102991 | AG79: 53.064264
D80: Crude Naphthalene | E80: 0.011613691 | AD80: Raw Acethylene (95.1 %vol) | AE80: 566.37178 | AF80: 0.57804258 | AG80: 327.387
D81: Benzene | E81: 0.039962299 | AD81: Ethylene (99.9% vol) | AE81: 486.94133 | AF81: 0.88929627 | AG81: 433.03511
D82: Raw Acethylene | E82: 0.24655269
D83: Hydrogen | E83: 0.37575582
D85: Variable operating cost
D86: Raw material_NG | F86: =R36/F51 -> 0.2443524
D87: Refrigeration | F87: =R39/$F$51 -> 0.06956966
D88: Electricity | F88: =R40/$F$51 -> 0.46668366
D89: Cooling water | F89: =R41/$F$51 -> 0.082145845
D90: High pressure steam | F90: =R42/$F$51 -> 0.00046146158
D91: Low pressure steam | F91: =R43/$F$51 -> 0.0097183943
D92: Fuel_NG | F92: =R44/$F$51 -> 0.11551036
D93: Other | F93: =1-SUM(F86:F92) -> 0.011558213
A99: 3. Sensitivity analysis
B102: Based | D102: 1327.8581
B103: Sensitivity | D103: =M62/10^6 -> 1407.9255
B105: Sensitivity on Total production cost
D106: Total production costs | F106: Gap value | H106: Increase (%)
D107: -0.2 | E107: 0.2 | F107: -0.2 | G107: 0.2 | H107: -0.2 | I107: 0.2
B108: Tax rate | D108: 1318.4933 | E108: 1339.4835 | F108: =D108-$D$102 -> -9.3648738 | G108: =E108-$D$102 -> 11.625361 | H108: =(D108-$D$102)/$D$102 -> -0.0070526162 | I108: =(E108-$D$102)/$D$102 -> 0.0087549719
B109: Interest rate | D109: 1305.2199 | E109: 1351.6878 | F109: =D109-$D$102 -> -22.638259 | G109: =E109-$D$102 -> 23.829645 | H109: =(D109-$D$102)/$D$102 -> -0.017048703 | I109: =(E109-$D$102)/$D$102 -> 0.017945927
B110: Lifetime | D110: 1333.4713 | E110: 1325.188 | F110: =D110-$D$102 -> 5.6132062 | G110: =E110-$D$102 -> -2.6701448 | H110: =(D110-$D$102)/$D$102 -> 0.0042272635 | I110: =(E110-$D$102)/$D$102 -> -0.002010866
B111: Natural gas price | D111: 1267.2449 | E111: 1388.4714 | F111: =D111-$D$102 -> -60.613256 | G111: =E111-$D$102 -> 60.613256 | H111: =(D111-$D$102)/$D$102 -> -0.045647388 | I111: =(E111-$D$102)/$D$102 -> 0.045647388
B112: Electricity price | D112: 1222.1376 | E112: 1433.5787 | F112: =D112-$D$102 -> -105.72056 | G112: =E112-$D$102 -> 105.72056 | H112: =(D112-$D$102)/$D$102 -> -0.079617363 | I112: =(E112-$D$102)/$D$102 -> 0.079617363
B113: Cooling water price | D113: 1309.2492 | E113: 1346.4671 | F113: =D113-$D$102 -> -18.608976 | G113: =E113-$D$102 -> 18.608976 | H113: =(D113-$D$102)/$D$102 -> -0.01401428 | I113: =(E113-$D$102)/$D$102 -> 0.01401428
B114: Refrigeration price | D114: 1312.0981 | E114: 1343.6182 | F114: =D114-$D$102 -> -15.76002 | G114: =E114-$D$102 -> 15.76002 | H114: =(D114-$D$102)/$D$102 -> -0.011868753 | I114: =(E114-$D$102)/$D$102 -> 0.011868753
...

Sheet Previous_Equipment cost
A1: EQUIP.ICS (Equipment)
J2: CASE 1
A3: Area Name | B3: Component Name | C3: Component Type | D3: Total Direct Cost | E3: Equipment Cost | F3: Equipment Weight | G3: Installed Weight | J3: Name | K3: Equipment Cost [USD] | L3: Installed Cost [USD] | M3: Equipment Weight [KG] | N3: Installed Weight [KG]
D4: (USD) | E4: (USD) | F4: KG | G4: KG | J4: HX2 | K4: 0 | L4: 0 | M4: 0 | N4: 0
J5: E7 | K5: 0 | L5: 0 | M5: 0 | N5: 0
J6: T1DST | K6: 34300 | L6: 174800 | M6: 2300 | N6: 8824
J7: M2 | K7: 0 | L7: 0 | M7: 0 | N7: 0
J8: E2 | K8: 15629000 | L8: 43390000 | M8: 950000 | N8: 1690049
J9: T3DST | K9: 1865200 | L9: 3069000 | M9: 375900 | N9: 462692
J10: MHX2 | K10: 5061400 | L10: 10643900 | M10: 654000 | N10: 827123
A11: R1 | B11: R1.MIXER | C11: C | D11: 0 | E11: 0 | F11: 0 | G11: 0 | J11: T1-bottoms split | K11: 0 | L11: 0 | M11: 0 | N11: 0
A12: R1 | B12: R1.B1 | C12: DVT CYLINDER | J12: T1-cond | K12: 25900 | L12: 41400 | M12: 2400 | N12: 3195
A13: R1 | B13: R1.SPLIT | C13: C | D13: 0 | E13: 0 | F13: 0 | G13: 0 | J13: T1-cond acc | K13: 16200 | L13: 65200 | M13: 1600 | N13: 3196
J14: T1-overhead split | K14: 0 | L14: 0 | M14: 0 | N14: 0
A15: Miscellaneous Flowsheet Area | B15: HX2 | C15: DHE TEMA EXCH | E15: 0 | J15: T1-reb | K15: 0 | L15: 0 | M15: 0 | N15: 0
A16: Miscellaneous Flowsheet Area | B16: E7 | C16: DHE TEMA EXCH | J16: T1-reflux pump | K16: 4900 | L16: 32000 | M16: 130 | N16: 1087
A17: Miscellaneous Flowsheet Area | B17: M2 | C17: C | D17: 0 | E17: 0 | F17: 0 | G17: 0 | J17: T1-tower | K17: 95400 | L17: 255800 | M17: 11700 | N17: 20146
A18: Miscellaneous Flowsheet Area | B18: E1 | C18: DHE TEMA EXCH | J18: MHX3 | K18: 2345100 | L18: 3753200 | M18: 303800 | N18: 359321
A19: Miscellaneous Flowsheet Area | B19: E2 | C19: DHE TEMA EXCH | D19: 35808000 | E19: 12850900 | F19: 1376100 | G19: 2054301 | J19: M5 | K19: 0 | L19: 0 | M19: 0 | N19: 0
A20: Miscellaneous Flowsheet Area | B20: T1-bottoms split | C20: C | D20: 0 | E20: 0 | F20: 0 | G20: 0 | J20: VAL1 | K20: 0 | L20: 0 | M20: 0 | N20: 0
A21: Miscellaneous Flowsheet Area | B21: T1-cond | C21: DHE TEMA EXCH | D21: 21400 | E21: 9200 | F21: 300 | G21: 782 | J21: V5-flash vessel | K21: 577200 | L21: 954600 | M21: 113800 | N21: 139463
A22: Miscellaneous Flowsheet Area | B22: T1-cond acc | C22: DHT HORIZ DRUM | D22: 78800 | E22: 19000 | F22: 2500 | G22: 4637 | J22: MCOMP1 | K22: 0 | L22: 0 | M22: 0 | N22: 0
A23: Miscellaneous Flowsheet Area | B23: T1-overhead split | C23: C | D23: 0 | E23: 0 | F23: 0 | G23: 0 | J23: M3 | K23: 0 | L23: 0 | M23: 0 | N23: 0
A24: Miscellaneous Flowsheet Area | B24: T1-reb | C24: DRB U TUBE | J24: MHX4 | K24: 1744500 | L24: 2138500 | M24: 226200 | N24: 265332
A25: Miscellaneous Flowsheet Area | B25: T1-reflux pump | C25: DCP CENTRIF | D25: 24600 | E25: 4600 | F25: 100 | G25: 711 | J25: T3-bottoms split | K25: 0 | L25: 0 | M25: 0 | N25: 0
A26: Miscellaneous Flowsheet Area | B26: T1-tower | C26: DTW TOWER | D26: 265400 | E26: 92500 | F26: 11800 | G26: 23261 | J26: T3-cond | K26: 579700 | L26: 669800 | M26: 82800 | N26: 88797
A27: Miscellaneous Flowsheet Area | B27: E3 | C27: DHE TEMA EXCH | D27: 7734700 | E27: 4429400 | F27: 690000 | G27: 833656 | J27: T3-cond acc | K27: 48700 | L27: 281800 | M27: 6600 | N27: 20275
A28: Miscellaneous Flowsheet Area | B28: M5 | C28: C | D28: 0 | E28: 0 | F28: 0 | G28: 0 | J28: T3-overhead split | K28: 0 | L28: 0 | M28: 0 | N28: 0
A29: Miscellaneous Flowsheet Area | B29: HX6 | C29: DHE TEMA EXCH | D29: 1241900 | E29: 801700 | F29: 130500 | G29: 149901 | J29: T3-reb | K29: 528300 | L29: 654800 | M29: 69000 | N29: 77396
A30: Miscellaneous Flowsheet Area | B30: C2 | C30: DGC CENTRIF | D30: 46112000 | E30: 43793400 | F30: 351600 | G30: 589107 | J30: T3-reflux pump | K30: 27000 | L30: 77500 | M30: 930 | N30: 3523
A31: Miscellaneous Flowsheet Area | B31: VAL1 | C31: C | D31: 0 | E31: 0 | F31: 0 | G31: 0 | J31: T3-tower | K31: 3011600 | L31: 4576000 | M31: 512300 | N31: 622567
A32: Miscellaneous Flowsheet Area | B32: V5-flash vessel | C32: DVT CYLINDER | D32: 772100 | E32: 443200 | F32: 89100 | G32: 113356 | J32: HX1 | K32: 0 | L32: 0 | M32: 0 | N32: 0
A33: Miscellaneous Flowsheet Area | B33: M3 | C33: C | D33: 0 | E33: 0 | F33: 0 | G33: 0 | J33: R2 | K33: 0 | L33: 0 | M33: 0 | N33: 0
A34: Miscellaneous Flowsheet Area | B34: $C-2 | C34: C | D34: 0 | E34: 0 | F34: 0 | G34: 0 | J34: E1 | K34: 0 | L34: 0 | M34: 0 | N34: 0
A35: Miscellaneous Flowsheet Area | B35: $C-1 | C35: C | D35: 0 | E35: 0 | F35: 0 | G35: 0 | J35: V1-flash vessel | K35: 1785500 | L35: 2089000 | M35: 362800 | N35: 384858
A36: Miscellaneous Flowsheet Area | B36: C1 | C36: DGC CENTRIF | J36: M4 | K36: 0 | L36: 0 | M36: 0 | N36: 0
A37: Miscellaneous Flowsheet Area | B37: T3-bottoms split | C37: C | D37: 0 | E37: 0 | F37: 0 | G37: 0 | J37: V3-flash vessel | K37: 1142700 | L37: 1375900 | M37: 228700 | N37: 245240
A38: Miscellaneous Flowsheet Area | B38: T3-cond | C38: DHE TEMA EXCH | D38: 1018500 | E38: 912000 | F38: 178000 | G38: 185445 | J38: M1 | K38: 0 | L38: 0 | M38: 0 | N38: 0
A39: Miscellaneous Flowsheet Area | B39: T3-cond acc | C39: DHT HORIZ DRUM | D39: 295400 | E39: 46600 | F39: 7900 | G39: 25178 | J39: V2-flash vessel | K39: 1289400 | L39: 1592500 | M39: 259400 | N39: 280277
A40: Miscellaneous Flowsheet Area | B40: T3-overhead split | C40: C | D40: 0 | E40: 0 | F40: 0 | G40: 0 | J40: MHX1 | K40: 2914300 | L40: 4885500 | M40: 378900 | N40: 459203
A41: Miscellaneous Flowsheet Area | B41: T3-reb | C41: DRB U TUBE | D41: 287100 | E41: 75400 | F41: 10900 | G41: 18757 | J41: T2-bottoms split | K41: 0 | L41: 0 | M41: 0 | N41: 0
A42: Miscellaneous Flowsheet Area | B42: T3-reflux pump | C42: DCP CENTRIF | D42: 93200 | E42: 38400 | F42: 1200 | G42: 4826 | J42: T2-cond | K42: 142900 | L42: 180800 | M42: 17900 | N42: 20059
A43: Miscellaneous Flowsheet Area | B43: T3-tower | C43: DTW TOWER | D43: 4191200 | E43: 2474800 | F43: 437800 | G43: 580967 | J43: T2-cond acc | K43: 34100 | L43: 185600 | M43: 4500 | N43: 12245
A44: Miscellaneous Flowsheet Area | B44: HX3 | C44: DHE TEMA EXCH | D44: 2214600 | E44: 1865400 | F44: 302400 | G44: 341321 | J44: T2-overhead split | K44: 0 | L44: 0 | M44: 0 | N44: 0
A45: Miscellaneous Flowsheet Area | B45: HX1 | C45: DHE TEMA EXCH | J45: T2-reb | K45: 642900 | L45: 746500 | M45: 79000 | N45: 86064
A46: Miscellaneous Flowsheet Area | B46: R2 | C46: DAT REACTOR | J46: T2-reflux pump | K46: 10300 | L46: 48700 | M46: 360 | N46: 1948
A47: Miscellaneous Flowsheet Area | B47: E4 | C47: DHE TEMA EXCH | D47: 9050100 | E47: 8613900 | F47: 1362500 | G47: 1396254 | J47: T2-tower | K47: 261400 | L47: 606800 | M47: 43100 | N47: 64698
A48: Miscellaneous Flowsheet Area | B48: V1-flash vessel | C48: DVT CYLINDER | D48: 1744800 | E48: 1476700 | F48: 312300 | G48: 335000 | J48: V4-flash vessel | K48: 689100 | L48: 1072300 | M48: 133200 | N48: 158951
A49: Miscellaneous Flowsheet Area | B49: $C-3 | C49: C | D49: 0 | E49: 0 | F49: 0 | G49: 0 | J49: T2DST | K49: 139000 | L49: 432400 | M49: 20900 | N49: 39177
A50: Miscellaneous Flowsheet Area | B50: M4 | C50: C | D50: 0 | E50: 0 | F50: 0 | G50: 0 | J50: MCOMP2 | K50: 61512900 | L50: 64613000 | M50: 459200 | N50: 740769
A51: Miscellaneous Flowsheet Area | B51: V3-flash vessel | C51: DVT CYLINDER | D51: 1188400 | E51: 949500 | F51: 196700 | G51: 212893 | J51: R1.B1 | K51: 0 | L51: 0 | M51: 0 | N51: 0
A52: Miscellaneous Flowsheet Area | B52: M1 | C52: C | D52: 0 | E52: 0 | F52: 0 | G52: 0 | J52: R1.B2 | K52: 0 | L52: 0 | M52: 0 | N52: 0
A53: Miscellaneous Flowsheet Area | B53: V2-flash vessel | C53: DVT CYLINDER | D53: 1361400 | E53: 1090800 | F53: 228400 | G53: 249955
A54: Miscellaneous Flowsheet Area | B54: T2-bottoms split | C54: C | D54: 0 | E54: 0 | F54: 0 | G54: 0
A55: Miscellaneous Flowsheet Area | B55: T2-cond | C55: DHE TEMA EXCH | D55: 511300 | E55: 450700 | F55: 77000 | G55: 80851
A56: Miscellaneous Flowsheet Area | B56: T2-cond acc | C56: DHT HORIZ DRUM | D56: 252900 | E56: 51700 | F56: 11400 | G56: 24412
A57: Miscellaneous Flowsheet Area | B57: T2-overhead split | C57: C | D57: 0 | E57: 0 | F57: 0 | G57: 0
A58: Miscellaneous Flowsheet Area | B58: T2-reb | C58: DRB U TUBE | D58: 277000 | E58: 82400 | F58: 11600 | G58: 18931
A59: Miscellaneous Flowsheet Area | B59: T2-reflux pump | C59: DCP CENTRIF | D59: 71400 | E59: 18600 | F59: 690 | G59: 4196
A60: Miscellaneous Flowsheet Area | B60: T2-tower | C60: DTW TOWER | D60: 926800 | E60: 428400 | F60: 73200 | G60: 112727
A61: Miscellaneous Flowsheet Area | B61: HX5 | C61: DHE TEMA EXCH | D61: 785000 | E61: 475200 | F61: 78000 | G61: 90521
A62: Miscellaneous Flowsheet Area | B62: HX4 | C62: DHE TEMA EXCH | D62: 617800 | E62: 409400 | F62: 66600 | G62: 76123
A63: Miscellaneous Flowsheet Area | B63: V4-flash vessel | C63: DVT CYLINDER | D63: 756700 | E63: 444700 | F63: 87300 | G63: 110404

Sheet DB_Aspen simulation_previous
B1: Process scheme
B32: Stream information
C33: Units | D33: 1-CH4 | E33: 2-H2 | F33: 3 | G33: 4 | H33: 5 | I33: 6 | J33: 7 | K33: 8 | L33: 9 | M33: 10 | N33: 11 | O33: 12-NAP | P33: 13 | Q33: 14 | R33: 15 | S33: 16 | T33: 17 | U33: 18 | V33: 19 | W33: 20-BEN | X33: 21 | Y33: 22 | Z33: 23 | AA33: 24 | AB33: 25 | AC33: 26 | AD33: 27-ETHYL | AE33: 28-C2 | AF33: 29 | AG33: 30 | AH33: 31 | AI33: 32 | AJ33: 33 | AK33: 34 | AL33: 35 | AM33: 36 | AN33: 37-H2 | AO33: 38 | AP33: 39 | AQ33: 40 | AR33: 41 | AS33: 42 | AT33: 43 | AU33: 44 | AV33: 46 | AW33: 47 | AX33: 48 | AY33: 49-COKE | AZ33: 50-O2 | BA33: 51 | BB33: 52 | BC33: 53 | BD33: 54-CO2
B34: Description
B35: From | F35: M1 | G35: HX1 | H35: HX2 | I35: E1 | J35: R1 | K35: HX1 | L35: E2 | M35: C1 | N35: E3 | O35: V1 | P35: V1 | Q35: C2 | R35: HX3 | S35: V2 | T35: V2 | U35: HX4 | V35: V3 | W35: T1 | X35: T1 | Y35: V3 | Z35: HX5 | AA35: E4 | AB35: V4 | AC35: T2 | AD35: T3 | AE35: T3 | AF35: V4 | AG35: HX6 | AH35: V5 | AI35: HX6 | AJ35: HX5 | AK35: HX4 | AL35: HX3 | AM35: M4 | AN35: M4 | AO35: V5 | AP35: VAL1 | AQ35: HX6 | AR35: HX5 | AS35: HX3 | AT35: M2 | AU35: M2 | AV35: HX5 | AW35: M3 | AX35: M3 | AY35: R1 | BA35: M5 | BB35: E7 | BC35: R2 | BD35: HX2
B36: To | D36: M1 | E36: M1 | F36: HX1 | G36: HX2 | H36: E1 | I36: R1 | J36: HX1 | K36: E2 | L36: C1 | M36: E3 | N36: V1 | P36: C2 | Q36: HX3 | R36: V2 | S36: V1 | T36: HX4 | U36: V3 | V36: T1 | X36: V3 | Y36: HX5 | Z36: E4 | AA36: V4 | AB36: T2 | AC36: T3 | AF36: HX6 | AG36: V5 | AH36: HX6 | AI36: HX5 | AJ36: HX4 | AK36: HX3 | AL36: M4 | AM36: M1 | AO36: VAL1 | AP36: HX6 | AQ36: HX5 | AR36: HX3 | AS36: M2 | AT36: M1 | AV36: M3 | AW36: M1 | AY36: M5 | AZ36: M5 | BA36: E7 | BB36: R2 | BC36: HX2
B37: Stream Class | D37: CONVEN | E37: CONVEN | F37: CONVEN | G37: CONVEN | H37: CONVEN | I37: CONVEN | J37: CONVEN | K37: CONVEN | L37: CONVEN | M37: CONVEN | N37: CONVEN | O37: CONVEN | P37: CONVEN | Q37: CONVEN | R37: CONVEN | S37: CONVEN | T37: CONVEN | U37: CONVEN | V37: CONVEN | W37: CONVEN | X37: CONVEN | Y37: CONVEN | Z37: CONVEN | AA37: CONVEN | AB37: CONVEN | AC37: CONVEN | AD37: CONVEN | AE37: CONVEN | AF37: CONVEN | AG37: CONVEN | AH37: CONVEN | AI37: CONVEN | AJ37: CONVEN | AK37: CONVEN | AL37: CONVEN | AM37: CONVEN | AN37: CONVEN | AO37: CONVEN | AP37: CONVEN | AQ37: CONVEN | AR37: CONVEN | AS37: CONVEN | AT37: CONVEN | AU37: CONVEN | AV37: CONVEN | AW37: CONVEN | AX37: CONVEN | AY37: CONVEN | AZ37: CONVEN | BA37: CONVEN | BB37: CONVEN | BC37: CONVEN | BD37: CONVEN
B38: Maximum Relative Error
B39: Cost Flow | C39: $/hr | D39: 68.076992 | E39: 0 | O39: 215.64894 | W39: 7421.0545 | AD39: 60265.014 | AE39: 0 | AN39: 58212.7 | AZ39: 1791.9328
B40: MIXED Substream
B41: Phase | D41: Vapor Phase | E41: Vapor Phase | F41: Vapor Phase | G41: Vapor Phase | H41: Vapor Phase | I41: Vapor Phase | J41: Vapor Phase | K41: Vapor Phase | L41: Vapor Phase | M41: Vapor Phase | O41: Liquid Phase | P41: Vapor Phase | Q41: Vapor Phase | S41: Liquid Phase | T41: Vapor Phase | V41: Liquid Phase | W41: Liquid Phase | X41: Vapor Phase | Y41: Vapor Phase | AB41: Liquid Phase | AC41: Liquid Phase | AD41: Liquid Phase | AE41: Liquid Phase | AF41: Vapor Phase | AH41: Vapor Phase | AI41: Vapor Phase | AJ41: Vapor Phase | AK41: Vapor Phase | AL41: Vapor Phase | AM41: Vapor Phase | AN41: Vapor Phase | AO41: Liquid Phase | AR41: Vapor Phase | AS41: Vapor Phase | AT41: Vapor Phase | AU41: Vapor Phase | AV41: Vapor Phase | AW41: Vapor Phase | AX41: Vapor Phase | AY41: Liquid Phase | AZ41: Vapor Phase | BC41: Vapor Phase | BD41: Vapor Phase
B42: Temperature | C42: C | D42: 30 | E42: 1114 | F42: -10.554718 | G42: 660.59126 | H42: 732.96885 | I42: 1230 | J42: 1230 | K42: 670.59853 | L42: 30 | M42: 451.57344 | N42: 30 | O42: 30 | P42: 30 | Q42: 72.178213 | R42: 5 | S42: 5 | T42: 5 | U42: -60 | V42: -60 | W42: 250.68601 | X42: -5.320321 | Y42: -60 | Z42: -78.159331 | AA42: -167 | AB42: -140 | AC42: -47.207088 | AD42: -104.13483 | AE42: -85.106054 | AF42: -140 | AG42: -152.45682 | AH42: -167 | AI42: -157 | AJ42: -157 | AK42: -79.808847 | AL42: -2 | AM42: -2 | AN42: 743 | AO42: -167 | AP42: -169.13916 | AQ42: -162 | AR42: -123 | AS42: -96.007384 | AT42: -96.007384 | AU42: -96.007384 | AV42: -71 | AW42: -71 | AX42: -71 | AY42: 1230 | AZ42: 30 | BA42: 876.49077 | BB42: 35 | BC42: 7712.0183 | BD42: 742.96482
B43: Pressure | C43: bar | D43: 1.013 | E43: 1.013 | F43: 1.013 | G43: 1.013 | H43: 1.013 | I43: 1.013 | J43: 1.013 | K43: 1.013 | L43: 1 | M43: 20 | N43: 20 | O43: 20 | P43: 20 | Q43: 30 | R43: 30 | S43: 30 | T43: 30 | U43: 30 | V43: 30 | W43: 30 | X43: 30 | Y43: 30 | Z43: 30 | AA43: 30 | AB43: 30 | AC43: 10 | AD43: 1.013 | AE43: 1.013 | AF43: 30 | AG43: 30 | AH43: 30 | AI43: 30 | AJ43: 30 | AK43: 30 | AL43: 30 | AM43: 30 | AN43: 30 | AO43: 30 | AP43: 1.013 | AQ43: 1.013 | AR43: 1.013 | AS43: 1.013 | AT43: 1.013 | AU43: 1.013 | AV43: 10 | AW43: 10 | AX43: 10 | AY43: 1.013 | AZ43: 10 | BA43: 1.013 | BB43: 1.013 | BC43: 1.013 | BD43: 1.013
B44: Molar Vapor Fraction | D44: 1 | E44: 1 | F44: 1 | G44: 1 | H44: 1 | I44: 1 | J44: 1 | K44: 1 | L44: 1 | M44: 1 | N44: 0.99988502 | O44: 0 | P44: 1 | Q44: 1 | R44: 0.99995237 | S44: 0 | T44: 1 | U44: 0.99928793 | V44: 0 | W44: 0 | X44: 1 | Y44: 1 | Z44: 0.99996672 | AA44: 0.87922871 | AB44: 0 | AC44: 0 | AD44: 0 | AE44: 0 | AF44: 1 | AG44: 0.98156341 | AH44: 1 | AI44: 1 | AJ44: 1 | AK44: 1 | AL44: 1 | AM44: 1 | AN44: 1 | AO44: 0 | AP44: 0.050558343 | AQ44: 0.37095439 | AR44: 1 | AS44: 1 | AT44: 1 | AU44: 1 | AV44: 1 | AW44: 1 | AX44: 1 | AY44: 0 | AZ44: 1 | BA44: 0.50143222 | BB44: 0.50143222 | BC44: 1 | BD44: 1
B45: Molar Liquid Fraction | D45: 0 | E45: 0 | F45: 0 | G45: 0 | H45: 0 | I45: 0 | J45: 0 | K45: 0 | L45: 0 | M45: 0 | N45: 0.00011497929 | O45: 1 | P45: 0 | Q45: 0 | R45: 4.762664e-05 | S45: 1 | T45: 0 | U45: 0.0007120714 | V45: 1 | W45: 1 | X45: 0 | Y45: 0 | Z45: 3.3275837e-05 | AA45: 0.12077129 | AB45: 1 | AC45: 1 | AD45: 1 | AE45: 1 | AF45: 0 | AG45: 0.018436593 | AH45: 0 | AI45: 0 | AJ45: 0 | AK45: 0 | AL45: 0 | AM45: 0 | AN45: 0 | AO45: 1 | AP45: 0.94944166 | AQ45: 0.62904561 | AR45: 0 | AS45: 0 | AT45: 0 | AU45: 0 | AV45: 0 | AW45: 0 | AX45: 0 | AY45: 1 | AZ45: 0 | BA45: 0.49856778 | BB45: 0.49856778 | BC45: 0 | BD45: 0
B46: Molar Solid Fraction | D46: 0 | E46: 0 | F46: 0 | G46: 0 | H46: 0 | I46: 0 | J46: 0 | K46: 0 | L46: 0 | M46: 0 | N46: 0 | O46: 0 | P46: 0 | Q46: 0 | R46: 0 | S46: 0 | T46: 0 | U46: 0 | V46: 0 | W46: 0 | X46: 0 | Y46: 0 | Z46: 0 | AA46: 0 | AB46: 0 | AC46: 0 | AD46: 0 | AE46: 0 | AF46: 0 | AG46: 0 | AH46: 0 | AI46: 0 | AJ46: 0 | AK46: 0 | AL46: 0 | AM46: 0 | AN46: 0 | AO46: 0 | AP46: 0 | AQ46: 0 | AR46: 0 | AS46: 0 | AT46: 0 | AU46: 0 | AV46: 0 | AW46: 0 | AX46: 0 | AY46: 0 | AZ46: 0 | BA46: 0 | BB46: 0 | BC46: 0 | BD46: 0
B47: Mass Vapor Fraction | D47: 1 | E47: 1 | F47: 1 | G47: 1 | H47: 1 | I47: 1 | J47: 1 | K47: 1 | L47: 1 | M47: 1 | N47: 0.9967679 | O47: 0 | P47: 1.0000005 | Q47: 1 | R47: 0.99878419 | S47: 0 | T47: 1 | U47: 0.98822426 | V47: 0 | W47: 0 | X47: 0.99999977 | Y47: 1 | Z47: 0.99949148 | AA47: 0.49826447 | AB47: 0 | AC47: 0 | AD47: 0 | AE47: 0 | AF47: 1 | AG47: 0.9139406 | AH47: 1 | AI47: 1 | AJ47: 1 | AK47: 1 | AL47: 1 | AM47: 1 | AN47: 1 | AO47: 0 | AP47: 0.02888122 | AQ47: 0.35068167 | AR47: 1 | AS47: 1 | AT47: 1 | AU47: 1 | AV47: 1 | AW47: 1 | AX47: 1 | AY47: 0 | AZ47: 1 | BA47: 0.72821883 | BB47: 0.72821883 | BC47: 1 | BD47: 1
B48: Mass Liquid Fraction | D48: 0 | E48: 0 | F48: 0 | G48: 0 | H48: 0 | I48: 0 | J48: 0 | K48: 0 | L48: 0 | M48: 0 | N48: 0.0032321027 | O48: 1 | P48: 0 | Q48: 0 | R48: 0.0012158145 | S48: 1 | T48: 0 | U48: 0.011775741 | V48: 1 | W48: 1 | X48: 2.2756469e-07 | Y48: 0 | Z48: 0.00050852202 | AA48: 0.50173553 | AB48: 1 | AC48: 1 | AD48: 1 | AE48: 1 | AF48: 0 | AG48: 0.086059403 | AH48: 0 | AI48: 0 | AJ48: 0 | AK48: 0 | AL48: 0 | AM48: 0 | AN48: 0 | AO48: 1 | AP48: 0.97111878 | AQ48: 0.64931833 | AR48: 0 | AS48: 0 | AT48: 0 | AU48: 0 | AV48: 0 | AW48: 0 | AX48: 0 | AY48: 1 | AZ48: 0 | BA48: 0.27178117 | BB48: 0.27178117 | BC48: 0 | BD48: 0
B49: Mass Solid Fraction | D49: 0 | E49: 0 | F49: 0 | G49: 0 | H49: 0 | I49: 0 | J49: 0 | K49: 0 | L49: 0 | M49: 0 | N49: 0 | O49: 0 | P49: 0 | Q49: 0 | R49: 0 | S49: 0 | T49: 0 | U49: 0 | V49: 0 | W49: 0 | X49: 0 | Y49: 0 | Z49: 0 | AA49: 0 | AB49: 0 | AC49: 0 | AD49: 0 | AE49: 0 | AF49: 0 | AG49: 0 | AH49: 0 | AI49: 0 | AJ49: 0 | AK49: 0 | AL49: 0 | AM49: 0 | AN49: 0 | AO49: 0 | AP49: 0 | AQ49: 0 | AR49: 0 | AS49: 0 | AT49: 0 | AU49: 0 | AV49: 0 | AW49: 0 | AX49: 0 | AY49: 0 | AZ49: 0 | BA49: 0 | BB49: 0 | BC49: 0 | BD49: 0
B50: Molar Enthalpy | C50: kcal/mol | D50: -17.760467 | E50: 7.8047125 | F50: -3.4822334 | G50: 1.9032867 | H50: 2.5567506 | I50: 7.3823903 | J50: 8.8733736 | K50: 3.7080778 | L50: -1.3828294 | M50: 1.8696017 | N50: -1.3918692 | O50: 22.634385 | P50: -1.3944097 | Q50: -1.0890586 | R50: -1.579896 | S50: 19.32718 | T50: -1.5808918 | U50: -2.0523747 | V50: 12.1075 | W50: 21.098334 | X50: 31.653217 | Y50: -2.0596901 | Z50: -2.1894438 | AA50: -3.0777336 | AB50: 5.1492127 | AC50: 30.041706 | AD50: 8.2024595 | AE50: 45.943855 | AF50: -3.0664649 | AG50: -3.1887881 | AH50: -1.9704971 | AI50: -1.8995756 | AJ50: -1.8995756 | AK50: -1.3658244 | AL50: -0.82874751 | AM50: -0.82874751 | AN50: -0.82874751 | AO50: -20.001742 | AP50: -20.001742 | AQ50: -19.281555 | AR50: -17.695201 | AS50: -17.478663 | AT50: -17.478663 | AU50: -17.478663 | AV50: -18.149159 | AW50: -18.149159 | AX50: -18.149159 | AY50: 45.20683 | AZ50: 0.012847868 | BA50: 22.545112 | BB50: 9.185074 | BC50: 18.317678 | BD50: -85.290836
B51: Mass Enthalpy | C51: kcal/kg | D51: -1107.0705 | E51: 3871.6156 | F51: -751.30357 | G51: 410.64052 | H51: 551.62754 | I51: 1592.7755 | J51: 2029.2581 | K51: 848.00294 | L51: -316.24024 | M51: 427.56054 | N51: -318.30756 | O51: 184.21399 | P51: -319.83096 | Q51: -249.79363 | R51: -362.37531 | S51: 173.65257 | T51: -363.02781 | U51: -471.29669 | V51: 168.1653 | W51: 269.07495 | X51: 1347.2084 | Y51: -478.09566 | Z51: -508.21411 | AA51: -714.40411 | AB51: 238.01889 | AC51: 1107.9663 | AD51: 292.43374 | AE51: 1742.9977 | AF51: -856.00155 | AG51: -890.14797 | AH51: -782.46489 | AI51: -754.30266 | AJ51: -754.30266 | AK51: -542.35532 | AL51: -329.08742 | AM51: -329.08742 | AN51: -329.08742 | AO51: -1253.2058 | AP51: -1253.2058 | AQ51: -1208.0825 | AR51: -1108.6898 | AS51: -1095.1227 | AT51: -1095.1227 | AU51: -1095.1227 | AV51: -1160.3023 | AW51: -1160.3023 | AX51: -1160.3023 | AY51: 3763.7857 | AZ51: 0.40151093 | BA51: 1023.2185 | BB51: 416.86808 | BC51: 416.86808 | BD51: -1941.0226
B52: Molar Entropy | C52: cal/mol-K | D52: -19.118113 | E52: 10.905624 | F52: -3.4787063 | G52: 6.460285 | H52: 7.1342323 | I52: 11.017206 | J52: 11.874367 | K52: 7.5963095 | L52: -1.2520701 | M52: -0.54940968 | N52: -7.2359702 | O52: -81.268213 | P52: -7.2276636 | Q52: -7.093824 | R52: -8.6739675 | S52: -77.581367 | T52: -8.6706855 | U52: -10.601095 | V52: -61.587866 | W52: -37.981172 | X52: -3.6318097 | Y52: -10.563851 | Z52: -11.200091 | AA52: -17.490913 | AB52: -32.771087 | AC52: -18.284216 | AD52: -36.752003 | AE52: -13.676644 | AF52: -13.861707 | AG52: -14.831407 | AH52: -14.300922 | AI52: -13.662363 | AJ52: -13.662363 | AK52: -10.135054 | AL52: -7.8013408 | AM52: -7.8013408 | AN52: -7.8013408 | AO52: -44.248749 | AP52: -43.875385 | AQ52: -37.296421 | AR52: -23.624966 | AS52: -22.298708 | AT52: -22.298708 | AU52: -22.298708 | AV52: -26.401582 | AW52: -26.401582 | AX52: -26.401582 | AY52: 2.0552916 | AZ52: -4.4883315 | BA52: 3.6736486 | BB52: -17.970273 | BC52: 44.258828 | BD52: 14.197766
B53: Mass Entropy | C53: cal/gm-K | D53: -1.1916973 | E53: 5.4098578 | F53: -0.75054259 | G53: 1.3938282 | H53: 1.5392346 | I53: 2.3769992 | J53: 2.7155574 | K53: 1.7372054 | L53: -0.28633679 | M53: -0.12564489 | N53: -1.6547992 | O53: -0.66141589 | P53: -1.6577843 | Q53: -1.6270859 | R53: -1.989518 | S53: -0.69705999 | T53: -1.9910913 | U53: -2.4343806 | V53: -0.85541538 | W53: -0.4843881 | X53: -0.15457527 | Y53: -2.4520831 | Z53: -2.5997673 | AA53: -4.059994 | AB53: -1.5148214 | AC53: -0.67433901 | AD53: -1.3102809 | AE53: -0.51885851 | AF53: -3.869486 | AG53: -4.1401769 | AH53: -5.6787546 | AI53: -5.4251887 | AJ53: -5.4251887 | AK53: -4.0245294 | AL53: -3.0978351 | AM53: -3.0978351 | AN53: -3.0978351 | AO53: -2.7723979 | AP53: -2.7490049 | AQ53: -2.336801 | AR53: -1.4802183 | AS53: -1.3971218 | AT53: -1.3971218 | AU53: -1.3971218 | AV53: -1.6878919 | AW53: -1.6878919 | AX53: -1.6878919 | AY53: 0.17111745 | AZ53: -0.14026562 | BA53: 0.16672994 | BB53: -0.81558767 | BC53: 1.0072288 | BD53: 0.32310839
B54: Molar Density | C54: kmol/cum | D54: 0.040272705 | E54: 0.0087821117 | F54: 0.046399587 | G54: 0.013045576 | H54: 0.012107248 | I54: 0.0081043355 | J54: 0.0081043506 | K54: 0.0129073 | L54: 0.039669876 | M54: 0.33030514 | N54: 0.79118444 | O54: 7.8947263 | P54: 0.79110404 | Q54: 1.0378664 | R54: 1.2932104 | S54: 8.7040409 | T54: 1.2931579 | U54: 1.7048034 | V54: 13.024725 | W54: 6.6905015 | X54: 1.7858013 | Y54: 1.7037704 | Z54: 1.8724672 | AA54: 3.9650326 | AB54: 27.109861 | AC54: 19.763367 | AD54: 22.05704 | AE54: 24.487248 | AF54: 2.8177846 | AG54: 3.1888371 | AH54: 3.5515916 | AI54: 3.2051312 | AJ54: 3.2051312 | AK54: 1.8609659 | AL54: 1.3192804 | AM54: 1.3192804 | AN54: 1.3192804 | AO54: 30.384215 | AP54: 2.1904309 | AQ54: 0.30261775 | AR54: 0.082419393 | AS54: 0.069479065 | AT54: 0.069479065 | AU54: 0.069479065 | AV54: 0.63897006 | AW54: 0.63897006 | AX54: 0.63897006 | AY54: 48.74804 | AZ54: 0.39966852 | BA54: 0.021126424 | BB54: 0.078844943 | BC54: 0.0015257398 | BD54: 0.011987515
B55: Mass Density | C55: kg/cum | D55: 0.64608535 | E55: 0.017703683 | F55: 0.21505846 | G55: 0.060465225 | H55: 0.056116147 | I55: 0.037562962 | J55: 0.03543804 | K55: 0.056439985 | L55: 0.17346519 | M55: 1.4443312 | N55: 3.4596265 | O55: 970.02552 | P55: 3.449082 | Q55: 4.5249246 | R55: 5.6381819 | S55: 968.74214 | T55: 5.6313668 | U55: 7.423976 | V55: 937.74914 | W55: 524.60639 | X55: 41.958137 | Y55: 7.3400355 | Z55: 8.0668001 | AA55: 17.081808 | AB55: 586.48471 | AC55: 535.86944 | AD55: 618.67683 | AE55: 645.46186 | AF55: 10.094184 | AG55: 11.42341 | AH55: 8.944045 | AI55: 8.0715468 | AJ55: 8.0715468 | AK55: 4.6865082 | AL55: 3.3223705 | AM55: 3.3223705 | AN55: 3.3223705 | AO55: 484.94608 | AP55: 34.960287 | AQ55: 4.8299188 | AR55: 1.3154515 | AS55: 1.1089179 | AT55: 1.1089179 | AU55: 1.1089179 | AV55: 9.9946098 | AW55: 9.9946098 | AX55: 9.9946098 | AY55: 585.51271 | AZ55: 12.788913 | BA55: 0.46548964 | BB55: 1.7372322 | BC55: 0.067042818 | BD55: 0.52674563
B56: Enthalpy Flow | C56: Gcal/hr | D56: -234.20372 | E56: 7.8047125e-08 | F56: -772.96496 | G56: 422.47999 | H56: 567.53191 | I56: 1638.698 | J56: 2053.6345 | K56: 858.18954 | L56: -320.03906 | M56: 432.69659 | N56: -322.13122 | O56: 0.79451012 | P56: -322.65728 | Q56: -252.00104 | R56: -365.5776 | S56: 0.21299504 | T56: -365.79059 | U56: -474.88344 | V56: 1.9958341 | W56: 3.0717575 | X56: 0.60938508 | Y56: -476.27623 | Z56: -506.28006 | AA56: -711.6854 | AB56: 47.874723 | AC56: 145.87942 | AD56: 17.799759 | AE56: 123.39809 | AF56: -680.56925 | AG56: -707.71757 | AH56: -402.74781 | AI56: -388.25224 | AJ56: -388.25224 | AK56: -279.15939 | AL56: -169.38682 | AM56: -154.97441 | AN56: -14.412412 | AO56: -351.37601 | AP56: -351.37601 | AQ56: -338.72428 | AR56: -310.85638 | AS56: -307.05239 | AT56: -303.98186 | AU56: -3.0705239 | AV56: -80.61107 | AW56: -79.804959 | AX56: -0.8061107 | AY56: 62.928021 | AZ56: 0.017987015 | BA56: 62.946008 | BB56: 25.64475 | BC56: 25.64475 | BD56: -119.40717
B57: Average MW | D57: 16.04276 | E57: 2.01588 | F57: 4.6349219 | G57: 4.6349219 | H57: 4.6349219 | I57: 4.6349219 | J57: 4.3727181 | K57: 4.3727181 | L57: 4.3727181 | M57: 4.3727181 | N57: 4.3727181 | O57: 122.87006 | P57: 4.3598336 | Q57: 4.3598336 | R57: 4.3598336 | S57: 111.29798 | T57: 4.3547403 | U57: 4.3547403 | V57: 71.997614 | W57: 78.410622 | X57: 23.495412 | Y57: 4.308113 | Z57: 4.308113 | AA57: 4.308113 | AB57: 21.63363 | AC57: 27.114278 | AD57: 28.048951 | AE57: 26.359102 | AF57: 3.5823124 | AG57: 3.5823124 | AH57: 2.5183202 | AI57: 2.5183202 | AJ57: 2.5183202 | AK57: 2.5183202 | AL57: 2.5183202 | AM57: 2.5183202 | AN57: 2.5183202 | AO57: 15.960461 | AP57: 15.960461 | AQ57: 15.960461 | AR57: 15.960461 | AS57: 15.960461 | AT57: 15.960461 | AU57: 15.960461 | AV57: 15.64175 | AW57: 15.64175 | AX57: 15.64175 | AY57: 12.011 | AZ57: 31.9988 | BA57: 22.033527 | BB57: 22.033527 | BC57: 43.941187 | BD57: 43.941187
B58: Mole Flows | C58: kmol/hr | D58: 13186.8 | E58: 1e-05 | F58: 221973.91 | G58: 221973.91 | H58: 221973.91 | I58: 221973.91 | J58: 231437.85 | K58: 231437.85 | L58: 231437.85 | M58: 231437.85 | N58: 231437.85 | O58: 35.101909 | P58: 231393.45 | Q58: 231393.45 | R58: 231393.45 | S58: 11.020493 | T58: 231382.43 | U58: 231382.43 | V58: 164.84279 | W58: 145.59242 | X58: 19.251916 | Y58: 231236.84 | Z58: 231236.84 | AA58: 231236.84 | AB58: 9297.484 | AC58: 4855.8969 | AD58: 2170.0515 | AE58: 2685.8454 | AF58: 221939.36 | AG58: 221939.36 | AH58: 204388.93 | AI58: 204388.93 | AJ58: 204388.93 | AK58: 204388.93 | AL58: 204388.93 | AM58: 186998.34 | AN58: 17390.595 | AO58: 17567.27 | AP58: 17567.27 | AQ58: 17567.27 | AR58: 17567.27 | AS58: 17567.27 | AT58: 17391.597 | AU58: 175.6727 | AV58: 4441.5872 | AW58: 4397.1713 | AX58: 44.415872 | AY58: 1392.0025 | AZ58: 1400 | BA58: 2792.0025 | BB58: 2792.0025 | BC58: 1400 | BD58: 1400
B59: H2 | C59: kmol/hr | D59: 0 | E59: 1e-05 | F59: 180869.01 | G59: 180869.01 | H59: 180869.01 | I59: 180869.01 | J59: 197643.84 | K59: 197643.84 | L59: 197643.84 | M59: 197643.84 | N59: 197643.84 | O59: 0.20996271 | P59: 197626.38 | Q59: 197626.38 | R59: 197626.38 | S59: 0.089658361 | T59: 197626.3 | U59: 197626.3 | V59: 1.0236404 | W59: 5.7435524e-08 | X59: 1.0237214 | Y59: 197626.3 | Z59: 197626.3 | AA59: 197626.3 | AB59: 127.16531 | AC59: 1.0538853e-09 | AD59: 1.0538853e-09 | AE59: 2.1702471e-39 | AF59: 197499.13 | AG59: 197499.13 | AH59: 197069.3 | AI59: 197069.3 | AJ59: 197069.3 | AK59: 197069.3 | AL59: 197069.3 | AM59: 180301.51 | AN59: 16767.799 | AO59: 446.07188 | AP59: 446.07188 | AQ59: 446.07188 | AR59: 446.07188 | AS59: 446.07188 | AT59: 441.61116 | AU59: 4.4607188 | AV59: 127.16531 | AW59: 125.89366 | AX59: 1.2716531 | AY59: 0 | AZ59: 0 | BA59: 0 | BB59: 0 | BC59: 0 | BD59: 0
B60: CH4 | C60: kmol/hr | D60: 13186.8 | E60: 0 | F60: 40695.935 | G60: 40695.935 | H60: 40695.935 | I60: 40695.935 | J60: 28344.536 | K60: 28344.536 | L60: 28344.536 | M60: 28344.536 | N60: 28344.536 | O60: 0.20312417 | P60: 28341.96 | Q60: 28341.96 | R60: 28341.96 | S60: 0.11235901 | T60: 28341.848 | U60: 28341.848 | V60: 3.1934555 | W60: 7.4918187e-06 | X60: 3.1937008 | Y60: 28341.848 | Z60: 28341.848 | AA60: 28341.848 | AB60: 4314.6358 | AC60: 0.43146133 | AD60: 0.43146133 | AE60: 1.1295021e-14 | AF60: 24027.213 | AG60: 24027.213 | AH60: 7317.8218 | AI60: 7317.8218 | AJ60: 7317.8218 | AK60: 7317.8218 | AL60: 7317.8218 | AM60: 6695.1791 | AN60: 622.64269 | AO60: 16709.993 | AP60: 16709.993 | AQ60: 16709.993 | AR60: 16709.993 | AS60: 16709.993 | AT60: 16542.894 | AU60: 167.09993 | AV60: 4314.2043 | AW60: 4271.0623 | AX60: 43.142043 | AY60: 0 | AZ60: 0 | BA60: 0 | BB60: 0 | BC60: 0 | BD60: 0
B61: C2H6 | C61: kmol/hr | D61: 0 | E61: 0 | F61: 3.8575921 | G61: 3.8575921 | H61: 3.8575921 | I61: 3.8575921 | J61: 126.35705 | K61: 126.35705 | L61: 126.35705 | M61: 126.35705 | N61: 126.35705 | O61: 0.0063581651 | P61: 126.34368 | Q61: 126.34368 | R61: 126.34368 | S61: 0.0042551352 | T61: 126.33942 | U61: 126.33942 | V61: 0.26025888 | W61: 0.00010754155 | X61: 0.26017223 | Y61: 126.33933 | Z61: 126.33933 | AA61: 126.33933 | AB61: 122.44256 | AC61: 122.44253 | AD61: 9.4418223e-13 | AE61: 122.44253 | AF61: 3.8967786 | AG61: 3.8967786 | AH61: 0.0032801066 | AI61: 0.0032801066 | AJ61: 0.0032801066 | AK61: 0.0032801066 | AL61: 0.0032801066 | AM61: 0.0030010161 | AN61: 0.00027909048 | AO61: 3.8934988 | AP61: 3.8934988 | AQ61: 3.8934988 | AR61: 3.8934988 | AS61: 3.8934988 | AT61: 3.8545638 | AU61: 0.038934988 | AV61: 2.751031e-05 | AW61: 2.7235207e-05 | AX61: 2.751031e-07 | AY61: 0 | AZ61: 0 | BA61: 0 | BB61: 0 | BC61: 0 | BD61: 0
B62: C2H4 | C62: kmol/hr | D62: 0 | E62: 0 | F62: 338.47624 | G62: 338.47624 | H62: 338.47624 | I62: 338.47624 | J62: 2511.5369 | K62: 2511.5369 | L62: 2511.5369 | M62: 2511.5369 | N62: 2511.5369 | O62: 0.084735456 | P62: 2511.2666 | Q62: 2511.2666 | R62: 2511.2666 | S62: 0.054819771 | T62: 2511.2118 | U62: 2511.2118 | V62: 2.8590082 | W62: 0.0003748476 | X62: 2.8588807 | Y62: 2511.2117 | Z62: 2511.2117 | AA62: 2511.2117 | AB62: 2169.3989 | AC62: 2169.1826 | AD62: 2167.0134 | AE62: 2.1691536 | AF62: 341.8128 | AG62: 341.8128 | AH62: 1.7670971 | AI62: 1.7670971 | AJ62: 1.7670971 | AK62: 1.7670971 | AL62: 1.7670971 | AM62: 1.6167422 | AN62: 0.15035486 | AO62: 340.04585 | AP62: 340.04585 | AQ62: 340.04585 | AR62: 340.04585 | AS62: 340.04585 | AT62: 336.64539 | AU62: 3.4004585 | AV62: 0.21626515 | AW62: 0.2141025 | AX62: 0.0021626515 | AY62: 0 | AZ62: 0 | BA62: 0 | BB62: 0 | BC62: 0 | BD62: 0
B63: C2H2 | C63: kmol/hr | D63: 0 | E63: 0 | F63: 66.628656 | G63: 66.628656 | H63: 66.628656 | I63: 66.628656 | J63: 2624.5266 | K63: 2624.5266 | L63: 2624.5266 | M63: 2624.5266 | N63: 2624.5266 | O63: 0.14815622 | P63: 2624.2552 | Q63: 2624.2552 | R63: 2624.2552 | S63: 0.11036678 | T63: 2624.1448 | U63: 2624.1448 | V63: 11.904654 | W63: 0.0046312008 | X63: 11.900967 | Y63: 2624.1412 | Z63: 2624.1412 | AA63: 2624.1412 | AB63: 2556.8379 | AC63: 2556.8366 | AD63: 2.6065817 | AE63: 2554.23 | AF63: 67.303296 | AG63: 67.303296 | AH63: 0.037903286 | AI63: 0.037903286 | AJ63: 0.037903286 | AK63: 0.037903286 | AL63: 0.037903286 | AM63: 0.034678254 | AN63: 0.0032250312 | AO63: 67.265395 | AP63: 67.265395 | AQ63: 67.265395 | AR63: 67.265395 | AS63: 67.265395 | AT63: 66.592741 | AU63: 0.67265395 | AV63: 0.001249196 | AW63: 0.001236704 | AX63: 1.249196e-05 | AY63: 0 | AZ63: 0 | BA63: 0 | BB63: 0 | BC63: 0 | BD63: 0
B64: C3-C5 | C64: kmol/hr | D64: 0 | E64: 0 | F64: 0 | G64: 0 | H64: 0 | I64: 0 | J64: 0 | K64: 0 | L64: 0 | M64: 0 | N64: 0 | O64: 0 | P64: 0 | Q64: 0 | R64: 0 | S64: 0 | T64: 0 | U64: 0 | V64: 0 | W64: 0 | X64: 0 | Y64: 0 | Z64: 0 | AA64: 0 | AB64: 0 | AC64: 0 | AD64: 0 | AE64: 0 | AF64: 0 | AG64: 0 | AH64: 0 | AI64: 0 | AJ64: 0 | AK64: 0 | AL64: 0 | AM64: 0 | AN64: 0 | AO64: 0 | AP64: 0 | AQ64: 0 | AR64: 0 | AS64: 0 | AT64: 0 | AU64: 0 | AV64: 0 | AW64: 0 | AX64: 0 | AY64: 0 | AZ64: 0 | BA64: 0 | BB64: 0 | BC64: 0 | BD64: 0
B65: BEN | C65: kmol/hr | D65: 0 | E65: 0 | F65: 3.5999699e-07 | G65: 3.5999699e-07 | H65: 3.5999699e-07 | I65: 3.5999699e-07 | J65: 153.98553 | K65: 153.98553 | L65: 153.98553 | M65: 153.98553 | N65: 153.98553 | O65: 2.2504466 | P65: 154.61621 | Q65: 154.61621 | R65: 154.61621 | S65: 2.8943025 | T65: 151.72191 | U65: 151.72191 | V65: 144.73274 | W65: 144.71826 | X65: 0.014474357 | Y65: 7.0036468 | Z65: 7.0036468 | AA65: 7.0036468 | AB65: 7.0036464 | AC65: 7.0036464 | AD65: 5.2571404e-239 | AE65: 7.0036464 | AF65: 3.6363333e-07 | AG65: 3.6363333e-07 | AH65: 7.8261764e-17 | AI65: 7.8261764e-17 | AJ65: 7.8261764e-17 | AK65: 7.8261764e-17 | AL65: 7.8261764e-17 | AM65: 7.16028e-17 | AN65: 6.6589645e-18 | AO65: 3.6363333e-07 | AP65: 3.6363333e-07 | AQ65: 3.6363333e-07 | AR65: 3.6363333e-07 | AS65: 3.6363333e-07 | AT65: 3.5999699e-07 | AU65: 3.6363333e-09 | AV65: 2.5258933e-26 | AW65: 2.5006344e-26 | AX65: 2.5258933e-28 | AY65: 0 | AZ65: 0 | BA65: 0 | BB65: 0 | BC65: 0 | BD65: 0
B66: NAP | C66: kmol/hr | D66: 0 | E66: 0 | F66: 1.8118093e-56 | G66: 1.8118093e-56 | H66: 1.8118093e-56 | I66: 1.8118093e-56 | J66: 33.068929 | K66: 33.068929 | L66: 33.068929 | M66: 33.068929 | N66: 33.068929 | O66: 32.199125 | P66: 8.6237759 | Q66: 8.6237759 | R66: 8.6237759 | S66: 7.7547311 | T66: 0.86904475 | U66: 0.86904475 | V66: 0.86903727 | W66: 0.86903727 | X66: 7.8992484e-11 | Y66: 7.4870779e-06 | Z66: 7.4870779e-06 | AA66: 7.4870779e-06 | AB66: 7.4870779e-06 | AC66: 7.4870779e-06 | AD66: 0 | AE66: 7.4870779e-06 | AF66: 8.0486058e-20 | AG66: 8.0486058e-20 | AH66: 0 | AI66: 0 | AJ66: 0 | AK66: 0 | AL66: 0 | AM66: 0 | AN66: 0 | AO66: 0 | AP66: 0 | AQ66: 0 | AR66: 0 | AS66: 0 | AT66: 0 | AU66: 0 | AV66: 1.8301104e-56 | AW66: 1.8118093e-56 | AX66: 1.8301104e-58 | AY66: 0 | AZ66: 0 | BA66: 0 | BB66: 0 | BC66: 0 | BD66: 0
B67: C | C67: kmol/hr | D67: 0 | E67: 0 | F67: 0 | G67: 0 | H67: 0 | I67: 0 | J67: 0 | K67: 0 | L67: 0 | M67: 0 | N67: 0 | O67: 0 | P67: 0 | Q67: 0 | R67: 0 | S67: 0 | T67: 0 | U67: 0 | V67: 0 | W67: 0 | X67: 0 | Y67: 0 | Z67: 0 | AA67: 0 | AB67: 0 | AC67: 0 | AD67: 0 | AE67: 0 | AF67: 0 | AG67: 0 | AH67: 0 | AI67: 0 | AJ67: 0 | AK67: 0 | AL67: 0 | AM67: 0 | AN67: 0 | AO67: 0 | AP67: 0 | AQ67: 0 | AR67: 0 | AS67: 0 | AT67: 0 | AU67: 0 | AV67: 0 | AW67: 0 | AX67: 0 | AY67: 1392.0025 | AZ67: 0 | BA67: 1392.0025 | BB67: 1392.0025 | BC67: 0 | BD67: 0
B68: WATER | C68: kmol/hr | D68: 0 | E68: 0 | F68: 0 | G68: 0 | H68: 0 | I68: 0 | J68: 0 | K68: 0 | L68: 0 | M68: 0 | N68: 0 | O68: 0 | P68: 0 | Q68: 0 | R68: 0 | S68: 0 | T68: 0 | U68: 0 | V68: 0 | W68: 0 | X68: 0 | Y68: 0 | Z68: 0 | AA68: 0 | AB68: 0 | AC68: 0 | AD68: 0 | AE68: 0 | AF68: 0 | AG68: 0 | AH68: 0 | AI68: 0 | AJ68: 0 | AK68: 0 | AL68: 0 | AM68: 0 | AN68: 0 | AO68: 0 | AP68: 0 | AQ68: 0 | AR68: 0 | AS68: 0 | AT68: 0 | AU68: 0 | AV68: 0 | AW68: 0 | AX68: 0 | AY68: 0 | AZ68: 0 | BA68: 0 | BB68: 0 | BC68: 0 | BD68: 0
B69: O2 | C69: kmol/hr | D69: 0 | E69: 0 | F69: 0 | G69: 0 | H69: 0 | I69: 0 | J69: 0 | K69: 0 | L69: 0 | M69: 0 | N69: 0 | O69: 0 | P69: 0 | Q69: 0 | R69: 0 | S69: 0 | T69: 0 | U69: 0 | V69: 0 | W69: 0 | X69: 0 | Y69: 0 | Z69: 0 | AA69: 0 | AB69: 0 | AC69: 0 | AD69: 0 | AE69: 0 | AF69: 0 | AG69: 0 | AH69: 0 | AI69: 0 | AJ69: 0 | AK69: 0 | AL69: 0 | AM69: 0 | AN69: 0 | AO69: 0 | AP69: 0 | AQ69: 0 | AR69: 0 | AS69: 0 | AT69: 0 | AU69: 0 | AV69: 0 | AW69: 0 | AX69: 0 | AY69: 0 | AZ69: 1400 | BA69: 1400 | BB69: 1400 | BC69: 7.9975 | BD69: 7.9975
B70: CO2 | C70: kmol/hr | D70: 0 | E70: 0 | F70: 0 | G70: 0 | H70: 0 | I70: 0 | J70: 0 | K70: 0 | L70: 0 | M70: 0 | N70: 0 | O70: 0 | P70: 0 | Q70: 0 | R70: 0 | S70: 0 | T70: 0 | U70: 0 | V70: 0 | W70: 0 | X70: 0 | Y70: 0 | Z70: 0 | AA70: 0 | AB70: 0 | AC70: 0 | AD70: 0 | AE70: 0 | AF70: 0 | AG70: 0 | AH70: 0 | AI70: 0 | AJ70: 0 | AK70: 0 | AL70: 0 | AM70: 0 | AN70: 0 | AO70: 0 | AP70: 0 | AQ70: 0 | AR70: 0 | AS70: 0 | AT70: 0 | AU70: 0 | AV70: 0 | AW70: 0 | AX70: 0 | AY70: 0 | AZ70: 0 | BA70: 0 | BB70: 0 | BC70: 1392.0025 | BD70: 1392.0025
B71: Mole Fractions
B72: H2 | D72: 0 | E72: 1 | F72: 0.81482104 | G72: 0.81482104 | H72: 0.81482104 | I72: 0.81482104 | J72: 0.85398235 | K72: 0.85398235 | L72: 0.85398235 | M72: 0.85398235 | N72: 0.85398235 | O72: 0.0059815184 | P72: 0.85407078 | Q72: 0.85407078 | R72: 0.85407078 | S72: 0.0081356038 | T72: 0.85411107 | U72: 0.85411107 | V72: 0.0062097975 | W72: 3.9449529e-10 | X72: 0.053175039 | Y72: 0.85464883 | Z72: 0.85464883 | AA72: 0.85464883 | AB72: 0.013677389 | AC72: 2.1703206e-13 | AD72: 4.8564991e-13 | AE72: 8.080313e-43 | AF72: 0.88987881 | AG72: 0.88987881 | AH72: 0.96418774 | AI72: 0.96418774 | AJ72: 0.96418774 | AK72: 0.96418774 | AL72: 0.96418774 | AM72: 0.96418774 | AN72: 0.96418774 | AO72: 0.025392214 | AP72: 0.025392214 | AQ72: 0.025392214 | AR72: 0.025392214 | AS72: 0.025392214 | AT72: 0.025392214 | AU72: 0.025392214 | AV72: 0.028630601 | AW72: 0.028630601 | AX72: 0.028630601 | AY72: 0 | AZ72: 0 | BA72: 0 | BB72: 0 | BC72: 0 | BD72: 0
B73: CH4 | D73: 1 | E73: 0 | F73: 0.18333657 | G73: 0.18333657 | H73: 0.18333657 | I73: 0.18333657 | J73: 0.12247148 | K73: 0.12247148 | L73: 0.12247148 | M73: 0.12247148 | N73: 0.12247148 | O73: 0.0057866986 | P73: 0.12248385 | Q73: 0.12248385 | R73: 0.12248385 | S73: 0.010195462 | T73: 0.1224892 | U73: 0.1224892 | V73: 0.019372734 | W73: 5.1457477e-08 | X73: 0.16589002 | Y73: 0.12256632 | Z73: 0.12256632 | AA73: 0.12256632 | AB73: 0.46406488 | AC73: 8.8853067e-05 | AD73: 0.00019882539 | AE73: 4.2053877e-18 | AF73: 0.10826026 | AG73: 0.10826026 | AH73: 0.035803415 | AI73: 0.035803415 | AJ73: 0.035803415 | AK73: 0.035803415 | AL73: 0.035803415 | AM73: 0.035803415 | AN73: 0.035803415 | AO73: 0.95120035 | AP73: 0.95120035 | AQ73: 0.95120035 | AR73: 0.95120035 | AS73: 0.95120035 | AT73: 0.95120035 | AU73: 0.95120035 | AV73: 0.97132042 | AW73: 0.97132042 | AX73: 0.97132042 | AY73: 0 | AZ73: 0 | BA73: 0 | BB73: 0 | BC73: 0 | BD73: 0
B74: C2H6 | D74: 0 | E74: 0 | F74: 1.7378583e-05 | G74: 1.7378583e-05 | H74: 1.7378583e-05 | I74: 1.7378583e-05 | J74: 0.00054596539 | K74: 0.00054596539 | L74: 0.00054596539 | M74: 0.00054596539 | N74: 0.00054596539 | O74: 0.00018113445 | P74: 0.00054601232 | Q74: 0.00054601232 | R74: 0.00054601232 | S74: 0.00038611116 | T74: 0.00054601994 | U74: 0.00054601994 | V74: 0.0015788308 | W74: 7.38648e-07 | X74: 0.013514095 | Y74: 0.00054636335 | Z74: 0.00054636335 | AA74: 0.00054636335 | AB74: 0.013169429 | AC74: 0.025215224 | AD74: 4.350967e-16 | AE74: 0.045588078 | AF74: 1.7557853e-05 | AG74: 1.7557853e-05 | AH74: 1.6048357e-08 | AI74: 1.6048357e-08 | AJ74: 1.6048357e-08 | AK74: 1.6048357e-08 | AL74: 1.6048357e-08 | AM74: 1.6048357e-08 | AN74: 1.6048357e-08 | AO74: 0.00022163368 | AP74: 0.00022163368 | AQ74: 0.00022163368 | AR74: 0.00022163368 | AS74: 0.00022163368 | AT74: 0.00022163368 | AU74: 0.00022163368 | AV74: 6.1938017e-09 | AW74: 6.1938017e-09 | AX74: 6.1938017e-09 | AY74: 0 | AZ74: 0 | BA74: 0 | BB74: 0 | BC74: 0 | BD74: 0
B75: C2H4 | D75: 0 | E75: 0 | F75: 0.001524847 | G75: 0.001524847 | H75: 0.001524847 | I75: 0.001524847 | J75: 0.010851885 | K75: 0.010851885 | L75: 0.010851885 | M75: 0.010851885 | N75: 0.010851885 | O75: 0.0024139843 | P75: 0.010852799 | Q75: 0.010852799 | R75: 0.010852799 | S75: 0.0049743485 | T75: 0.010853079 | U75: 0.010853079 | V75: 0.017343847 | W75: 2.5746368e-06 | X75: 0.1484985 | Y75: 0.010859912 | Z75: 0.010859912 | AA75: 0.010859912 | AB75: 0.23333182 | AC75: 0.44671101 | AD75: 0.99860001 | AE75: 0.00080762415 | AF75: 0.001540118 | AG75: 0.001540118 | AH75: 8.645757e-06 | AI75: 8.645757e-06 | AJ75: 8.645757e-06 | AK75: 8.645757e-06 | AL75: 8.645757e-06 | AM75: 8.645757e-06 | AN75: 8.645757e-06 | AO75: 0.019356784 | AP75: 0.019356784 | AQ75: 0.019356784 | AR75: 0.019356784 | AS75: 0.019356784 | AT75: 0.019356784 | AU75: 0.019356784 | AV75: 4.8690962e-05 | AW75: 4.8690962e-05 | AX75: 4.8690962e-05 | AY75: 0 | AZ75: 0 | BA75: 0 | BB75: 0 | BC75: 0 | BD75: 0
B76: C2H2 | D76: 0 | E76: 0 | F76: 0.00030016436 | G76: 0.00030016436 | H76: 0.00030016436 | I76: 0.00030016436 | J76: 0.011340093 | K76: 0.011340093 | L76: 0.011340093 | M76: 0.011340093 | N76: 0.011340093 | O76: 0.0042207454 | P76: 0.011341095 | Q76: 0.011341095 | R76: 0.011341095 | S76: 0.010014687 | T76: 0.011341159 | U76: 0.011341159 | V76: 0.072218228 | W76: 3.1809354e-05 | X76: 0.6181705 | Y76: 0.011348283 | Z76: 0.011348283 | AA76: 0.011348283 | AB76: 0.2750032 | AC76: 0.52654261 | AD76: 0.0012011612 | AE76: 0.95099668 | AF76: 0.00030325084 | AG76: 0.00030325084 | AH76: 1.8544686e-07 | AI76: 1.8544686e-07 | AJ76: 1.8544686e-07 | AK76: 1.8544686e-07 | AL76: 1.8544686e-07 | AM76: 1.8544686e-07 | AN76: 1.8544686e-07 | AO76: 0.0038290181 | AP76: 0.0038290181 | AQ76: 0.0038290181 | AR76: 0.0038290181 | AS76: 0.0038290181 | AT76: 0.0038290181 | AU76: 0.0038290181 | AV76: 2.8124991e-07 | AW76: 2.8124991e-07 | AX76: 2.8124991e-07 | AY76: 0 | AZ76: 0 | BA76: 0 | BB76: 0 | BC76: 0 | BD76: 0
B77: C3-C5 | D77: 0 | E77: 0 | F77: 0 | G77: 0 | H77: 0 | I77: 0 | J77: 0 | K77: 0 | L77: 0 | M77: 0 | N77: 0 | O77: 0 | P77: 0 | Q77: 0 | R77: 0 | S77: 0 | T77: 0 | U77: 0 | V77: 0 | W77: 0 | X77: 0 | Y77: 0 | Z77: 0 | AA77: 0 | AB77: 0 | AC77: 0 | AD77: 0 | AE77: 0 | AF77: 0 | AG77: 0 | AH77: 0 | AI77: 0 | AJ77: 0 | AK77: 0 | AL77: 0 | AM77: 0 | AN77: 0 | AO77: 0 | AP77: 0 | AQ77: 0 | AR77: 0 | AS77: 0 | AT77: 0 | AU77: 0 | AV77: 0 | AW77: 0 | AX77: 0 | AY77: 0 | AZ77: 0 | BA77: 0 | BB77: 0 | BC77: 0 | BD77: 0
B78: BEN | D78: 0 | E78: 0 | F78: 1.6217987e-12 | G78: 1.6217987e-12 | H78: 1.6217987e-12 | I78: 1.6217987e-12 | J78: 0.00066534292 | K78: 0.00066534292 | L78: 0.00066534292 | M78: 0.00066534292 | N78: 0.00066534292 | O78: 0.064111802 | P78: 0.00066819614 | Q78: 0.00066819614 | R78: 0.00066819614 | S78: 0.26262914 | T78: 0.00065571923 | U78: 0.00065571923 | V78: 0.87800465 | W78: 0.99399585 | X78: 0.00075183981 | Y78: 3.0287764e-05 | Z78: 3.0287764e-05 | AA78: 3.0287764e-05 | AB78: 0.00075328405 | AC78: 0.0014422972 | AD78: 2.4225879e-242 | AE78: 0.0026076134 | AF78: 1.6384355e-12 | AG78: 1.6384355e-12 | AH78: 3.8290607e-22 | AI78: 3.8290607e-22 | AJ78: 3.8290607e-22 | AK78: 3.8290607e-22 | AL78: 3.8290607e-22 | AM78: 3.8290607e-22 | AN78: 3.8290607e-22 | AO78: 2.0699478e-11 | AP78: 2.0699478e-11 | AQ78: 2.0699478e-11 | AR78: 2.0699478e-11 | AS78: 2.0699478e-11 | AT78: 2.0699478e-11 | AU78: 2.0699478e-11 | AV78: 5.6869159e-30 | AW78: 5.6869159e-30 | AX78: 5.6869159e-30 | AY78: 0 | AZ78: 0 | BA78: 0 | BB78: 0 | BC78: 0 | BD78: 0
B79: NAP | D79: 0 | E79: 0 | F79: 8.1622625e-62 | G79: 8.1622625e-62 | H79: 8.1622625e-62 | I79: 8.1622625e-62 | J79: 0.00014288471 | K79: 0.00014288471 | L79: 0.00014288471 | M79: 0.00014288471 | N79: 0.00014288471 | O79: 0.91730412 | P79: 3.7268885e-05 | Q79: 3.7268885e-05 | R79: 3.7268885e-05 | S79: 0.70366465 | T79: 3.7558805e-06 | U79: 3.7558805e-06 | V79: 0.0052719155 | W79: 0.0059689732 | X79: 4.1030973e-12 | Y79: 3.2378396e-11 | Z79: 3.2378396e-11 | AA79: 3.2378396e-11 | AB79: 8.0527999e-10 | AC79: 1.5418527e-09 | AD79: 0 | AE79: 2.7876057e-09 | AF79: 3.6264887e-25 | AG79: 3.6264887e-25 | AH79: 0 | AI79: 0 | AJ79: 0 | AK79: 0 | AL79: 0 | AM79: 0 | AN79: 0 | AO79: 0 | AP79: 0 | AQ79: 0 | AR79: 0 | AS79: 0 | AT79: 0 | AU79: 0 | AV79: 4.1203973e-60 | AW79: 4.1203973e-60 | AX79: 4.1203973e-60 | AY79: 0 | AZ79: 0 | BA79: 0 | BB79: 0 | BC79: 0 | BD79: 0
B80: C | D80: 0 | E80: 0 | F80: 0 | G80: 0 | H80: 0 | I80: 0 | J80: 0 | K80: 0 | L80: 0 | M80: 0 | N80: 0 | O80: 0 | P80: 0 | Q80: 0 | R80: 0 | S80: 0 | T80: 0 | U80: 0 | V80: 0 | W80: 0 | X80: 0 | Y80: 0 | Z80: 0 | AA80: 0 | AB80: 0 | AC80: 0 | AD80: 0 | AE80: 0 | AF80: 0 | AG80: 0 | AH80: 0 | AI80: 0 | AJ80: 0 | AK80: 0 | AL80: 0 | AM80: 0 | AN80: 0 | AO80: 0 | AP80: 0 | AQ80: 0 | AR80: 0 | AS80: 0 | AT80: 0 | AU80: 0 | AV80: 0 | AW80: 0 | AX80: 0 | AY80: 1 | AZ80: 0 | BA80: 0.49856778 | BB80: 0.49856778 | BC80: 0 | BD80: 0
B81: WATER | D81: 0 | E81: 0 | F81: 0 | G81: 0 | H81: 0 | I81: 0 | J81: 0 | K81: 0 | L81: 0 | M81: 0 | N81: 0 | O81: 0 | P81: 0 | Q81: 0 | R81: 0 | S81: 0 | T81: 0 | U81: 0 | V81: 0 | W81: 0 | X81: 0 | Y81: 0 | Z81: 0 | AA81: 0 | AB81: 0 | AC81: 0 | AD81: 0 | AE81: 0 | AF81: 0 | AG81: 0 | AH81: 0 | AI81: 0 | AJ81: 0 | AK81: 0 | AL81: 0 | AM81: 0 | AN81: 0 | AO81: 0 | AP81: 0 | AQ81: 0 | AR81: 0 | AS81: 0 | AT81: 0 | AU81: 0 | AV81: 0 | AW81: 0 | AX81: 0 | AY81: 0 | AZ81: 0 | BA81: 0 | BB81: 0 | BC81: 0 | BD81: 0
B82: O2 | D82: 0 | E82: 0 | F82: 0 | G82: 0 | H82: 0 | I82: 0 | J82: 0 | K82: 0 | L82: 0 | M82: 0 | N82: 0 | O82: 0 | P82: 0 | Q82: 0 | R82: 0 | S82: 0 | T82: 0 | U82: 0 | V82: 0 | W82: 0 | X82: 0 | Y82: 0 | Z82: 0 | AA82: 0 | AB82: 0 | AC82: 0 | AD82: 0 | AE82: 0 | AF82: 0 | AG82: 0 | AH82: 0 | AI82: 0 | AJ82: 0 | AK82: 0 | AL82: 0 | AM82: 0 | AN82: 0 | AO82: 0 | AP82: 0 | AQ82: 0 | AR82: 0 | AS82: 0 | AT82: 0 | AU82: 0 | AV82: 0 | AW82: 0 | AX82: 0 | AY82: 0 | AZ82: 1 | BA82: 0.50143222 | BB82: 0.50143222 | BC82: 0.0057125 | BD82: 0.0057125
B83: CO2 | D83: 0 | E83: 0 | F83: 0 | G83: 0 | H83: 0 | I83: 0 | J83: 0 | K83: 0 | L83: 0 | M83: 0 | N83: 0 | O83: 0 | P83: 0 | Q83: 0 | R83: 0 | S83: 0 | T83: 0 | U83: 0 | V83: 0 | W83: 0 | X83: 0 | Y83: 0 | Z83: 0 | AA83: 0 | AB83: 0 | AC83: 0 | AD83: 0 | AE83: 0 | AF83: 0 | AG83: 0 | AH83: 0 | AI83: 0 | AJ83: 0 | AK83: 0 | AL83: 0 | AM83: 0 | AN83: 0 | AO83: 0 | AP83: 0 | AQ83: 0 | AR83: 0 | AS83: 0 | AT83: 0 | AU83: 0 | AV83: 0 | AW83: 0 | AX83: 0 | AY83: 0 | AZ83: 0 | BA83: 0 | BB83: 0 | BC83: 0.9942875 | BD83: 0.9942875
B84: Mass Flows | C84: kg/hr | D84: 211552.67 | E84: 2.01588e-05 | F84: 1028831.7 | G84: 1028831.7 | H84: 1028831.7 | I84: 1028831.7 | J84: 1012012.5 | K84: 1012012.5 | L84: 1012012.5 | M84: 1012012.5 | N84: 1012012.5 | O84: 4312.9738 | P84: 1008836.9 | Q84: 1008836.9 | R84: 1008836.9 | S84: 1226.5585 | T84: 1007610.4 | U84: 1007610.4 | V84: 11868.288 | W84: 11415.992 | X84: 452.3317 | Y84: 996194.43 | Z84: 996194.43 | AA84: 996194.43 | AB84: 201138.33 | AC84: 131664.14 | AD84: 60867.667 | AE84: 70796.472 | AF84: 795056.09 | AG84: 795056.09 | AH84: 514716.79 | AI84: 514716.79 | AJ84: 514716.79 | AK84: 514716.79 | AL84: 514716.79 | AM84: 470921.7 | AN84: 43795.087 | AO84: 280381.73 | AP84: 280381.73 | AQ84: 280381.73 | AR84: 280381.73 | AS84: 280381.73 | AT84: 277577.91 | AU84: 2803.8173 | AV84: 69474.195 | AW84: 68779.453 | AX84: 694.74195 | AY84: 16719.342 | AZ84: 44798.32 | BA84: 61517.662 | BB84: 61517.662 | BC84: 61517.662 | BD84: 61517.662
B85: H2 | C85: kg/hr | D85: 0 | E85: 2.01588e-05 | F85: 364610.22 | G85: 364610.22 | H85: 364610.22 | I85: 364610.22 | J85: 398426.26 | K85: 398426.26 | L85: 398426.26 | M85: 398426.26 | N85: 398426.26 | O85: 0.42325964 | P85: 398391.08 | Q85: 398391.08 | R85: 398391.08 | S85: 0.1807405 | T85: 398390.9 | U85: 398390.9 | V85: 2.0635361 | W85: 1.1578313e-07 | X85: 2.0636995 | Y85: 398390.9 | Z85: 398390.9 | AA85: 398390.9 | AB85: 256.35 | AC85: 2.1245063e-09 | AD85: 2.1245063e-09 | AE85: 4.3749578e-39 | AF85: 398134.55 | AG85: 398134.55 | AH85: 397268.07 | AI85: 397268.07 | AJ85: 397268.07 | AK85: 397268.07 | AL85: 397268.07 | AM85: 363466.2 | AN85: 33801.87 | AO85: 899.22738 | AP85: 899.22738 | AQ85: 899.22738 | AR85: 899.22738 | AS85: 899.22738 | AT85: 890.23511 | AU85: 8.9922738 | AV85: 256.35 | AW85: 253.7865 | AX85: 2.5635 | AY85: 0 | AZ85: 0 | BA85: 0 | BB85: 0 | BC85: 0 | BD85: 0
B86: CH4 | C86: kg/hr | D86: 211552.67 | E86: 0 | F86: 652875.12 | G86: 652875.12 | H86: 652875.12 | I86: 652875.12 | J86: 454724.6 | K86: 454724.6 | L86: 454724.6 | M86: 454724.6 | N86: 454724.6 | O86: 3.2586723 | P86: 454683.27 | Q86: 454683.27 | R86: 454683.27 | S86: 1.8025487 | T86: 454681.47 | U86: 454681.47 | V86: 51.23184 | W86: 0.00012018945 | X86: 51.235775 | Y86: 454681.47 | Z86: 454681.47 | AA86: 454681.47 | AB86: 69218.666 | AC86: 6.9218306 | AD86: 6.9218306 | AE86: 1.8120331e-13 | AF86: 385462.8 | AG86: 385462.8 | AH86: 117398.06 | AI86: 117398.06 | AJ86: 117398.06 | AK86: 117398.06 | AL86: 117398.06 | AM86: 107409.15 | AN86: 9988.9073 | AO86: 268074.41 | AP86: 268074.41 | AQ86: 268074.41 | AR86: 268074.41 | AS86: 268074.41 | AT86: 265393.67 | AU86: 2680.7441 | AV86: 69211.745 | AW86: 68519.627 | AX86: 692.11745 | AY86: 0 | AZ86: 0 | BA86: 0 | BB86: 0 | BC86: 0 | BD86: 0
B87: C2H6 | C87: kg/hr | D87: 0 | E87: 0 | F87: 115.9964 | G87: 115.9964 | H87: 115.9964 | I87: 115.9964 | J87: 3799.5111 | K87: 3799.5111 | L87: 3799.5111 | M87: 3799.5111 | N87: 3799.5111 | O87: 0.19118773 | P87: 3799.1088 | Q87: 3799.1088 | R87: 3799.1088 | S87: 0.12795038 | T87: 3798.9809 | U87: 3798.9809 | V87: 7.8258908 | W87: 0.0032337358 | X87: 7.8232852 | Y87: 3798.9783 | Z87: 3798.9783 | AA87: 3798.9783 | AB87: 3681.8036 | AC87: 3681.8027 | AD87: 2.839122e-11 | AE87: 3681.8027 | AF87: 117.17473 | AG87: 117.17473 | AH87: 0.098631624 | AI87: 0.098631624 | AJ87: 0.098631624 | AK87: 0.098631624 | AL87: 0.098631624 | AM87: 0.090239474 | AN87: 0.0083921502 | AO87: 117.07611 | AP87: 117.07611 | AQ87: 117.07611 | AR87: 117.07611 | AS87: 117.07611 | AT87: 115.90535 | AU87: 1.1707611 | AV87: 0.00082722513 | AW87: 0.00081895288 | AX87: 8.2722513e-06 | AY87: 0 | AZ87: 0 | BA87: 0 | BB87: 0 | BC87: 0 | BD87: 0
B88: C2H4 | C88: kg/hr | D88: 0 | E88: 0 | F88: 9495.5312 | G88: 9495.5312 | H88: 9495.5312 | I88: 9495.5312 | J88: 70458.053 | K88: 70458.053 | L88: 70458.053 | M88: 70458.053 | N88: 70458.053 | O88: 2.3771481 | P88: 70450.471 | Q88: 70450.471 | R88: 70450.471 | S88: 1.5379007 | T88: 70448.933 | U88: 70448.933 | V88: 80.20593 | W88: 0.010515885 | X88: 80.202354 | Y88: 70448.929 | Z88: 70448.929 | AA88: 70448.929 | AB88: 60859.795 | AC88: 60853.728 | AD88: 60792.875 | AE88: 60.852914 | AF88: 9589.1342 | AG88: 9589.1342 | AH88: 49.573717 | AI88: 49.573717 | AJ88: 49.573717 | AK88: 49.573717 | AL88: 49.573717 | AM88: 45.355698 | AN88: 4.2180192 | AO88: 9539.5647 | AP88: 9539.5647 | AQ88: 9539.5647 | AR88: 9539.5647 | AS88: 9539.5647 | AT88: 9444.1691 | AU88: 95.395647 | AV88: 6.0670507 | AW88: 6.0063802 | AX88: 0.060670507 | AY88: 0 | AZ88: 0 | BA88: 0 | BB88: 0 | BC88: 0 | BD88: 0
B89: C2H2 | C89: kg/hr | D89: 0 | E89: 0 | F89: 1734.869 | G89: 1734.869 | H89: 1734.869 | I89: 1734.869 | J89: 68337.109 | K89: 68337.109 | L89: 68337.109 | M89: 68337.109 | N89: 68337.109 | O89: 3.8576739 | P89: 68330.042 | Q89: 68330.042 | R89: 68330.042 | S89: 2.873717 | T89: 68327.169 | U89: 68327.169 | V89: 309.97196 | W89: 0.12058665 | X89: 309.87594 | Y89: 68327.073 | Z89: 68327.073 | AA89: 68327.073 | AB89: 66574.638 | AC89: 66574.605 | AD89: 67.869862 | AE89: 66506.735 | AF89: 1752.4351 | AG89: 1752.4351 | AH89: 0.9869212 | AI89: 0.9869212 | AJ89: 0.9869212 | AK89: 0.9869212 | AL89: 0.9869212 | AM89: 0.90294823 | AN89: 0.083972976 | AO89: 1751.4483 | AP89: 1751.4483 | AQ89: 1751.4483 | AR89: 1751.4483 | AS89: 1751.4483 | AT89: 1733.9338 | AU89: 17.514483 | AV89: 0.032526415 | AW89: 0.032201151 | AX89: 0.00032526415 | AY89: 0 | AZ89: 0 | BA89: 0 | BB89: 0 | BC89: 0 | BD89: 0
B90: C3-C5 | C90: kg/hr | D90: 0 | E90: 0 | F90: 0 | G90: 0 | H90: 0 | I90: 0 | J90: 0 | K90: 0 | L90: 0 | M90: 0 | N90: 0 | O90: 0 | P90: 0 | Q90: 0 | R90: 0 | S90: 0 | T90: 0 | U90: 0 | V90: 0 | W90: 0 | X90: 0 | Y90: 0 | Z90: 0 | AA90: 0 | AB90: 0 | AC90: 0 | AD90: 0 | AE90: 0 | AF90: 0 | AG90: 0 | AH90: 0 | AI90: 0 | AJ90: 0 | AK90: 0 | AL90: 0 | AM90: 0 | AN90: 0 | AO90: 0 | AP90: 0 | AQ90: 0 | AR90: 0 | AS90: 0 | AT90: 0 | AU90: 0 | AV90: 0 | AW90: 0 | AX90: 0 | AY90: 0 | AZ90: 0 | BA90: 0 | BB90: 0 | BC90: 0 | BD90: 0
B91: BEN | C91: kg/hr | D91: 0 | E91: 0 | F91: 2.8120675e-05 | G91: 2.8120675e-05 | H91: 2.8120675e-05 | I91: 2.8120675e-05 | J91: 12028.371 | K91: 12028.371 | L91: 12028.371 | M91: 12028.371 | N91: 12028.371 | O91: 175.79058 | P91: 12077.635 | Q91: 12077.635 | R91: 12077.635 | S91: 226.0845 | T91: 11851.551 | U91: 11851.551 | V91: 11305.601 | W91: 11304.47 | X91: 1.1306447 | Y91: 547.08034 | Z91: 547.08034 | AA91: 547.08034 | AB91: 547.08032 | AC91: 547.08032 | AD91: 4.1065437e-237 | AE91: 547.08032 | AF91: 2.8404723e-05 | AG91: 2.8404723e-05 | AH91: 6.1133113e-15 | AI91: 6.1133113e-15 | AJ91: 6.1133113e-15 | AK91: 6.1133113e-15 | AL91: 6.1133113e-15 | AM91: 5.5931553e-15 | AN91: 5.2015596e-16 | AO91: 2.8404723e-05 | AP91: 2.8404723e-05 | AQ91: 2.8404723e-05 | AR91: 2.8404723e-05 | AS91: 2.8404723e-05 | AT91: 2.8120675e-05 | AU91: 2.8404723e-07 | AV91: 1.9730672e-24 | AW91: 1.9533365e-24 | AX91: 1.9730672e-26 | AY91: 0 | AZ91: 0 | BA91: 0 | BB91: 0 | BC91: 0 | BD91: 0
B92: NAP | C92: kg/hr | D92: 0 | E92: 0 | F92: 2.3222597e-54 | G92: 2.3222597e-54 | H92: 2.3222597e-54 | I92: 2.3222597e-54 | J92: 4238.5611 | K92: 4238.5611 | L92: 4238.5611 | M92: 4238.5611 | N92: 4238.5611 | O92: 4127.0753 | P92: 1105.3397 | Q92: 1105.3397 | R92: 1105.3397 | S92: 993.95119 | T92: 111.38853 | U92: 111.38853 | V92: 111.38757 | W92: 111.38757 | X92: 1.0124745e-08 | Y92: 0.00095964512 | Z92: 0.00095964512 | AA92: 0.00095964512 | AB92: 0.00095964512 | AC92: 0.00095964512 | AD92: 0 | AE92: 0.00095964512 | AF92: 1.0316181e-17 | AG92: 1.0316181e-17 | AH92: 0 | AI92: 0 | AJ92: 0 | AK92: 0 | AL92: 0 | AM92: 0 | AN92: 0 | AO92: 0 | AP92: 0 | AQ92: 0 | AR92: 0 | AS92: 0 | AT92: 0 | AU92: 0 | AV92: 2.3457169e-54 | AW92: 2.3222597e-54 | AX92: 2.3457169e-56 | AY92: 0 | AZ92: 0 | BA92: 0 | BB92: 0 | BC92: 0 | BD92: 0
B93: C | C93: kg/hr | D93: 0 | E93: 0 | F93: 0 | G93: 0 | H93: 0 | I93: 0 | J93: 0 | K93: 0 | L93: 0 | M93: 0 | N93: 0 | O93: 0 | P93: 0 | Q93: 0 | R93: 0 | S93: 0 | T93: 0 | U93: 0 | V93: 0 | W93: 0 | X93: 0 | Y93: 0 | Z93: 0 | AA93: 0 | AB93: 0 | AC93: 0 | AD93: 0 | AE93: 0 | AF93: 0 | AG93: 0 | AH93: 0 | AI93: 0 | AJ93: 0 | AK93: 0 | AL93: 0 | AM93: 0 | AN93: 0 | AO93: 0 | AP93: 0 | AQ93: 0 | AR93: 0 | AS93: 0 | AT93: 0 | AU93: 0 | AV93: 0 | AW93: 0 | AX93: 0 | AY93: 16719.342 | AZ93: 0 | BA93: 16719.342 | BB93: 16719.342 | BC93: 0 | BD93: 0
B94: WATER | C94: kg/hr | D94: 0 | E94: 0 | F94: 0 | G94: 0 | H94: 0 | I94: 0 | J94: 0 | K94: 0 | L94: 0 | M94: 0 | N94: 0 | O94: 0 | P94: 0 | Q94: 0 | R94: 0 | S94: 0 | T94: 0 | U94: 0 | V94: 0 | W94: 0 | X94: 0 | Y94: 0 | Z94: 0 | AA94: 0 | AB94: 0 | AC94: 0 | AD94: 0 | AE94: 0 | AF94: 0 | AG94: 0 | AH94: 0 | AI94: 0 | AJ94: 0 | AK94: 0 | AL94: 0 | AM94: 0 | AN94: 0 | AO94: 0 | AP94: 0 | AQ94: 0 | AR94: 0 | AS94: 0 | AT94: 0 | AU94: 0 | AV94: 0 | AW94: 0 | AX94: 0 | AY94: 0 | AZ94: 0 | BA94: 0 | BB94: 0 | BC94: 0 | BD94: 0
B95: O2 | C95: kg/hr | D95: 0 | E95: 0 | F95: 0 | G95: 0 | H95: 0 | I95: 0 | J95: 0 | K95: 0 | L95: 0 | M95: 0 | N95: 0 | O95: 0 | P95: 0 | Q95: 0 | R95: 0 | S95: 0 | T95: 0 | U95: 0 | V95: 0 | W95: 0 | X95: 0 | Y95: 0 | Z95: 0 | AA95: 0 | AB95: 0 | AC95: 0 | AD95: 0 | AE95: 0 | AF95: 0 | AG95: 0 | AH95: 0 | AI95: 0 | AJ95: 0 | AK95: 0 | AL95: 0 | AM95: 0 | AN95: 0 | AO95: 0 | AP95: 0 | AQ95: 0 | AR95: 0 | AS95: 0 | AT95: 0 | AU95: 0 | AV95: 0 | AW95: 0 | AX95: 0 | AY95: 0 | AZ95: 44798.32 | BA95: 44798.32 | BB95: 44798.32 | BC95: 255.9104 | BD95: 255.9104
B96: CO2 | C96: kg/hr | D96: 0 | E96: 0 | F96: 0 | G96: 0 | H96: 0 | I96: 0 | J96: 0 | K96: 0 | L96: 0 | M96: 0 | N96: 0 | O96: 0 | P96: 0 | Q96: 0 | R96: 0 | S96: 0 | T96: 0 | U96: 0 | V96: 0 | W96: 0 | X96: 0 | Y96: 0 | Z96: 0 | AA96: 0 | AB96: 0 | AC96: 0 | AD96: 0 | AE96: 0 | AF96: 0 | AG96: 0 | AH96: 0 | AI96: 0 | AJ96: 0 | AK96: 0 | AL96: 0 | AM96: 0 | AN96: 0 | AO96: 0 | AP96: 0 | AQ96: 0 | AR96: 0 | AS96: 0 | AT96: 0 | AU96: 0 | AV96: 0 | AW96: 0 | AX96: 0 | AY96: 0 | AZ96: 0 | BA96: 0 | BB96: 0 | BC96: 61261.752 | BD96: 61261.752
B97: Mass Fractions
B98: H2 | D98: 0 | E98: 1 | F98: 0.35439247 | G98: 0.35439247 | H98: 0.35439247 | I98: 0.35439247 | J98: 0.39369699 | K98: 0.39369699 | L98: 0.39369699 | M98: 0.39369699 | N98: 0.39369699 | O98: 9.8136381e-05 | P98: 0.39490136 | Q98: 0.39490136 | R98: 0.39490136 | S98: 0.00014735579 | T98: 0.39538189 | U98: 0.39538189 | V98: 0.00017386974 | W98: 1.0142187e-11 | X98: 0.0045623587 | Y98: 0.39991279 | Z98: 0.39991279 | AA98: 0.39991279 | AB98: 0.001274496 | AC98: 1.6135801e-14 | AD98: 3.4903692e-14 | AE98: 6.1796269e-44 | AF98: 0.50076284 | AG98: 0.50076284 | AH98: 0.77181875 | AI98: 0.77181875 | AJ98: 0.77181875 | AK98: 0.77181875 | AL98: 0.77181875 | AM98: 0.77181875 | AN98: 0.77181875 | AO98: 0.003207154 | AP98: 0.003207154 | AQ98: 0.003207154 | AR98: 0.003207154 | AS98: 0.003207154 | AT98: 0.003207154 | AU98: 0.003207154 | AV98: 0.0036898593 | AW98: 0.0036898593 | AX98: 0.0036898593 | AY98: 0 | AZ98: 0 | BA98: 0 | BB98: 0 | BC98: 0 | BD98: 0
B99: CH4 | D99: 1 | E99: 0 | F99: 0.6345791 | G99: 0.6345791 | H99: 0.6345791 | I99: 0.6345791 | J99: 0.44932707 | K99: 0.44932707 | L99: 0.44932707 | M99: 0.44932707 | N99: 0.44932707 | O99: 0.00075555115 | P99: 0.45070046 | Q99: 0.45070046 | R99: 0.45070046 | S99: 0.0014695986 | T99: 0.4512473 | U99: 0.4512473 | V99: 0.0043167002 | W99: 1.0528165e-08 | X99: 0.11327036 | Y99: 0.4564184 | Z99: 0.4564184 | AA99: 0.4564184 | AB99: 0.34413463 | AC99: 5.2571874e-05 | AD99: 0.00011371933 | AE99: 2.5594963e-18 | AF99: 0.48482466 | AG99: 0.48482466 | AH99: 0.22808283 | AI99: 0.22808283 | AJ99: 0.22808283 | AK99: 0.22808283 | AL99: 0.22808283 | AM99: 0.22808283 | AN99: 0.22808283 | AO99: 0.95610514 | AP99: 0.95610514 | AQ99: 0.95610514 | AR99: 0.95610514 | AS99: 0.95610514 | AT99: 0.95610514 | AU99: 0.95610514 | AV99: 0.99622233 | AW99: 0.99622233 | AX99: 0.99622233 | AY99: 0 | AZ99: 0 | BA99: 0 | BB99: 0 | BC99: 0 | BD99: 0
B100: C2H6 | D100: 0 | E100: 0 | F100: 0.00011274575 | G100: 0.00011274575 | H100: 0.00011274575 | I100: 0.00011274575 | J100: 0.0037544114 | K100: 0.0037544114 | L100: 0.0037544114 | M100: 0.0037544114 | N100: 0.0037544114 | O100: 4.4328518e-05 | P100: 0.0037658304 | Q100: 0.0037658304 | R100: 0.0037658304 | S100: 0.00010431657 | T100: 0.0037702876 | U100: 0.0037702876 | V100: 0.00065939511 | W100: 2.8326366e-07 | X100: 0.017295461 | Y100: 0.0038134908 | Z100: 0.0038134908 | AA100: 0.0038134908 | AB100: 0.018304833 | AC100: 0.027963596 | AD100: 4.6644173e-16 | AE100: 0.052005455 | AF100: 0.0001473792 | AG100: 0.0001473792 | AH100: 1.916231e-07 | AI100: 1.916231e-07 | AJ100: 1.916231e-07 | AK100: 1.916231e-07 | AL100: 1.916231e-07 | AM100: 1.916231e-07 | AN100: 1.916231e-07 | AO100: 0.00041755968 | AP100: 0.00041755968 | AQ100: 0.00041755968 | AR100: 0.00041755968 | AS100: 0.00041755968 | AT100: 0.00041755968 | AU100: 0.00041755968 | AV100: 1.1906941e-08 | AW100: 1.1906941e-08 | AX100: 1.1906941e-08 | AY100: 0 | AZ100: 0 | BA100: 0 | BB100: 0 | BC100: 0 | BD100: 0
B101: C2H4 | D101: 0 | E101: 0 | F101: 0.0092294307 | G101: 0.0092294307 | H101: 0.0092294307 | I101: 0.0092294307 | J101: 0.069621724 | K101: 0.069621724 | L101: 0.069621724 | M101: 0.069621724 | N101: 0.069621724 | O101: 0.00055116221 | P101: 0.069833357 | Q101: 0.069833357 | R101: 0.069833357 | S101: 0.0012538339 | T101: 0.069916839 | U101: 0.069916839 | V101: 0.0067580036 | W101: 9.2115379e-07 | X101: 0.17730872 | Y101: 0.070718052 | Z101: 0.070718052 | AA101: 0.070718052 | AB101: 0.30257681 | AC101: 0.46218909 | AD101: 0.99877124 | AE101: 0.00085954726 | AF101: 0.012060953 | AG101: 0.012060953 | AH101: 9.631261e-05 | AI101: 9.631261e-05 | AJ101: 9.631261e-05 | AK101: 9.631261e-05 | AL101: 9.631261e-05 | AM101: 9.631261e-05 | AN101: 9.631261e-05 | AO101: 0.034023489 | AP101: 0.034023489 | AQ101: 0.034023489 | AR101: 0.034023489 | AS101: 0.034023489 | AT101: 0.034023489 | AU101: 0.034023489 | AV101: 8.7328119e-05 | AW101: 8.7328119e-05 | AX101: 8.7328119e-05 | AY101: 0 | AZ101: 0 | BA101: 0 | BB101: 0 | BC101: 0 | BD101: 0
B102: C2H2 | D102: 0 | E102: 0 | F102: 0.0016862514 | G102: 0.0016862514 | H102: 0.0016862514 | I102: 0.0016862514 | J102: 0.067525956 | K102: 0.067525956 | L102: 0.067525956 | M102: 0.067525956 | N102: 0.067525956 | O102: 0.00089443481 | P102: 0.067731503 | Q102: 0.067731503 | R102: 0.067731503 | S102: 0.0023429106 | T102: 0.0678111 | U102: 0.0678111 | V102: 0.026117665 | W102: 1.0562958e-05 | X102: 0.68506351 | Y102: 0.06858809 | Z102: 0.06858809 | AA102: 0.06858809 | AB102: 0.33098931 | AC102: 0.50563962 | AD102: 0.0011150397 | AE102: 0.93940748 | AF102: 0.0022041654 | AG102: 0.0022041654 | AH102: 1.9174063e-06 | AI102: 1.9174063e-06 | AJ102: 1.9174063e-06 | AK102: 1.9174063e-06 | AL102: 1.9174063e-06 | AM102: 1.9174063e-06 | AN102: 1.9174063e-06 | AO102: 0.0062466562 | AP102: 0.0062466562 | AQ102: 0.0062466562 | AR102: 0.0062466562 | AS102: 0.0062466562 | AT102: 0.0062466562 | AU102: 0.0062466562 | AV102: 4.681798e-07 | AW102: 4.681798e-07 | AX102: 4.681798e-07 | AY102: 0 | AZ102: 0 | BA102: 0 | BB102: 0 | BC102: 0 | BD102: 0
B103: C3-C5 | D103: 0 | E103: 0 | F103: 0 | G103: 0 | H103: 0 | I103: 0 | J103: 0 | K103: 0 | L103: 0 | M103: 0 | N103: 0 | O103: 0 | P103: 0 | Q103: 0 | R103: 0 | S103: 0 | T103: 0 | U103: 0 | V103: 0 | W103: 0 | X103: 0 | Y103: 0 | Z103: 0 | AA103: 0 | AB103: 0 | AC103: 0 | AD103: 0 | AE103: 0 | AF103: 0 | AG103: 0 | AH103: 0 | AI103: 0 | AJ103: 0 | AK103: 0 | AL103: 0 | AM103: 0 | AN103: 0 | AO103: 0 | AP103: 0 | AQ103: 0 | AR103: 0 | AS103: 0 | AT103: 0 | AU103: 0 | AV103: 0 | AW103: 0 | AX103: 0 | AY103: 0 | AZ103: 0 | BA103: 0 | BB103: 0 | BC103: 0 | BD103: 0
B104: BEN | D104: 0 | E104: 0 | F104: 2.7332628e-11 | G104: 2.7332628e-11 | H104: 2.7332628e-11 | I104: 2.7332628e-11 | J104: 0.011885595 | K104: 0.011885595 | L104: 0.011885595 | M104: 0.011885595 | N104: 0.011885595 | O104: 0.040758555 | P104: 0.011971841 | Q104: 0.011971841 | R104: 0.011971841 | S104: 0.18432426 | T104: 0.011762037 | U104: 0.011762037 | V104: 0.95258906 | W104: 0.99023107 | X104: 0.002499592 | Y104: 0.00054917025 | Z104: 0.00054917025 | AA104: 0.00054917025 | AB104: 0.0027199207 | AC104: 0.0041551202 | AD104: 6.7466751e-242 | AE104: 0.0077275082 | AF104: 3.572669e-11 | AG104: 3.572669e-11 | AH104: 1.1877039e-20 | AI104: 1.1877039e-20 | AJ104: 1.1877039e-20 | AK104: 1.1877039e-20 | AL104: 1.1877039e-20 | AM104: 1.1877039e-20 | AN104: 1.1877039e-20 | AO104: 1.0130732e-10 | AP104: 1.0130732e-10 | AQ104: 1.0130732e-10 | AR104: 1.0130732e-10 | AS104: 1.0130732e-10 | AT104: 1.0130732e-10 | AU104: 1.0130732e-10 | AV104: 2.8400001e-29 | AW104: 2.8400001e-29 | AX104: 2.8400001e-29 | AY104: 0 | AZ104: 0 | BA104: 0 | BB104: 0 | BC104: 0 | BD104: 0
B105: NAP | D105: 0 | E105: 0 | F105: 2.2571813e-60 | G105: 2.2571813e-60 | H105: 2.2571813e-60 | I105: 2.2571813e-60 | J105: 0.0041882499 | K105: 0.0041882499 | L105: 0.0041882499 | M105: 0.0041882499 | N105: 0.0041882499 | O105: 0.95689783 | P105: 0.0010956574 | Q105: 0.0010956574 | R105: 0.0010956574 | S105: 0.81035772 | T105: 0.00011054722 | U105: 0.00011054722 | V105: 0.0093853106 | W105: 0.0097571514 | X105: 2.2383452e-11 | Y105: 9.6331107e-10 | Z105: 9.6331107e-10 | AA105: 9.6331107e-10 | AB105: 4.7710703e-09 | AC105: 7.2885839e-09 | AD105: 0 | AE105: 1.3554985e-08 | AF105: 1.2975413e-23 | AG105: 1.2975413e-23 | AH105: 0 | AI105: 0 | AJ105: 0 | AK105: 0 | AL105: 0 | AM105: 0 | AN105: 0 | AO105: 0 | AP105: 0 | AQ105: 0 | AR105: 0 | AS105: 0 | AT105: 0 | AU105: 0 | AV105: 3.3763859e-59 | AW105: 3.3763859e-59 | AX105: 3.3763859e-59 | AY105: 0 | AZ105: 0 | BA105: 0 | BB105: 0 | BC105: 0 | BD105: 0
B106: C | D106: 0 | E106: 0 | F106: 0 | G106: 0 | H106: 0 | I106: 0 | J106: 0 | K106: 0 | L106: 0 | M106: 0 | N106: 0 | O106: 0 | P106: 0 | Q106: 0 | R106: 0 | S106: 0 | T106: 0 | U106: 0 | V106: 0 | W106: 0 | X106: 0 | Y106: 0 | Z106: 0 | AA106: 0 | AB106: 0 | AC106: 0 | AD106: 0 | AE106: 0 | AF106: 0 | AG106: 0 | AH106: 0 | AI106: 0 | AJ106: 0 | AK106: 0 | AL106: 0 | AM106: 0 | AN106: 0 | AO106: 0 | AP106: 0 | AQ106: 0 | AR106: 0 | AS106: 0 | AT106: 0 | AU106: 0 | AV106: 0 | AW106: 0 | AX106: 0 | AY106: 1 | AZ106: 0 | BA106: 0.27178117 | BB106: 0.27178117 | BC106: 0 | BD106: 0
B107: WATER | D107: 0 | E107: 0 | F107: 0 | G107: 0 | H107: 0 | I107: 0 | J107: 0 | K107: 0 | L107: 0 | M107: 0 | N107: 0 | O107: 0 | P107: 0 | Q107: 0 | R107: 0 | S107: 0 | T107: 0 | U107: 0 | V107: 0 | W107: 0 | X107: 0 | Y107: 0 | Z107: 0 | AA107: 0 | AB107: 0 | AC107: 0 | AD107: 0 | AE107: 0 | AF107: 0 | AG107: 0 | AH107: 0 | AI107: 0 | AJ107: 0 | AK107: 0 | AL107: 0 | AM107: 0 | AN107: 0 | AO107: 0 | AP107: 0 | AQ107: 0 | AR107: 0 | AS107: 0 | AT107: 0 | AU107: 0 | AV107: 0 | AW107: 0 | AX107: 0 | AY107: 0 | AZ107: 0 | BA107: 0 | BB107: 0 | BC107: 0 | BD107: 0
B108: O2 | D108: 0 | E108: 0 | F108: 0 | G108: 0 | H108: 0 | I108: 0 | J108: 0 | K108: 0 | L108: 0 | M108: 0 | N108: 0 | O108: 0 | P108: 0 | Q108: 0 | R108: 0 | S108: 0 | T108: 0 | U108: 0 | V108: 0 | W108: 0 | X108: 0 | Y108: 0 | Z108: 0 | AA108: 0 | AB108: 0 | AC108: 0 | AD108: 0 | AE108: 0 | AF108: 0 | AG108: 0 | AH108: 0 | AI108: 0 | AJ108: 0 | AK108: 0 | AL108: 0 | AM108: 0 | AN108: 0 | AO108: 0 | AP108: 0 | AQ108: 0 | AR108: 0 | AS108: 0 | AT108: 0 | AU108: 0 | AV108: 0 | AW108: 0 | AX108: 0 | AY108: 0 | AZ108: 1 | BA108: 0.72821883 | BB108: 0.72821883 | BC108: 0.0041599501 | BD108: 0.0041599501
B109: CO2 | D109: 0 | E109: 0 | F109: 0 | G109: 0 | H109: 0 | I109: 0 | J109: 0 | K109: 0 | L109: 0 | M109: 0 | N109: 0 | O109: 0 | P109: 0 | Q109: 0 | R109: 0 | S109: 0 | T109: 0 | U109: 0 | V109: 0 | W109: 0 | X109: 0 | Y109: 0 | Z109: 0 | AA109: 0 | AB109: 0 | AC109: 0 | AD109: 0 | AE109: 0 | AF109: 0 | AG109: 0 | AH109: 0 | AI109: 0 | AJ109: 0 | AK109: 0 | AL109: 0 | AM109: 0 | AN109: 0 | AO109: 0 | AP109: 0 | AQ109: 0 | AR109: 0 | AS109: 0 | AT109: 0 | AU109: 0 | AV109: 0 | AW109: 0 | AX109: 0 | AY109: 0 | AZ109: 0 | BA109: 0 | BB109: 0 | BC109: 0.99584005 | BD109: 0.99584005
B110: Volume Flow | C110: cum/hr | D110: 327437.65 | E110: 0.0011386783 | F110: 4783963 | G110: 17015264 | H110: 18333970 | I110: 27389526 | J110: 28557235 | K110: 17930771 | L110: 5834095.5 | M110: 700678.92 | N110: 292520.73 | O110: 4.4462477 | P110: 292494.34 | Q110: 222951.1 | R110: 178929.48 | S110: 1.2661352 | T110: 178928.21 | U110: 135723.82 | V110: 12.656143 | W110: 21.761063 | X110: 10.780548 | Y110: 135720.65 | Z110: 123493.13 | AA110: 58319.026 | AB110: 342.9558 | AC110: 245.7019 | AD110: 98.383621 | AE110: 109.68343 | AF110: 78763.777 | AG110: 69598.838 | AH110: 57548.546 | AI110: 63769.287 | AJ110: 63769.287 | AK110: 109829.49 | AL110: 154924.56 | AM110: 141742.68 | AN110: 13181.879 | AO110: 578.17094 | AP110: 8020.0066 | AQ110: 58051.024 | AR110: 213144.86 | AS110: 252842.64 | AT110: 250314.21 | AU110: 2528.4264 | AV110: 6951.1663 | AW110: 6881.6547 | AX110: 69.511663 | AY110: 28.555045 | AZ110: 3502.9029 | BA110: 132156.89 | BB110: 35411.307 | BC110: 917587.65 | BD110: 116788.18
B116: MAJOR STREAM INFORMATION
D117: 1-CH4 | E117: 50-O2 | F117: 6-RXNin | G117: 7-RXN-out | H117: 27-Ethylene | I117: 28-C2 | J117: 12-Naphthalene | K117: 20-Benzene | L117: 37-H2 | M117: 54-CO2 | N117: 49-COKE
B118: =B58 -> Mole Flows | C118: =C58 -> kmol/hr | D118: =D58 -> 13186.8 | E118: =AZ58 -> 1400 | F118: =I58 -> 221973.91 | G118: =J58 -> 231437.85 | H118: =AD58 -> 2170.0515 | I118: =AE58 -> 2685.8454 | J118: =O58 -> 35.101909 | K118: =W58 -> 145.59242 | L118: =AN58 -> 17390.595 | M118: =BD58 -> 1400 | N118: =AY58 -> 1392.0025
B119: =B59 -> H2 | C119: =C59 -> kmol/hr | D119: =D59 -> 0 | E119: =AZ59 -> 0 | F119: =I59 -> 180869.01 | G119: =J59 -> 197643.84 | H119: =AD59 -> 1.0538853e-09 | I119: =AE59 -> 2.1702471e-39 | J119: =O59 -> 0.20996271 | K119: =W59 -> 5.7435524e-08 | L119: =AN59 -> 16767.799 | M119: =BD59 -> 0 | N119: =AY59 -> 0
B120: =B60 -> CH4 | C120: =C60 -> kmol/hr | D120: =D60 -> 13186.8 | E120: =AZ60 -> 0 | F120: =I60 -> 40695.935 | G120: =J60 -> 28344.536 | H120: =AD60 -> 0.43146133 | I120: =AE60 -> 1.1295021e-14 | J120: =O60 -> 0.20312417 | K120: =W60 -> 7.4918187e-06 | L120: =AN60 -> 622.64269 | M120: =BD60 -> 0 | N120: =AY60 -> 0
B121: =B61 -> C2H6 | C121: =C61 -> kmol/hr | D121: =D61 -> 0 | E121: =AZ61 -> 0 | F121: =I61 -> 3.8575921 | G121: =J61 -> 126.35705 | H121: =AD61 -> 9.4418223e-13 | I121: =AE61 -> 122.44253 | J121: =O61 -> 0.0063581651 | K121: =W61 -> 0.00010754155 | L121: =AN61 -> 0.00027909048 | M121: =BD61 -> 0 | N121: =AY61 -> 0
B122: =B62 -> C2H4 | C122: =C62 -> kmol/hr | D122: =D62 -> 0 | E122: =AZ62 -> 0 | F122: =I62 -> 338.47624 | G122: =J62 -> 2511.5369 | H122: =AD62 -> 2167.0134 | I122: =AE62 -> 2.1691536 | J122: =O62 -> 0.084735456 | K122: =W62 -> 0.0003748476 | L122: =AN62 -> 0.15035486 | M122: =BD62 -> 0 | N122: =AY62 -> 0
B123: =B63 -> C2H2 | C123: =C63 -> kmol/hr | D123: =D63 -> 0 | E123: =AZ63 -> 0 | F123: =I63 -> 66.628656 | G123: =J63 -> 2624.5266 | H123: =AD63 -> 2.6065817 | I123: =AE63 -> 2554.23 | J123: =O63 -> 0.14815622 | K123: =W63 -> 0.0046312008 | L123: =AN63 -> 0.0032250312 | M123: =BD63 -> 0 | N123: =AY63 -> 0
B124: =B64 -> C3-C5 | C124: =C64 -> kmol/hr | D124: =D64 -> 0 | E124: =AZ64 -> 0 | F124: =I64 -> 0 | G124: =J64 -> 0 | H124: =AD64 -> 0 | I124: =AE64 -> 0 | J124: =O64 -> 0 | K124: =W64 -> 0 | L124: =AN64 -> 0 | M124: =BD64 -> 0 | N124: =AY64 -> 0
B125: =B65 -> BEN | C125: =C65 -> kmol/hr | D125: =D65 -> 0 | E125: =AZ65 -> 0 | F125: =I65 -> 3.5999699e-07 | G125: =J65 -> 153.98553 | H125: =AD65 -> 5.2571404e-239 | I125: =AE65 -> 7.0036464 | J125: =O65 -> 2.2504466 | K125: =W65 -> 144.71826 | L125: =AN65 -> 6.6589645e-18 | M125: =BD65 -> 0 | N125: =AY65 -> 0
B126: =B66 -> NAP | C126: =C66 -> kmol/hr | D126: =D66 -> 0 | E126: =AZ66 -> 0 | F126: =I66 -> 1.8118093e-56 | G126: =J66 -> 33.068929 | H126: =AD66 -> 0 | I126: =AE66 -> 7.4870779e-06 | J126: =O66 -> 32.199125 | K126: =W66 -> 0.86903727 | L126: =AN66 -> 0 | M126: =BD66 -> 0 | N126: =AY66 -> 0
B127: =B67 -> C | C127: =C67 -> kmol/hr | D127: =D67 -> 0 | E127: =AZ67 -> 0 | F127: =I67 -> 0 | G127: =J67 -> 0 | H127: =AD67 -> 0 | I127: =AE67 -> 0 | J127: =O67 -> 0 | K127: =W67 -> 0 | L127: =AN67 -> 0 | M127: =BD67 -> 0 | N127: =AY67 -> 1392.0025
B128: =B68 -> WATER | C128: =C68 -> kmol/hr | D128: =D68 -> 0 | E128: =AZ68 -> 0 | F128: =I68 -> 0 | G128: =J68 -> 0 | H128: =AD68 -> 0 | I128: =AE68 -> 0 | J128: =O68 -> 0 | K128: =W68 -> 0 | L128: =AN68 -> 0 | M128: =BD68 -> 0 | N128: =AY68 -> 0
B129: =B69 -> O2 | C129: =C69 -> kmol/hr | D129: =D69 -> 0 | E129: =AZ69 -> 1400 | F129: =I69 -> 0 | G129: =J69 -> 0 | H129: =AD69 -> 0 | I129: =AE69 -> 0 | J129: =O69 -> 0 | K129: =W69 -> 0 | L129: =AN69 -> 0 | M129: =BD69 -> 7.9975 | N129: =AY69 -> 0
B130: =B70 -> CO2 | C130: =C70 -> kmol/hr | D130: =D70 -> 0 | E130: =AZ70 -> 0 | F130: =I70 -> 0 | G130: =J70 -> 0 | H130: =AD70 -> 0 | I130: =AE70 -> 0 | J130: =O70 -> 0 | K130: =W70 -> 0 | L130: =AN70 -> 0 | M130: =BD70 -> 1392.0025 | N130: =AY70 -> 0
B131: =B71 -> Mole Fractions
B132: =B72 -> H2 | D132: =D72 -> 0 | E132: =AZ72 -> 0 | F132: =I72 -> 0.81482104 | G132: =J72 -> 0.85398235 | H132: =AD72 -> 4.8564991e-13 | I132: =AE72 -> 8.080313e-43 | J132: =O72 -> 0.0059815184 | K132: =W72 -> 3.9449529e-10 | L132: =AN72 -> 0.96418774 | M132: =BD72 -> 0 | N132: =AY72 -> 0
B133: =B73 -> CH4 | D133: =D73 -> 1 | E133: =AZ73 -> 0 | F133: =I73 -> 0.18333657 | G133: =J73 -> 0.12247148 | H133: =AD73 -> 0.00019882539 | I133: =AE73 -> 4.2053877e-18 | J133: =O73 -> 0.0057866986 | K133: =W73 -> 5.1457477e-08 | L133: =AN73 -> 0.035803415 | M133: =BD73 -> 0 | N133: =AY73 -> 0
B134: =B74 -> C2H6 | D134: =D74 -> 0 | E134: =AZ74 -> 0 | F134: =I74 -> 1.7378583e-05 | G134: =J74 -> 0.00054596539 | H134: =AD74 -> 4.350967e-16 | I134: =AE74 -> 0.045588078 | J134: =O74 -> 0.00018113445 | K134: =W74 -> 7.38648e-07 | L134: =AN74 -> 1.6048357e-08 | M134: =BD74 -> 0 | N134: =AY74 -> 0
B135: =B75 -> C2H4 | D135: =D75 -> 0 | E135: =AZ75 -> 0 | F135: =I75 -> 0.001524847 | G135: =J75 -> 0.010851885 | H135: =AD75 -> 0.99860001 | I135: =AE75 -> 0.00080762415 | J135: =O75 -> 0.0024139843 | K135: =W75 -> 2.5746368e-06 | L135: =AN75 -> 8.645757e-06 | M135: =BD75 -> 0 | N135: =AY75 -> 0
...

Sheet DB_APEA_EXECUTIVE SUMMARY
B1: EXECUTIVE SUMMARY
A2: =================================================================================
A4: PROJECT NAME: | B4: 20909C1
A6: CAPACITY: | B6: 486941710 KG/Year 27-ETHYL @ 0.990 USD/KG
A8: PLANT LOCATION: | B8: North America
A10: BRIEF DESCRIPTION: | B10: 1
A14: SCHEDULE: | B14: ---------------------------------------------------------------------------------------
A15: Start Date for Engineering | B15: 42370
A16: Duration of EPC Phase | B16: 96 | C16: Weeks
A17: Completion Date for Construction | B17: Thursday, November 09, 2017
A18: Length of Start-up Period | B18: 20 | C18: Weeks
A21: INVESTMENT: | B21: ---------------------------------------------------------------------------------------
A22: Currency Conversion Rate | B22: 1 | C22: USD/U.S. DOLLAR
A23: Total Project Capital Cost | B23: 2.0344443e+08 | C23: USD
A24: Total Operating Cost | B24: 3.9702651e+08 | C24: USD/Year
A25: Total Raw Materials Cost | B25: 14880094 | C25: USD/Year
A26: Total Utilities Cost | B26: 3.4843704e+08 | C26: USD/Year
A27: Total Product Sales | B27: 1009148872 | C27: USD/Year
A28: Desired Rate of Return | B28: 8 | C28: Percent/'Year
A29: P.O. Period | B29: 3.04 | C29: Year
A31: PROJECT INFORMATION: | B31: ---------------------------------------------------------------------------------------
A32: Simulator Type | B32: Aspen Plus
A33: Version
A34: Report File | B34: C:\Users\Ngan\Desktop\C1 refinery\Aspen case\20190918_Final economic\_5615tfr.ads
A35: Report Date | B35: Wednesday, September 18, 2019
A37: Economic Analysis Type | B37: IPE
A38: Version | B38: 36.1.0
A39: System Cost Base Date | B39: 1Q 16
A40: Project Directory | B40: C:\Users\Ngan\Documents\AspenTech\My Economic Evaluation V10.0 Files\My Econ_Process Projects\20909C1\1
A41: Analysis Date | B41: Wed Sep 18 13:08:03 2019
A42: Country Base | B42: US
A43: Project Type | B43: Grass roots/Clear field
A44: Design code | B44: ASME
A45: Prepared By | B45: NganDo
A47: NOTES:----------------------------------------------------- | B47: ---------------------------------------------------------------------------------------

Sheet DB_APEA_PROJSUM.ICS
A1: PROJSUM.ICS (Project Summary)
A3: ITEM | B3: UNITS | C3: VALUE
A4: ************************************************************************
A6: PROJECT INFORMATION
A8: Project Name | C8: 20909C1
A9: Project Description | C9: 1
A10: Analysis Date and Time | C10: Wed Sep 18 13:08:03 2019
A11: Simulator Type | C11: Aspen Plus
A12: Simulator Version
A13: Simulator Report File | C13: C:\Users\Ngan\Desktop\C1 refinery\Aspen case\20190918_Final economic\_5615tfr.ads
A14: Simulator Report Date | C14: Wednesday, September 18, 2019
A15: Economic Analysis Type | C15: IPE
A16: Version | C16: 36.1.0
A17: Project Directory | C17: C:\Users\Ngan\Documents\AspenTech\My Economic Evaluation V10.0 Files\My Econ_Process Projects\20909C1\1
A18: Scenario Name | C18: 1
A19: Scenario Description | C19: C1 Refinery
A20: ************************************************************************
A21: CAPITAL COST EVALUATION BASIS
A23: Date | C23: 43726
A24: Country | C24: US
A25: Units of Measure | C25: METRIC
A26: Currency (Cost) Symbol | C26: U.S. DOLLAR
A27: Currency Conversion Rate | B27: USD/U.S. DOLLAR | C27: 1
A28: System Cost Base Date | C28: 1Q 16
A29: Project Type | C29: Grass roots/Clear field
A30: Design code | C30: ASME
A31: Prepared By | C31: NganDo
A32: Plant Location | C32: North America
A33: Capacity | C33: 486941710 KG/Year 27-ETHYL @ 0.990 USD/KG
A34: Time Difference Between System Cost Base Date and Start Date for Engineering | B34: Days | C34: -90
A35: User Currency Name | C35: DOLLARS
A36: User Currency Description | C36: U.S. DOLLARS
A37: User Currency Symbol | C37: USD
A39: ************************************************************************
A41: TIME PERIOD
A43: Period Description | C43: Year
A44: Operating Hours per Period | B44: Hours/period | C44: 8000
A45: Number of Weeks per Period | B45: Weeks/period | C45: 52
A46: Number of Periods for Analysis | B46: Period | C46: 30
A57: ************************************************************************
A59: SCHEDULE
A61: Start Date for Engineering | C61: 42370
A62: Duration of EPC Phase | B62: Weeks | C62: 96
A63: Length of Start-up Period | B63: Weeks | C63: 20
A64: Duration of Construction Phase | B64: Weeks | C64: 62
A65: Completion Date for Construction | C65: Thursday, November 09, 2017
A75: ************************************************************************
A77: CAPITAL COSTS PARAMETERS
A79: Working Capital Percentage | B79: Percent/period | C79: 5
A91: ************************************************************************
A93: OPERATING COSTS PARAMETERS
A95: Operating Supplies (lump-sum) | B95: Cost/period | C95: 0
A96: Laboratory Charges (lump-sum) | B96: Cost/period | C96: 0
A97: User Entered Operating Charges (as percentage) | B97: Percent/period | C97: 25
A98: Operating Charges (Percent of Operating Labor Costs) | B98: Percent/period | C98: 25
A99: Plant Overhead (Percent of Operating Labor and Maintenance Costs) | B99: Percent/period | C99: 50
A100: G and A Expenses (Percent of Subtotal Operating Costs) | B100: Percent/period | C100: 8
A108: ************************************************************************
A110: GENERAL INVESTMENT PARAMETERS
A112: Tax Rate | B112: Percent/period | C112: 35
A113: Interest Rate | B113: Percent/period | C113: 8
A114: Economic Life of Project | B114: Period | C114: 30
A115: Salvage Value (Fraction of Initial Capital Cost) | B115: Percent | C115: 20
A116: Depreciation Method | C116: Straight Line
A128: ************************************************************************
A130: ESCALATION
A132: Project Capital Escalation | B132: Percent/period | C132: 5
A133: Products Escalation | B133: Percent/period | C133: 5
A134: Raw Material Escalation | B134: Percent/period | C134: 3.5
A135: Operating and Maintenance Labor Escalation | B135: Percent/period | C135: 3
A136: Utilities Escalation | B136: Percent/period | C136: 3
A148: ************************************************************************
A150: PROJECT RESULTS SUMMARY
A152: Total Project Capital Cost | B152: Cost | C152: 2.0344443e+08
A153: Total Raw Materials Cost | B153: Cost/period | C153: 14880094
A154: Total Products Sales | B154: Cost/period | C154: 1009148872
A155: Total Operating Labor and Maintenance Cost | B155: Cost/period | C155: 2740000
A156: Total Utilities Cost | B156: Cost/period | C156: 3.4843704e+08
A157: Total Operating Cost | B157: Cost/period | C157: 3.9702651e+08
A159: Operating Labor Cost | B159: Cost/period | C159: 760000
A160: Maintenance Cost | B160: Cost/period | C160: 1980000
A161: Operating Charges | B161: Cost/period | C161: 190000
A162: Plant Overhead | B162: Cost/period | C162: 1370000
A163: Subtotal Operating Cost | B163: Cost/period | C163: 3.6761714e+08 | E163: =SUM(C159:C162)+C156+C155 -> 3.5547704e+08
A164: G and A Cost | C164: 29409371
A168: ************************************************************************
A170: PROJECT CAPITAL SUMMARY | C170: Total Cost | D170: Design, Eng, Procurement | E170: Construction Material | F170: Construction Manhours | G170: Construction Manpower | H170: Construction Indirects
A172: Purchased Equipment | B172: Cost | C172: 87888904 | E172: 87888904
A173: Equipment Setting | B173: Cost | C173: 550517.7 | F173: 16919 | G173: 550517.7
A174: Piping | B174: Cost | C174: 29088516 | E174: 16387426 | F174: 391048 | G174: 12701090
A175: Civil | B175: Cost | C175: 1570387.4 | E175: 974963.8 | F175: 22743 | G175: 595423.6
A176: Steel | B176: Cost | C176: 334385.2 | E176: 286162.5 | F176: 1607 | G176: 48222.6
A177: Instrumentation | B177: Cost | C177: 1521794.2 | E177: 1283153.6 | F177: 7330 | G177: 238640.7
A178: Electrical | B178: Cost | C178: 4357876 | E178: 4007078.5 | F178: 11202 | G178: 350797.5
A179: Insulation | B179: Cost | C179: 2890263.8 | E179: 1606870.1 | F179: 53768 | G179: 1283393.5
A180: Paint | B180: Cost | C180: 120116.6 | E180: 39539.4 | F180: 3363 | G180: 80577.2
A181: Other | B181: Cost | C181: 36462100 | D181: 5354700 | E181: 11528601 | H181: 19578800
A182: Subcontracts | B182: Cost | C182: 0
A183: G and A Overheads | B183: Cost | C183: 4782905 | D183: 0 | E183: 3720080.5 | G183: 475459.9 | H183: 587364
A184: Contract Fee | B184: Cost | C184: 5000898.5 | D184: 257025.6 | E184: 2554455.2 | G184: 979447.4 | H184: 1209970
...

Sheet DB_APEA_CASHFLOW.ICS
A1: CASHFLOW.ICS (Cashflow) | B1: Year | C1: 0 | D1: 1 | E1: 2 | F1: 3 | G1: 4 | H1: 5 | I1: 6 | J1: 7 | K1: 8 | L1: 9 | M1: 10 | N1: 11 | O1: 12 | P1: 13 | Q1: 14 | R1: 15 | S1: 16 | T1: 17 | U1: 18 | V1: 19 | W1: 20 | X1: 21 | Y1: 22 | Z1: 23 | AA1: 24 | AB1: 25 | AC1: 26 | AD1: 27 | AE1: 28 | AF1: 29 | AG1: 30
A5: ITEM | B5: UNITS
A7: TW (Number of Weeks per Period) | B7: Weeks/period | C7: 52
A8: T (Number of Periods for Analysis) | B8: Period | C8: 30
A9: DTEPC (Duration of EPC Phase) | B9: Period | C9: 1.85
A10: DT (Duration of EPC Phase and Startup) | B10: Period | C10: 2.23
A11: WORKP (Working Capital Percentage) | B11: Percent/period | C11: 5
A12: OPCHG (Operating Charges) | B12: Percent/period | C12: 25
A13: PLANTOVH (Plant Overhead) | B13: Percent/period | C13: 50
A14: CAPT (Total Project Cost) | B14: Cost | C14: 2.0344443e+08
A15: RAWT (Total Raw Material Cost) | B15: Cost/period | C15: 14880094
A16: PRODT (Total Product Sales) | B16: Cost/period | C16: 1009148872
A17: OPMT (Total Operating Labor and Maintenance Cost) | B17: Cost/period | C17: 2740000
A18: UTILT (Total Utilities Cost) | B18: Cost/period | C18: 3.4843704e+08
A19: ROR (Desired Rate of Return/Interest Rate) | B19: Percent/period | C19: 8
A20: AF (ROR Annuity Factor) | C20: 12.5
A21: TAXR (Tax Rate) | B21: Percent/period | C21: 35
A22: IF (ROR Interest Factor) | C22: 1.08
A23: ECONLIFE (Economic Life of Project) | B23: Period | C23: 30
A24: SALVAL (Salvage Value (Percent of Initial Capital Cost)) | B24: Percent | C24: 20
A25: DEPMETH (Depreciation Method) | C25: Straight Line
A26: DEPMETHN (Depreciation Method Id) | C26: 1
A27: ESCAP (Project Capital Escalation) | B27: Percent/period | C27: 5
A28: ESPROD (Products Escalation) | B28: Percent/period | C28: 5
A29: ESRAW (Raw Material Escalation) | B29: Percent/period | C29: 3.5
A30: ESLAB (Operating and Maintenance Labor Escalation) | B30: Percent/period | C30: 3
A31: ESUT (Utilities Escalation) | B31: Percent/period | C31: 3
A32: START (Start Period for Plant Startup) | B32: Period | C32: 2
A33: PODE (Desired Payout Period (excluding EPC and Startup Phases)) | B33: Period
A34: POD (Desired Payout Period) | B34: Period
A35: DESRET (Desired Return on Project for Sales Forecasting) | B35: Percent/Period | C35: 10.5
A36: END (End Period for Economic Life of Project) | B36: Period | C36: 31
A37: GA (G and A Expenses) | B37: Percent/Period | C37: 8
A38: DTEP (Duration of EP Phase before Start of Construction) | B38: Period | C38: 0.65
A39: OP (Total Operating Labor Cost) | B39: Cost/period | C39: 760000
A40: MT (Total Maintenance Cost) | B40: Cost/period | C40: 1980000
A51: Sales
A52: SP (Products Sales) | B52: Cost/Period | C52: 0 | D52: 0 | E52: 0 | F52: 8.9862766e+08 | G52: 1.2266268e+09 | H52: 1.2879581e+09 | I52: 1.352356e+09 | J52: 1.4199738e+09 | K52: 1.4909725e+09 | L52: 1.5655211e+09 | M52: 1.6437972e+09 | N52: 1.725987e+09 | O52: 1.8122864e+09 | P52: 1.9029007e+09 | Q52: 1.9980457e+09 | R52: 2.097948e+09 | S52: 2.2028454e+09 | T52: 2.3129877e+09 | U52: 2.4286371e+09 | V52: 2.5500689e+09 | W52: 2.6775724e+09 | X52: 2.811451e+09 | Y52: 2.9520236e+09 | Z52: 3.0996247e+09 | AA52: 3.254606e+09 | AB52: 3.4173363e+09 | AC52: 3.5882031e+09 | AD52: 3.7676132e+09 | AE52: 3.9559939e+09 | AF52: 4.1537936e+09 | AG52: 4.3614833e+09 | AH52: 0 | AI52: 0 | AJ52: 0 | AK52: 0 | AL52: 0 | AM52: 0 | AN52: 0 | AO52: 0 | AP52: 0 | AQ52: 0 | AR52: 0 | AS52: 0 | AT52: 0 | AU52: 0 | AV52: 0 | AW52: 0 | AX52: 0 | AY52: 0 | AZ52: 0 | BA52: 0
A53: SPF (Forecasted Sales Annuity Factor) | C53: 0 | D53: 0 | E53: 0 | F53: 0 | G53: 0 | H53: 0 | I53: 0 | J53: 0 | K53: 0 | L53: 0 | M53: 0 | N53: 0 | O53: 0 | P53: 0 | Q53: 0 | R53: 0 | S53: 0 | T53: 0 | U53: 0 | V53: 0 | W53: 0 | X53: 0 | Y53: 0 | Z53: 0 | AA53: 0 | AB53: 0 | AC53: 0 | AD53: 0 | AE53: 0 | AF53: 0 | AG53: 0 | AH53: 0 | AI53: 0 | AJ53: 0 | AK53: 0 | AL53: 0 | AM53: 0 | AN53: 0 | AO53: 0 | AP53: 0 | AQ53: 0 | AR53: 0 | AS53: 0 | AT53: 0 | AU53: 0 | AV53: 0 | AW53: 0 | AX53: 0 | AY53: 0 | AZ53: 0 | BA53: 0
A54: SF (Forecasted Sales) | B54: Cost/Period | C54: 0 | D54: 0 | E54: 0 | F54: 0 | G54: 0 | H54: 0 | I54: 0 | J54: 0 | K54: 0 | L54: 0 | M54: 0 | N54: 0 | O54: 0 | P54: 0 | Q54: 0 | R54: 0 | S54: 0 | T54: 0 | U54: 0 | V54: 0 | W54: 0 | X54: 0 | Y54: 0 | Z54: 0 | AA54: 0 | AB54: 0 | AC54: 0 | AD54: 0 | AE54: 0 | AF54: 0 | AG54: 0 | AH54: 0 | AI54: 0 | AJ54: 0 | AK54: 0 | AL54: 0 | AM54: 0 | AN54: 0 | AO54: 0 | AP54: 0 | AQ54: 0 | AR54: 0 | AS54: 0 | AT54: 0 | AU54: 0 | AV54: 0 | AW54: 0 | AX54: 0 | AY54: 0 | AZ54: 0 | BA54: 0
A55: S (Total Sales) | B55: Cost/Period | C55: 0 | D55: 0 | E55: 0 | F55: 8.9862766e+08 | G55: 1.2266268e+09 | H55: 1.2879581e+09 | I55: 1.352356e+09 | J55: 1.4199738e+09 | K55: 1.4909725e+09 | L55: 1.5655211e+09 | M55: 1.6437972e+09 | N55: 1.725987e+09 | O55: 1.8122864e+09 | P55: 1.9029007e+09 | Q55: 1.9980457e+09 | R55: 2.097948e+09 | S55: 2.2028454e+09 | T55: 2.3129877e+09 | U55: 2.4286371e+09 | V55: 2.5500689e+09 | W55: 2.6775724e+09 | X55: 2.811451e+09 | Y55: 2.9520236e+09 | Z55: 3.0996247e+09 | AA55: 3.254606e+09 | AB55: 3.4173363e+09 | AC55: 3.5882031e+09 | AD55: 3.7676132e+09 | AE55: 3.9559939e+09 | AF55: 4.1537936e+09 | AG55: 4.3614833e+09 | AH55: 0 | AI55: 0 | AJ55: 0 | AK55: 0 | AL55: 0 | AM55: 0 | AN55: 0 | AO55: 0 | AP55: 0 | AQ55: 0 | AR55: 0 | AS55: 0 | AT55: 0 | AU55: 0 | AV55: 0 | AW55: 0 | AX55: 0 | AY55: 0 | AZ55: 0 | BA55: 0
A61: Expenses
A62: CAP (Capital Costs) | B62: Cost/Period | C62: 0 | D62: 96127493 | E62: 1.2848914e+08 | AH62: 0 | AI62: 0 | AJ62: 0 | AK62: 0 | AL62: 0 | AM62: 0 | AN62: 0 | AO62: 0 | AP62: 0 | AQ62: 0 | AR62: 0 | AS62: 0 | AT62: 0 | AU62: 0 | AV62: 0 | AW62: 0 | AX62: 0 | AY62: 0 | AZ62: 0 | BA62: 0
A63: Unescalated Cumulative Capital Cost | B63: Cost/Period | C63: 0 | D63: 91549994 | E63: 2.0344443e+08 | F63: 2.0344443e+08 | G63: 2.0344443e+08 | H63: 2.0344443e+08 | I63: 2.0344443e+08 | J63: 2.0344443e+08 | K63: 2.0344443e+08 | L63: 2.0344443e+08 | M63: 2.0344443e+08 | N63: 2.0344443e+08 | O63: 2.0344443e+08 | P63: 2.0344443e+08 | Q63: 2.0344443e+08 | R63: 2.0344443e+08 | S63: 2.0344443e+08 | T63: 2.0344443e+08 | U63: 2.0344443e+08 | V63: 2.0344443e+08 | W63: 2.0344443e+08 | X63: 2.0344443e+08 | Y63: 2.0344443e+08 | Z63: 2.0344443e+08 | AA63: 2.0344443e+08 | AB63: 2.0344443e+08 | AC63: 2.0344443e+08 | AD63: 2.0344443e+08 | AE63: 2.0344443e+08 | AF63: 2.0344443e+08 | AG63: 2.0344443e+08 | AH63: 0 | AI63: 0 | AJ63: 0 | AK63: 0 | AL63: 0 | AM63: 0 | AN63: 0 | AO63: 0 | AP63: 0 | AQ63: 0 | AR63: 0 | AS63: 0 | AT63: 0 | AU63: 0 | AV63: 0 | AW63: 0 | AX63: 0 | AY63: 0 | AZ63: 0 | BA63: 0
A64: Capital Cost | B64: Cost/period | C64: 0 | D64: 96127493 | E64: 1.1831692e+08 | AH64: 0 | AI64: 0 | AJ64: 0 | AK64: 0 | AL64: 0 | AM64: 0 | AN64: 0 | AO64: 0 | AP64: 0 | AQ64: 0 | AR64: 0 | AS64: 0 | AT64: 0 | AU64: 0 | AV64: 0 | AW64: 0 | AX64: 0 | AY64: 0 | AZ64: 0 | BA64: 0
