Workbook

Sheet 1. DB_Experiment_VER1
C1: SABIC | D1: KRICT (5.8%) | E1: KRICT (10%) | F1: KRICT (20%) | G1: KRICT (30%) | H1: KRICT (업데이트 실험결과)
A2: Reference | C2: PCT/US2018/012064
C3: US 7,919,431 B2
A4: Preheating | J4: lb | K4: g
A5: Temp (oC) | C5: 500 | D5: - | J5: 1 | K5: 453.592
A7: CH4 pyrolysis | J7: 43.5
A8: Temp (oC) | C8: 2500 | D8: 1114 | E8: 1114 | F8: 1114 | G8: 1114 | H8: 1230
A9: CH4 feed (lb/h) | C9: 43.5
A10: CH4 feed (g/h) | C10: =C9*K5 -> 19731.252
A11: CH4 feed (ml/min) | D11: 20 | E11: 20 | F11: 20 | G11: 20 | H11: 14.4
A12: CH4 feed (mol/h) | C12: =C10/16 -> 1233.2033 | D12: =D11*60/22400 -> 0.053571429 | E12: =E11*60/22400 -> 0.053571429 | F12: =F11*60/22400 -> 0.053571429 | G12: =G11*60/22400 -> 0.053571429 | H12: =H11*60/22400 -> 0.038571429
A13: H2 feed (ml/min) | D13: 60 | E13: 60 | F13: 60 | G13: 60 | H13: 64
A14: H2 feed (mol/h) | D14: =D13*60/22400 -> 0.16071429 | E14: =E13*60/22400 -> 0.16071429 | F14: =F13*60/22400 -> 0.16071429 | G14: =G13*60/22400 -> 0.16071429 | H14: =H13*60/22400 -> 0.17142857 | I14: H2/CH4 | J14: =H14/H12 -> 4.4444444
A15: CH4 fuel (lb/h) | C15: 55.6
A16: CH4 fuel (g/h) | C16: =C15*K5 -> 25219.715
A17: CH4 fuel (mol/h) | C17: =C16/16 -> 1576.2322
A18: Pure O2 (lb/h) | C18: 182.8
A19: O2 fuel (g/h) | C19: =C18*K5 -> 82916.618
A20: O2 fuel (mol/h) | C20: =C19/32 -> 2591.1443
A21: Duty (Mbtu/h) | C21: 1114
A22: O2 stoichometry (%) | C22: 88.4
A27: Methane conversion (%) | C27: 51.3 | D27: 5.8 | E27: 10 | F27: 20 | G27: 30 | H27: 30.353963
A29: Product composition (C%)
A30: C2H6 | D30: 5.5 | E30: 5.5 | F30: 5.5 | G30: 5.5 | H30: 1.9832376
A31: C2H4 | D31: 60.3 | E31: 60.3 | F31: 60.3 | G31: 60.3 | H31: 35.180966
A32: C2H2 | D32: 2.9 | E32: 2.9 | F32: 2.9 | G32: 2.9 | H32: 41.411786
A33: C3-C5 | D33: 1.3 | E33: 1.3 | F33: 1.3 | G33: 1.3 | H33: 0
A34: Benzene | D34: 4.3 | E34: 4.3 | F34: 4.3 | G34: 4.3 | H34: 7.4789878
A35: Naphthalene | D35: 25.6 | E35: 25.6 | F35: 25.6 | G35: 25.6 | H35: 2.6768978
A36: Coke | H36: 11.268125
A37: Total | D37: =SUM(D30:D35) -> 99.9 | E37: =SUM(E30:E35) -> 99.9 | F37: =SUM(F30:F35) -> 99.9 | G37: =SUM(G30:G35) -> 99.9 | H37: =SUM(H30:H36) -> 100
L38: -253 | M38: Hydrogen in hydrocarbon | N38: 1 CASE | O38: 2 CASE | P38: 3 CASE | Q38: 4 CASE | R38: KRICT (업데이트 실험결과)
A39: Product composition (mol/h) (1) | L39: -164 | M39: CH4 | N39: =D12*D27/100*2 -> 0.0062142857 | O39: =E12*E27/100*2 -> 0.010714286 | P39: =F12*F27/100*2 -> 0.021428571 | Q39: =G12*G27/100*2 -> 0.032142857 | R39: =H12*H27/100*2 -> 0.023415914 | S39: =Q39/$Q$48*100 -> 48.056122
A40: H2 | C40: =$C$42*C54/$C$56 -> 1544.3952 | D40: =D14+N47 -> 0.1643282 | E40: =E14+O47 -> 0.1688282 | F40: =F14+P47 -> 0.17954249 | G40: =G14+Q47 -> 0.19025678 | H40: =H14+R47 -> 0.1873898 | I40: =H40*10000 -> 1873.898 | L40: -89 | M40: C2H6 | N40: =D43*3 -> 0.00025633929 | O40: =E43*3 -> 0.00025633929 | P40: =F43*3 -> 0.00025633929 | Q40: =G43*3 -> 0.00025633929 | R40: =H43*3 -> 0.0003482949 | S40: =Q40/$Q$48*100 -> 0.38324757
A41: CO2 | C41: =$C$42*C55/$C$56 -> 859.26123 | I41: =H41*10000 -> 0 | L41: -104 | M41: C2H4 | N41: =D44*2 -> 0.0018736071 | O41: =E44*2 -> 0.0018736071 | P41: =F44*2 -> 0.0018736071 | Q41: =G44*2 -> 0.0018736071 | R41: =H44*2 -> 0.0041189724 | S41: =Q41/$Q$48*100 -> 2.8011913
A42: CH4 | C42: =C12*C27/100 -> 632.63327 | D42: =D12*(100-D27)/100 -> 0.050464286 | E42: =E12*(100-E27)/100 -> 0.048214286 | F42: =F12*(100-F27)/100 -> 0.042857143 | G42: =G12*(100-G27)/100 -> 0.0375 | H42: =H12*(100-H27)/100 -> 0.026863472 | I42: =H42*10000 -> 268.63472 | L42: -84 | M42: C2H2 | N42: =D45*1 -> 4.5053571e-05 | O42: =E45*1 -> 4.5053571e-05 | P42: =F45*1 -> 4.5053571e-05 | Q42: =G45*1 -> 4.5053571e-05 | R42: =H45*1 -> 0.002424237 | S42: =Q42/$Q$48*100 -> 0.067358664
A43: C2H6 | D43: =($D$12-$D$42)*D30/100/2 -> 8.5446429e-05 | E43: =($D$12-$D$42)*E30/100/2 -> 8.5446429e-05 | F43: =($D$12-$D$42)*F30/100/2 -> 8.5446429e-05 | G43: =($D$12-$D$42)*G30/100/2 -> 8.5446429e-05 | H43: =($H$12-$H$42)*H30/100/2 -> 0.0001160983 | I43: =H43*10000 -> 1.160983 | L43: -84 | M43: C3-C5 | N43: =D46*3 -> 4.0392857e-05 | O43: =E46*3 -> 4.0392857e-05 | P43: =F46*3 -> 4.0392857e-05 | Q43: =G46*3 -> 4.0392857e-05 | R43: =H46*3 -> 0 | S43: =Q43/$Q$48*100 -> 0.060390526
A44: C2H4 | C44: =$C$42*C58/$C$56 -> 21.000274 | D44: =($D$12-$D$42)*D31/100/2 -> 0.00093680357 | E44: =($D$12-$D$42)*E31/100/2 -> 0.00093680357 | F44: =($D$12-$D$42)*F31/100/2 -> 0.00093680357 | G44: =($D$12-$D$42)*G31/100/2 -> 0.00093680357 | H44: =($H$12-$H$42)*H31/100/2 -> 0.0020594862 | I44: =H44*10000 -> 20.594862 | L44: -47 -> 36 | M44: Benzene | N44: =D47*3 -> 6.6803571e-05 | O44: =E47*3 -> 6.6803571e-05 | P44: =F47*3 -> 6.6803571e-05 | Q44: =G47*3 -> 6.6803571e-05 | R44: =H47*3 -> 0.00043781834 | S44: =Q44/$Q$48*100 -> 0.09987664
A45: C2H2 | C45: =$C$42*C59/$C$56 -> 200.37762 | D45: =($D$12-$D$42)*D32/100/2 -> 4.5053571e-05 | E45: =($D$12-$D$42)*E32/100/2 -> 4.5053571e-05 | F45: =($D$12-$D$42)*F32/100/2 -> 4.5053571e-05 | G45: =($D$12-$D$42)*G32/100/2 -> 4.5053571e-05 | H45: =($H$12-$H$42)*H32/100/2 -> 0.002424237 | I45: =H45*10000 -> 24.24237 | L45: 80 | M45: Naphthalene | N45: =D48*4 -> 0.00031817143 | O45: =E48*4 -> 0.00031817143 | P45: =F48*4 -> 0.00031817143 | Q45: =G48*4 -> 0.00031817143 | R45: =H48*4 -> 0.00012536402 | S45: =Q45/$Q$48*100 -> 0.47569153
A46: C3-C5 | D46: =($D$12-$D$42)*D33/100/3 -> 1.3464286e-05 | E46: =($D$12-$D$42)*E33/100/3 -> 1.3464286e-05 | F46: =($D$12-$D$42)*F33/100/3 -> 1.3464286e-05 | G46: =($D$12-$D$42)*G33/100/3 -> 1.3464286e-05 | H46: =($H$12-$H$42)*H33/100/3 -> 0 | I46: =H46*10000 -> 0 | L46: 218 | M46: H2 | N46: =SUM(N40:N45) -> 0.0026003679 | O46: =SUM(O40:O45) -> 0.0026003679 | P46: =SUM(P40:P45) -> 0.0026003679 | Q46: =SUM(Q40:Q45) -> 0.0026003679 | R46: =SUM(R40:R45) -> 0.0074546866 | S46: =(Q46+Q47)/Q48*100 -> 48.056122
A47: Benzene | D47: =($D$12-$D$42)*D34/100/6 -> 2.2267857e-05 | E47: =($D$12-$D$42)*E34/100/6 -> 2.2267857e-05 | F47: =($D$12-$D$42)*F34/100/6 -> 2.2267857e-05 | G47: =($D$12-$D$42)*G34/100/6 -> 2.2267857e-05 | H47: =($H$12-$H$42)*H34/100/6 -> 0.00014593945 | I47: =H47*10000 -> 1.4593945 | M47: Produced hydrogen | N47: =N39-N46 -> 0.0036139179 | O47: =O39-O46 -> 0.0081139179 | P47: =P39-P46 -> 0.018828204 | Q47: =Q39-Q46 -> 0.029542489 | R47: =R39-R46 -> 0.015961227 | S47: =SUM(S39:S46) -> 100
A48: Naphthalene | D48: =($D$12-$D$42)*D35/100/10 -> 7.9542857e-05 | E48: =($D$12-$D$42)*E35/100/10 -> 7.9542857e-05 | F48: =($D$12-$D$42)*F35/100/10 -> 7.9542857e-05 | G48: =($D$12-$D$42)*G35/100/10 -> 7.9542857e-05 | H48: =($H$12-$H$42)*H35/100/10 -> 3.1341004e-05 | I48: =H48*10000 -> 0.31341004 | Q48: =SUM(Q39:Q47) -> 0.066886082
A49: CO | C49: =$C$42*C63/$C$56 -> 1053.9513 | I49: =H49*10000 -> 0
A50: C | H50: =($H$12-$H$42)*H36/100/2 -> 0.00065963364 | I50: =H50*10000 -> 6.5963364
A51: Total | C51: =SUM(C40:C49) -> 4311.6188 | D51: =SUM(D42:D49) -> 0.051646864 | E51: =SUM(E42:E49) -> 0.049396864 | F51: =SUM(F42:F49) -> 0.044039721 | G51: =SUM(G42:G49) -> 0.038682579 | H51: =SUM(H42:H50) -> 0.032300207
A53: Effluent composition (vol%) (1)
A54: H2 | C54: 35.3 | D54: =D40/D51*100 -> 318.17654 | E54: =E40/E51*100 -> 341.77919 | F54: =F40/F51*100 -> 407.68307 | G54: =G40/G51*100 -> 491.84098 | H54: =H40/H51*100 -> 580.15046
A55: CO2 | C55: 19.64
A56: CH4 | C56: 14.46 | D56: =D42/D51*100 -> 97.710261 | E56: =E42/E51*100 -> 97.605964 | F56: =F42/F51*100 -> 97.314746 | G56: =G42/G51*100 -> 96.942865 | H56: =H42/H51*100 -> 83.168109
A57: C2H6 | D57: =D43/D51*100 -> 0.16544359 | E57: =E43/E51*100 -> 0.17297946 | F57: =F43/F51*100 -> 0.19402127 | G57: =G43/G51*100 -> 0.22089124 | H57: =H43/H51*100 -> 0.35943516
A58: C2H4 | C58: 0.48 | D58: =D44/D51*100 -> 1.8138634 | E58: =E44/E51*100 -> 1.8964839 | F58: =F44/F51*100 -> 2.1271787 | G58: =G44/G51*100 -> 2.4217713 | H58: =H44/H51*100 -> 6.3760773
A59: C2H2 | C59: 4.58 | D59: =D45/D51*100 -> 0.087233895 | E59: =E45/E51*100 -> 0.091207351 | F59: =F45/F51*100 -> 0.10230213 | G59: =G45/G51*100 -> 0.11646993 | H59: =H45/H51*100 -> 7.5053297
A60: C3-C5 | D60: =D46/D51*100 -> 0.0260699 | E60: =E46/E51*100 -> 0.027257369 | F60: =F46/F51*100 -> 0.030573049 | G60: =G46/G51*100 -> 0.034807105 | H60: =H46/H51*100 -> 0
A61: Benzene | D61: =D47/D51*100 -> 0.043115603 | E61: =E47/E51*100 -> 0.045079495 | F61: =F47/F51*100 -> 0.05056312 | G61: =G47/G51*100 -> 0.057565597 | H61: =H47/H51*100 -> 0.45182202
A62: Naphthalene | D62: =D48/D51*100 -> 0.15401295 | E62: =E48/E51*100 -> 0.16102815 | F62: =F48/F51*100 -> 0.18061617 | G62: =G48/G51*100 -> 0.20562967 | H62: =H48/H51*100 -> 0.097030351
A63: CO | C63: 24.09
A64: C | H64: =H50/H51*100 -> 2.0421963
A65: Total | C65: =SUM(C54:C63) -> 98.55 | D65: =SUM(D54:D63) -> 418.17654 | E65: =SUM(E54:E63) -> 441.77919 | F65: =SUM(F54:F63) -> 507.68307 | G65: =SUM(G54:G63) -> 591.84098 | H65: =SUM(H54:H64) -> 680.15046
A67: Coolant quenching
A68: Temp (oC) | C68: 300
A69: Water
A71: Quenched product composition (mol/h) (2)
A72: H2 | C72: =C40 -> 1544.3952
A73: CO2 | C73: =C41 -> 859.26123
A74: CH4 | C74: =C42 -> 632.63327
A75: C2H6
A76: C2H4 | C76: =C44 -> 21.000274
A77: C2H2
A78: C3-C5
A79: Benzene
A80: Naphthalene
A81: CO | C81: =C49 -> 1053.9513
A82: Total | C82: =SUM(C72:C81) -> 4111.2412
A84: Liquid phase hydrogenation | C84: n-methyl-2-pyrrolidone (NMP)
A85: Temp (oC) | C85: 111
A86: Press (psig) | C86: 150
A87: 1.5 wt% acetylene in Liquid NMP flow rate (ml/min) | C87: 18
A88: (1) gaseous flow rate (ml/min) | C88: 30
A90: Quenched product composition (mol/h) (3)
A91: H2 | C91: =$C$51*C104/$C$114 -> 1544.4526
A92: CO2 | C92: =$C$51*C105/$C$114 -> 859.29318
A93: CH4 | C93: =$C$51*C106/$C$114 -> 632.65679
A94: C2H6 | C94: =$C$51*C107/$C$114 -> 4.0477784
A95: C2H4 | C95: =$C$51*C108/$C$114 -> 216.3765
A96: C2H2 | C96: =$C$51*C109/$C$114 -> 0.80154027
A97: C3-C5
A98: Benzene
A99: Naphthalene
A100: CO | C100: =$C$51*C113/$C$114 -> 1053.9905
A101: Total | C101: =SUM(C91:C100) -> 4311.6188
A103: Effluent composition (vol%) (3)
A104: H2 | C104: 35.3
A105: CO2 | C105: 19.64
A106: CH4 | C106: 14.46
A107: C2H6 | C107: =C59*2.02/100 -> 0.092516
A108: C2H4 | C108: =C58+C59*97.5/100 -> 4.9455
A109: C2H2 | C109: =C59*0.4/100 -> 0.01832
A110: C3-C5
A111: Benzene
A112: Naphthalene
...

Sheet 2. Aspen_stream info
A1: Case 1: Feed H2/CH4=4.56
C37: Units | D37: 1 | E37: 2 | F37: 3 | G37: 4 | H37: 5 | I37: 6 | J37: 7 | K37: 8 | L37: 9 | M37: 10 | N37: 11 | O37: 12 | P37: 13 | Q37: 14 | R37: 15 | S37: 16 | T37: 17 | U37: 18 | AK37: 33 | AL37: 34 | AM37: 35 | AN37: 36 | AO37: 37-H2PRO | AP37: 38 | AQ37: 39 | AR37: 40 | AS37: 41 | AT37: 42 | AU37: 43 | AV37: 44 | AW37: 44-RECY | AX37: 45 | AY37: 45D | AZ37: 46 | BA37: 47 | BB37: 48 | BC37: DECOKING | BD37: EXHAUTED | BE37: FUELGAS | BF37: O2 | BG37: S2 | BH37: S3 | BI37: S4 | BJ37: S5 | BK37: S6 | BL37: S7 | BM37: S8 | BN37: S14 | BO37: S17 | BQ37: 49 | BR37: 50 | BS37: 51-H20 | BT37: 52 | BU37: 53-CO2 | BV37: 54
B38: Temperature | C38: C | D38: 30 | E38: 670.68848 | F38: 30 | G38: 30 | H38: 35 | I38: 0.014251963 | J38: -60 | K38: -116.46255 | L38: -140 | M38: -140 | N38: -125.13065 | O38: 35 | P38: 250.11226 | Q38: -86.520964 | R38: -104.08476 | S38: 30 | T38: 73.417094 | U38: 435.97057
B39: Pressure | C39: bar | D39: 1.013 | E39: 1.013 | F39: 1.013 | G39: 1.013 | H39: 20.000001 | I39: 30 | J39: 30 | K39: 30 | L39: 30 | M39: 30 | N39: 10 | O39: 20 | P39: 30 | Q39: 1.013 | R39: 1.013 | S39: 30 | T39: 1 | U39: 100
B40: Mass Flows | C40: kg/hr | D40: 211552.67 | E40: 1205811.6 | F40: 170758.44 | G40: 694833.86 | H40: 1201147.2 | I40: 1201851.9 | J40: 14202.474 | K40: 1186011.2 | L40: 242525.68 | M40: 943485.52 | N40: 82436.757 | O40: 1639.5145 | P40: 13579.035 | Q40: 14988.357 | R40: 145100.57 | S40: 29499.336 | T40: 259541.22 | U40: 462488.73
B41: Mole Flows | C41: kmol/hr | D41: 13186.8 | E41: 262299.21 | F41: 10643.957 | G41: 21714.472 | H41: 268714.41 | I41: 268723.02 | J41: 192.14321 | K41: 268548.3 | L41: 10927.346 | M41: 257620.96 | N41: 5311.429 | O41: 13.281328 | P41: 173.26753 | Q41: 443.95684 | R41: 5171.9601 | S41: 13684.157 | T41: =SUM(T42:T58) -> 4661.1285 | U41: =SUM(U42:U58) -> 12258.962
B42: H2 | C42: kmol/hr | D42: 0 | E42: 214570.8 | F42: 0 | G42: 0 | H42: 228104.44 | I42: 228104.54 | J42: 1.2403407 | K42: 228122.29 | L42: 198.16268 | M42: 227924.13 | N42: 198.16268 | O42: 0.08087674 | P42: 0.00054280782 | Q42: 4.9527945e-128 | R42: 3.1212174e-08 | S42: 13547.725 | T42: 0 | U42: 0
B43: CH4 | C43: kmol/hr | D43: 13186.8 | E43: 47100.907 | F43: 10643.957 | G43: 0 | H43: 34177.99 | I43: 34178.154 | J43: 3.9210295 | K43: 34179.988 | L43: 5113.2663 | M43: 29066.722 | N43: 5112.7352 | O43: 0.077206607 | P43: 0.004607 | Q43: 2.1145211e-55 | R43: 0.53114204 | S43: 136.43213 | T43: 0 | U43: 0
B44: C2H6 | C44: kmol/hr | D44: 0 | E44: 14.990365 | F44: 0 | G44: 0 | H44: 404.47038 | I44: 404.48959 | J44: 0.85583746 | K44: 404.48513 | L44: 389.41961 | M44: 15.065518 | N44: 0.00011652648 | O44: 0.0061573979 | P44: 0.0047991323 | Q44: 382.46465 | R44: 6.9548468 | S44: 0 | T44: 0 | U44: 0
B45: C2H4 | C45: kmol/hr | D45: 0 | E45: 612.50984 | F45: 0 | G45: 0 | H45: 5784.909 | I45: 5785.0832 | J45: 6.9300903 | K45: 5785.2169 | L45: 5170.1747 | M45: 615.0422 | N45: 0.53102555 | O45: 0.059518262 | P45: 0.027274211 | Q45: 5.169639 | R45: 5164.4741 | S45: 0 | T45: 0 | U45: 0
B46: C2H2 | C46: kmol/hr | D46: 0 | E46: 0 | F46: 0 | G46: 0 | H46: 0 | I46: 0 | J46: 0 | K46: 0 | L46: 0 | M46: 0 | N46: 0 | O46: 0 | P46: 0 | Q46: 0 | R46: 0 | S46: 0 | T46: 0 | U46: 0
B47: C3-C5 | C47: kmol/hr | D47: 0 | E47: 0 | F47: 0 | G47: 0 | H47: 0 | I47: 0 | J47: 0 | K47: 0 | L47: 0 | M47: 0 | N47: 0 | O47: 0 | P47: 0 | Q47: 0 | R47: 0 | S47: 0 | T47: 0 | U47: 0
B48: BEN | C48: kmol/hr | D48: 0 | E48: 1.2479361e-06 | F48: 0 | G48: 0 | H48: 179.03478 | I48: 185.78118 | J48: 170.24839 | K48: 8.2673701 | L48: 8.2673688 | M48: 1.2542071e-06 | N48: 1.6725117e-28 | O48: 0.71855832 | P48: 170.05968 | Q48: 8.2673689 | R48: 4.5597692e-184 | S48: 0 | T48: 0 | U48: 0
B49: TOL | C49: kmol/hr | D49: 0 | E49: 4.8846085e-36 | F49: 0 | G49: 0 | H49: 2.0798313 | I49: 2.3257184 | J49: 2.0357775 | K49: 0.01952693 | L49: 0.01952693 | M49: 2.0840603e-10 | N49: 4.9091543e-36 | O49: 0.02469848 | P49: 2.0357316 | Q49: 0.01952693 | R49: 5.0573522e-256 | S49: 0 | T49: 0 | U49: 0
B50: NAP | C50: kmol/hr | D50: 0 | E50: 7.428528e-62 | F50: 0 | G50: 0 | H50: 12.900267 | I50: 14.027632 | J50: 0.59417385 | K50: 5.1250835e-06 | L50: 5.1250835e-06 | M50: 1.8140352e-19 | N50: 7.4658573e-62 | O50: 12.307157 | P50: 0.59417385 | Q50: 5.1250835e-06 | R50: 0 | S50: 0 | T50: 0 | U50: 0
B51: C | C51: kmol/hr | D51: 0 | E51: 0 | F51: 0 | G51: 0 | H51: 0 | I51: 0 | J51: 0 | K51: 0 | L51: 0 | M51: 0 | N51: 0 | O51: 0 | P51: 0 | Q51: 0 | R51: 0 | S51: 0 | T51: 0 | U51: 0
B52: WATER | C52: kmol/hr | D52: 0 | E52: 0 | F52: 0 | G52: 0 | H52: 0 | I52: 0 | J52: 0 | K52: 0 | L52: 0 | M52: 0 | N52: 0 | O52: 0 | P52: 0 | Q52: 0 | R52: 0 | S52: 0 | T52: 2172.1047 | U52: 208.95196
B53: O2 | C53: kmol/hr | D53: 0 | E53: 0 | F53: 0 | G53: 21713.672 | H53: 0 | I53: 0 | J53: 0 | K53: 0 | L53: 0 | M53: 0 | N53: 0 | O53: 0 | P53: 0 | Q53: 0 | R53: 0 | S53: 0 | T53: 616.33614 | U53: 0.092282654
... B58: MEA | C58: kmol/hr | D58: 0 | E58: 0 | F58: 0 | G58: 0 | H58: 0 | I58: 0 | J58: 0 | K58: 0 | L58: 0 | M58: 0 | N58: 0 | O58: 0 | P58: 0 | Q58: 0 | R58: 0 | S58: 0 | T58: 0.98631149 | U58: 8.7063481e-14
A134: Case 2: Feed H2/CH4=3.44
C174: Units | D174: 1 | E174: 2 | F174: 3 | G174: 4 | H174: 5 | I174: 6 | J174: 7 | K174: 8 | L174: 9 | M174: 10 | N174: 11 | O174: 12 | P174: 13 | Q174: 14 | R174: 15 | S174: 16 | T174: 17 | U174: 18 | CD174: 49 | CE174: 50 | CF174: 51-H20 | CG174: 52 | CH174: 53-CO2 | CI174: 54
B175: Temperature | C175: C | D175: 30 | E175: -17.405867 | F175: 30 | G175: 30 | H175: 35 | I175: 5 | J175: -60 | K175: -115.5874 | L175: -140 | M175: -140 | N175: -121.63486 | O175: 35 | P175: 236.73034 | Q175: -86.622042 | R175: -104.10278 | S175: 30 | T175: 70.357541 | U175: 454.88512
B176: Pressure | C176: bar | D176: 1.013 | E176: 1.013 | F176: 1.013 | G176: 1.013 | H176: 12.000001 | I176: 30 | J176: 30 | K176: 30 | L176: 30 | M176: 30 | N176: 10 | O176: 12.000001 | P176: 30 | Q176: 1.013 | R176: 1.013 | S176: 30 | T176: 1 | U176: 100 | CD176: B1 | CE176: B3 | CF176: B3 | CH176: REG | CI176: ABS
B177: Mass Flows | C177: kg/hr | D177: 211552.67 | E177: 973264.55 | F177: 128009.95 | G177: 520891.41 | H177: 961723.57 | I177: 960620.51 | J177: 19335.514 | K177: 939991.21 | L177: 245831.07 | M177: 694160.14 | N177: 100891.48 | O177: 2743.1846 | P177: 18915.199 | Q177: 11496.629 | R177: 133442.96 | S177: 31440.49 | T177: 259541.22 | U177: 462488.73 | CD177: B2 | CE177: ABS | CG177: P-2
B178: Mole Flows | C178: kmol/hr | D178: 13186.8 | E178: 186082.31 | F178: 7979.2973 | G178: 16278.566 | H178: 192970.26 | I178: 192950.63 | J178: 264.93512 | K178: 192687.73 | L178: 11530.333 | M178: 181157.4 | N178: 6437.4849 | O178: 22.201642 | P178: 245.65464 | Q178: 336.18263 | R178: 4756.6655 | S178: 14585.699 | T178: 9566.4568 | U178: 10699.893 | CD178: CONVEN | CE178: CONVEN | CF178: CONVEN | CG178: CONVEN | CH178: CONVEN | CI178: CONVEN
B179: H2 | C179: kmol/hr | D179: 0 | E179: 143846.48 | F179: 0 | G179: 0 | H179: 158295.65 | I179: 158283.72 | J179: 1.6946171 | K179: 158283.57 | L179: 225.06672 | M179: 158058.51 | N179: 225.06672 | O179: 0.078875336 | P179: 2.033959e-10 | Q179: 3.9036005e-131 | R179: 5.9429166e-11 | S179: 14440.444 | T179: 0 | U179: 0
B180: CH4 | C180: kmol/hr | D180: 13186.8 | E180: 41761.88 | F180: 7979.2973 | G180: 0 | H180: 28837.904 | I180: 28835.837 | J180: 6.4321517 | K180: 28835.625 | L180: 6148.6807 | M180: 22686.944 | N180: 6148.0433 | O180: 0.092530506 | P180: 2.5752669e-05 | Q180: 1.9701817e-55 | R180: 0.63736686 | S180: 145.25476 | T180: 0 | U180: 0
B181: C2H6 | C181: kmol/hr | D181: 0 | E181: 7.5975226 | F181: 0 | G181: 0 | H181: 290.25931 | I181: 290.24834 | J181: 1.1842817 | K181: 289.4443 | L181: 281.92498 | M181: 7.5193134 | N181: 0.11636206 | O181: 0.006375187 | P181: 0.78624235 | Q181: 277.71083 | R181: 4.0977882 | S181: 0 | T181: 0 | U181: 0
B182: C2H4 | C182: kmol/hr | D182: 0 | E182: 466.35309 | F182: 0 | G182: 0 | H182: 5232.0225 | I182: 5231.7179 | J182: 12.122394 | K182: 5230.1415 | L182: 4825.7118 | M182: 404.42971 | N182: 64.258479 | O182: 0.077267539 | P182: 1.3668024 | Q182: 9.5229459 | R182: 4751.9304 | S182: 0 | T182: 0 | U182: 0 | CD182: Vapor Phase | CE182: Vapor Phase | CF182: Liquid Phase | CG182: Liquid Phase | CH182: Vapor Phase | CI182: Vapor Phase
B183: C2H2 | C183: kmol/hr | D183: 0 | E183: 0 | F183: 0 | G183: 0 | H183: 0 | I183: 0 | J183: 0 | K183: 0 | L183: 0 | M183: 0 | N183: 0 | O183: 0 | P183: 0 | Q183: 0 | R183: 0 | S183: 0 | T183: 0 | U183: 0 | CD183: 751.89471 | CE183: 25 | CF183: 25 | CG183: 40 | CH183: 61.824198 | CI183: 70.664026
B184: C3-C5 | C184: kmol/hr | D184: 0 | E184: 0 | F184: 0 | G184: 0 | H184: 0 | I184: 0 | J184: 0 | K184: 0 | L184: 0 | M184: 0 | N184: 0 | O184: 0 | P184: 0 | Q184: 0 | R184: 0 | S184: 0 | T184: 0 | U184: 0 | CD184: 1.013 | CE184: 1.013 | CF184: 1.013 | CG184: 1.01 | CH184: 1.9 | CI184: 1
B185: BEN | C185: kmol/hr | D185: 0 | E185: 7.4581557e-07 | F185: 0 | G185: 0 | H185: 236.4843 | I185: 243.33751 | J185: 229.06156 | K185: 5.9904154 | L185: 5.9904146 | M185: 7.4956339e-07 | N185: 1.9520816e-19 | O185: 1.4146569 | P185: 229.06155 | Q185: 5.9904146 | R185: 1.6576132e-184 | S185: 0 | T185: 0 | U185: 0 | CD185: 1 | CE185: 1 | CF185: 0 | CG185: 0 | CH185: 1 | CI185: 1
B186: TOL | C186: kmol/hr | D186: 0 | E186: 1.8582774e-10 | F186: 0 | G186: 0 | H186: 3.2521056 | I186: 3.5401487 | J186: 3.17645 | K186: 0.016240968 | L186: 0.016240968 | M186: 1.8676155e-10 | N186: 6.2522786e-26 | O186: 0.059175205 | P186: 3.17645 | Q186: 0.016240968 | R186: 1.9177343e-256 | S186: 0 | T186: 0 | U186: 0 | CD186: 0 | CE186: 0 | CF186: 1 | CG186: 1 | CH186: 0 | CI186: 0
B187: NAP | C187: kmol/hr | D187: 0 | E187: 1.0519083e-45 | F187: 0 | G187: 0 | H187: 20.95804 | I187: 8.4695451 | J187: 0.4958011 | K187: 2.3536126e-06 | L187: 2.3536126e-06 | M187: 8.0835416e-20 | N187: 1.0571943e-45 | O187: 20.461098 | P187: 0.4958011 | Q187: 2.3536126e-06 | R187: 0 | S187: 0 | T187: 0 | U187: 0 | CD187: 0 | CE187: 0 | CF187: 0 | CG187: 0 | CH187: 0 | CI187: 0
B188: C | C188: kmol/hr | D188: 0 | E188: 0 | F188: 0 | G188: 0 | H188: 0 | I188: 0 | J188: 0 | K188: 0 | L188: 0 | M188: 0 | N188: 0 | O188: 0 | P188: 0 | Q188: 0 | R188: 0 | S188: 0 | T188: 0 | U188: 0 | CD188: 1 | CE188: 1 | CF188: 0 | CG188: 0 | CH188: 1 | CI188: 1
B189: WATER | C189: kmol/hr | D189: 0 | E189: 0 | F189: 0 | G189: 0 | H189: 0 | I189: 0 | J189: 0 | K189: 0 | L189: 0 | M189: 0 | N189: 0 | O189: 0 | P189: 0 | Q189: 0 | R189: 0 | S189: 0 | T189: 2695.6741 | U189: 323.31007 | CD189: 0 | CE189: 0 | CF189: 1 | CG189: 1 | CH189: 0 | CI189: 0
B190: O2 | C190: kmol/hr | D190: 0 | E190: 0 | F190: 0 | G190: 16277.766 | H190: 0 | I190: 0 | J190: 0 | K190: 0 | L190: 0 | M190: 0 | N190: 0 | O190: 0 | P190: 0 | Q190: 0 | R190: 0 | S190: 0 | T190: 609.2772 | U190: 0.079046293 | CD190: 0 | CE190: 0 | CF190: 0 | CG190: 0 | CH190: 0 | CI190: 0
B191: CO2 | C191: kmol/hr | D191: 0 | E191: 0 | F191: 0 | G191: 0 | H191: 0 | I191: 0 | J191: 0 | K191: 0 | L191: 0 | M191: 0 | N191: 0 | O191: 0 | P191: 0 | Q191: 0 | R191: 0 | S191: 0 | T191: 1001.677 | U191: 10376.118 | CD191: -53899.406 | CE191: -64255.221 | CF191: -68280.84 | CG191: -67998.295 | CH191: -89477.616 | CI191: -26777.892
B192: CO | C192: kmol/hr | D192: 0 | E192: 0 | F192: 0 | G192: 0 | H192: 0 | I192: 0 | J192: 0 | K192: 0 | L192: 0 | M192: 0 | N192: 0 | O192: 0 | P192: 0 | Q192: 0 | R192: 0 | S192: 0 | T192: 0 | U192: 0 | CD192: -1962.6556 | CE192: -1672.3602 | CF192: -3787.9228 | CG192: -3770.5832 | CH192: -2182.3107 | CI192: -985.58994
B193: N2 | C193: kmol/hr | D193: 0 | E193: 0 | F193: 0 | G193: 0.8 | H193: 0 | I193: 0 | J193: 0 | K193: 0 | L193: 0 | M193: 0 | N193: 0 | O193: 0 | P193: 0 | Q193: 0 | R193: 0 | S193: 0 | T193: 5258.2544 | U193: 0.38496625 | CD193: 7.7189661 | CE193: 1.7570559 | CF193: -38.972575 | CG193: -38.129924 | CH193: -0.14160151 | CI193: 0.27526904
B194: C4H8 | C194: kmol/hr | D194: 0 | E194: 0.0014733913 | F194: 0 | G194: 0 | H194: 53.727168 | I194: 53.76024 | J194: 10.767872 | K194: 42.943669 | L194: 42.942188 | M194: 0.0014807952 | N194: 2.9897251e-11 | O194: 0.011663333 | P194: 10.767763 | Q194: 42.942188 | R194: 2.5813107e-97 | S194: 0 | T194: 0 | U194: 0 | CD194: 0.28107308 | CE194: 0.045730609 | CF194: -2.1620283 | CG194: -2.1143479 | CH194: -0.0034535842 | CI194: 0.010131581
B195: MEA | C195: kmol/hr | D195: 0 | E195: 0 | F195: 0 | G195: 0 | H195: 0 | I195: 0 | J195: 0 | K195: 0 | L195: 0 | M195: 0 | N195: 0 | O195: 0 | P195: 0 | Q195: 0 | R195: 0 | S195: 0 | T195: 1.5739734 | U195: 4.385517e-13 | CD195: 1.1887429e-05 | CE195: 4.1004773e-05 | CF195: 0.055294289 | CG195: 0.055024862 | CH195: 6.8751657e-05 | CI195: 3.5055452e-05
CD196: 0.00032645837 | CE196: 0.0015754804 | CF196: 0.99673111 | CG196: 0.9923125 | CH196: 0.0028189086 | CI196: 0.00095243577
CD197: -4.4183707e+08 | CE197: -2.4370085e+08 | CF197: -3.0075865e+08 | CG197: -49605173 | CH197: -2.3294347e+08 | CI197: -51377219
CD198: 27.462488 | CE198: 38.421878 | CF198: 18.025932 | CG198: 18.033893 | CH198: 41.001319 | CI198: 27.169405
CD199: 29510.779 | CE199: 13653.724 | CF199: 15857.027 | CG199: 2626.222 | CH199: 9372.1372 | CI199: 6907.1152
CD200: 0 | CE200: 0 | CF200: 0 | CG200: 1.1350016 | CH200: 3.8735969e-05 | CI200: 1.1349629
CD201: 0 | CE201: 0 | CF201: 0 | CG201: 0 | CH201: 0 | CI201: 0
CD202: 0 | CE202: 0 | CF202: 0 | CG202: 0 | CH202: 0 | CI202: 0
CD203: 0 | CE203: 0 | CF203: 0 | CG203: 0 | CH203: 0 | CI203: 0
CD204: 0 | CE204: 0 | CF204: 0 | CG204: 0 | CH204: 0 | CI204: 0
CD205: 0 | CE205: 0 | CF205: 0 | CG205: 0 | CH205: 0 | CI205: 0
CD206: 0 | CE206: 0 | CF206: 0 | CG206: 0 | CH206: 0 | CI206: 0
CD207: 0 | CE207: 0 | CF207: 0 | CG207: 0 | CH207: 0 | CI207: 0
... CD267: 41375333 | CE267: 5549648.2 | CF267: 4779.5856 | CG267: 795.46528 | CH267: 2271978.5 | CI267: 3283899.7
A271: Case 3: Feed H2/CH4=2.33
C308: Units | D308: 1 | E308: 2 | F308: 3 | G308: 4 | H308: 5 | I308: 6 | J308: 7 | K308: 8 | L308: 9 | M308: 10 | N308: 11 | O308: 12 | P308: 13 | Q308: 14 | R308: 15 | S308: 16 | T308: 17 | U308: 18 | CF308: 49 | CG308: 50 | CH308: 51-H20 | CI308: 52 | CJ308: 53-CO2 | CK308: 54
B309: Temperature | C309: C | D309: 30 | E309: 723.16522 | F309: 30 | G309: 30 | H309: 35 | I309: 12 | J309: -60 | K309: -113.19138 | L309: -140 | M309: -140 | N309: -121.5969 | O309: 35 | P309: 250.41214 | Q309: -84.27599 | R309: -104.05372 | S309: 30 | T309: 75.873981 | U309: 454.88484
B310: Pressure | C310: bar | D310: 1.013 | E310: 1.013 | F310: 1.013 | G310: 1.013 | H310: 6.0000003 | I310: 30 | J310: 30 | K310: 30 | L310: 30 | M310: 30 | N310: 10 | O310: 6.0000003 | P310: 30 | Q310: 1.013 | R310: 1.013 | S310: 30 | T310: 1 | U310: 100 | CF310: B1 | CG310: B4 | CH310: B4 | CJ310: REG | CK310: ABS
B311: Mass Flows | C311: kg/hr | D311: 211552.67 | E311: 855273.57 | F311: 105775.69 | G311: 430420.81 | H311: 842994.23 | I311: 840421.71 | J311: 27050.929 | K311: 814572.31 | L311: 288397.17 | M311: 526175.14 | N311: 151835.53 | O311: 4278.3967 | P311: 24132.566 | Q311: 11237.857 | R311: 125323.78 | S311: 32334.183 | T311: 277570 | U311: 394380.11 | CF311: B2 | CG311: ABS | CI311: P-2
B312: Mole Flows | C312: kmol/hr | D312: 13186.8 | E312: 102061 | F312: 6593.36 | G312: 13451.254 | H312: 143258.49 | I312: 143239.78 | J312: 383.27095 | K312: 142913.48 | L312: 14443.813 | M312: 128469.67 | N312: 9671.2396 | O312: 34.419788 | P312: 307.85897 | Q312: 305.55619 | R312: 4467.0172 | S312: 14996.606 | T312: 10725.396 | U312: 9124.1624 | CF312: CONVEN | CG312: CONVEN | CH312: CONVEN | CI312: CONVEN | CJ312: CONVEN | CK312: CONVEN
B313: H2 | C313: kmol/hr | D313: 0 | E313: 56074.852 | F313: 0 | G313: 0 | H313: 109953.57 | I313: 109951.27 | J313: 2.4879666 | K313: 109951.11 | L313: 319.3644 | M313: 109631.75 | N313: 319.3644 | O313: 0.057354545 | P313: 2.2935141e-09 | Q313: 3.6431029e-153 | R313: 6.8344224e-11 | S313: 14846.692 | T313: 0 | U313: 0
B314: CH4 | C314: kmol/hr | D314: 13186.8 | E314: 45877.519 | F314: 6593.36 | G314: 0 | H314: 27847.852 | I314: 27847.76 | J314: 12.826501 | K314: 27847.48 | L314: 9255.2585 | M314: 18592.221 | N314: 9255.1628 | O314: 0.094494323 | P314: 3.1932275e-07 | Q314: 4.7571233e-66 | R314: 0.095746523 | S314: 149.91392 | T314: 0 | U314: 0
B315: C2H6 | C315: kmol/hr | D315: 0 | E315: 1.46987 | F315: 0 | G315: 0 | H315: 228.77039 | I315: 228.78055 | J315: 1.9120639 | K315: 228.76294 | L315: 225.11327 | M315: 3.6496671 | N315: 0.11458744 | O315: 0.0053853887 | P315: 1.0577744e-05 | Q315: 220.88198 | R315: 4.1166993 | S315: 0 | T315: 0 | U315: 0
B316: C2H4 | C316: kmol/hr | D316: 0 | E316: 107.33152 | F316: 0 | G316: 0 | H316: 4810.5123 | I316: 4810.6393 | J316: 22.735405 | K316: 4810.3923 | L316: 4568.346 | M316: 242.04632 | N316: 96.597808 | O316: 0.075817867 | P316: 3.5450931e-05 | Q316: 8.943494 | R316: 4462.8047 | S316: 0 | T316: 0 | U316: 0 | CF316: Vapor Phase | CG316: Vapor Phase | CH316: Liquid Phase | CI316: Liquid Phase | CJ316: Vapor Phase | CK316: Vapor Phase
B317: C2H2 | C317: kmol/hr | D317: 0 | E317: 0.14420957 | F317: 0 | G317: 0 | H317: 0 | I317: 0 | J317: 0 | K317: 0 | L317: 0 | M317: 0 | N317: 0 | O317: 0 | P317: 0 | Q317: 0 | R317: 0 | S317: 0 | T317: 0 | U317: 0 | CF317: 821.34239 | CG317: 25 | CH317: 25 | CI317: 40 | CJ317: 61.215836 | CK317: 70.163666
B318: C3-C5 | C318: kmol/hr | D318: 0 | E318: 0 | F318: 0 | G318: 0 | H318: 0 | I318: 0 | J318: 0 | K318: 0 | L318: 0 | M318: 0 | N318: 0 | O318: 0 | P318: 0 | Q318: 0 | R318: 0 | S318: 0 | T318: 0 | U318: 0 | CF318: 1.013 | CG318: 1.013 | CH318: 1.013 | CI318: 1.01 | CJ318: 1.9 | CK318: 1
B319: BEN | C319: kmol/hr | D319: 0 | E319: 4.5020098e-07 | F319: 0 | G319: 0 | H319: 307.52195 | I319: 316.32837 | J319: 302.19692 | K319: 4.3403306 | L319: 4.3403302 | M319: 4.524633e-07 | N319: 4.4159419e-19 | O319: 2.0359916 | P319: 301.14242 | Q319: 4.3403302 | R319: 4.8148478e-154 | S319: 0 | T319: 0 | U319: 0 | CF319: 1 | CG319: 1 | CH319: 0 | CI319: 0 | CJ319: 1 | CK319: 1
B320: TOL | C320: kmol/hr | D320: 0 | E320: 2.2716141e-10 | F320: 0 | G320: 0 | H320: 5.6135355 | I320: 6.083523 | J320: 5.4829274 | K320: 0.015014773 | L320: 0.015014773 | M320: 2.2830293e-10 | N320: 1.0748238e-25 | O320: 0.11679292 | P320: 5.4816637 | Q320: 0.015014773 | R320: 2.5427242e-214 | S320: 0 | T320: 0 | U320: 0 | CF320: 0 | CG320: 0 | CH320: 1 | CI320: 1 | CJ320: 0 | CK320: 0
B321: NAP | C321: kmol/hr | D321: 0 | E321: 1.0118276e-44 | F321: 0 | G321: 0 | H321: 32.50112 | I321: 6.7174147 | J321: 0.48381501 | K321: 1.3274451e-06 | L321: 1.3274451e-06 | M321: 5.1410224e-20 | N321: 1.0169122e-44 | O321: 32.01691 | P321: 0.48381481 | Q321: 1.3274451e-06 | R321: 0 | S321: 0 | T321: 0 | U321: 0 | CF321: 0 | CG321: 0 | CH321: 0 | CI321: 0 | CJ321: 0 | CK321: 0
B322: C | C322: kmol/hr | D322: 0 | E322: 0 | F322: 0 | G322: 0 | H322: 0 | I322: 0 | J322: 0 | K322: 0 | L322: 0 | M322: 0 | N322: 0 | O322: 0 | P322: 0 | Q322: 0 | R322: 0 | S322: 0 | T322: 0 | U322: 0 | CF322: 1 | CG322: 1 | CH322: 0 | CI322: 0 | CJ322: 1 | CK322: 1
B323: WATER | C323: kmol/hr | D323: 0 | E323: 0 | F323: 0 | G323: 0 | H323: 0 | I323: 0 | J323: 0 | K323: 0 | L323: 0 | M323: 0 | N323: 0 | O323: 0 | P323: 0 | Q323: 0 | R323: 0 | S323: 0 | T323: 3807.9093 | U323: 275.6973 | CF323: 0 | CG323: 0 | CH323: 1 | CI323: 1 | CJ323: 0 | CK323: 0
B324: O2 | C324: kmol/hr | D324: 0 | E324: 0 | F324: 0 | G324: 13450.454 | H324: 0 | I324: 0 | J324: 0 | K324: 0 | L324: 0 | M324: 0 | N324: 0 | O324: 0 | P324: 0 | Q324: 0 | R324: 0 | S324: 0 | T324: 543.08975 | U324: 0.055619491 | CF324: 0 | CG324: 0 | CH324: 0 | CI324: 0 | CJ324: 0 | CK324: 0
B325: CO2 | C325: kmol/hr | D325: 0 | E325: 0 | F325: 0 | G325: 0 | H325: 0 | I325: 0 | J325: 0 | K325: 0 | L325: 0 | M325: 0 | N325: 0 | O325: 0 | P325: 0 | Q325: 0 | R325: 0 | S325: 0 | T325: 806.2589 | U325: 8848.0866 | CF325: -51433.279 | CG325: -60304.507 | CH325: -68280.019 | CI325: -67998.239 | CJ325: -89597.163 | CK325: -25009.421
B326: CO | C326: kmol/hr | D326: 0 | E326: 0 | F326: 0 | G326: 0 | H326: 0 | I326: 0 | J326: 0 | K326: 0 | L326: 0 | M326: 0 | N326: 0 | O326: 0 | P326: 0 | Q326: 0 | R326: 0 | S326: 0 | T326: 0 | U326: 0 | CF326: -1862.3706 | CG326: -1597.8062 | CH326: -3788.0168 | CI326: -3770.2221 | CJ326: -2180.8575 | CK326: -927.72473
B327: N2 | C327: kmol/hr | D327: 0 | E327: 0 | F327: 0 | G327: 0.8 | H327: 0 | I327: 0 | J327: 0 | K327: 0 | L327: 0 | M327: 0 | N327: 0 | O327: 0 | P327: 0 | Q327: 0 | R327: 0 | S327: 0 | T327: 5564.3581 | U327: 0.32286435 | CF327: 8.6597253 | CG327: 1.7827474 | CH327: -38.973178 | CI327: -38.132669 | CJ327: -0.13489481 | CK327: 0.21513376
B328: C4H8 | C328: kmol/hr | D328: 0 | E328: 0.0014647954 | F328: 0 | G328: 0 | H328: 72.146116 | I328: 72.205086 | J328: 35.145349 | K328: 71.377065 | L328: 71.37536 | M328: 0.0017047584 | N328: 9.7868052e-11 | O328: 0.017041279 | P328: 0.75102647 | Q328: 71.37536 | R328: 7.4041053e-81 | S328: 0 | T328: 0 | U328: 0 | CF328: 0.31356387 | CG328: 0.047235025 | CH328: -2.1621414 | CI328: -2.1142993 | CJ328: -0.0032834338 | CK328: 0.0079803891
B329: MEA | C329: kmol/hr | D329: 0 | E329: 0 | F329: 0 | G329: 0 | H329: 0 | I329: 0 | J329: 0 | K329: 0 | L329: 0 | M329: 0 | N329: 0 | O329: 0 | P329: 0 | Q329: 0 | R329: 0 | S329: 0 | T329: 3.7800657 | U329: 5.9556913e-12 | CF329: 1.1132502e-05 | CG329: 4.0995654e-05 | CH329: 0.055297037 | CI329: 0.055019711 | CJ329: 6.8877465e-05 | CK329: 3.5103341e-05
CF330: 0.00030744743 | CG330: 0.0015472607 | CH330: 0.99674391 | CI330: 0.99231382 | CJ330: 0.0028297243 | CK330: 0.00094630897
CF331: -3.6715665e+08 | CG331: -2.094223e+08 | CH331: -2.502975e+08 | CI331: -46250539 | CJ331: -1.9903498e+08 | CK331: -48300643
CF332: 27.617102 | CG332: 37.742065 | CH332: 18.025268 | CI332: 18.035606 | CJ332: 41.083456 | CK332: 26.957803
CF333: 25698.613 | CG333: 12501.89 | CH333: 13196.701 | CI333: 2448.6214 | CJ333: 7997.1943 | CK333: 6952.6726
CF334: 0 | CG334: 0 | CH334: 0 | CI334: 1.1555987 | CJ334: 2.909277e-05 | CK334: 1.1555696
CF335: 0 | CG335: 0 | CH335: 0 | CI335: 0 | CJ335: 0 | CK335: 0
CF336: 0 | CG336: 0 | CH336: 0 | CI336: 0 | CJ336: 0 | CK336: 0
CF337: 0 | CG337: 0 | CH337: 0 | CI337: 0 | CJ337: 0 | CK337: 0
CF338: 0 | CG338: 0 | CH338: 0 | CI338: 0 | CJ338: 0 | CK338: 0
CF339: 0 | CG339: 0 | CH339: 0 | CI339: 0 | CJ339: 0 | CK339: 0
CF340: 0 | CG340: 0 | CH340: 0 | CI340: 0 | CJ340: 0 | CK340: 0
CF341: 0 | CG341: 0 | CH341: 0 | CI341: 0 | CJ341: 0 | CK341: 0
... CF401: 38473852 | CG401: 5082607.7 | CH401: 3977.5191 | CI401: 741.74064 | CJ401: 1935126 | CK401: 3301049.8
A406: Case 4: Feed H2/CH4=1.22
C445: Units | D445: 1 | E445: 2 | F445: 3 | G445: 4 | H445: 5 | I445: 6 | J445: 7 | K445: 8 | L445: 9 | M445: 10 | N445: 11 | O445: 12 | P445: 13 | Q445: 14 | R445: 15 | S445: 16 | T445: 17 | U445: 18 | CJ445: 49 | CK445: 50 | CL445: 51-H20 | CM445: 52 | CN445: 53-CO2 | CO445: 54
B446: Temperature | C446: C | D446: 30 | E446: 30 | F446: 30 | G446: 30 | H446: 35 | I446: 20 | J446: -60 | K446: -102.79897 | L446: -140 | M446: -140 | N446: -125.03857 | O446: 35 | P446: 250.42402 | Q446: -80.639382 | R446: -104.02463 | S446: 30 | T446: 70.006146 | U446: 454.88959
B447: Pressure | C447: bar | D447: 1.013 | E447: 1.013 | F447: 1.013 | G447: 1.013 | H447: 3.5 | I447: 30 | J447: 30 | K447: 30 | L447: 30 | M447: 30 | N447: 10 | O447: 3.5 | P447: 30 | Q447: 1.013 | R447: 1.013 | S447: 30 | T447: 1 | U447: 100 | CJ447: B1 | CK447: B4 | CL447: B4 | CN447: REG | CO447: ABS
B448: Mass Flows | C448: kg/hr | D448: 211552.67 | E448: 7.257168e-08 | F448: 92046.647 | G448: 374557.7 | H448: 838225.47 | I448: 833708.67 | J448: 37647.586 | K448: 801700.74 | L448: 420879.54 | M448: 380821.2 | N448: 295490.62 | O448: 6081.5511 | P448: 30380.708 | Q448: 11783.993 | R448: 113604.93 | S448: 33306.629 | T448: 464264 | U448: 364013.87 | CJ448: B2 | CK448: ABS | CM448: P-2
B449: Mole Flows | C449: kmol/hr | D449: 13186.8 | E449: 3.6e-08 | F449: 5737.5817 | G449: 11705.467 | H449: 109274.41 | I449: 109235.72 | J449: 563.72417 | K449: 108830.51 | L449: 23310.441 | M449: 85520.072 | N449: 18961.933 | O449: 48.834528 | P449: 386.92128 | Q449: 298.82542 | R449: 4049.6824 | S449: 15451.253 | T449: 17635.972 | U449: 8421.7167 | CJ449: CONVEN | CK449: CONVEN | CL449: CONVEN | CM449: CONVEN | CN449: CONVEN | CO449: CONVEN
B450: H2 | C450: kmol/hr | D450: 0 | E450: 3.6e-08 | F450: 0 | G450: 0 | H450: 71381.577 | I450: 71376.373 | J450: 3.5975552 | K450: 71376.225 | L450: 621.19281 | M450: 70755.032 | N450: 621.19281 | O450: 0.040536085 | P450: 9.4867446e-09 | Q450: 0 | R450: 0 | S450: 15297.352 | T450: 0 | U450: 0
B451: CH4 | C451: kmol/hr | D451: 13186.8 | E451: 0 | F451: 5737.5817 | G451: 0 | H451: 32998.883 | I451: 32996.714 | J451: 32.039674 | K451: 32996.305 | L451: 18340.569 | M451: 14655.736 | N451: 18340.55 | O451: 0.12212177 | P451: 1.9181914e-06 | Q451: 1.9935859e-58 | R451: 0.018961658 | S451: 153.9014 | T451: 0 | U451: 0
B452: C2H6 | C452: kmol/hr | D452: 0 | E452: 0 | F452: 0 | G452: 0 | H452: 192.03853 | I452: 192.03594 | J452: 3.3086997 | K452: 192.01917 | L452: 190.54192 | M452: 1.4772482 | N452: 4.8079154e-06 | O452: 0.0049599848 | P452: 2.7357959e-05 | Q452: 181.26603 | R452: 9.2758833 | S452: 0 | T452: 0 | U452: 0
...

Sheet 2-1. Aspen Utility
D2: Case 1 (BASE) | E2: Case 2 (BASE) | F2: Case 3 (BASE) | G2: Case 4 (BASE) | H2: Case 1 (Base w CCS) | I2: Case 2 (Base w CCS) | J2: Case 3 (Base w CCS) | K2: Case 4 (Base w CCS) | L2: Case 1 (E-furnace) | M2: Case 2 (E-furnace) | N2: Case 3 (E-furnace) | O2: Case 4 (E-furnace) | P2: Case 1 (E-furnace w CCS) | Q2: Case 2 (E-furnace w CCS) | R2: Case 3 (E-furnace w CCS) | S2: Case 4 (E-furnace w CCS)
B3: CW | C3: ton/h | D3: =B16 -> 276952 | E3: =L16 -> 194306.1 | F3: =V16 -> 61413.7 | G3: =AF16 -> 129859.3 | H3: =AP16 -> 438472.11 | I3: =BA16 -> 339963.65 | J3: =BL16 -> 180775.04 | K3: =BW16 -> 236478.38 | L3: =CH16 -> 276952 | M3: =CS16 -> 194306.1 | N3: =DD16 -> 61413.7 | O3: =DO16 -> 129859.3 | P3: =DZ16 -> 279960.02 | Q3: =B73 -> 201731.48 | R3: =L73 -> 69354.823 | S3: =V73 -> 142032.07
B4: Grid-Electricity | C4: kWh | D4: =B27 -> 969998 | E4: =L27 -> 705579 | F4: =V27 -> 511184 | G4: =AF27 -> 386920 | H4: =AP27 -> 1029961.3 | I4: =BA27 -> 759523.39 | J4: =BL27 -> 557152.34 | K4: =BW27 -> 429367.09 | L4: =CH27+2418*1000*(8000/8760) -> 3178217.2 | M4: =CS27+1880*1000*(8000/8760) -> 2422474 | N4: =DD27+1541*1000*(8000/8760) -> 1918489.9 | O4: =DO27+1337*1000*(8000/8760) -> 1607924.6 | P4: =DZ27+2418*1000*(8000/8760) -> 3179994.5 | Q4: =B84+1880*1000*(8000/8760) -> 2426821.8 | R4: =L84+1541*1000*(8000/8760) -> 1923163.4 | S4: =V84+1337*1000*(8000/8760) -> 1615304.6
B5: Res-Electricity | C5: kWh
B6: Res-Heat | C6: kWh | BM6: Cal/sec | BN6: -18313676
B7: Fired heat | C7: kWh | D7: =B37 -> 0 | E7: =L37 -> 0 | F7: =V37 -> 0 | G7: =AF37 -> 0 | H7: =AP37 -> 0 | I7: =BA37 -> 0 | J7: =BL37 -> 0 | K7: =BW37 -> 0 | L7: =CH37 -> 0 | M7: =CS37 -> 0 | N7: =DD37 -> 0 | O7: =DO37 -> 0 | P7: =DZ37 -> 0 | Q7: =B94 -> 0 | R7: =L94 -> 0 | S7: =V94 -> 0 | BM7: GJ/hr | BN7: =-BN6*3600/239000000 -> 275.85454 | BP7: kW | BQ7: tonne/hr
B8: HPS (0.78 kWh/kg) | C8: ton/h | D8: =B44 -> 0 | E8: =L44 -> 0 | F8: =V44 -> 0 | G8: =AF44 -> 0 | H8: =AP44 -> 0 | I8: =BA44 -> 0 | J8: =BL44 -> 0 | K8: =BW44 -> 0 | L8: =CH44 -> 0 | M8: =CS44 -> 0 | N8: =DD44 -> 0 | O8: =DO44 -> 0 | P8: =DZ44 -> 0 | Q8: =B101 -> 0 | R8: =L101 -> 0 | S8: =V101 -> 0 | BM8: kW | BN8: =BN7*277.778 -> 76626.321 | BP8: 58333.3 | BQ8: 95.808
B9: LPS (0.75 kWh/kg) | C9: ton/h | D9: =B51 -> 0 | E9: =L51 -> 0 | F9: =V51 -> 0 | G9: =AF51 -> 0 | H9: =AP51 -> 787.09123 | I9: =BA51 -> 649.23816 | J9: =BL51 -> 529.53666 | K9: =BW51 -> 446.3177 | L9: =CH51 -> 0 | M9: =CS51 -> 0 | N9: =DD51 -> 0 | O9: =DO51 -> 0 | P9: =DZ51 -> 22.298386 | Q9: =B108 -> 49.879329 | R9: =L108 -> 50.793452 | S9: =V108 -> 125.85289 | AF9: -18313676 | BM9: tonne/hr | BN9: =BN8*BQ8/BP8 -> 125.85289
B10: Refrigeration | C10: kWh | D10: =B58 -> 238557.95 | E10: =L58 -> 169532.29 | F10: =V58 -> 174006.8 | G10: =AF58 -> 170031.17 | H10: =AP58 -> 238557.95 | I10: =BA58 -> 169532.29 | J10: =BL58 -> 174006.8 | K10: =BW58 -> 170031.17 | L10: =CH58 -> 238557.95 | M10: =CS58 -> 169532.29 | N10: =DD58 -> 174006.8 | O10: =DO58 -> 170031.17 | P10: =DZ58 -> 238557.95 | Q10: =B115 -> 169532.29 | R10: =L115 -> 174006.8 | S10: =V115 -> 170031.17
B11: Enerygy consumption | C11: kWh | D11: =D4+D5+D6+D7+D8*1000*0.78+D9*1000*0.75+D10 -> 1208555.9 | E11: =E4+E5+E6+E7+E8*1000*0.78+E9*1000*0.75+E10 -> 875111.29 | F11: =F4+F5+F6+F7+F8*1000*0.78+F9*1000*0.75+F10 -> 685190.8 | G11: =G4+G5+G6+G7+G8*1000*0.78+G9*1000*0.75+G10 -> 556951.17 | H11: =H4+H5+H6+H7+H8*1000*0.78+H9*1000*0.75+H10 -> 1858837.7 | I11: =I4+I5+I6+I7+I8*1000*0.78+I9*1000*0.75+I10 -> 1415984.3 | J11: =J4+J5+J6+J7+J8*1000*0.78+J9*1000*0.75+J10 -> 1128311.6 | K11: =K4+K5+K6+K7+K8*1000*0.78+K9*1000*0.75+K10 -> 934136.53 | ... S11: =S4+S5+S6+S7+S8*1000*0.78+S9*1000*0.75+S10 -> 1879725.5
AF12: R1 (-3438 MW) | AG12: R1 (-2409 MW) | AH12: R1 (-1944 MW) | AI12: R1 (-1655 MW)
B14: Case 1 (Base) | L14: Case 2 (Base) | V14: Case 3 (Base) | AF14: Case 4 (Base) | AP14: Case 1 (Base w CCS) | BA14: Case 2 (Base w CCS) | BL14: Case 3 (Base w CCS) | BW14: Case 4 (Base w CCS) | CH14: Case 1 (E-furnace) | CS14: Case 2 (E-furnace) | DD14: Case 3 (E-furnace) | DO14: Case 4 (E-furnace) | DZ14: Case 1 (E-furnace w CCS)
B15: CW | D15: Block ID | E15: Block type | F15: Duty | G15: Usage | H15: Cost | I15: CO2 emission rate | L15: CW | N15: Block ID | O15: Block type | P15: Duty | Q15: Usage | R15: Cost | S15: CO2 emission rate | V15: CW | X15: Block ID | Y15: Block type | Z15: Duty | AA15: Usage | AB15: Cost | AC15: CO2 emission rate | AF15: CW | AH15: Block ID | AI15: Block type | AJ15: Duty | AK15: Usage | AL15: Cost | AM15: CO2 emission rate | AP15: CW | AR15: Block ID | AS15: Block type | AT15: Duty | AU15: Usage | AV15: Cost | AW15: CO2 emission rate | BA15: CW | BC15: Block ID | BD15: Block type | BE15: Duty | BF15: Usage | BG15: Cost | BH15: CO2 emission rate | BL15: CW | BN15: Block ID | BO15: Block type | BP15: Duty | BQ15: Usage | BR15: Cost | BS15: CO2 emission rate | BW15: CW | BY15: Block ID | BZ15: Block type | CA15: Duty | CB15: Usage | CC15: Cost | CD15: CO2 emission rate | CH15: CW | CJ15: Block ID | CK15: Block type | CL15: Duty | CM15: Usage | CN15: Cost | CO15: CO2 emission rate | CS15: CW | CU15: Block ID | CV15: Block type | CW15: Duty | CX15: Usage | CY15: Cost | CZ15: CO2 emission rate | DD15: CW | DF15: Block ID | DG15: Block type | DH15: Duty | DI15: Usage | DJ15: Cost | DK15: CO2 emission rate | DO15: CW | DQ15: Block ID | DR15: Block type | DS15: Duty | DT15: Usage | DU15: Cost | DV15: CO2 emission rate | DZ15: CW | EB15: Block ID | EC15: Block type | ED15: Duty | EE15: Usage | EF15: Cost | EG15: CO2 emission rate
B16: =SUM(G17:G25) -> 276952 | C16: ton/h | F16: kW | G16: tonne/hr | H16: $/hr | L16: =SUM(Q17:Q25) -> 194306.1 | M16: ton/h | P16: kW | Q16: tonne/hr | R16: $/hr | V16: =SUM(AA17:AA25) -> 61413.7 | W16: ton/h | Z16: kW | AA16: tonne/hr | AB16: $/hr | AF16: =SUM(AK17:AK25) -> 129859.3 | AG16: ton/h | AJ16: kW | AK16: tonne/hr | AL16: $/hr | AP16: =SUM(AU17:AU25) -> 438472.11 | AQ16: ton/h | AT16: kW | AU16: tonne/hr | AV16: $/hr | BA16: =SUM(BF17:BF25) -> 339963.65 | BB16: ton/h | BE16: kW | BF16: tonne/hr | BG16: $/hr | BL16: =SUM(BQ17:BQ25) -> 180775.04 | BM16: ton/h | BP16: kW | BQ16: tonne/hr | BR16: $/hr | BW16: =SUM(CB17:CB25) -> 236478.38 | BX16: ton/h | CA16: kW | CB16: tonne/hr | CC16: $/hr | CH16: =SUM(CM17:CM25) -> 276952 | CI16: ton/h | CL16: kW | CM16: tonne/hr | CN16: $/hr | CS16: =SUM(CX17:CX25) -> 194306.1 | CT16: ton/h | CW16: kW | CX16: tonne/hr | CY16: $/hr | DD16: =SUM(DI17:DI25) -> 61413.7 | DE16: ton/h | DH16: kW | DI16: tonne/hr | DJ16: $/hr | DO16: =SUM(DT17:DT25) -> 129859.3 | DP16: ton/h | DS16: kW | DT16: tonne/hr | DU16: $/hr | DZ16: =SUM(EE17:EE25) -> 279960.02 | EA16: ton/h | ED16: kW | EE16: tonne/hr | EF16: $/hr
D17: E2 | E17: HEATER | F17: 866610 | G17: 149446 | H17: 661.397 | N17: E2 | O17: HEATER | P17: 648746 | Q17: 111876 | R17: 495.123 | X17: MCOMP1 | Y17: MCOMPR | Z17: 174182 | AA17: 30037.4 | AB17: 132.935 | AH17: E2 | AI17: HEATER | AJ17: 366431 | AK17: 63190.6 | AL17: 279.66 | AR17: E2 | AS17: HEATER | AT17: 866610 | AU17: 149446 | AV17: 661.397 | BC17: E2 | BD17: HEATER | BE17: 648746 | BF17: 111876 | BG17: 495.123 | BN17: MCOMP1 | BO17: MCOMPR | BP17: 174182 | BQ17: 30037.4 | BR17: 132.935 | BY17: E2 | BZ17: HEATER | CA17: 366431 | CB17: 63190.6 | CC17: 279.66 | CJ17: E2 | CK17: HEATER | CL17: 866610 | CM17: 149446 | CN17: 661.397 | CU17: E2 | CV17: HEATER | CW17: 648746 | CX17: 111876 | CY17: 495.123 | DF17: MCOMP1 | DG17: MCOMPR | DH17: 174182 | DI17: 30037.4 | DJ17: 132.935 | DQ17: E2 | DR17: HEATER | DS17: 366431 | DT17: 63190.6 | DU17: 279.66 | EB17: E2 | EC17: HEATER | ED17: 866610 | EE17: 149446 | EF17: 661.397
D18: MCOMP1 | E18: MCOMPR | F18: 676047 | G18: 116584 | H18: 515.959 | N18: MCOMP1 | O18: MCOMPR | P18: 341259 | Q18: 58849.7 | R18: 260.449 | X18: MCOMP2 | Y18: MCOMPR | Z18: 181945 | AA18: 31376.3 | AB18: 138.861 | AH18: MCOMP1 | AI18: MCOMPR | AJ18: 134414 | AK18: 23179.6 | AL18: 102.585 | AR18: MCOMP1 | AS18: MCOMPR | AT18: 676047 | AU18: 116584 | AV18: 515.959 | BC18: MCOMP1 | BD18: MCOMPR | BE18: 341259 | BF18: 58849.7 | BG18: 260.449 | BN18: MCOMP2 | BO18: MCOMPR | BP18: 181945 | BQ18: 31376.3 | BR18: 138.861 | BY18: MCOMP1 | BZ18: MCOMPR | CA18: 134414 | CB18: 23179.6 | CC18: 102.585 | CJ18: MCOMP1 | CK18: MCOMPR | CL18: 676047 | CM18: 116584 | CN18: 515.959 | CU18: MCOMP1 | CV18: MCOMPR | CW18: 341259 | CX18: 58849.7 | CY18: 260.449 | DF18: MCOMP2 | DG18: MCOMPR | DH18: 181945 | DI18: 31376.3 | DJ18: 138.861 | DQ18: MCOMP1 | DR18: MCOMPR | DS18: 134414 | DT18: 23179.6 | DU18: 102.585 | EB18: MCOMP1 | EC18: MCOMPR | ED18: 676047 | EE18: 116584 | EF18: 515.959
D19: MCOMP2 | E19: MCOMPR | F19: 63334.6 | G19: 10922 | H19: 48.337 | N19: MCOMP2 | O19: MCOMPR | P19: 136739 | Q19: 23580.4 | R19: 104.359 | AH19: MCOMP2 | AI19: MCOMPR | AJ19: 252186 | AK19: 43489.1 | AL19: 192.468 | AR19: MCOMP2 | AS19: MCOMPR | AT19: 63334.6 | AU19: 10922 | AV19: 48.337 | BC19: MCOMP2 | BD19: MCOMPR | BE19: 136739 | BF19: 23580.4 | BG19: 104.359 | BY19: MCOMP2 | BZ19: MCOMPR | CA19: 252186 | CB19: 43489.1 | CC19: 192.468 | CJ19: MCOMP2 | CK19: MCOMPR | CL19: 63334.6 | CM19: 10922 | CN19: 48.337 | CU19: MCOMP2 | CV19: MCOMPR | CW19: 136739 | CX19: 23580.4 | CY19: 104.359 | DQ19: MCOMP2 | DR19: MCOMPR | DS19: 252186 | DT19: 43489.1 | DU19: 192.468 | EB19: MCOMP2 | EC19: MCOMPR | ED19: 63334.6 | EE19: 10922 | EF19: 48.337
AR20: B6 | AS20: HEATER | AT20: 19722.8 | AU20: 3397.41 | AV20: 15.0525 | BC20: B5 | BD20: HEATER | BE20: 281103 | BF20: 48422.2 | BG20: 214.538 | BN20: B6 | BO20: HEATER | BP20: 234034 | BQ20: 40314.1 | BR20: 178.614 | BY20: B6 | BZ20: HEATER | CA20: 206973 | CB20: 35652.7 | CC20: 157.962 | EB20: B1 | EC20: HEATER | ED20: 2313.69 | EE20: 398.551 | EF20: 1.7658
AR21: B8 | AS21: HEATER | AT21: 284996 | AU21: 49092.8 | AV21: 217.509 | BC21: B6 | BD21: HEATER | BE21: 16390.9 | BF21: 2823.46 | BG21: 12.5095 | BN21: B7 | BO21: HEATER | BP21: 34853.9 | BQ21: 6003.85 | BR21: 26.6005 | BY21: B7 | BZ21: HEATER | CA21: 13443.2 | CB21: 2315.7 | CC21: 10.2599 | EB21: B5 | EC21: HEATER | ED21: 98.7501 | EE21: 17.0105 | EF21: 0.0753661
AR22: H-1 | AS22: HEATER | AT22: 570966 | AU22: 98353.4 | AV22: 435.761 | BC22: H-1 | BD22: HEATER | BE22: 494811 | BF22: 85235.1 | BG22: 377.64 | BN22: H-1 | BO22: HEATER | BP22: 374000 | BQ22: 64424.5 | BR22: 285.437 | BY22: H-1 | BZ22: HEATER | CA22: 356512 | CB22: 61411.9 | CC22: 272.09 | EB22: H-1 | EC22: HEATER | ED22: 13324.2 | EE22: 2295.21 | EF22: 10.1691
AR23: REG | AS23: RADFRAC | AT23: 61979.9 | AU23: 10676.5 | AV23: 47.3031 | BC23: REG | BD23: RADFRAC | BE23: 53273.6 | BF23: 9176.79 | BG23: 40.6584 | BN23: REG | BO23: RADFRAC | BP23: 50034.8 | BQ23: 8618.89 | BR23: 38.1865 | BY23: REG | BZ23: RADFRAC | CA23: 42022.9 | CB23: 7238.78 | CC23: 32.0719 | EB23: REG | EC23: RADFRAC | ED23: 1725.6 | EE23: 297.249 | EF23: 1.31698
B26: Electricity | D26: Block ID | E26: Block type | F26: Duty | G26: Usage | H26: Cost | I26: CO2 emission rate | L26: Electricity | N26: Block ID | O26: Block type | P26: Duty | Q26: Usage | R26: Cost | S26: CO2 emission rate | V26: Electricity | X26: Block ID | Y26: Block type | Z26: Duty | AA26: Usage | AB26: Cost | AC26: CO2 emission rate | AF26: Electricity | AH26: Block ID | AI26: Block type | AJ26: Duty | AK26: Usage | AL26: Cost | AM26: CO2 emission rate | AP26: Electricity | AR26: Block ID | AS26: Block type | AT26: Duty | AU26: Usage | AV26: Cost | AW26: CO2 emission rate | BA26: Electricity | BC26: Block ID | BD26: Block type | BE26: Duty | BF26: Usage | BG26: Cost | BH26: CO2 emission rate | BL26: Electricity | BN26: Block ID | BO26: Block type | BP26: Duty | BQ26: Usage | BR26: Cost | BS26: CO2 emission rate | BW26: Electricity | BY26: Block ID | BZ26: Block type | CA26: Duty | CB26: Usage | CC26: Cost | CD26: CO2 emission rate | CH26: Electricity | CJ26: Block ID | CK26: Block type | CL26: Duty | CM26: Usage | CN26: Cost | CO26: CO2 emission rate | CS26: Electricity | CU26: Block ID | CV26: Block type | CW26: Duty | CX26: Usage | CY26: Cost | CZ26: CO2 emission rate | DD26: Electricity | DF26: Block ID | DG26: Block type | DH26: Duty | DI26: Usage | DJ26: Cost | DK26: CO2 emission rate | DO26: Electricity | DQ26: Block ID | DR26: Block type | DS26: Duty | DT26: Usage | DU26: Cost | DV26: CO2 emission rate | DZ26: Electricity | EB26: Block ID | EC26: Block type | ED26: Duty | EE26: Usage | EF26: Cost | EG26: CO2 emission rate
B27: =SUM(G28:G35) -> 969998 | C27: kWh | F27: kW | G27: kW | H27: $/hr | I27: kg/hr | L27: =SUM(Q28:Q35) -> 705579 | M27: kWh | P27: kW | Q27: kW | R27: $/hr | S27: kg/hr | V27: =SUM(AA28:AA35) -> 511184 | W27: kWh | Z27: kW | AA27: kW | AB27: $/hr | AC27: kg/hr | AF27: =SUM(AK28:AK35) -> 386920 | AG27: kWh | AJ27: kW | AK27: kW | AL27: $/hr | AM27: kg/hr | AP27: =SUM(AU28:AU35) -> 1029961.3 | AQ27: kWh | AT27: kW | AU27: kW | AV27: $/hr | AW27: kg/hr | BA27: =SUM(BF28:BF35) -> 759523.39 | BB27: kWh | BE27: kW | BF27: kW | BG27: $/hr | BH27: kg/hr | BL27: =SUM(BQ28:BQ35) -> 557152.34 | BM27: kWh | BP27: kW | BQ27: kW | BR27: $/hr | BS27: kg/hr | BW27: =SUM(CB28:CB35) -> 429367.09 | BX27: kWh | CA27: kW | CB27: kW | CC27: $/hr | CD27: kg/hr | CH27: =SUM(CM28:CM35) -> 969998 | CI27: kWh | CL27: kW | CM27: kW | CN27: $/hr | CO27: kg/hr | CS27: =SUM(CX28:CX35) -> 705579 | CT27: kWh | CW27: kW | CX27: kW | CY27: $/hr | CZ27: kg/hr | DD27: =SUM(DI28:DI35) -> 511184 | DE27: kWh | DH27: kW | DI27: kW | DJ27: $/hr | DK27: kg/hr | DO27: =SUM(DT28:DT35) -> 386920 | DP27: kWh | DS27: kW | DT27: kW | DU27: $/hr | DV27: kg/hr | DZ27: =SUM(EE28:EE35) -> 971775.29 | EA27: kWh | ED27: kW | EE27: kW | EF27: $/hr | EG27: kg/hr
D28: MCOMP1 | E28: MCOMPR | F28: 858629 | G28: 858629 | H28: 66543.8 | I28: 297861 | N28: MCOMP1 | O28: MCOMPR | P28: 524990 | Q28: 524990 | R28: 40686.7 | S28: 182121 | X28: MCOMP1 | Y28: MCOMPR | Z28: 270842 | AA28: 270842 | AB28: 20990.2 | AC28: 93955.8 | AH28: MCOMP1 | AI28: MCOMPR | AJ28: 138593 | AK28: 138593 | AL28: 10740.9 | AM28: 48078.2 | AR28: MCOMP1 | AS28: MCOMPR | AT28: 858629 | AU28: 858629 | AV28: 66543.8 | AW28: 297861 | BC28: MCOMP1 | BD28: MCOMPR | BE28: 524990 | BF28: 524990 | BG28: 40686.7 | BH28: 182121 | BN28: MCOMP1 | BO28: MCOMPR | BP28: 270842 | BQ28: 270842 | BR28: 20990.2 | BS28: 93955.8 | BY28: MCOMP1 | BZ28: MCOMPR | CA28: 138593 | CB28: 138593 | CC28: 10740.9 | CD28: 48078.2 | CJ28: MCOMP1 | CK28: MCOMPR | CL28: 858629 | CM28: 858629 | CN28: 66543.8 | CO28: 297861 | CU28: MCOMP1 | CV28: MCOMPR | CW28: 524990 | CX28: 524990 | CY28: 40686.7 | CZ28: 182121 | DF28: MCOMP1 | DG28: MCOMPR | DH28: 270842 | DI28: 270842 | DJ28: 20990.2 | DK28: 93955.8 | DQ28: MCOMP1 | DR28: MCOMPR | DS28: 138593 | DT28: 138593 | DU28: 10740.9 | DV28: 48078.2 | EB28: MCOMP1 | EC28: MCOMPR | ED28: 858629 | EE28: 858629 | EF28: 66543.8 | EG28: 297861
D29: MCOMP2 | E29: MCOMPR | F29: 111369 | G29: 111369 | H29: 8631.06 | I29: 38634.1 | N29: MCOMP2 | O29: MCOMPR | P29: 180589 | Q29: 180589 | R29: 13995.7 | S29: 62646.9 | X29: MCOMP2 | Y29: MCOMPR | Z29: 240342 | AA29: 240342 | AB29: 18626.5 | AC29: 83375.5 | AH29: MCOMP2 | AI29: MCOMPR | AJ29: 248327 | AK29: 248327 | AL29: 19245.3 | AM29: 86145.4 | AR29: MCOMP2 | AS29: MCOMPR | AT29: 111369 | AU29: 111369 | AV29: 8631.06 | AW29: 38634.1 | BC29: MCOMP2 | BD29: MCOMPR | BE29: 180589 | BF29: 180589 | BG29: 13995.7 | BH29: 62646.9 | BN29: MCOMP2 | BO29: MCOMPR | BP29: 240342 | BQ29: 240342 | BR29: 18626.5 | BS29: 83375.5 | BY29: MCOMP2 | BZ29: MCOMPR | CA29: 248327 | CB29: 248327 | CC29: 19245.3 | CD29: 86145.4 | CJ29: MCOMP2 | CK29: MCOMPR | CL29: 111369 | CM29: 111369 | CN29: 8631.06 | CO29: 38634.1 | CU29: MCOMP2 | CV29: MCOMPR | CW29: 180589 | CX29: 180589 | CY29: 13995.7 | CZ29: 62646.9 | DF29: MCOMP2 | DG29: MCOMPR | DH29: 240342 | DI29: 240342 | DJ29: 18626.5 | DK29: 83375.5 | DQ29: MCOMP2 | DR29: MCOMPR | DS29: 248327 | DT29: 248327 | DU29: 19245.3 | DV29: 86145.4 | EB29: MCOMP2 | EC29: MCOMPR | ED29: 111369 | EE29: 111369 | EF29: 8631.06 | EG29: 38634.1
AR30: P-1 | AS30: PUMP | AT30: 312.438 | AU30: 312.438 | AV30: 24.214 | AW30: 108.386 | BC30: P-1 | BD30: PUMP | BE30: 273.893 | BF30: 273.893 | BG30: 21.2267 | BH30: 95.0143 | BN30: P-1 | BO30: PUMP | BP30: 201.742 | BQ30: 201.742 | BR30: 15.635 | BS30: 69.9851 | BY30: P-1 | BZ30: PUMP | CA30: 203.686 | CB30: 203.686 | CC30: 15.7857 | CD30: 70.6593 | EB30: P-1 | EC30: PUMP | ED30: 8.56357 | EE30: 8.56357 | EF30: 0.663677 | EG30: 2.97073
AR31: B7 | AS31: COMPR | AT31: 59650.9 | AU31: 59650.9 | AV31: 4622.95 | AW31: 20693.1 | BC31: B8 | BD31: COMPR | BE31: 53670.5 | BF31: 53670.5 | BG31: 4159.46 | BH31: 18618.5 | BN31: B10 | BO31: COMPR | BP31: 45766.6 | BQ31: 45766.6 | BR31: 3546.91 | BS31: 15876.6 | BY31: B8 | BZ31: COMPR | CA31: 42243.4 | CB31: 42243.4 | CC31: 3273.86 | CD31: 14654.4 | EB31: B7 | EC31: COMPR | ED31: 1768.73 | EE31: 1768.73 | EF31: 137.077 | EG31: 613.579
B36: Fired heat | D36: Block ID | E36: Block type | F36: Duty | G36: Usage | H36: Cost | I36: CO2 emission rate | L36: Fired heat | N36: Block ID | O36: Block type | P36: Duty | Q36: Usage | R36: Cost | S36: CO2 emission rate | V36: Fired heat | X36: Block ID | Y36: Block type | Z36: Duty | AA36: Usage | AB36: Cost | AC36: CO2 emission rate | AF36: Fired heat | AH36: Block ID | AI36: Block type | AJ36: Duty | AK36: Usage | AL36: Cost | AM36: CO2 emission rate | AP36: Fired heat | AR36: Block ID | AS36: Block type | AT36: Duty | AU36: Usage | AV36: Cost | AW36: CO2 emission rate | BA36: Fired heat | BC36: Block ID | BD36: Block type | BE36: Duty | BF36: Usage | BG36: Cost | BH36: CO2 emission rate | BL36: Fired heat | BN36: Block ID | BO36: Block type | BP36: Duty | BQ36: Usage | BR36: Cost | BS36: CO2 emission rate | BW36: Fired heat | BY36: Block ID | BZ36: Block type | CA36: Duty | CB36: Usage | CC36: Cost | CD36: CO2 emission rate | CH36: Fired heat | CJ36: Block ID | CK36: Block type | CL36: Duty | CM36: Usage | CN36: Cost | CO36: CO2 emission rate | CS36: Fired heat | CU36: Block ID | CV36: Block type | CW36: Duty | CX36: Usage | CY36: Cost | CZ36: CO2 emission rate | DD36: Fired heat | DF36: Block ID | DG36: Block type | DH36: Duty | DI36: Usage | DJ36: Cost | DK36: CO2 emission rate | DO36: Fired heat | DQ36: Block ID | DR36: Block type | DS36: Duty | DT36: Usage | DU36: Cost | DV36: CO2 emission rate | DZ36: Fired heat | EB36: Block ID | EC36: Block type | ED36: Duty | EE36: Usage | EF36: Cost | EG36: CO2 emission rate
B37: =SUM(F38:F42) -> 0 | C37: kW | F37: kW | G37: kg/day | H37: $/hr | I37: kg/hr | L37: =SUM(P38:P42) -> 0 | M37: kW | P37: kW | Q37: kg/hr | R37: $/hr | S37: kg/hr | V37: =SUM(Z38:Z42) -> 0 | W37: kW | Z37: kW | AA37: kg/hr | AB37: $/hr | AC37: kg/hr | AF37: =SUM(AJ38:AJ42) -> 0 | AG37: kW | AJ37: kW | AK37: kg/hr | AL37: $/hr | AM37: kg/hr | AP37: =SUM(AT38:AT42) -> 0 | AQ37: kW | AT37: kW | AU37: kg/hr | AV37: $/hr | AW37: kg/hr | BA37: =SUM(BE38:BE42) -> 0 | BB37: kW | BE37: kW | BF37: kg/hr | BG37: $/hr | BH37: kg/hr | BL37: =SUM(BP38:BP42) -> 0 | BM37: kW | BP37: kW | BQ37: kg/hr | BR37: $/hr | BS37: kg/hr | BW37: =SUM(CA38:CA42) -> 0 | BX37: kW | CA37: kW | CB37: kg/hr | CC37: $/hr | CD37: kg/hr | CH37: =SUM(CL38:CL42) -> 0 | CI37: kW | CL37: kW | CM37: kg/hr | CN37: $/hr | CO37: kg/hr | CS37: =SUM(CW38:CW42) -> 0 | CT37: kW | CW37: kW | CX37: kg/hr | CY37: $/hr | CZ37: kg/hr | DD37: =SUM(DH38:DH42) -> 0 | DE37: kW | DH37: kW | DI37: kg/hr | DJ37: $/hr | DK37: kg/hr | DO37: =SUM(DS38:DS42) -> 0 | DP37: kW | DS37: kW | DT37: kg/hr | DU37: $/hr | DV37: kg/hr | DZ37: =SUM(ED38:ED42) -> 0 | EA37: kW | ED37: kW | EE37: kg/hr | EF37: $/hr | EG37: kg/hr
B43: High-pressure steam | D43: Block ID | E43: Block type | F43: Duty | G43: Usage | H43: Cost | I43: CO2 emission rate | L43: High-pressure steam | N43: Block ID | O43: Block type | P43: Duty | Q43: Usage | R43: Cost | S43: CO2 emission rate | V43: High-pressure steam | X43: Block ID | Y43: Block type | Z43: Duty | AA43: Usage | AB43: Cost | AC43: CO2 emission rate | AF43: High-pressure steam | AH43: Block ID | AI43: Block type | AJ43: Duty | AK43: Usage | AL43: Cost | AM43: CO2 emission rate | AP43: High-pressure steam | AR43: Block ID | AS43: Block type | AT43: Duty | AU43: Usage | AV43: Cost | AW43: CO2 emission rate | BA43: High-pressure steam | BC43: Block ID | BD43: Block type | BE43: Duty | BF43: Usage | BG43: Cost | BH43: CO2 emission rate | BL43: High-pressure steam | BN43: Block ID | BO43: Block type | BP43: Duty | BQ43: Usage | BR43: Cost | BS43: CO2 emission rate | BW43: High-pressure steam | BY43: Block ID | BZ43: Block type | CA43: Duty | CB43: Usage | CC43: Cost | CD43: CO2 emission rate | CH43: High-pressure steam | CJ43: Block ID | CK43: Block type | CL43: Duty | CM43: Usage | CN43: Cost | CO43: CO2 emission rate | CS43: High-pressure steam | CU43: Block ID | CV43: Block type | CW43: Duty | CX43: Usage | CY43: Cost | CZ43: CO2 emission rate | DD43: High-pressure steam | DF43: Block ID | DG43: Block type | DH43: Duty | DI43: Usage | DJ43: Cost | DK43: CO2 emission rate | DO43: High-pressure steam | DQ43: Block ID | DR43: Block type | DS43: Duty | DT43: Usage | DU43: Cost | DV43: CO2 emission rate | DZ43: High-pressure steam | EB43: Block ID | EC43: Block type | ED43: Duty | EE43: Usage | EF43: Cost | EG43: CO2 emission rate
B44: =SUM(G45:G49) -> 0 | C44: ton/h | F44: kW | G44: tonne/hr | H44: $/hr | I44: kg/hr | L44: =SUM(Q45:Q49) -> 0 | M44: ton/h | P44: kW | Q44: tonne/hr | R44: $/hr | S44: kg/hr | V44: =SUM(AA45:AA49) -> 0 | W44: ton/h | Z44: kW | AA44: tonne/hr | AB44: $/hr | AC44: kg/hr | AF44: =SUM(AK45:AK49) -> 0 | AG44: ton/h | AJ44: kW | AK44: tonne/hr | AL44: $/hr | AM44: kg/hr | AP44: =SUM(AU45:AU49) -> 0 | AQ44: ton/h | AT44: kW | AU44: tonne/hr | AV44: $/hr | AW44: kg/hr | BA44: =SUM(BF45:BF49) -> 0 | BB44: ton/h | BE44: kW | BF44: tonne/hr | BG44: $/hr | BH44: kg/hr | BL44: =SUM(BQ45:BQ49) -> 0 | BM44: ton/h | BP44: kW | BQ44: tonne/hr | BR44: $/hr | BS44: kg/hr | BW44: =SUM(CB45:CB49) -> 0 | BX44: ton/h | CA44: kW | CB44: tonne/hr | CC44: $/hr | CD44: kg/hr | CH44: =SUM(CM45:CM49) -> 0 | CI44: ton/h | CL44: kW | CM44: tonne/hr | CN44: $/hr | CO44: kg/hr | CS44: =SUM(CX45:CX49) -> 0 | CT44: ton/h | CW44: kW | CX44: tonne/hr | CY44: $/hr | CZ44: kg/hr | DD44: =SUM(DI45:DI49) -> 0 | DE44: ton/h | DH44: kW | DI44: tonne/hr | DJ44: $/hr | DK44: kg/hr | DO44: =SUM(DT45:DT49) -> 0 | DP44: ton/h | DS44: kW | DT44: tonne/hr | DU44: $/hr | DV44: kg/hr | DZ44: =SUM(EE45:EE49) -> 0 | EA44: ton/h | ED44: kW | EE44: tonne/hr | EF44: $/hr | EG44: kg/hr
B45: =SUM(F45:F49) -> 0 | C45: kW | L45: =SUM(P45:P49) -> 0 | M45: kW | V45: =SUM(Z45:Z49) -> 0 | W45: kW | AF45: =SUM(AJ45:AJ49) -> 0 | AG45: kW | AP45: =SUM(AT45:AT49) -> 0 | AQ45: kW | BA45: =SUM(BE45:BE49) -> 0 | BB45: kW | BL45: =SUM(BP45:BP49) -> 0 | BM45: kW | BW45: =SUM(CA45:CA49) -> 0 | BX45: kW | CH45: =SUM(CL45:CL49) -> 0 | CI45: kW | CS45: =SUM(CW45:CW49) -> 0 | CT45: kW | DD45: =SUM(DH45:DH49) -> 0 | DE45: kW | DO45: =SUM(DS45:DS49) -> 0 | DP45: kW | DZ45: =SUM(ED45:ED49) -> 0 | EA45: kW
B50: Low-pressure steam | D50: Block ID | E50: Block type | F50: Duty | G50: Usage | H50: Cost | I50: CO2 emission rate | L50: Low-pressure steam | N50: Block ID | O50: Block type | P50: Duty | Q50: Usage | R50: Cost | S50: CO2 emission rate | V50: Low-pressure steam | X50: Block ID | Y50: Block type | Z50: Duty | AA50: Usage | AB50: Cost | AC50: CO2 emission rate | AF50: Low-pressure steam | AH50: Block ID | AI50: Block type | AJ50: Duty | AK50: Usage | AL50: Cost | AM50: CO2 emission rate | AP50: Low-pressure steam | AR50: Block ID | AS50: Block type | AT50: Duty | AU50: Usage | AV50: Cost | AW50: CO2 emission rate | BA50: Low-pressure steam | BC50: Block ID | BD50: Block type | BE50: Duty | BF50: Usage | BG50: Cost | BH50: CO2 emission rate | BL50: Low-pressure steam | BN50: Block ID | BO50: Block type | BP50: Duty | BQ50: Usage | BR50: Cost | BS50: CO2 emission rate | BW50: Low-pressure steam | BY50: Block ID | BZ50: Block type | CA50: Duty | CB50: Usage | CC50: Cost | CD50: CO2 emission rate | CH50: Low-pressure steam | CJ50: Block ID | CK50: Block type | CL50: Duty | CM50: Usage | CN50: Cost | CO50: CO2 emission rate | CS50: Low-pressure steam | CU50: Block ID | CV50: Block type | CW50: Duty | CX50: Usage | CY50: Cost | CZ50: CO2 emission rate | DD50: Low-pressure steam | DF50: Block ID | DG50: Block type | DH50: Duty | DI50: Usage | DJ50: Cost | DK50: CO2 emission rate | DO50: Low-pressure steam | DQ50: Block ID | DR50: Block type | DS50: Duty | DT50: Usage | DU50: Cost | DV50: CO2 emission rate | DZ50: Low-pressure steam | EB50: Block ID | EC50: Block type | ED50: Duty | EE50: Usage | EF50: Cost | EG50: CO2 emission rate
B51: =SUM(G52:G56) -> 0 | C51: ton/h | F51: kW | G51: tonne/hr | H51: $/hr | I51: kg/hr | L51: =SUM(Q52:Q56) -> 0 | M51: ton/h | P51: kW | Q51: tonne/hr | R51: $/hr | S51: kg/hr | V51: =SUM(AA52:AA56) -> 0 | W51: ton/h | Z51: kW | AA51: tonne/hr | AB51: $/hr | AC51: kg/hr | AF51: =SUM(AK52:AK56) -> 0 | AG51: ton/h | AJ51: kW | AK51: tonne/hr | AL51: $/hr | AM51: kg/hr | AP51: =SUM(AU52:AU56) -> 787.09123 | AQ51: ton/h | AT51: kW | AU51: tonne/hr | AV51: $/hr | AW51: kg/hr | BA51: =SUM(BF52:BF56) -> 649.23816 | BB51: ton/h | BE51: kW | BF51: tonne/hr | BG51: $/hr | BH51: kg/hr | BL51: =SUM(BQ52:BQ56) -> 529.53666 | BM51: ton/h | BP51: kW | BQ51: tonne/hr | BR51: $/hr | BS51: kg/hr | BW51: =SUM(CB52:CB56) -> 446.3177 | BX51: ton/h | CA51: kW | CB51: tonne/hr | CC51: $/hr | CD51: kg/hr | CH51: =SUM(CM52:CM56) -> 0 | CI51: ton/h | CL51: kW | CM51: tonne/hr | CN51: $/hr | CO51: kg/hr | CS51: =SUM(CX52:CX56) -> 0 | CT51: ton/h | CW51: kW | CX51: tonne/hr | CY51: $/hr | CZ51: kg/hr | DD51: =SUM(DI52:DI56) -> 0 | DE51: ton/h | DH51: kW | DI51: tonne/hr | DJ51: $/hr | DK51: kg/hr | DO51: =SUM(DT52:DT56) -> 0 | DP51: ton/h | DS51: kW | DT51: tonne/hr | DU51: $/hr | DV51: kg/hr | DZ51: =SUM(EE52:EE56) -> 22.298386 | EA51: ton/h | ED51: kW | EE51: tonne/hr | EF51: $/hr | EG51: kg/hr
B52: =SUM(F52:F56) -> 0 | C52: kW | L52: =SUM(P52:P56) -> 0 | M52: kW | V52: =SUM(Z52:Z56) -> 0 | W52: kW | AF52: =SUM(AJ52:AJ56) -> 0 | AG52: kW | AP52: =SUM(AT52:AT56) -> 479225.42 | AQ52: kW | AR52: REG | AS52: RADFRAC | AT52: 479225.42 | AU52: 787.09123 | AV52: 4604.26 | AW52: 159339 | BA52: =SUM(BE52:BE56) -> 395292.71 | BB52: kW | BC52: REG | BD52: RADFRAC | BE52: 395292.71 | BF52: 649.23816 | BG52: 4041.12 | BH52: 139850 | BL52: =SUM(BP52:BP56) -> 322411.71 | BM52: kW | BP52: 322411.71 | BQ52: 529.53666 | BW52: =SUM(CA52:CA56) -> 271743.32 | BX52: kW | BY52: REG | BZ52: RADFRAC | CA52: 271743.32 | CB52: 446.3177 | CH52: =SUM(CL52:CL56) -> 0 | CI52: kW | CS52: =SUM(CW52:CW56) -> 0 | CT52: kW | DD52: =SUM(DH52:DH56) -> 0 | DE52: kW | DO52: =SUM(DS52:DS56) -> 0 | DP52: kW | DZ52: =SUM(ED52:ED56) -> 13576.512 | EA52: kW | EB52: REG | EC52: RADFRAC | ED52: 13576.512 | EE52: 22.298386 | EF52: 144.587 | EG52: 5003.68
B57: Refrigeration | D57: Block ID | E57: Block type | F57: Duty | G57: Usage | H57: Cost | I57: CO2 emission rate | L57: Refrigeration | N57: Block ID | O57: Block type | P57: Duty | Q57: Usage | R57: Cost | S57: CO2 emission rate | V57: Refrigeration | X57: Block ID | Y57: Block type | Z57: Duty | AA57: Usage | AB57: Cost | AC57: CO2 emission rate | AF57: Refrigeration | AH57: Block ID | AI57: Block type | AJ57: Duty | AK57: Usage | AL57: Cost | AM57: CO2 emission rate | AP57: Refrigeration | AR57: Block ID | AS57: Block type | AT57: Duty | AU57: Usage | AV57: Cost | AW57: CO2 emission rate | BA57: Refrigeration | BC57: Block ID | BD57: Block type | BE57: Duty | BF57: Usage | BG57: Cost | BH57: CO2 emission rate | BL57: Refrigeration | BN57: Block ID | BO57: Block type | BP57: Duty | BQ57: Usage | BR57: Cost | BS57: CO2 emission rate | BW57: Refrigeration | BY57: Block ID | BZ57: Block type | CA57: Duty | CB57: Usage | CC57: Cost | CD57: CO2 emission rate | CH57: Refrigeration | CJ57: Block ID | CK57: Block type | CL57: Duty | CM57: Usage | CN57: Cost | CO57: CO2 emission rate | CS57: Refrigeration | CU57: Block ID | CV57: Block type | CW57: Duty | CX57: Usage | CY57: Cost | CZ57: CO2 emission rate | DD57: Refrigeration | DF57: Block ID | DG57: Block type | DH57: Duty | DI57: Usage | DJ57: Cost | DK57: CO2 emission rate | DO57: Refrigeration | DQ57: Block ID | DR57: Block type | DS57: Duty | DT57: Usage | DU57: Cost | DV57: CO2 emission rate | DZ57: Refrigeration | EB57: Block ID | EC57: Block type | ED57: Duty | EE57: Usage | EF57: Cost | EG57: CO2 emission rate
B58: =SUM(F59:F66) -> 238557.95 | C58: kWh | F58: kW | G58: kg/hr | H58: $/hr | I58: kg/hr | L58: =SUM(P59:P66) -> 169532.29 | M58: kWh | P58: kW | Q58: kg/hr | R58: $/hr | S58: kg/hr | V58: =SUM(Z59:Z66) -> 174006.8 | W58: kWh | Z58: kW | AA58: kg/hr | AB58: $/hr | AC58: kg/hr | AF58: =SUM(AJ59:AJ66) -> 170031.17 | AG58: kWh | AJ58: kW | AK58: kg/hr | AL58: $/hr | AM58: kg/hr | AP58: =SUM(AT59:AT66) -> 238557.95 | AQ58: kWh | AT58: kW | AU58: kg/hr | AV58: $/hr | AW58: kg/hr | BA58: =SUM(BE59:BE66) -> 169532.29 | BB58: kWh | BE58: kW | BF58: kg/hr | BG58: $/hr | BH58: kg/hr | BL58: =SUM(BP59:BP66) -> 174006.8 | BM58: kWh | BP58: kW | BQ58: kg/hr | BR58: $/hr | BS58: kg/hr | BW58: =SUM(CA59:CA66) -> 170031.17 | BX58: kWh | CA58: kW | CB58: kg/hr | CC58: $/hr | CD58: kg/hr | CH58: =SUM(CL59:CL66) -> 238557.95 | CI58: kWh | CL58: kW | CM58: kg/hr | CN58: $/hr | CO58: kg/hr | CS58: =SUM(CW59:CW66) -> 169532.29 | CT58: kWh | CW58: kW | CX58: kg/hr | CY58: $/hr | CZ58: kg/hr | DD58: =SUM(DH59:DH66) -> 174006.8 | DE58: kWh | DH58: kW | DI58: kg/hr | DJ58: $/hr | DK58: kg/hr | DO58: =SUM(DS59:DS66) -> 170031.17 | DP58: kWh | DS58: kW | DT58: kg/hr | DU58: $/hr | DV58: kg/hr | DZ58: =SUM(ED59:ED66) -> 238557.95 | EA58: kWh | ED58: kW | EE58: kg/hr | EF58: $/hr | EG58: kg/hr
D59: V3 | E59: FLASH2 | F59: 19369.6 | G59: 51998800 | H59: 620.601 | I59: 3897.23 | N59: V3 | O59: FLASH2 | P59: 19701.5 | Q59: 52889900 | R59: 631.236 | S59: 3964.02 | X59: V3 | Y59: FLASH2 | Z59: 22838.6 | AA59: 61311700 | AB59: 731.749 | AC59: 4595.21 | AH59: V3 | AI59: FLASH2 | AJ59: 28362.4 | AK59: 76140600 | AL59: 908.73 | AM59: 5706.62 | AR59: V3 | AS59: FLASH2 | AT59: 19369.6 | AU59: 51998800 | AV59: 620.601 | AW59: 3897.23 | BC59: V3 | BD59: FLASH2 | BE59: 19701.5 | BF59: 52889900 | BG59: 631.236 | BH59: 3964.02 | BN59: V3 | BO59: FLASH2 | BP59: 22838.6 | BQ59: 61311700 | BR59: 731.749 | BS59: 4595.21 | BY59: V3 | BZ59: FLASH2 | CA59: 28362.4 | CB59: 76140600 | CC59: 908.73 | CD59: 5706.62 | CJ59: V3 | CK59: FLASH2 | CL59: 19369.6 | CM59: 51998800 | CN59: 620.601 | CO59: 3897.23 | CU59: V3 | CV59: FLASH2 | CW59: 19701.5 | CX59: 52889900 | CY59: 631.236 | CZ59: 3964.02 | DF59: V3 | DG59: FLASH2 | DH59: 22838.6 | DI59: 61311700 | DJ59: 731.749 | DK59: 4595.21 | DQ59: V3 | DR59: FLASH2 | DS59: 28362.4 | DT59: 76140600 | DU59: 908.73 | DV59: 5706.62 | EB59: V3 | EC59: FLASH2 | ED59: 19369.6 | EE59: 51998800 | EF59: 620.601 | EG59: 3897.23
D60: V4 | E60: FLASH2 | F60: 77737.3 | G60: 208691000 | H60: 2490.7 | I60: 15641 | N60: V4 | O60: FLASH2 | P60: 62776.1 | Q60: 168527000 | R60: 2011.35 | S60: 12630.8 | X60: V4 | Y60: FLASH2 | Z60: 59537.9 | AA60: 159833000 | AB60: 1907.59 | AC60: 11979.3 | AH60: V4 | AI60: FLASH2 | AJ60: 81160.5 | AK60: 217881000 | AL60: 2600.38 | AM60: 16329.8 | AR60: V4 | AS60: FLASH2 | AT60: 77737.3 | AU60: 208691000 | AV60: 2490.7 | AW60: 15641 | BC60: V4 | BD60: FLASH2 | BE60: 62776.1 | BF60: 168527000 | BG60: 2011.35 | BH60: 12630.8 | BN60: V4 | BO60: FLASH2 | BP60: 59537.9 | BQ60: 159833000 | BR60: 1907.59 | BS60: 11979.3 | BY60: V4 | BZ60: FLASH2 | CA60: 81160.5 | CB60: 217881000 | CC60: 2600.38 | CD60: 16329.8 | CJ60: V4 | CK60: FLASH2 | CL60: 77737.3 | CM60: 208691000 | CN60: 2490.7 | CO60: 15641 | CU60: V4 | CV60: FLASH2 | CW60: 62776.1 | CX60: 168527000 | CY60: 2011.35 | CZ60: 12630.8 | DF60: V4 | DG60: FLASH2 | DH60: 59537.9 | DI60: 159833000 | DJ60: 1907.59 | DK60: 11979.3 | DQ60: V4 | DR60: FLASH2 | DS60: 81160.5 | DT60: 217881000 | DU60: 2600.38 | DV60: 16329.8 | EB60: V4 | EC60: FLASH2 | ED60: 77737.3 | EE60: 208691000 | EF60: 2490.7 | EG60: 15641
D61: V5 | E61: FLASH2 | F61: 65954.6 | G61: 177059000 | H61: 2113.19 | I61: 13270.3 | N61: V5 | O61: FLASH2 | P61: 48031.6 | Q61: 128944000 | R61: 1538.93 | S61: 9664.13 | X61: V5 | Y61: FLASH2 | Z61: 34337.4 | AA61: 92180900 | AB61: 1100.17 | AC61: 6908.81 | AH61: V5 | AI61: FLASH2 | AJ61: 10858 | AK61: 29148900 | AL61: 347.89 | AM61: 2184.67 | AR61: V5 | AS61: FLASH2 | AT61: 65954.6 | AU61: 177059000 | AV61: 2113.19 | AW61: 13270.3 | BC61: V5 | BD61: FLASH2 | BE61: 48031.6 | BF61: 128944000 | BG61: 1538.93 | BH61: 9664.13 | BN61: V5 | BO61: FLASH2 | BP61: 34337.4 | BQ61: 92180900 | BR61: 1100.17 | BS61: 6908.81 | BY61: V5 | BZ61: FLASH2 | CA61: 10858 | CB61: 29148900 | CC61: 347.89 | CD61: 2184.67 | CJ61: V5 | CK61: FLASH2 | CL61: 65954.6 | CM61: 177059000 | CN61: 2113.19 | CO61: 13270.3 | CU61: V5 | CV61: FLASH2 | CW61: 48031.6 | CX61: 128944000 | CY61: 1538.93 | CZ61: 9664.13 | DF61: V5 | DG61: FLASH2 | DH61: 34337.4 | DI61: 92180900 | DJ61: 1100.17 | DK61: 6908.81 | DQ61: V5 | DR61: FLASH2 | DS61: 10858 | DT61: 29148900 | DU61: 347.89 | DV61: 2184.67 | EB61: V5 | EC61: FLASH2 | ED61: 65954.6 | EE61: 177059000 | EF61: 2113.19 | EG61: 13270.3
D62: T1 | E62: RADFRAC | F62: 2070.45 | G62: 5558270 | H62: 66.3374 | I62: 416.583 | N62: T1 | O62: RADFRAC | P62: 847.365 | Q62: 2274800 | R62: 27.1496 | S62: 170.493 | X62: T1 | Y62: RADFRAC | Z62: 13736.7 | AA62: 36877000 | AB62: 440.123 | AC62: 2763.87 | AH62: T1 | AI62: RADFRAC | AJ62: 4.76957 | AK62: 12804.2 | AL62: 0.152817 | AM62: 0.959656 | AR62: T1 | AS62: RADFRAC | AT62: 2070.45 | AU62: 5558270 | AV62: 66.3374 | AW62: 416.583 | BC62: T1 | BD62: RADFRAC | BE62: 847.365 | BF62: 2274800 | BG62: 27.1496 | BH62: 170.493 | BN62: T1 | BO62: RADFRAC | BP62: 13736.7 | BQ62: 36877000 | BR62: 440.123 | BS62: 2763.87 | BY62: T1 | BZ62: RADFRAC | CA62: 4.76957 | CB62: 12804.2 | CC62: 0.152817 | CD62: 0.959656 | CJ62: T1 | CK62: RADFRAC | CL62: 2070.45 | CM62: 5558270 | CN62: 66.3374 | CO62: 416.583 | CU62: T1 | CV62: RADFRAC | CW62: 847.365 | CX62: 2274800 | CY62: 27.1496 | CZ62: 170.493 | DF62: T1 | DG62: RADFRAC | DH62: 13736.7 | DI62: 36877000 | DJ62: 440.123 | DK62: 2763.87 | DQ62: T1 | DR62: RADFRAC | DS62: 4.76957 | DT62: 12804.2 | DU62: 0.152817 | DV62: 0.959656 | EB62: T1 | EC62: RADFRAC | ED62: 2070.45 | EE62: 5558270 | EF62: 66.3374 | EG62: 416.583
D63: T2 | E63: RADFRAC | F63: 35996.6 | G63: 96635300 | H63: 1153.33 | I63: 7242.66 | N63: T2 | O63: RADFRAC | P63: 3633.12 | Q63: 9753350 | R63: 116.405 | S63: 730.998 | X63: T2 | Y63: RADFRAC | Z63: 11144.4 | AA63: 29917800 | AB63: 357.067 | AC63: 2242.3 | AH63: T2 | AI63: RADFRAC | AJ63: 10153.6 | AK63: 27258000 | AL63: 325.322 | AM63: 2042.95 | AR63: T2 | AS63: RADFRAC | AT63: 35996.6 | AU63: 96635300 | AV63: 1153.33 | AW63: 7242.66 | BC63: T2 | BD63: RADFRAC | BE63: 3633.12 | BF63: 9753350 | BG63: 116.405 | BH63: 730.998 | BN63: T2 | BO63: RADFRAC | BP63: 11144.4 | BQ63: 29917800 | BR63: 357.067 | BS63: 2242.3 | BY63: T2 | BZ63: RADFRAC | CA63: 10153.6 | CB63: 27258000 | CC63: 325.322 | CD63: 2042.95 | CJ63: T2 | CK63: RADFRAC | CL63: 35996.6 | CM63: 96635300 | CN63: 1153.33 | CO63: 7242.66 | CU63: T2 | CV63: RADFRAC | CW63: 3633.12 | CX63: 9753350 | CY63: 116.405 | CZ63: 730.998 | DF63: T2 | DG63: RADFRAC | DH63: 11144.4 | DI63: 29917800 | DJ63: 357.067 | DK63: 2242.3 | DQ63: T2 | DR63: RADFRAC | DS63: 10153.6 | DT63: 27258000 | DU63: 325.322 | DV63: 2042.95 | EB63: T2 | EC63: RADFRAC | ED63: 35996.6 | EE63: 96635300 | EF63: 1153.33 | EG63: 7242.66
D64: T3 | E64: RADFRAC | F64: 37429.4 | G64: 100482000 | H64: 1199.24 | I64: 7530.94 | N64: T3 | O64: RADFRAC | P64: 34542.6 | Q64: 92731700 | R64: 1106.74 | S64: 6950.1 | X64: T3 | Y64: RADFRAC | Z64: 32411.8 | AA64: 87011500 | AB64: 1038.47 | AC64: 6521.37 | AH64: T3 | AI64: RADFRAC | AJ64: 39491.9 | AK64: 106018000 | AL64: 1265.32 | AM64: 7945.92 | AR64: T3 | AS64: RADFRAC | AT64: 37429.4 | AU64: 100482000 | AV64: 1199.24 | AW64: 7530.94 | BC64: T3 | BD64: RADFRAC | BE64: 34542.6 | BF64: 92731700 | BG64: 1106.74 | BH64: 6950.1 | BN64: T3 | BO64: RADFRAC | BP64: 32411.8 | BQ64: 87011500 | BR64: 1038.47 | BS64: 6521.37 | BY64: T3 | BZ64: RADFRAC | CA64: 39491.9 | CB64: 106018000 | CC64: 1265.32 | CD64: 7945.92 | CJ64: T3 | CK64: RADFRAC | CL64: 37429.4 | CM64: 100482000 | CN64: 1199.24 | CO64: 7530.94 | CU64: T3 | CV64: RADFRAC | CW64: 34542.6 | CX64: 92731700 | CY64: 1106.74 | CZ64: 6950.1 | DF64: T3 | DG64: RADFRAC | DH64: 32411.8 | DI64: 87011500 | DJ64: 1038.47 | DK64: 6521.37 | DQ64: T3 | DR64: RADFRAC | DS64: 39491.9 | DT64: 106018000 | DU64: 1265.32 | DV64: 7945.92 | EB64: T3 | EC64: RADFRAC | ED64: 37429.4 | EE64: 100482000 | EF64: 1199.24 | EG64: 7530.94
X68: 21089831
X69: 2776154.6
X70: =X68-X69 -> 18313676
B71: Case 2 (E-furnace w CCS) | L71: Case 3 (E-furnace w CCS) | V71: Case 4 (E-furnace w CCS) | AF71: Case 17: Feed H2/CH4=4.09091, LPM=2.2, T=1280, SV = 30.5 | AP71: Case 18: Feed H2/CH4=2.95455, LPM=2.2, T=1250, SV = 23.7 | BA71: Case 19: Feed H2/CH4=2.95455, LPM=2.2, T=1240, SV = 23.7 | BL71: Case 20: Feed H2/CH4=2.95455, LPM=2.2, T=1230, SV = 23.7 | BW71: Case 21: Feed H2/CH4=4.09091, LPM=2.2, T=1220, SV = 30.5 | CH71: Case 22: Feed H2/CH4=4.09091, LPM=2.2, T=1210, SV = 30.5 | CS71: Case 23: Feed H2/CH4=3.86196, LPM=2.3, T=1200, SV = 30.3 | DD71: Case 24: Feed H2/CH4=4.18182, LPM=1.1, T=1150, SV = 15.5 | DO71: Case 25: Feed H2/CH4=3.38462, LPM=1.3, T=1150, SV = 15.5
B72: CW | D72: Block ID | E72: Block type | F72: Duty | G72: Usage | H72: Cost | I72: CO2 emission rate | L72: CW | N72: Block ID | O72: Block type | P72: Duty | Q72: Usage | R72: Cost | S72: CO2 emission rate | V72: CW | X72: Block ID | Y72: Block type | Z72: Duty | AA72: Usage | AB72: Cost | AC72: CO2 emission rate | AF72: CW | AH72: Block ID | AI72: Block type | AJ72: Duty | AK72: Usage | AL72: Cost | AM72: CO2 emission rate | AP72: CW | AR72: Block ID | AS72: Block type | AT72: Duty | AU72: Usage | AV72: Cost | AW72: CO2 emission rate | BA72: CW | BC72: Block ID | BD72: Block type | BE72: Duty | BF72: Usage | BG72: Cost | BH72: CO2 emission rate | BL72: CW | BN72: Block ID | BO72: Block type | BP72: Duty | BQ72: Usage | BR72: Cost | BS72: CO2 emission rate | BW72: CW | BY72: Block ID | BZ72: Block type | CA72: Duty | CB72: Usage | CC72: Cost | CD72: CO2 emission rate | CH72: CW | CJ72: Block ID | CK72: Block type | CL72: Duty | CM72: Usage | CN72: Cost | CO72: CO2 emission rate | CS72: CW | CU72: Block ID | CV72: Block type | CW72: Duty | CX72: Usage | CY72: Cost | CZ72: CO2 emission rate | DD72: CW | DF72: Block ID | DG72: Block type | DH72: Duty | DI72: Usage | DJ72: Cost | DK72: CO2 emission rate | DO72: CW | DQ72: Block ID | DR72: Block type | DS72: Duty | DT72: Usage | DU72: Cost | DV72: CO2 emission rate
B73: =SUM(G74:G82) -> 201731.48 | C73: ton/h | F73: kW | G73: tonne/hr | H73: $/hr | L73: =SUM(Q74:Q82) -> 69354.823 | M73: ton/h | P73: kW | Q73: tonne/hr | R73: $/hr | V73: =SUM(AA74:AA82) -> 142032.07 | W73: ton/h | Z73: kW | AA73: tonne/hr | AB73: $/hr | AF73: =SUM(AK74:AK82) -> 559665.3 | AG73: ton/h | AJ73: kW | AK73: tonne/hr | AL73: $/hr | AP73: =SUM(AU74:AU82) -> 443405 | AQ73: ton/h | AT73: kW | AU73: tonne/hr | AV73: $/hr | BA73: =SUM(BF74:BF82) -> 500277.4 | BB73: ton/h | BE73: kW | BF73: tonne/hr | BG73: $/hr | BL73: =SUM(BQ74:BQ82) -> 563390 | BM73: ton/h | BP73: kW | BQ73: tonne/hr | BR73: $/hr | BW73: =SUM(CB74:CB82) -> 1114275.5 | BX73: ton/h | CA73: kW | CB73: tonne/hr | CC73: $/hr | CH73: =SUM(CM74:CM82) -> 1304024.3 | CI73: ton/h | CL73: kW | CM73: tonne/hr | CN73: $/hr | CS73: =SUM(CX74:CX82) -> 1464045.8 | CT73: ton/h | CW73: kW | CX73: tonne/hr | CY73: $/hr | DD73: =SUM(DI74:DI82) -> 1790388.4 | DE73: ton/h | DH73: kW | DI73: tonne/hr | DJ73: $/hr | DO73: =SUM(DT74:DT82) -> 1436651.6 | DP73: ton/h | DS73: kW | DT73: tonne/hr | DU73: $/hr
D74: E2 | E74: HEATER | F74: 648746 | G74: 111876 | H74: 495.123 | N74: MCOMP1 | O74: MCOMPR | P74: 174182 | Q74: 30037.4 | R74: 132.935 | X74: E2 | Y74: HEATER | Z74: 366431 | AA74: 63190.6 | AB74: 279.66 | AH74: E2 | AI74: HEATER | AJ74: 2279750 | AK74: 393139 | AL74: 1739.9 | AR74: E2 | AS74: HEATER | AT74: 1829040 | AU74: 315415 | AV74: 1395.92 | BC74: E2 | BD74: HEATER | BE74: 2041860 | BF74: 352117 | BG74: 1558.35 | BN74: E2 | BO74: HEATER | BP74: 2288090 | BQ74: 394578 | BR74: 1746.27 | BY74: E2 | BZ74: HEATER | CA74: 4444960 | CB74: 766528 | CC74: 3392.4 | CJ74: E2 | CK74: HEATER | CL74: 5183270 | CM74: 893849 | CN74: 3955.87 | CU74: E2 | CV74: HEATER | CW74: 5807510 | CX74: 1001500 | CY74: 4432.29 | DF74: E2 | DG74: HEATER | DH74: 6951430 | DI74: 1198770 | DJ74: 5305.33 | DQ74: E2 | DR74: HEATER | DS74: 5647370 | DT74: 973881 | DU74: 4310.07
D75: MCOMP1 | E75: MCOMPR | F75: 341259 | G75: 58849.7 | H75: 260.449 | N75: MCOMP2 | O75: MCOMPR | P75: 181945 | Q75: 31376.3 | R75: 138.861 | X75: MCOMP1 | Y75: MCOMPR | Z75: 134414 | AA75: 23179.6 | AB75: 102.585 | AH75: MCOMP1 | AI75: MCOMPR | AJ75: 882924 | AK75: 152259 | AL75: 673.848 | AR75: MCOMP1 | AS75: MCOMPR | AT75: 678585 | AU75: 117021 | AV75: 517.896 | BC75: MCOMP1 | BD75: MCOMPR | BE75: 785519 | BF75: 135462 | BG75: 599.508 | BN75: MCOMP1 | BO75: MCOMPR | BP75: 895008 | BQ75: 154343 | BR75: 683.07 | BY75: MCOMP1 | BZ75: MCOMPR | CA75: 1843740 | CB75: 317950 | CC75: 1407.14 | CJ75: MCOMP1 | CK75: MCOMPR | CL75: 2174720 | CM75: 375028 | CN75: 1659.75 | CU75: MCOMP1 | CV75: MCOMPR | CW75: 2452370 | CX75: 422908 | CY75: 1871.65 | DF75: MCOMP1 | DG75: MCOMPR | DH75: 3136720 | DI75: 540923 | DJ75: 2393.94 | DQ75: MCOMP1 | DR75: MCOMPR | DS75: 2453520 | DT75: 423107 | DU75: 1872.53
D76: MCOMP2 | E76: MCOMPR | F76: 136739 | G76: 23580.4 | H76: 104.359 | X76: MCOMP2 | Y76: MCOMPR | Z76: 252186 | AA76: 43489.1 | AB76: 192.468 | AH76: MCOMP2 | AI76: MCOMPR | AJ76: 82733.6 | AK76: 14267.3 | AL76: 63.1423 | AR76: MCOMP2 | AS76: MCOMPR | AT76: 63607.4 | AU76: 10969 | AV76: 48.5452 | BC76: MCOMP2 | BD76: MCOMPR | BE76: 73635.6 | BF76: 12698.4 | BG76: 56.1987 | BN76: MCOMP2 | BO76: MCOMPR | BP76: 83903.1 | BQ76: 14469 | BR76: 64.0349 | BY76: MCOMP2 | BZ76: MCOMPR | CA76: 172790 | CB76: 29797.5 | CC76: 131.874 | CJ76: MCOMP2 | CK76: MCOMPR | CL76: 203813 | CM76: 35147.3 | CN76: 155.55 | CU76: MCOMP2 | CV76: MCOMPR | CW76: 229853 | CX76: 39637.8 | CY76: 175.424 | DF76: MCOMP2 | DG76: MCOMPR | DH76: 293974 | DI76: 50695.4 | DJ76: 224.361 | DQ76: MCOMP2 | DR76: MCOMPR | DS76: 230002 | DT76: 39663.6 | DU76: 175.538
D77: B1 | E77: HEATER | F77: 5793.44 | G77: 997.965 | H77: 4.42155 | N77: B1 | O77: HEATER | P77: 6132.93 | Q77: 1056.45 | R77: 4.68065 | X77: B1 | Y77: HEATER | Z77: 11623.2 | AA77: 2002.19 | AB77: 8.87083
D78: B5 | E78: HEATER | F78: 56.3606 | G78: 9.70856 | H78: 0.0430144 | N78: B5 | O78: HEATER | P78: 175.518 | Q78: 30.2344 | R78: 0.133956 | X78: B5 | Y78: HEATER | Z78: 250.503 | AA78: 43.1512 | AB78: 0.191184
D79: H-1 | E79: HEATER | F79: 33008.9 | G79: 5686.05 | H79: 25.1924 | N79: H-1 | O79: HEATER | P79: 35245.1 | Q79: 6071.24 | R79: 26.899 | X79: H-1 | Y79: HEATER | Z79: 51755.4 | AA79: 8915.28 | AB79: 39.4997
D80: REG | E80: RADFRAC | F80: 4247.43 | G80: 731.654 | H80: 3.24164 | N80: REG | O80: RADFRAC | P80: 4546.67 | Q80: 783.199 | R80: 3.47002 | X80: REG | Y80: RADFRAC | Z80: 7036.83 | AA80: 1212.15 | AB80: 5.37051
B83: Electricity | D83: Block ID | E83: Block type | F83: Duty | G83: Usage | H83: Cost | I83: CO2 emission rate | L83: Electricity | N83: Block ID | O83: Block type | P83: Duty | Q83: Usage | R83: Cost | S83: CO2 emission rate | V83: Electricity | X83: Block ID | Y83: Block type | Z83: Duty | AA83: Usage | AB83: Cost | AC83: CO2 emission rate | AF83: Electricity | AH83: Block ID | AI83: Block type | AJ83: Duty | AK83: Usage | AL83: Cost | AM83: CO2 emission rate | AP83: Electricity | AR83: Block ID | AS83: Block type | AT83: Duty | AU83: Usage | AV83: Cost | AW83: CO2 emission rate | BA83: Electricity | BC83: Block ID | BD83: Block type | BE83: Duty | BF83: Usage | BG83: Cost | BH83: CO2 emission rate | BL83: Electricity | BN83: Block ID | BO83: Block type | BP83: Duty | BQ83: Usage | BR83: Cost | BS83: CO2 emission rate | BW83: Electricity | BY83: Block ID | BZ83: Block type | CA83: Duty | CB83: Usage | CC83: Cost | CD83: CO2 emission rate | CH83: Electricity | CJ83: Block ID | CK83: Block type | CL83: Duty | CM83: Usage | CN83: Cost | CO83: CO2 emission rate | CS83: Electricity | CU83: Block ID | CV83: Block type | CW83: Duty | CX83: Usage | CY83: Cost | CZ83: CO2 emission rate | DD83: Electricity | DF83: Block ID | DG83: Block type | DH83: Duty | DI83: Usage | DJ83: Cost | DK83: CO2 emission rate | DO83: Electricity | DQ83: Block ID | DR83: Block type | DS83: Duty | DT83: Usage | DU83: Cost | DV83: CO2 emission rate
B84: =SUM(G85:G92) -> 709926.78 | C84: kWh | F84: kW | G84: kW | H84: $/hr | I84: kg/hr | L84: =SUM(Q85:Q92) -> 515857.46 | M84: kWh | P84: kW | Q84: kW | R84: $/hr | S84: kg/hr | V84: =SUM(AA85:AA92) -> 394300.06 | W84: kWh | Z84: kW | AA84: kW | AB84: $/hr | AC84: kg/hr | AF84: =SUM(AK85:AK92) -> 1266611 | AG84: kWh | AJ84: kW | AK84: kW | AL84: $/hr | AM84: kg/hr | AP84: =SUM(AU85:AU92) -> 972955 | AQ84: kWh | AT84: kW | AU84: kW | AV84: $/hr | AW84: kg/hr | BA84: =SUM(BF85:BF92) -> 1126215 | BB84: kWh | BE84: kW | BF84: kW | BG84: $/hr | BH84: kg/hr | BL84: =SUM(BQ85:BQ92) -> 1283152 | BM84: kWh | BP84: kW | BQ84: kW | BR84: $/hr | BS84: kg/hr | BW84: =SUM(CB85:CB92) -> 2644721 | BX84: kWh | CA84: kW | CB84: kW | CC84: $/hr | CD84: kg/hr | CH84: =SUM(CM85:CM92) -> 3119461 | CI84: kWh | CL84: kW | CM84: kW | CN84: $/hr | CO84: kg/hr | CS84: =SUM(CX85:CX92) -> 3517352 | CT84: kWh | CW84: kW | CX84: kW | CY84: $/hr | CZ84: kg/hr | DD84: =SUM(DI85:DI92) -> 4499421 | DE84: kWh | DH84: kW | DI84: kW | DJ84: $/hr | DK84: kg/hr | DO84: =SUM(DT85:DT92) -> 3518176 | DP84: kWh | DS84: kW | DT84: kW | DU84: $/hr | DV84: kg/hr
D85: MCOMP1 | E85: MCOMPR | F85: 524990 | G85: 524990 | H85: 40686.7 | I85: 182121 | N85: MCOMP1 | O85: MCOMPR | P85: 270842 | Q85: 270842 | R85: 20990.2 | S85: 93955.8 | X85: MCOMP1 | Y85: MCOMPR | Z85: 138593 | AA85: 138593 | AB85: 10740.9 | AC85: 48078.2 | AH85: MCOMP1 | AI85: MCOMPR | AJ85: 1121210 | AK85: 1121210 | AL85: 86893.5 | AM85: 388950 | AR85: MCOMP1 | AS85: MCOMPR | AT85: 861293 | AU85: 861293 | AV85: 66750.2 | AW85: 298785 | BC85: MCOMP1 | BD85: MCOMPR | BE85: 996969 | BF85: 996969 | BG85: 77265.1 | BH85: 345852 | BN85: MCOMP1 | BO85: MCOMPR | BP85: 1135900 | BQ85: 1135900 | BR85: 88032.1 | BS85: 394047 | BY85: MCOMP1 | BZ85: MCOMPR | CA85: 2341140 | CB85: 2341140 | CC85: 181438 | CD85: 812149 | CJ85: MCOMP1 | CK85: MCOMPR | CL85: 2761390 | CM85: 2761390 | CN85: 214008 | CO85: 957934 | CU85: MCOMP1 | CV85: MCOMPR | CW85: 3113630 | CX85: 3113630 | CY85: 241306 | CZ85: 1080130 | DF85: MCOMP1 | DG85: MCOMPR | DH85: 3982950 | DI85: 3982950 | DJ85: 308678 | DK85: 1381700 | DQ85: MCOMP1 | DR85: MCOMPR | DS85: 3114410 | DT85: 3114410 | DU85: 241367 | DV85: 1080400
D86: MCOMP2 | E86: MCOMPR | F86: 180589 | G86: 180589 | H86: 13995.7 | I86: 62646.9 | N86: MCOMP2 | O86: MCOMPR | P86: 240342 | Q86: 240342 | R86: 18626.5 | S86: 83375.5 | X86: MCOMP2 | Y86: MCOMPR | Z86: 248327 | AA86: 248327 | AB86: 19245.3 | AC86: 86145.4 | AH86: MCOMP2 | AI86: MCOMPR | AJ86: 145401 | AK86: 145401 | AL86: 11268.6 | AM86: 50440.1 | AR86: MCOMP2 | AS86: MCOMPR | AT86: 111662 | AU86: 111662 | AV86: 8653.81 | AW86: 38735.9 | BC86: MCOMP2 | BD86: MCOMPR | BE86: 129246 | BF86: 129246 | BG86: 10016.6 | BH86: 44835.8 | BN86: MCOMP2 | BO86: MCOMPR | BP86: 147252 | BQ86: 147252 | BR86: 11412.1 | BS86: 51082.3 | BY86: MCOMP2 | BZ86: MCOMPR | CA86: 303581 | CB86: 303581 | CC86: 23527.5 | CD86: 105313 | CJ86: MCOMP2 | CK86: MCOMPR | CL86: 358071 | CM86: 358071 | CN86: 27750.5 | CO86: 124216 | CU86: MCOMP2 | CV86: MCOMPR | CW86: 403722 | CX86: 403722 | CY86: 31288.5 | CZ86: 140053 | DF86: MCOMP2 | DG86: MCOMPR | DH86: 516471 | DI86: 516471 | DJ86: 40026.5 | DK86: 179165 | DQ86: MCOMP2 | DR86: MCOMPR | DS86: 403766 | DT86: 403766 | DU86: 31291.8 | DV86: 140068
D87: P-1 | E87: PUMP | F87: 21.3463 | G87: 21.3463 | H87: 1.65434 | I87: 7.40509 | N87: P-1 | O87: PUMP | P87: 22.7024 | Q87: 22.7024 | R87: 1.75943 | S87: 7.87553 | X87: P-1 | Y87: PUMP | Z87: 34.4361 | AA87: 34.4361 | AB87: 2.6688 | AC87: 11.946
D88: B7 | E88: COMPR | F88: 4326.43 | G88: 4326.43 | H88: 335.298 | I88: 1500.85 | N88: B7 | O88: COMPR | P88: 4650.76 | Q88: 4650.76 | R88: 360.434 | S88: 1613.36 | X88: B7 | Y88: COMPR | Z88: 7345.62 | AA88: 7345.62 | AB88: 569.285 | AC88: 2548.22
B93: Fired heat | D93: Block ID | E93: Block type | F93: Duty | G93: Usage | H93: Cost | I93: CO2 emission rate | L93: Fired heat | N93: Block ID | O93: Block type | P93: Duty | Q93: Usage | R93: Cost | S93: CO2 emission rate | V93: Fired heat | X93: Block ID | Y93: Block type | Z93: Duty | AA93: Usage | AB93: Cost | AC93: CO2 emission rate | AF93: Fired heat | AH93: Block ID | AI93: Block type | AJ93: Duty | AK93: Usage | AL93: Cost | AM93: CO2 emission rate | AP93: Fired heat | AR93: Block ID | AS93: Block type | AT93: Duty | AU93: Usage | AV93: Cost | AW93: CO2 emission rate | BA93: Fired heat | BC93: Block ID | BD93: Block type | BE93: Duty | BF93: Usage | BG93: Cost | BH93: CO2 emission rate | BL93: Fired heat | BN93: Block ID | BO93: Block type | BP93: Duty | BQ93: Usage | BR93: Cost | BS93: CO2 emission rate | BW93: Fired heat | BY93: Block ID | BZ93: Block type | CA93: Duty | CB93: Usage | CC93: Cost | CD93: CO2 emission rate | CH93: Fired heat | CJ93: Block ID | CK93: Block type | CL93: Duty | CM93: Usage | CN93: Cost | CO93: CO2 emission rate | CS93: Fired heat | CU93: Block ID | CV93: Block type | CW93: Duty | CX93: Usage | CY93: Cost | CZ93: CO2 emission rate | DD93: Fired heat | DF93: Block ID | DG93: Block type | DH93: Duty | DI93: Usage | DJ93: Cost | DK93: CO2 emission rate | DO93: Fired heat | DQ93: Block ID | DR93: Block type | DS93: Duty | DT93: Usage | DU93: Cost | DV93: CO2 emission rate
B94: =SUM(F95:F99) -> 0 | C94: kW | F94: kW | G94: kg/hr | H94: $/hr | I94: kg/hr | L94: =SUM(P95:P99) -> 0 | M94: kW | P94: kW | Q94: kg/hr | R94: $/hr | S94: kg/hr | V94: =SUM(Z95:Z99) -> 0 | W94: kW | Z94: kW | AA94: kg/hr | AB94: $/hr | AC94: kg/hr | AF94: =SUM(AJ95:AJ99) -> 0 | AG94: kW | AJ94: kW | AK94: kg/hr | AL94: $/hr | AM94: kg/hr | AP94: =SUM(AT95:AT99) -> 0 | AQ94: kW | AT94: kW | AU94: kg/hr | AV94: $/hr | AW94: kg/hr | BA94: =SUM(BE95:BE99) -> 0 | BB94: kW | BE94: kW | BF94: kg/hr | BG94: $/hr | BH94: kg/hr | BL94: =SUM(BP95:BP99) -> 0 | BM94: kW | BP94: kW | BQ94: kg/hr | BR94: $/hr | BS94: kg/hr | BW94: =SUM(CA95:CA99) -> 0 | BX94: kW | CA94: kW | CB94: kg/hr | CC94: $/hr | CD94: kg/hr | CH94: =SUM(CL95:CL99) -> 0 | CI94: kW | CL94: kW | CM94: kg/hr | CN94: $/hr | CO94: kg/hr | CS94: =SUM(CW95:CW99) -> 0 | CT94: kW | CW94: kW | CX94: kg/hr | CY94: $/hr | CZ94: kg/hr | DD94: =SUM(DH95:DH99) -> 0 | DE94: kW | DH94: kW | DI94: kg/hr | DJ94: $/hr | DK94: kg/hr | DO94: =SUM(DS95:DS99) -> 0 | DP94: kW | DS94: kW | DT94: kg/hr | DU94: $/hr | DV94: kg/hr
B100: High-pressure steam | D100: Block ID | E100: Block type | F100: Duty | G100: Usage | H100: Cost | I100: CO2 emission rate | L100: High-pressure steam | N100: Block ID | O100: Block type | P100: Duty | Q100: Usage | R100: Cost | S100: CO2 emission rate | V100: High-pressure steam | X100: Block ID | Y100: Block type | Z100: Duty | AA100: Usage | AB100: Cost | AC100: CO2 emission rate | AF100: High-pressure steam | AH100: Block ID | AI100: Block type | AJ100: Duty | AK100: Usage | AL100: Cost | AM100: CO2 emission rate | AP100: High-pressure steam | AR100: Block ID | AS100: Block type | AT100: Duty | AU100: Usage | AV100: Cost | AW100: CO2 emission rate | BA100: High-pressure steam | BC100: Block ID | BD100: Block type | BE100: Duty | BF100: Usage | BG100: Cost | BH100: CO2 emission rate | BL100: High-pressure steam | BN100: Block ID | BO100: Block type | BP100: Duty | BQ100: Usage | BR100: Cost | BS100: CO2 emission rate | BW100: High-pressure steam | BY100: Block ID | BZ100: Block type | CA100: Duty | CB100: Usage | CC100: Cost | CD100: CO2 emission rate | CH100: High-pressure steam | CJ100: Block ID | CK100: Block type | CL100: Duty | CM100: Usage | CN100: Cost | CO100: CO2 emission rate | CS100: High-pressure steam | CU100: Block ID | CV100: Block type | CW100: Duty | CX100: Usage | CY100: Cost | CZ100: CO2 emission rate | DD100: High-pressure steam | DF100: Block ID | DG100: Block type | DH100: Duty | DI100: Usage | DJ100: Cost | DK100: CO2 emission rate | DO100: High-pressure steam | DQ100: Block ID | DR100: Block type | DS100: Duty | DT100: Usage | DU100: Cost | DV100: CO2 emission rate
B101: =SUM(G102:G106) -> 0 | C101: ton/h | F101: kW | G101: tonne/hr | H101: $/hr | I101: kg/hr | L101: =SUM(Q102:Q106) -> 0 | M101: ton/h | P101: kW | Q101: tonne/hr | R101: $/hr | S101: kg/hr | V101: =SUM(AA102:AA106) -> 0 | W101: ton/h | Z101: kW | AA101: tonne/hr | AB101: $/hr | AC101: kg/hr | AF101: =SUM(AK102:AK106) -> 0 | AG101: ton/h | AJ101: kW | AK101: tonne/hr | AL101: $/hr | AM101: kg/hr | AP101: =SUM(AU102:AU106) -> 0 | AQ101: ton/h | AT101: kW | AU101: tonne/hr | AV101: $/hr | AW101: kg/hr | BA101: =SUM(BF102:BF106) -> 0 | BB101: ton/h | BE101: kW | BF101: tonne/hr | BG101: $/hr | BH101: kg/hr | BL101: =SUM(BQ102:BQ106) -> 0 | BM101: ton/h | BP101: kW | BQ101: tonne/hr | BR101: $/hr | BS101: kg/hr | BW101: =SUM(CB102:CB106) -> 0 | BX101: ton/h | CA101: kW | CB101: tonne/hr | CC101: $/hr | CD101: kg/hr | CH101: =SUM(CM102:CM106) -> 0 | CI101: ton/h | CL101: kW | CM101: tonne/hr | CN101: $/hr | CO101: kg/hr | CS101: =SUM(CX102:CX106) -> 0 | CT101: ton/h | CW101: kW | CX101: tonne/hr | CY101: $/hr | CZ101: kg/hr | DD101: =SUM(DI102:DI106) -> 0 | DE101: ton/h | DH101: kW | DI101: tonne/hr | DJ101: $/hr | DK101: kg/hr | DO101: =SUM(DT102:DT106) -> 0 | DP101: ton/h | DS101: kW | DT101: tonne/hr | DU101: $/hr | DV101: kg/hr
B102: =SUM(F102:F106) -> 0 | C102: kW | L102: =SUM(P102:P106) -> 0 | M102: kW | V102: =SUM(Z102:Z106) -> 0 | W102: kW | AF102: =SUM(AJ102:AJ106) -> 0 | AG102: kW | AP102: =SUM(AT102:AT106) -> 0 | AQ102: kW | BA102: =SUM(BE102:BE106) -> 0 | BB102: kW | BL102: =SUM(BP102:BP106) -> 0 | BM102: kW | BW102: =SUM(CA102:CA106) -> 0 | BX102: kW | CH102: =SUM(CL102:CL106) -> 0 | CI102: kW | CS102: =SUM(CW102:CW106) -> 0 | CT102: kW | DD102: =SUM(DH102:DH106) -> 0 | DE102: kW | DO102: =SUM(DS102:DS106) -> 0 | DP102: kW
B107: Low-pressure steam | D107: Block ID | E107: Block type | F107: Duty | G107: Usage | H107: Cost | I107: CO2 emission rate | L107: Low-pressure steam | N107: Block ID | O107: Block type | P107: Duty | Q107: Usage | R107: Cost | S107: CO2 emission rate | V107: Low-pressure steam | X107: Block ID | Y107: Block type | Z107: Duty | AA107: Usage | AB107: Cost | AC107: CO2 emission rate | AF107: Low-pressure steam | AH107: Block ID | AI107: Block type | AJ107: Duty | AK107: Usage | AL107: Cost | AM107: CO2 emission rate | AP107: Low-pressure steam | AR107: Block ID | AS107: Block type | AT107: Duty | AU107: Usage | AV107: Cost | AW107: CO2 emission rate | BA107: Low-pressure steam | BC107: Block ID | BD107: Block type | BE107: Duty | BF107: Usage | BG107: Cost | BH107: CO2 emission rate | BL107: Low-pressure steam | BN107: Block ID | BO107: Block type | BP107: Duty | BQ107: Usage | BR107: Cost | BS107: CO2 emission rate | BW107: Low-pressure steam | BY107: Block ID | BZ107: Block type | CA107: Duty | CB107: Usage | CC107: Cost | CD107: CO2 emission rate | CH107: Low-pressure steam | CJ107: Block ID | CK107: Block type | CL107: Duty | CM107: Usage | CN107: Cost | CO107: CO2 emission rate | CS107: Low-pressure steam | CU107: Block ID | CV107: Block type | CW107: Duty | CX107: Usage | CY107: Cost | CZ107: CO2 emission rate | DD107: Low-pressure steam | DF107: Block ID | DG107: Block type | DH107: Duty | DI107: Usage | DJ107: Cost | DK107: CO2 emission rate | DO107: Low-pressure steam | DQ107: Block ID | DR107: Block type | DS107: Duty | DT107: Usage | DU107: Cost | DV107: CO2 emission rate
B108: =SUM(G109:G113) -> 49.879329 | C108: ton/h | F108: kW | G108: tonne/hr | H108: $/hr | I108: kg/hr | L108: =SUM(Q109:Q113) -> 50.793452 | M108: ton/h | P108: kW | Q108: tonne/hr | R108: $/hr | S108: kg/hr | V108: =SUM(AA109:AA113) -> 125.85289 | W108: ton/h | Z108: kW | AA108: tonne/hr | AB108: $/hr | AC108: kg/hr | AF108: =SUM(AK109:AK113) -> 0 | AG108: ton/h | AJ108: kW | AK108: tonne/hr | AL108: $/hr | AM108: kg/hr | AP108: =SUM(AU109:AU113) -> 0 | AQ108: ton/h | AT108: kW | AU108: tonne/hr | AV108: $/hr | AW108: kg/hr | BA108: =SUM(BF109:BF113) -> 0 | BB108: ton/h | BE108: kW | BF108: tonne/hr | BG108: $/hr | BH108: kg/hr | BL108: =SUM(BQ109:BQ113) -> 0 | BM108: ton/h | BP108: kW | BQ108: tonne/hr | BR108: $/hr | BS108: kg/hr | BW108: =SUM(CB109:CB113) -> 0 | BX108: ton/h | CA108: kW | CB108: tonne/hr | CC108: $/hr | CD108: kg/hr | CH108: =SUM(CM109:CM113) -> 0 | CI108: ton/h | CL108: kW | CM108: tonne/hr | CN108: $/hr | CO108: kg/hr | CS108: =SUM(CX109:CX113) -> 0 | CT108: ton/h | CW108: kW | CX108: tonne/hr | CY108: $/hr | CZ108: kg/hr | DD108: =SUM(DI109:DI113) -> 0 | DE108: ton/h | DH108: kW | DI108: tonne/hr | DJ108: $/hr | DK108: kg/hr | DO108: =SUM(DT109:DT113) -> 0 | DP108: ton/h | DS108: kW | DT108: tonne/hr | DU108: $/hr | DV108: kg/hr
B109: =SUM(F109:F113) -> 30369.341 | C109: kW | D109: REG | E109: RADFRAC | F109: 30369.341 | G109: 49.879329 | L109: =SUM(P109:P113) -> 30925.911 | M109: kW | N109: REG | O109: RADFRAC | P109: 30925.911 | Q109: 50.793452 | V109: =SUM(Z109:Z113) -> 76626.321 | W109: kW | X109: REG | Y109: RADFRAC | Z109: 76626.321 | AA109: 125.85289 | AF109: =SUM(AJ109:AJ113) -> 0 | AG109: kW | AP109: =SUM(AT109:AT113) -> 0 | AQ109: kW | BA109: =SUM(BE109:BE113) -> 0 | BB109: kW | BL109: =SUM(BP109:BP113) -> 0 | BM109: kW | BW109: =SUM(CA109:CA113) -> 0 | BX109: kW | CH109: =SUM(CL109:CL113) -> 0 | CI109: kW | CS109: =SUM(CW109:CW113) -> 0 | CT109: kW | DD109: =SUM(DH109:DH113) -> 0 | DE109: kW | DO109: =SUM(DS109:DS113) -> 0 | DP109: kW
B114: Refrigeration | D114: Block ID | E114: Block type | F114: Duty | G114: Usage | H114: Cost | I114: CO2 emission rate | L114: Refrigeration | N114: Block ID | O114: Block type | P114: Duty | Q114: Usage | R114: Cost | S114: CO2 emission rate | V114: Refrigeration | X114: Block ID | Y114: Block type | Z114: Duty | AA114: Usage | AB114: Cost | AC114: CO2 emission rate | AF114: Refrigeration | AH114: Block ID | AI114: Block type | AJ114: Duty | AK114: Usage | AL114: Cost | AM114: CO2 emission rate | AP114: Refrigeration | AR114: Block ID | AS114: Block type | AT114: Duty | AU114: Usage | AV114: Cost | AW114: CO2 emission rate | BA114: Refrigeration | BC114: Block ID | BD114: Block type | BE114: Duty | BF114: Usage | BG114: Cost | BH114: CO2 emission rate | BL114: Refrigeration | BN114: Block ID | BO114: Block type | BP114: Duty | BQ114: Usage | BR114: Cost | BS114: CO2 emission rate | BW114: Refrigeration | BY114: Block ID | BZ114: Block type | CA114: Duty | CB114: Usage | CC114: Cost | CD114: CO2 emission rate | CH114: Refrigeration | CJ114: Block ID | CK114: Block type | CL114: Duty | CM114: Usage | CN114: Cost | CO114: CO2 emission rate | CS114: Refrigeration | CU114: Block ID | CV114: Block type | CW114: Duty | CX114: Usage | CY114: Cost | CZ114: CO2 emission rate | DD114: Refrigeration | DF114: Block ID | DG114: Block type | DH114: Duty | DI114: Usage | DJ114: Cost | DK114: CO2 emission rate | DO114: Refrigeration | DQ114: Block ID | DR114: Block type | DS114: Duty | DT114: Usage | DU114: Cost | DV114: CO2 emission rate
B115: =SUM(F116:F123) -> 169532.29 | C115: kWh | F115: kW | G115: kg/hr | H115: $/hr | I115: kg/hr | L115: =SUM(P116:P123) -> 174006.8 | M115: kWh | P115: kW | Q115: kg/hr | R115: $/hr | S115: kg/hr | V115: =SUM(Z116:Z123) -> 170031.17 | W115: kWh | Z115: kW | AA115: kg/hr | AB115: $/hr | AC115: kg/hr | AF115: =SUM(AJ116:AJ123) -> 272908.79 | AG115: kWh | AJ115: kW | AK115: kg/hr | AL115: $/hr | AM115: kg/hr | AP115: =SUM(AT116:AT123) -> 237440.92 | AQ115: kWh | AT115: kW | AU115: kg/hr | AV115: $/hr | AW115: kg/hr | BA115: =SUM(BE116:BE123) -> 269747.86 | BB115: kWh | BE115: kW | BF115: kg/hr | BG115: $/hr | BH115: kg/hr | BL115: =SUM(BP116:BP123) -> 296150.17 | BM115: kWh | BP115: kW | BQ115: kg/hr | BR115: $/hr | BS115: kg/hr | BW115: =SUM(CA116:CA123) -> 456542.37 | BX115: kWh | CA115: kW | CB115: kg/hr | CC115: $/hr | CD115: kg/hr | CH115: =SUM(CL116:CL123) -> 519187.18 | CI115: kWh | CL115: kW | CM115: kg/hr | CN115: $/hr | CO115: kg/hr | CS115: =SUM(CW116:CW123) -> 582770.6 | CT115: kWh | CW115: kW | CX115: kg/hr | CY115: $/hr | CZ115: kg/hr | DD115: =SUM(DH116:DH123) -> 701690.6 | DE115: kWh | DH115: kW | DI115: kg/hr | DJ115: $/hr | DK115: kg/hr | DO115: =SUM(DS116:DS123) -> 608541.7 | DP115: kWh | DS115: kW | DT115: kg/hr | DU115: $/hr | DV115: kg/hr
D116: V3 | E116: FLASH2 | F116: 19701.5 | G116: 52889900 | H116: 631.236 | I116: 3964.02 | N116: V3 | O116: FLASH2 | P116: 22838.6 | Q116: 61311700 | R116: 731.749 | S116: 4595.21 | X116: V3 | Y116: FLASH2 | Z116: 28362.4 | AA116: 76140600 | AB116: 908.73 | AC116: 5706.62 | AH116: V3 | AI116: FLASH2 | AJ116: 22172.4 | AK116: 59523100 | AL116: 710.403 | AM116: 4461.16 | AR116: V3 | AS116: FLASH2 | AT116: 22190.3 | AU116: 59571300 | AV116: 710.978 | AW116: 4464.78 | BC116: V3 | BD116: FLASH2 | BE116: 25712.9 | BF116: 69027800 | BG116: 823.84 | BH116: 5173.52 | BN116: V3 | BO116: FLASH2 | BP116: 28975.9 | BQ116: 77787500 | BR116: 928.387 | BS116: 5830.05 | BY116: V3 | BZ116: FLASH2 | CA116: 40028.9 | CB116: 107460000 | CC116: 1282.53 | CD116: 8053.96 | CJ116: V3 | CK116: FLASH2 | CL116: 45877.5 | CM116: 123161000 | CN116: 1469.92 | CO116: 9230.73 | CU116: V3 | CV116: FLASH2 | CW116: 53123.3 | CX116: 142613000 | CY116: 1702.07 | CZ116: 10688.6 | DF116: V3 | DG116: FLASH2 | DH116: 61776.6 | DI116: 165843000 | DJ116: 1979.32 | DK116: 12429.7 | DQ116: V3 | DR116: FLASH2 | DS116: 60044.7 | DT116: 161194000 | DU116: 1923.83 | DV116: 12081.2
D117: V4 | E117: FLASH2 | F117: 62776.1 | G117: 168527000 | H117: 2011.35 | I117: 12630.8 | N117: V4 | O117: FLASH2 | P117: 59537.9 | Q117: 159833000 | R117: 1907.59 | S117: 11979.3 | X117: V4 | Y117: FLASH2 | Z117: 81160.5 | AA117: 217881000 | AB117: 2600.38 | AC117: 16329.8 | AH117: V4 | AI117: FLASH2 | AJ117: 90390.8 | AK117: 242660000 | AL117: 2896.12 | AM117: 18187 | AR117: V4 | AS117: FLASH2 | AT117: 87218.2 | AU117: 234143000 | AV117: 2794.47 | AW117: 17548.6 | BC117: V4 | BD117: FLASH2 | BE117: 100664 | BF117: 270239000 | BG117: 3225.28 | BH117: 20254 | BN117: V4 | BO117: FLASH2 | BP117: 113207 | BQ117: 303913000 | BR117: 3627.17 | BS117: 22777.8 | BY117: V4 | BZ117: FLASH2 | CA117: 156598 | CB117: 420398000 | CC117: 5017.41 | CD117: 31508.2 | CJ117: V4 | CK117: FLASH2 | CL117: 179017 | CM117: 480584000 | CN117: 5735.72 | CO117: 36019 | CU117: V4 | CV117: FLASH2 | CW117: 208691 | CX117: 560245000 | CY117: 6686.47 | CZ117: 41989.5 | DF117: V4 | DG117: FLASH2 | DH117: 241625 | DI117: 648658000 | DJ117: 7741.68 | DK117: 48615.9 | DQ117: V4 | DR117: FLASH2 | DS117: 240726 | DT117: 646245000 | DU117: 7712.88 | DV117: 48435.1
D118: V5 | E118: FLASH2 | F118: 48031.6 | G118: 128944000 | H118: 1538.93 | I118: 9664.13 | N118: V5 | O118: FLASH2 | P118: 34337.4 | Q118: 92180900 | R118: 1100.17 | S118: 6908.81 | X118: V5 | Y118: FLASH2 | Z118: 10858 | AA118: 29148900 | AB118: 347.89 | AC118: 2184.67 | AH118: V5 | AI118: FLASH2 | AJ118: 92145.2 | AK118: 247370000 | AL118: 2952.33 | AM118: 18540 | AR118: V5 | AS118: FLASH2 | AT118: 70021 | AU118: 187976000 | AV118: 2243.47 | AW118: 14088.5 | BC118: V5 | BD118: FLASH2 | BE118: 80918 | BF118: 217229000 | BG118: 2592.61 | BH118: 16281 | BN118: V5 | BO118: FLASH2 | BP118: 92004.8 | BQ118: 246993000 | BR118: 2947.84 | BS118: 18511.7 | BY118: V5 | BZ118: FLASH2 | CA118: 198810 | CB118: 533719000 | CC118: 6369.89 | CD118: 40001.4 | CJ118: V5 | CK118: FLASH2 | CL118: 234875 | CM118: 630537000 | CN118: 7525.4 | CO118: 47257.7 | CU118: V5 | CV118: FLASH2 | CW118: 262176 | CX118: 703828000 | CY118: 8400.11 | CZ118: 52750.8 | DF118: V5 | DG118: FLASH2 | DH118: 339253 | DI118: 910745000 | DJ118: 10869.7 | DK118: 68258.9 | DQ118: V5 | DR118: FLASH2 | DS118: 251380 | DT118: 674847000 | DU118: 8054.23 | DV118: 50578.7
D119: T1 | E119: RADFRAC | F119: 847.365 | G119: 2274800 | H119: 27.1496 | I119: 170.493 | N119: T1 | O119: RADFRAC | P119: 13736.7 | Q119: 36877000 | R119: 440.123 | S119: 2763.87 | X119: T1 | Y119: RADFRAC | Z119: 4.76957 | AA119: 12804.2 | AB119: 0.152817 | AC119: 0.959656 | AH119: T1 | AI119: RADFRAC | AJ119: 155.895 | AK119: 418510 | AL119: 4.99488 | AM119: 31.3667 | AR119: T1 | AS119: RADFRAC | AT119: 245.221 | AU119: 658312 | AV119: 7.85689 | AW119: 49.3394 | BC119: T1 | BD119: RADFRAC | BE119: 210.862 | BF119: 566074 | BG119: 6.75604 | BH119: 42.4263 | BN119: T1 | BO119: RADFRAC | BP119: 131.973 | BQ119: 354290 | BR119: 4.22842 | BS119: 26.5535 | BY119: T1 | BZ119: RADFRAC | CA119: 0.474068 | CB119: 1272.67 | CC119: 0.0151891 | CD119: 0.0953843 | CJ119: T1 | CK119: RADFRAC | CL119: 0.477111 | CM119: 1280.83 | CN119: 0.0152866 | CO119: 0.0959965 | CU119: T1 | CV119: RADFRAC | CW119: 0 | CX119: 0 | CY119: 0 | DF119: T1 | DG119: RADFRAC | DH119: 0 | DI119: 0 | DJ119: 0 | DQ119: T1 | DR119: RADFRAC | DS119: 0 | DT119: 0 | DU119: 0
D120: T2 | E120: RADFRAC | F120: 3633.12 | G120: 9753350 | H120: 116.405 | I120: 730.998 | N120: T2 | O120: RADFRAC | P120: 11144.4 | Q120: 29917800 | R120: 357.067 | S120: 2242.3 | X120: T2 | Y120: RADFRAC | Z120: 10153.6 | AA120: 27258000 | AB120: 325.322 | AC120: 2042.95 | AH120: T2 | AI120: RADFRAC | AJ120: 29857.4 | AK120: 80154000 | AL120: 956.63 | AM120: 6007.42 | AR120: T2 | AS120: RADFRAC | AT120: 23683.4 | AU120: 63579700 | AV120: 758.818 | AW120: 4765.2 | BC120: T2 | BD120: RADFRAC | BE120: 23659.2 | BF120: 63514500 | BG120: 758.04 | BH120: 4760.31 | BN120: T2 | BO120: RADFRAC | BP120: 23137.7 | BQ120: 62114600 | BR120: 741.332 | BS120: 4655.39 | BY120: T2 | BZ120: RADFRAC | CA120: 23982.6 | CB120: 64382900 | CC120: 768.404 | CD120: 4825.4 | CJ120: T2 | CK120: RADFRAC | CL120: 22917.1 | CM120: 61522400 | CN120: 734.264 | CO120: 4611 | CU120: T2 | CV120: RADFRAC | CW120: 22106 | CX120: 59345100 | CY120: 708.278 | CZ120: 4447.82 | DF120: T2 | DG120: RADFRAC | DH120: 22686.7 | DI120: 60903900 | DJ120: 726.882 | DK120: 4564.65 | DQ120: T2 | DR120: RADFRAC | DS120: 22461.8 | DT120: 60300100 | DU120: 719.676 | DV120: 4519.39
D121: T3 | E121: RADFRAC | F121: 34542.6 | G121: 92731700 | H121: 1106.74 | I121: 6950.1 | N121: T3 | O121: RADFRAC | P121: 32411.8 | Q121: 87011500 | R121: 1038.47 | S121: 6521.37 | X121: T3 | Y121: RADFRAC | Z121: 39491.9 | AA121: 106018000 | AB121: 1265.32 | AC121: 7945.92 | AH121: T3 | AI121: RADFRAC | AJ121: 38187.1 | AK121: 102516000 | AL121: 1223.52 | AM121: 7683.39 | AR121: T3 | AS121: RADFRAC | AT121: 34082.8 | AU121: 91497400 | AV121: 1092.01 | AW121: 6857.58 | BC121: T3 | BD121: RADFRAC | BE121: 38582.9 | BF121: 103578000 | BG121: 1236.2 | BH121: 7763.02 | BN121: T3 | BO121: RADFRAC | BP121: 38692.8 | BQ121: 103873000 | BR121: 1239.72 | BS121: 7785.13 | BY121: T3 | BZ121: RADFRAC | CA121: 37122.4 | CB121: 99657500 | CC121: 1189.4 | CD121: 7469.17 | CJ121: T3 | CK121: RADFRAC | CL121: 36500.1 | CM121: 97987000 | CN121: 1169.46 | CO121: 7343.97 | CU121: T3 | CV121: RADFRAC | CW121: 36674.3 | CX121: 98454500 | CY121: 1175.05 | CZ121: 7379.01 | DF121: T3 | DG121: RADFRAC | DH121: 36349.3 | DI121: 97581900 | DJ121: 1164.63 | DK121: 7313.61 | DQ121: T3 | DR121: RADFRAC | DS121: 33929.2 | DT121: 91085100 | DU121: 1087.09 | DV121: 6826.68

Sheet 5. HEN_equip
A1: EQUIP.ICS (Equipment)
A3: Area Name | B3: Component Name | C3: Component Type | D3: Total Direct Cost | E3: Equipment Cost | F3: Equipment Weight | G3: Installed Weight
D4: (USD) | E4: (USD) | F4: LBS | G4: LBS
A11: R1 | B11: R1.RADIANT1 | C11: DHE TEMA EXCH
A12: R1 | B12: R1.M5 | C12: C | D12: 0 | E12: 0 | F12: 0 | G12: 0
A13: R1 | B13: R1.M402 | C13: C | D13: 0 | E13: 0 | F13: 0 | G13: 0
A14: R1 | B14: R1.DECOKING | C14: DAT REACTOR
A15: R1 | B15: R1.CONVECT2 | C15: DHE TEMA EXCH
A16: R1 | B16: R1.CONVECT1 | C16: DHE TEMA EXCH
A17: R1 | B17: R1.COMBUST | C17: DAT REACTOR
A18: R1 | B18: R1.B6 | C18: C | D18: 0 | E18: 0 | F18: 0 | G18: 0
A19: R1 | B19: R1.B1 | C19: DVT CYLINDER
A21: Miscellaneous Flowsheet Area | B21: VAL1 | C21: C | D21: 0 | E21: 0 | F21: 0 | G21: 0
A22: Miscellaneous Flowsheet Area | B22: V5-flash vessel | C22: DVT CYLINDER | D22: 449600 | E22: 165100 | F22: 77400 | G22: 123720
A23: Miscellaneous Flowsheet Area | B23: V4-flash vessel | C23: DVT CYLINDER | D23: 827300 | E23: 465200 | F23: 201800 | G23: 260882
A24: Miscellaneous Flowsheet Area | B24: V3-flash vessel | C24: DVT CYLINDER | D24: 812700 | E24: 583200 | F24: 245600 | G24: 284078
A25: Miscellaneous Flowsheet Area | B25: V2-flash vessel | C25: DVT CYLINDER | D25: 879100 | E25: 674200 | F25: 288900 | G25: 324361
A26: Miscellaneous Flowsheet Area | B26: V1-flash vessel | C26: DVT CYLINDER | D26: 3166900 | E26: 2366000 | F26: 1062700 | G26: 1216094
A27: Miscellaneous Flowsheet Area | B27: T3-bottoms split | C27: C | D27: 0 | E27: 0 | F27: 0 | G27: 0
A28: Miscellaneous Flowsheet Area | B28: T3-cond | C28: DHE TEMA EXCH | D28: 897800 | E28: 785600 | F28: 251000 | G28: 267561
A29: Miscellaneous Flowsheet Area | B29: T3-cond acc | C29: DHT HORIZ DRUM | D29: 348500 | E29: 58600 | F29: 17500 | G29: 60908
A30: Miscellaneous Flowsheet Area | B30: T3-overhead split | C30: C | D30: 0 | E30: 0 | F30: 0 | G30: 0
A31: Miscellaneous Flowsheet Area | B31: T3-reb | C31: DRB U TUBE | D31: 955000 | E31: 777800 | F31: 224700 | G31: 251939
A32: Miscellaneous Flowsheet Area | B32: T3-reflux pump | C32: DCP CENTRIF | D32: 116200 | E32: 33900 | F32: 2500 | G32: 15774
... A47: Miscellaneous Flowsheet Area | B47: T1-tower | C47: DTW TOWER | D47: 359100 | E47: 158600 | F47: 56300 | G47: 83523
A48: Miscellaneous Flowsheet Area | B48: MCOMP2 | C48: DGC CENTRIF
A49: Miscellaneous Flowsheet Area | B49: MCOMP1 | C49: DGC CENTRIF
A50: Miscellaneous Flowsheet Area | B50: M4 | C50: C | D50: 0 | E50: 0 | F50: 0 | G50: 0
A51: Miscellaneous Flowsheet Area | B51: M3 | C51: C | D51: 0 | E51: 0 | F51: 0 | G51: 0
A52: Miscellaneous Flowsheet Area | B52: M2 | C52: C | D52: 0 | E52: 0 | F52: 0 | G52: 0
A53: Miscellaneous Flowsheet Area | B53: M1 | C53: C | D53: 0 | E53: 0 | F53: 0 | G53: 0
A54: Miscellaneous Flowsheet Area | B54: HX1 | C54: DHE TEMA EXCH
A55: Miscellaneous Flowsheet Area | B55: E9 | C55: DHE TEMA EXCH | D55: 799000 | E55: 770000 | F55: 245500 | G55: 249322
A56: Miscellaneous Flowsheet Area | B56: E8 | C56: DHE TEMA EXCH | D56: 667300 | E56: 646300 | F56: 180000 | G56: 182261
A57: Miscellaneous Flowsheet Area | B57: E7 | C57: DHE TEMA EXCH | D57: 1435300 | E57: 1316700 | F57: 373600 | G57: 391318
A58: Miscellaneous Flowsheet Area | B58: E6 | C58: DHE TEMA EXCH | D58: 1191300 | E58: 1112400 | F58: 314800 | G58: 327046
A59: Miscellaneous Flowsheet Area | B59: E5 | C59: DHE TEMA EXCH | D59: 970300 | E59: 949000 | F59: 272400 | G59: 274711
A60: Miscellaneous Flowsheet Area | B60: E4 | C60: DHE TEMA EXCH | D60: 252900 | E60: 236100 | F60: 66900 | G60: 68962
A61: Miscellaneous Flowsheet Area | B61: E3 | C61: DHE TEMA EXCH
A62: Miscellaneous Flowsheet Area | B62: E2 | C62: DHE TEMA EXCH | D62: 17682200 | E62: 7976800 | F62: 1048800 | G62: 1675328
A63: Miscellaneous Flowsheet Area | B63: E10 | C63: DHE TEMA EXCH | D63: 3472500 | E63: 3419400 | F63: 981200 | G63: 988913
A64: Miscellaneous Flowsheet Area | B64: B1 | C64: C | D64: 0 | E64: 0 | F64: 0 | G64: 0

Sheet 3. UPC & MSP (fixed)
A1: 1. Assumption and parameters
B3: ASSUMPTION AND PARAMETERS
B4: Location | E4: North America
B5: System Cost Base Date | E5: 1Q 16
B6: Project Type | E6: Grass roots/Clear field
B7: Plant lifetime (y) | E7: 30
B8: Annual operating hours (h) | E8: 8000
B9: Depreciation method | E9: Straight line
B10: Interest rate (%) | E10: 0.08
B11: Tax rate (%) | E11: 0.35
B12: Operating charges [% of operating labor cost] | E12: 0.15
B13: Plant overhead [% of labor and maintenance costs] | E13: 0.25
B14: G&A [% of fixed-operating cost] | E14: 0.06
B15: Capital charge factor | E15: =E10*POWER(1+E10,E7)/(POWER(1+E10,E7)-1) -> 0.088827433
A18: 2. Production Costs, UPC, and MSP
E20: Previous | F20: Case 1 | G20: Case 2 | H20: Case 3 | I20: Case 4
B21: 1. Total capital investment cost (TCI) ($) | D21: =SUBTOTAL(9,D22:D36) -> 5.04 | E21: =SUBTOTAL(9,E22:E36) -> 2.5298291e+09 | F21: =SUBTOTAL(9,F22:F36) -> 3.0959305e+09 | G21: =SUBTOTAL(9,G22:G36) -> 2.2739022e+09 | H21: =SUBTOTAL(9,H22:H36) -> 1.9751287e+09 | I21: =SUBTOTAL(9,I22:I36) -> 1.7921087e+09
B22: 1.1. Direct plan cost | D22: =SUBTOTAL(9,D23:D30) -> 3.6 | E22: =SUBTOTAL(9,E23:E30) -> 1.8070208e+09 | F22: =SUBTOTAL(9,F23:F30) -> 2.2113789e+09 | G22: =SUBTOTAL(9,G23:G30) -> 1.6242158e+09 | H22: =SUBTOTAL(9,H23:H30) -> 1.4108062e+09 | I22: =SUBTOTAL(9,I23:I30) -> 1.2800776e+09
B23: Purchased equipment (PE) | D23: 1 | E23: 5.0195021e+08 | F23: 6.1427193e+08 | G23: 4.5117106e+08 | H23: 3.9189061e+08 | I23: 3.5557711e+08
B24: Equipment setting | D24: 0.47 | E24: =$D24*E$23/$D$23 -> 2.359166e+08 | F24: =$D24*F$23/$D$23 -> 2.8870781e+08 | G24: =$D24*G$23/$D$23 -> 2.120504e+08 | H24: =$D24*H$23/$D$23 -> 1.8418859e+08 | I24: =$D24*I$23/$D$23 -> 1.6712124e+08
B25: Instrumentation and control | D25: 0.36 | E25: =$D25*E$23/$D$23 -> 1.8070208e+08 | F25: =$D25*F$23/$D$23 -> 2.2113789e+08 | G25: =$D25*G$23/$D$23 -> 1.6242158e+08 | H25: =$D25*H$23/$D$23 -> 1.4108062e+08 | I25: =$D25*I$23/$D$23 -> 1.2800776e+08
B26: Piping | D26: 0.68 | E26: =$D26*E$23/$D$23 -> 3.4132614e+08 | F26: =$D26*F$23/$D$23 -> 4.1770491e+08 | G26: =$D26*G$23/$D$23 -> 3.0679632e+08 | H26: =$D26*H$23/$D$23 -> 2.6648561e+08 | I26: =$D26*I$23/$D$23 -> 2.4179244e+08
B27: Electrical installation | D27: 0.11 | E27: =$D27*E$23/$D$23 -> 55214523 | F27: =$D27*F$23/$D$23 -> 67569912 | G27: =$D27*G$23/$D$23 -> 49628817 | H27: =$D27*H$23/$D$23 -> 43107967 | I27: =$D27*I$23/$D$23 -> 39113483
B28: Building and building services | D28: 0.18 | E28: =$D28*E$23/$D$23 -> 90351038 | F28: =$D28*F$23/$D$23 -> 1.1056895e+08 | G28: =$D28*G$23/$D$23 -> 81210792 | H28: =$D28*H$23/$D$23 -> 70540310 | I28: =$D28*I$23/$D$23 -> 64003881
B29: Yard improvements | D29: 0.1 | E29: =$D29*E$23/$D$23 -> 50195021 | F29: =$D29*F$23/$D$23 -> 61427193 | G29: =$D29*G$23/$D$23 -> 45117106 | H29: =$D29*H$23/$D$23 -> 39189061 | I29: =$D29*I$23/$D$23 -> 35557711
B30: Services facilities | D30: 0.7 | E30: =$D30*E$23/$D$23 -> 3.5136515e+08 | F30: =$D30*F$23/$D$23 -> 4.2999035e+08 | G30: =$D30*G$23/$D$23 -> 3.1581975e+08 | H30: =$D30*H$23/$D$23 -> 2.7432343e+08 | I30: =$D30*I$23/$D$23 -> 2.4890398e+08
B31: 1.2. Indirect plant cost | D31: =SUBTOTAL(9,D32:D36) -> 1.44 | E31: =SUBTOTAL(9,E32:E36) -> 7.2280831e+08 | F31: =SUBTOTAL(9,F32:F36) -> 8.8455158e+08 | G31: =SUBTOTAL(9,G32:G36) -> 6.4968633e+08 | H31: =SUBTOTAL(9,H32:H36) -> 5.6432248e+08 | I31: =SUBTOTAL(9,I32:I36) -> 5.1203104e+08
B32: Engineering | D32: 0.33 | E32: =$D32*E$23/$D$23 -> 1.6564357e+08 | F32: =$D32*F$23/$D$23 -> 2.0270974e+08 | G32: =$D32*G$23/$D$23 -> 1.4888645e+08 | H32: =$D32*H$23/$D$23 -> 1.293239e+08 | I32: =$D32*I$23/$D$23 -> 1.1734045e+08
B33: Construction expenses | D33: 0.41 | E33: =$D33*E$23/$D$23 -> 2.0579959e+08 | F33: =$D33*F$23/$D$23 -> 2.5185149e+08 | G33: =$D33*G$23/$D$23 -> 1.8498014e+08 | H33: =$D33*H$23/$D$23 -> 1.6067515e+08 | I33: =$D33*I$23/$D$23 -> 1.4578662e+08
B34: Legal expenses | D34: 0.04 | E34: =$D34*E$23/$D$23 -> 20078008 | F34: =$D34*F$23/$D$23 -> 24570877 | G34: =$D34*G$23/$D$23 -> 18046843 | H34: =$D34*H$23/$D$23 -> 15675624 | I34: =$D34*I$23/$D$23 -> 14223085
B35: Contractor's fee | D35: 0.22 | E35: =$D35*E$23/$D$23 -> 1.1042905e+08 | F35: =$D35*F$23/$D$23 -> 1.3513982e+08 | G35: =$D35*G$23/$D$23 -> 99257634 | H35: =$D35*H$23/$D$23 -> 86215934 | I35: =$D35*I$23/$D$23 -> 78226965
B36: Contingency | D36: 0.44 | E36: =$D36*E$23/$D$23 -> 2.2085809e+08 | F36: =$D36*F$23/$D$23 -> 2.7027965e+08 | G36: =$D36*G$23/$D$23 -> 1.9851527e+08 | H36: =$D36*H$23/$D$23 -> 1.7243187e+08 | I36: =$D36*I$23/$D$23 -> 1.5645393e+08
B37: Annualized TCI | E37: =E21*$E$15 -> 2.2471822e+08 | F37: =F21*$E$15 -> 2.7500356e+08 | G37: =G21*$E$15 -> 2.0198489e+08 | H37: =H21*$E$15 -> 1.7544561e+08 | I37: =I21*$E$15 -> 1.5918841e+08
B39: 2. Total perationg cost ($) | E39: =SUBTOTAL(9,E40:E54) -> 1.2502726e+09 | F39: =SUBTOTAL(9,F40:F54) -> 1.5037352e+09 | G39: =SUBTOTAL(9,G40:G54) -> 1.1987966e+09 | H39: =SUBTOTAL(9,H40:H54) -> 1.004324e+09 | I39: =SUBTOTAL(9,I40:I54) -> 8.5671061e+08 | K39: Assumption | O39: Yeraly consumprtion (8000 hr/y) | V39: lb | W39: kg
B40: 2.1. Variable operating cost | E40: =SUBTOTAL(9,E41:E48) -> 1.2401759e+09 | F40: =SUBTOTAL(9,F41:F48) -> 1.4916324e+09 | G40: =SUBTOTAL(9,G41:G48) -> 1.1896068e+09 | H40: =SUBTOTAL(9,H41:H48) -> 9.9619288e+08 | I40: =SUBTOTAL(9,I41:I48) -> 8.4922809e+08 | L40: Value | M40: Unit price | N40: Weight factor | O40: Unit | P40: Previous | Q40: Case 1 | R40: Case 2 | S40: Case 3 | T40: Case 4 | V40: 1 | W40: 0.45359237
B41: Natural gas feedstock | E41: =P41*$L41*$N41 -> 3.0306628e+08 | F41: =Q41*$L41*$N41 -> 3.0306628e+08 | G41: =R41*$L41*$N41 -> 3.0306628e+08 | H41: =S41*$L41*$N41 -> 3.0306628e+08 | I41: =T41*$L41*$N41 -> 3.0306628e+08 | K41: Natural gas feedstock | L41: 3.27 | M41: $/MMBTU | N41: 1 | O41: MMBTU | P41: 92680819 | Q41: 92680819 | R41: =327437.649716956/28.263682*8000 -> 92680819 | S41: =327437.649716956/28.263682*8000 -> 92680819 | T41: =327437.649716956/28.263682*8000 -> 92680819 | V41: 1 MMBTU = 28.263682 m3 NG
B42: Fuel gas | E42: =P42*$L42*$N42 -> 1.4326561e+08 | F42: =Q42*$L42*$N42 -> 2.431001e+08 | G42: =R42*$L42*$N42 -> 1.8710409e+08 | H42: =S42*$L42*$N42 -> 1.5613069e+08 | I42: =T42*$L42*$N42 -> 1.3639264e+08 | K42: Fuel gas | L42: =L41 -> 3.27 | M42: $/MMBTU | N42: 1 | O42: MMBTU | P42: 43812113 | Q42: =262649.228386354/28.263682*8000 -> 74342537 | R42: =202150.247312389/28.263682*8000 -> 57218376 | S42: =168686.087475501/28.263682*8000 -> 47746387 | T42: =147360.785925464/28.263682*8000 -> 41710287 | V42: 1MMBTU=1055MJ, 4251 MMBTU, 0.85 ef by Gavin Towler book
B43: O2 | E43: =P43*$L43*$N43 -> 14335462 | F43: =Q43*$L43*$N43 -> 2.2096061e+08 | G43: =R43*$L43*$N43 -> 1.700659e+08 | H43: =S43*$L43*$N43 -> 1.419142e+08 | I43: =T43*$L43*$N43 -> 1.2397431e+08 | K43: O2 | L43: 40 | M43: $/ton | N43: 1 | O43: ton | P43: 358386.56 | Q43: =690501.918117916/1000*8000 -> 5524015.3 | R43: =531455.927757318/1000*8000 -> 4251647.4 | S43: =443481.876816915/1000*8000 -> 3547855 | T43: =387419.714371281/1000*8000 -> 3099357.7
B44: CW | E44: =P44*$L44*$N44 -> 1.0188414e+08 | F44: =Q44*$L44*$N44 -> 1.0007561e+08 | G44: =R44*$L44*$N44 -> 70529292 | H44: =S44*$L44*$N44 -> 53760234 | I44: =T44*$L44*$N44 -> 44886792 | K44: CW | L44: 0.03 | M44: $/ton | N44: 1 | O44: ton | P44: 3396138120 | Q44: 3335853552 | R44: 2350976388 | S44: 1792007796 | T44: 1496226396
B45: Electricity | E45: =P45*$L45*$N45 -> 5.7882009e+08 | F45: =Q45*$L45*$N45 -> 5.693438e+08 | G45: =R45*$L45*$N45 -> 4.1372467e+08 | H45: =S45*$L45*$N45 -> 2.994831e+08 | I45: =T45*$L45*$N45 -> 1.9299286e+08 | K45: Electricity | L45: 0.069 | M45: $/kWh | N45: 1 | O45: kWh | P45: 8388696888 | Q45: 8251359360 | R45: 5996009760 | S45: 4340334720 | T45: 2796997920
B46: HPS | E46: =P46*$L46*$N46 -> 572343.23 | F46: =Q46*$L46*$N46 -> 0 | G46: =R46*$L46*$N46 -> 0 | H46: =S46*$L46*$N46 -> 0 | I46: =T46*$L46*$N46 -> 0 | K46: HPS | L46: 14.5 | M46: $/ton | N46: 1 | O46: ton | P46: 39471.947 | Q46: 0 | R46: 0 | S46: 0 | T46: 0
B47: LPS | E47: =P47*$L47*$N47 -> 12053565 | F47: =Q47*$L47*$N47 -> 0 | G47: =R47*$L47*$N47 -> 0 | H47: =S47*$L47*$N47 -> 0 | I47: =T47*$L47*$N47 -> 0 | K47: LPS | L47: 10.5 | M47: $/ton | N47: 1 | O47: ton | P47: 1147958.6 | Q47: 0 | R47: 0 | S47: 0 | T47: 0
B48: Refrigeration | E48: =P48*$L48*$N48 -> 86178385 | F48: =Q48*$L48*$N48 -> 55085994 | G48: =R48*$L48*$N48 -> 45116572 | H48: =S48*$L48*$N48 -> 41838381 | I48: =T48*$L48*$N48 -> 47915218 | K48: Refrigeration | L48: 0.032 | M48: $/kWh | N48: 1 | O48: kWh | P48: 2.6930745e+09 | Q48: 1.7214373e+09 | R48: 1.4098929e+09 | S48: 1.3074494e+09 | T48: 1.4973506e+09
B49: Fixed operating costs | E49: =SUBTOTAL(9,E50:E54) -> 10096738 | F49: =SUBTOTAL(9,F50:F54) -> 12102802 | G49: =SUBTOTAL(9,G50:G54) -> 9189824.3 | H49: =SUBTOTAL(9,H50:H54) -> 8131077.8 | I49: =SUBTOTAL(9,I50:I54) -> 7482520.9
B50: Operating labor cost | E50: 760000 | F50: 760000 | G50: 760001 | H50: 760002 | I50: 760003 | N50: Natural gas feedstock | P50: =E41/E$39 -> 0.24240016 | Q50: =F41/F$39 -> 0.20154232 | R50: =G41/G$39 -> 0.25280875 | S50: =H41/H$39 -> 0.30176148 | T50: =I41/I$39 -> 0.35375572
B51: Maintenance cost | E51: =0.03*E75 -> 6741546.7 | F51: =0.03*F75 -> 8250106.9 | G51: =0.03*G75 -> 6059546.8 | H51: =0.03*H75 -> 5263368.3 | I51: =0.03*I75 -> 4775652.4 | N51: Fuel gas | P51: =E42/E$39 -> 0.1145875 | Q51: =F42/F$39 -> 0.16166417 | R51: =G42/G$39 -> 0.15607659 | S51: =H42/H$39 -> 0.15545849 | T51: =I42/I$39 -> 0.15920503
B52: Operating charges | E52: =0.15*E50 -> 114000 | F52: =0.15*F50 -> 114000 | G52: =0.15*G50 -> 114000.15 | H52: =0.15*H50 -> 114000.3 | I52: =0.15*I50 -> 114000.45 | N52: O2 | P52: =E43/E$39 -> 0.011465869 | Q52: =F43/F$39 -> 0.14694117 | R52: =G43/G$39 -> 0.14186384 | S52: =H43/H$39 -> 0.14130321 | T52: =I43/I$39 -> 0.14470967
B53: Plant overhead | E53: =0.25*(E50+E51) -> 1875386.7 | F53: =0.25*(F50+F51) -> 2252526.7 | G53: =0.25*(G50+G51) -> 1704886.9 | H53: =0.25*(H50+H51) -> 1505842.6 | I53: =0.25*(I50+I51) -> 1383913.8 | N53: CW | P53: =E44/E$39 -> 0.081489543 | Q53: =F44/F$39 -> 0.06655135 | R53: =G44/G$39 -> 0.058833409 | S53: =H44/H$39 -> 0.053528778 | T53: =I44/I$39 -> 0.052394346
B54: G&A cost | E54: =SUM(E50:E53)/0.94*0.06 -> 605804.26 | F54: =SUM(F50:F53)/0.94*0.06 -> 726168.1 | G54: =SUM(G50:G53)/0.94*0.06 -> 551389.46 | H54: =SUM(H50:H53)/0.94*0.06 -> 487864.67 | I54: =SUM(I50:I53)/0.94*0.06 -> 448951.25 | N54: Electricity | P54: =E45/E$39 -> 0.4629551 | Q54: =F45/F$39 -> 0.37861972 | R54: =G45/G$39 -> 0.34511665 | S54: =H45/H$39 -> 0.29819372 | T54: =I45/I$39 -> 0.22527193
N55: HPS | P55: =E46/E$39 -> 0.00045777475 | Q55: =F46/F$39 -> 0 | R55: =G46/G$39 -> 0 | S55: =H46/H$39 -> 0 | T55: =I46/I$39 -> 0
B56: Production amount (kg/y) | N56: LPS | P56: =E47/E$39 -> 0.0096407495 | Q56: =F47/F$39 -> 0 | R56: =G47/G$39 -> 0 | S56: =H47/H$39 -> 0 | T56: =I47/I$39 -> 0
B57: Ethylene (99.9% vol) | D57: kg/y | E57: =P65 -> 4.8694133e+08 | F57: =Q65 -> 9.9704611e+08 | G57: =R65 -> 9.5257016e+08 | H57: =S65 -> 9.23201e+08 | I57: =T65 -> 8.5601968e+08 | N57: Refrigeration | P57: =E48/E$39 -> 0.068927676 | Q57: =F48/F$39 -> 0.036632776 | R57: =G48/G$39 -> 0.037634884 | S57: =H48/H$39 -> 0.041658253 | T57: =I48/I$39 -> 0.055929292
B58: Hydrogen (96 %vol) | D58: kg/y | E58: =P66 -> 3.503607e+08 | F58: =Q66 -> 2.7474281e+08 | G58: =R66 -> 2.9320363e+08 | H58: =S66 -> 3.0101806e+08 | I58: =T66 -> 3.1024314e+08 | N58: Fixed operating costs | P58: =E49/E$39 -> 0.0080756289 | Q58: =F49/F$39 -> 0.0080484927 | R58: =G49/G$39 -> 0.0076658744 | S58: =H49/H$39 -> 0.0080960708 | T58: =I49/I$39 -> 0.0087340122
B59: Crude Naphthalene (95.7 %wt) | D59: kg/y | E59: =P67 -> 34503790 | F59: =Q67 -> 12756501 | G59: =R67 -> 21305721 | H59: =S67 -> 32966567 | I59: =T67 -> 47398147
B60: Benzene (99 %wt) | D60: kg/y | E60: =P68 -> 91327939 | F60: =Q68 -> 1.0528551e+08 | G60: =R68 -> 1.4167665e+08 | H60: =S68 -> 1.8677811e+08 | I60: =T68 -> 2.3403433e+08
B61: C2-C5 hydrocarbon | D61: kg/y | E61: =P69 -> 0 | F61: =Q69 -> 1.1342609e+08 | G61: =R69 -> 88112436 | H61: =S69 -> 78865736 | I61: =T69 -> 85277185
B62: Raw Acethylene (95.1 %vol) | D62: kg/y | E62: =P70 -> 5.6637178e+08 | F62: =Q70 -> 0 | G62: =R70 -> 0 | H62: =S70 -> 0 | I62: =T70 -> 0
B64: Total production cost ($/y) | E64: =E39+E37 -> 1.4749908e+09 | F64: =F39+F37 -> 1.7787387e+09 | G64: =G39+G37 -> 1.4007815e+09 | H64: =H39+H37 -> 1.1797696e+09 | I64: =I39+I37 -> 1.015899e+09 | K64: Product | L64: Value | M64: Unit price | N64: Weight factor | O64: Unit | P64: Previous | Q64: Case 1 | R64: Case 2 | S64: Case 3 | T64: Case 4 | V64: H2 price in correlation to NG gas H2=0.1515NG+0.9287 ($/kg)
B65: Ethylene (99.9% vol) | D65: $/y | E65: =E64-SUM(E66:E70) -> 5.5059714e+08 | F65: =F64-SUM(F66:F70) -> 1.2968527e+09 | G65: =G64-SUM(G66:G70) -> 8.6980483e+08 | H65: =H64-SUM(H66:H70) -> 6.0528563e+08 | I65: =I64-SUM(I66:I70) -> 3.9066008e+08 | K65: Ethylene (99.9% vol) | L65: - | M65: $/kg | N65: 1 | O65: kg/y | P65: 4.8694133e+08 | Q65: 9.9704611e+08 | R65: 9.5257016e+08 | S65: 9.23201e+08 | T65: 8.5601968e+08 | V65: Naphthalene and benzene price in correlation to ethylene price
B66: Hydrogen (96 %vol) | D66: $/y | E66: =$L66*$N66*P66 -> 4.9895042e+08 | F66: =$L66*$N66*Q66 -> 3.9126261e+08 | G66: =$L66*$N66*R66 -> 4.1755276e+08 | H66: =$L66*$N66*S66 -> 4.2868132e+08 | I66: =$L66*$N66*T66 -> 4.418188e+08 | K66: Hydrogen (96 %vol) | L66: =0.1515*L41+0.9287 -> 1.424105 | M66: $/kg | N66: 1 | O66: kg/y | P66: 3.503607e+08 | Q66: 2.7474281e+08 | R66: 2.9320363e+08 | S66: 3.0101806e+08 | T66: 3.1024314e+08 | V66: Ben=0.695ethylene - 37.031/1000 ($/kg), Nap=0.5/0.65*Ben ($/kg)
B67: Crude Naphthalene (95.7 %wt) | D67: $/y | E67: =$L67*$N67*P67 -> 16633322 | F67: =$L67*$N67*Q67 -> 6149555.9 | G67: =$L67*$N67*R67 -> 10270898 | H67: =$L67*$N67*S67 -> 15892269 | I67: =$L67*$N67*T67 -> 22849334 | K67: Crude Naphthalene (95.7 %wt) | L67: =L68*0.5/0.65 -> 0.48207231 | M67: $/kg | N67: 1 | O67: kg/y | P67: 34503790 | Q67: 12756501 | R67: 21305721 | S67: 32966567 | T67: 47398147 | V67: Acetylene = 0.65 ethylene
B68: Benzene (99 %wt) | D68: $/y | E68: =$L68*$N68*P68 -> 57234671 | F68: =$L68*$N68*Q68 -> 65981797 | G68: =$L68*$N68*R68 -> 88787903 | H68: =$L68*$N68*S68 -> 1.1705272e+08 | I68: =$L68*$N68*T68 -> 1.4666791e+08 | K68: Benzene (99 %wt) | L68: =0.695*0.955-37.031/1000 -> 0.626694 | M68: $/kg | N68: 1 | O68: kg/y | P68: 91327939 | Q68: 1.0528551e+08 | R68: 1.4167665e+08 | S68: 1.8677811e+08 | T68: 2.3403433e+08 | V68: 0.955 $/kg ethylene (korean market 2020 - https://www.fibre2fashion.com/market-intelligence/textile-market-watch/ethylene-price-trends-industry-reports/16/?gcode=1)
B69: C2-C5 hydrocarbon | D69: $/y | E69: =$L69*$N69*P69 -> 0 | F69: =$L69*$N69*Q69 -> 18492064 | G69: =$L69*$N69*R69 -> 14365133 | H69: =$L69*$N69*S69 -> 12857626 | I69: =$L69*$N69*T69 -> 13902897 | K69: C2-C5 hydrocarbon (85%vol C2, 15% C3-C5) | L69: =(8.7/100/0.45359237)*0.85 -> 0.16303184 | M69: $/kg | N69: 1 | O69: kg/y | P69: 0 | Q69: 1.1342609e+08 | R69: 88112436 | S69: 78865736 | T69: 85277185 | V69: etrhane 8.7 cent/lb (https://investors.westlake.com/industry-pricing/default.aspx)
B70: Raw Acethylene (95.1 %vol) | D70: $/y | E70: =$L70*$N70*P70 -> 3.5157528e+08 | F70: =$L70*$N70*Q70 -> 0 | G70: =$L70*$N70*R70 -> 0 | H70: =$L70*$N70*S70 -> 0 | I70: =$L70*$N70*T70 -> 0 | K70: Raw Acethylene (95.1 %vol) | L70: =0.955*0.65 -> 0.62075 | M70: $/kg | N70: 1 | O70: kg/y | P70: 5.6637178e+08 | Q70: 0 | R70: 0 | S70: 0 | T70: 0
B71: UPC_Ethylene | D71: $/kg | E71: =E65/E57 -> 1.1307258 | F71: =F65/F57 -> 1.3006948 | G71: =G65/G57 -> 0.91311367 | H71: =H65/H57 -> 0.65563797 | I71: =I65/I57 -> 0.4563681
B74: Expenditure ($) | E74: =(E75-$E$11*E76+(1-$E$11)*E80)/(1-$E$11) -> 1.5505858e+09 | F74: =(F75-$E$11*F76+(1-$E$11)*F80)/(1-$E$11) -> 1.8712496e+09 | G74: =(G75-$E$11*G76+(1-$E$11)*G80)/(1-$E$11) -> 1.468729e+09 | H74: =(H75-$E$11*H76+(1-$E$11)*H80)/(1-$E$11) -> 1.2387892e+09 | I74: =(I75-$E$11*I76+(1-$E$11)*I80)/(1-$E$11) -> 1.0694498e+09
B75: Annualized TCI | D75: $/y | E75: =E21*$E$15 -> 2.2471822e+08 | F75: =F21*$E$15 -> 2.7500356e+08 | G75: =G21*$E$15 -> 2.0198489e+08 | H75: =H21*$E$15 -> 1.7544561e+08 | I75: =I21*$E$15 -> 1.5918841e+08
B76: Depreciation = TPI / Life time | D76: $/y | E76: =E21/$E$7 -> 84327636 | F76: =F21/$E$7 -> 1.0319768e+08 | G76: =G21/$E$7 -> 75796739 | H76: =H21/$E$7 -> 65837622 | I76: =I21/$E$7 -> 59736955
B77: Tax = (Profit - Depreciation)* Tax rate | D77: $/y | E77: =(E79-E76)*$E$11 -> 75594932 | F77: =(F79-F76)*$E$11 -> 92510857 | G77: =(G79-G76)*$E$11 -> 67947468 | H77: =(H79-H76)*$E$11 -> 59019686 | I77: =(I79-I76)*$E$11 -> 53550785
B78: ROI = Profit - Tax | D78: $/y | E78: =E79-E77 -> 2.2471822e+08 | F78: =F79-F77 -> 2.7500356e+08 | G78: =G79-G77 -> 2.0198489e+08 | H78: =H79-H77 -> 1.7544561e+08 | I78: =I79-I77 -> 1.5918841e+08
B79: Profit = Revenue - Expenses | D79: $/y | E79: =E74-E80 -> 3.0031315e+08 | F79: =F74-F80 -> 3.6751442e+08 | G79: =G74-G80 -> 2.6993236e+08 | H79: =H74-H80 -> 2.344653e+08 | I79: =I74-I80 -> 2.127392e+08
B80: Expense (OPEX) = Variable + Fixed costs | D80: $/y | E80: =E39 -> 1.2502726e+09 | F80: =F39 -> 1.5037352e+09 | G80: =G39 -> 1.1987966e+09 | H80: =H39 -> 1.004324e+09 | I80: =I39 -> 8.5671061e+08
B81: Revenue (at break-even point) ($) | E81: =E74 -> 1.5505858e+09 | F81: =F74 -> 1.8712496e+09 | G81: =G74 -> 1.468729e+09 | H81: =H74 -> 1.2387892e+09 | I81: =I74 -> 1.0694498e+09
B82: Ethylene (99.9% vol) | D82: $/y | E82: =E81-SUM(E83:E87) -> 6.2619207e+08 | F82: =F81-SUM(F83:F87) -> 1.3893636e+09 | G82: =G81-SUM(G83:G87) -> 9.377523e+08 | H82: =H81-SUM(H83:H87) -> 6.6430531e+08 | I82: =I81-SUM(I83:I87) -> 4.4421086e+08
B83: Hydrogen (96 %vol) | D83: $/y | E83: =$L66*$N66*P66 -> 4.9895042e+08 | F83: =$L66*$N66*Q66 -> 3.9126261e+08 | G83: =$L66*$N66*R66 -> 4.1755276e+08 | H83: =$L66*$N66*S66 -> 4.2868132e+08 | I83: =$L66*$N66*T66 -> 4.418188e+08
B84: Crude Naphthalene (95.7 %wt) | D84: $/y | E84: =$L67*$N67*P67 -> 16633322 | F84: =$L67*$N67*Q67 -> 6149555.9 | G84: =$L67*$N67*R67 -> 10270898 | H84: =$L67*$N67*S67 -> 15892269 | I84: =$L67*$N67*T67 -> 22849334
B85: Benzene (99 %wt) | D85: $/y | E85: =$L68*$N68*P68 -> 57234671 | F85: =$L68*$N68*Q68 -> 65981797 | G85: =$L68*$N68*R68 -> 88787903 | H85: =$L68*$N68*S68 -> 1.1705272e+08 | I85: =$L68*$N68*T68 -> 1.4666791e+08
B86: C2-C5 hydrocarbon | D86: $/y | E86: =$L69*$N69*P69 -> 0 | F86: =$L69*$N69*Q69 -> 18492064 | G86: =$L69*$N69*R69 -> 14365133 | H86: =$L69*$N69*S69 -> 12857626 | I86: =$L69*$N69*T69 -> 13902897
B87: Raw Acethylene (95.1 %vol) | D87: $/y | E87: =$L70*$N70*P70 -> 3.5157528e+08 | F87: =$L70*$N70*Q70 -> 0 | G87: =$L70*$N70*R70 -> 0 | H87: =$L70*$N70*S70 -> 0 | I87: =$L70*$N70*T70 -> 0
B88: Unit price ($/kg)
B89: MSP_Ethylene (99.9% vol) | D89: $/kg | E89: =E82/E57 -> 1.2859703 | F89: =F82/F57 -> 1.3934798 | G89: =G82/G57 -> 0.98444434 | H89: =H82/H57 -> 0.71956737 | I89: =I82/I57 -> 0.51892599
B90: Hydrogen (96 %vol) | D90: $/kg | E90: =$L$66 -> 1.424105 | F90: =$L$66 -> 1.424105 | G90: =$L$66 -> 1.424105 | H90: =$L$66 -> 1.424105 | I90: =$L$66 -> 1.424105
B91: Crude Naphthalene (95.7 %wt) | D91: $/kg | E91: =$L$67 -> 0.48207231 | F91: =$L$67 -> 0.48207231 | G91: =$L$67 -> 0.48207231 | H91: =$L$67 -> 0.48207231 | I91: =$L$67 -> 0.48207231
B92: Benzene (99 %wt) | D92: $/kg | E92: =$L$68 -> 0.626694 | F92: =$L$68 -> 0.626694 | G92: =$L$68 -> 0.626694 | H92: =$L$68 -> 0.626694 | I92: =$L$68 -> 0.626694
B93: C2-C5 hydrocarbon | D93: $/kg | E93: =$L$69 -> 0.16303184 | F93: =$L$69 -> 0.16303184 | G93: =$L$69 -> 0.16303184 | H93: =$L$69 -> 0.16303184 | I93: =$L$69 -> 0.16303184
B94: Raw Acethylene (95.1 %vol) | D94: $/kg | E94: =$L$70 -> 0.62075 | F94: =$L$70 -> 0.62075 | G94: =$L$70 -> 0.62075 | H94: =$L$70 -> 0.62075 | I94: =$L$70 -> 0.62075
D97: Production cost
E98: Previous | F98: Case 1 | G98: Case 2 | H98: Case 3 | I98: Case 4
D99: Total production cost ($/y) | E99: =E64 -> 1.4749908e+09 | F99: =F64 -> 1.7787387e+09 | G99: =G64 -> 1.4007815e+09 | H99: =H64 -> 1.1797696e+09 | I99: =I64 -> 1.015899e+09
D100: Ethylene | E100: =E65 -> 5.5059714e+08 | F100: =F65 -> 1.2968527e+09 | G100: =G65 -> 8.6980483e+08 | H100: =H65 -> 6.0528563e+08 | I100: =I65 -> 3.9066008e+08
D101: Hydrogen | E101: =-E66 -> -4.9895042e+08 | F101: =-F66 -> -3.9126261e+08 | G101: =-G66 -> -4.1755276e+08 | H101: =-H66 -> -4.2868132e+08 | I101: =-I66 -> -4.418188e+08
D102: Raw Naphthalene | E102: =-E67 -> -16633322 | F102: =-F67 -> -6149555.9 | G102: =-G67 -> -10270898 | H102: =-H67 -> -15892269 | I102: =-I67 -> -22849334
D103: Benzene | E103: =-E68 -> -57234671 | F103: =-F68 -> -65981797 | G103: =-G68 -> -88787903 | H103: =-H68 -> -1.1705272e+08 | I103: =-I68 -> -1.4666791e+08
D104: C2-C5 | E104: =-E69 -> 0 | F104: =-F69 -> -18492064 | G104: =-G69 -> -14365133 | H104: =-H69 -> -12857626 | I104: =-I69 -> -13902897
D105: Raw Acethylene | E105: =-E70 -> -3.5157528e+08 | F105: =-F70 -> 0 | G105: =-G70 -> 0 | H105: =-H70 -> 0 | I105: =-I70 -> 0
D107: UPC
E108: Previous | F108: Case 1 | G108: Case 2 | H108: Case 3 | I108: Case 4
D109: Annualized capital cost | E109: =E71/E64*E37 -> 0.17226866 | F109: =F71/F64*F37 -> 0.20109514 | G109: =G71/G64*G37 -> 0.13166591 | H109: =H71/H64*H37 -> 0.097501077 | I109: =I71/I64*I37 -> 0.07151155
D110: Raw material | E110: =E71/E64*E41 -> 0.23233017 | F110: =F71/F64*F41 -> 0.22161587 | G110: =G71/G64*G41 -> 0.19755683 | H110: =H71/H64*H41 -> 0.16842421 | I110: =I71/I64*I41 -> 0.13614521
D111: Utility | E111: =E71/E64*SUM(E42:E48) -> 0.71838685 | F111: =F71/F64*SUM(F42:F48) -> 0.8691337 | G111: =G71/G64*SUM(G42:G48) -> 0.57790045 | H111: =H71/H64*SUM(H42:H48) -> 0.38519396 | I111: =I71/I64*SUM(I42:I48) -> 0.24535
...

Sheet Previous_Technical performance
B2: Catlatyst performance (conversion, selectivity) | H2: BOILING TEMPERATURE AT 1ATM (°C)
E3: Experiment | F3: Aspen (checked) | H3: H2 | J3: -253
B4: Reactor inlet: H2/CH4 ratio | E4: ='1. DB_Experiment_VER1'!$J$14 -> 4.4444444 | F4: =F47/F48 -> 4.4443999 | H4: CH4 | J4: -164
B5: Conversion (%) | E5: 30.353963 | F5: =(F48-G48)/F48*100 -> 30.350448 | H5: C2H6 | J5: -89
B6: Selectivity (%) | E6: =SUM(E7:E12) -> 100 | F6: =SUM(F7:F12) -> 100.01719 | H6: C2H4 | J6: -104
C7: C2H6 | E7: 1.9832376 | F7: =(G49-F49)*2/($F$48-$G$48)*100 -> 1.9835724 | H7: C2H2 | J7: -84
C8: C2H4 | E8: 35.180966 | F8: =(G50-F50)*2/($F$48-$G$48)*100 -> 35.187281 | H8: C3-C5 | J8: -84
C9: C2H2 | E9: 41.411786 | F9: =(G51-F51)*2/($F$48-$G$48)*100 -> 41.418759 | H9: Benzene | J9: -47~36
C10: Benzene | E10: 7.4789878 | F10: =(G53-F53)*6/($F$48-$G$48)*100 -> 7.4802315 | H10: Naphthalene | J10: 80
C11: Naphthalene | E11: 2.6768978 | F11: =(G54-F54)*10/($F$48-$G$48)*100 -> 2.6773429
C12: Coke | E12: 11.268125 | F12: =N55/($F$48-$G$48)*100 -> 11.269999 | H12: PRODUCT STREAM (KG/H) | K12: ton/y | L12: MT/y | M12: CH4Fd ton/y | S12: Mole flowrate (kmol/h) | T12: Mass flow rate (kg/h)
B13: Yields (%) | E13: =SUM(E14:E19) -> 30.355664 | H13: Ethylene (99.9% vol) | J13: =H59 -> 60867.667 | K13: =J13*8000/1000 -> 486941.33 | L13: =J13*8000/10^9 -> 0.48694133 | M13: =D59*8 -> 1692421.3 | R13: Raw materials
C14: C2H6 | E14: =F7*$F$5/100 -> 0.60202309 | H14: Acethylene (95.1 %vol) | J14: =I59 -> 70796.472 | K14: =J14*8000/1000 -> 566371.78 | L14: =J14*8000/10^9 -> 0.56637178 | R14: Methane | S14: =D46 -> 13186.8 | T14: =D59 -> 211552.67
C15: C2H4 | E15: =F8*$F$5/100 -> 10.679497 | H15: Naphthalene (95.7 %wt) | J15: =J59 -> 4312.9738 | K15: =J15*8000/1000 -> 34503.79 | L15: =J15*8000/10^9 -> 0.03450379 | R15: Products
C16: C2H2 | E16: =F9*$F$5/100 -> 12.570779 | H16: Benzene (99 %wt) | J16: =K59 -> 11415.992 | K16: =J16*8000/1000 -> 91327.939 | L16: =J16*8000/10^9 -> 0.091327939 | R16: Ethylene (99.9% vol) | S16: =H46 -> 2170.0515 | T16: 60867.667
C17: Benzene | E17: =F10*$F$5/100 -> 2.2702838 | H17: Hydrogen (96 %vol) | J17: =L59 -> 43795.087 | K17: =J17*8000/1000 -> 350360.7 | L17: =J17*8000/10^9 -> 0.3503607 | R17: Acethylene (95.1 %vol) | S17: =I46 -> 2685.8454 | T17: 70796.472
C18: Naphthalene | E18: =F11*$F$5/100 -> 0.81258557 | R18: Naphthalene (95.7 %wt) | S18: =J46 -> 35.101909 | T18: 4312.9738
C19: Coke | E19: =F12*$F$5/100 -> 3.4204952 | R19: Benzene (99 %wt) | S19: =K46 -> 145.59242 | T19: 11415.992
R20: Hydrogen (96 %vol) | S20: =L46 -> 17390.595 | T20: 43795.087
B44: MAJOR STREAM INFORMATION
D45: ='DB_Aspen simulation_previous'!D117 -> 1-CH4 | E45: ='DB_Aspen simulation_previous'!E117 -> 50-O2 | F45: ='DB_Aspen simulation_previous'!F117 -> 6-RXNin | G45: ='DB_Aspen simulation_previous'!G117 -> 7-RXN-out | H45: ='DB_Aspen simulation_previous'!H117 -> 27-Ethylene | I45: ='DB_Aspen simulation_previous'!I117 -> 28-C2 | J45: ='DB_Aspen simulation_previous'!J117 -> 12-Naphthalene | K45: ='DB_Aspen simulation_previous'!K117 -> 20-Benzene | ... N45: ='DB_Aspen simulation_previous'!N117 -> 49-COKE
B46: ='DB_Aspen simulation_previous'!B118 -> Mole Flows | C46: ='DB_Aspen simulation_previous'!C118 -> kmol/hr | D46: ='DB_Aspen simulation_previous'!D118 -> 13186.8 | E46: ='DB_Aspen simulation_previous'!E118 -> 1400 | F46: ='DB_Aspen simulation_previous'!F118 -> 221973.91 | G46: ='DB_Aspen simulation_previous'!G118 -> 231437.85 | H46: ='DB_Aspen simulation_previous'!H118 -> 2170.0515 | I46: ='DB_Aspen simulation_previous'!I118 -> 2685.8454 | ... N46: ='DB_Aspen simulation_previous'!N118 -> 1392.0025 | R46: 13186.8 | S46: 1400 | T46: 221973.91 | U46: 231437.85 | V46: 2170.0515 | W46: 2685.8454 | X46: 35.101909 | Y46: 145.59242 | Z46: 17390.595 | AA46: 1400 | AB46: 1392.0025
B47: ='DB_Aspen simulation_previous'!B119 -> H2 | C47: ='DB_Aspen simulation_previous'!C119 -> kmol/hr | D47: ='DB_Aspen simulation_previous'!D119 -> 0 | E47: ='DB_Aspen simulation_previous'!E119 -> 0 | F47: ='DB_Aspen simulation_previous'!F119 -> 180869.01 | G47: ='DB_Aspen simulation_previous'!G119 -> 197643.84 | H47: ='DB_Aspen simulation_previous'!H119 -> 1.0538853e-09 | I47: ='DB_Aspen simulation_previous'!I119 -> 2.1702471e-39 | ... N47: ='DB_Aspen simulation_previous'!N119 -> 0 | R47: 0 | S47: 0 | T47: 180869.01 | U47: 197643.84 | V47: 1.0538853e-09 | W47: 2.1702471e-39 | X47: 0.20996271 | Y47: 5.7435524e-08 | Z47: 16767.799 | AA47: 0 | AB47: 0
B48: ='DB_Aspen simulation_previous'!B120 -> CH4 | C48: ='DB_Aspen simulation_previous'!C120 -> kmol/hr | D48: ='DB_Aspen simulation_previous'!D120 -> 13186.8 | E48: ='DB_Aspen simulation_previous'!E120 -> 0 | F48: ='DB_Aspen simulation_previous'!F120 -> 40695.935 | G48: ='DB_Aspen simulation_previous'!G120 -> 28344.536 | H48: ='DB_Aspen simulation_previous'!H120 -> 0.43146133 | I48: ='DB_Aspen simulation_previous'!I120 -> 1.1295021e-14 | ... N48: ='DB_Aspen simulation_previous'!N120 -> 0 | R48: 13186.8 | S48: 0 | T48: 40695.935 | U48: 28344.536 | V48: 0.43146133 | W48: 1.1295021e-14 | X48: 0.20312417 | Y48: 7.4918187e-06 | Z48: 622.64269 | AA48: 0 | AB48: 0
B49: ='DB_Aspen simulation_previous'!B121 -> C2H6 | C49: ='DB_Aspen simulation_previous'!C121 -> kmol/hr | D49: ='DB_Aspen simulation_previous'!D121 -> 0 | E49: ='DB_Aspen simulation_previous'!E121 -> 0 | F49: ='DB_Aspen simulation_previous'!F121 -> 3.8575921 | G49: ='DB_Aspen simulation_previous'!G121 -> 126.35705 | H49: ='DB_Aspen simulation_previous'!H121 -> 9.4418223e-13 | I49: ='DB_Aspen simulation_previous'!I121 -> 122.44253 | ... N49: ='DB_Aspen simulation_previous'!N121 -> 0 | R49: 0 | S49: 0 | T49: 3.8575921 | U49: 126.35705 | V49: 9.4418223e-13 | W49: 122.44253 | X49: 0.0063581651 | Y49: 0.00010754155 | Z49: 0.00027909048 | AA49: 0 | AB49: 0
B50: ='DB_Aspen simulation_previous'!B122 -> C2H4 | C50: ='DB_Aspen simulation_previous'!C122 -> kmol/hr | D50: ='DB_Aspen simulation_previous'!D122 -> 0 | E50: ='DB_Aspen simulation_previous'!E122 -> 0 | F50: ='DB_Aspen simulation_previous'!F122 -> 338.47624 | G50: ='DB_Aspen simulation_previous'!G122 -> 2511.5369 | H50: ='DB_Aspen simulation_previous'!H122 -> 2167.0134 | I50: ='DB_Aspen simulation_previous'!I122 -> 2.1691536 | ... N50: ='DB_Aspen simulation_previous'!N122 -> 0 | R50: 0 | S50: 0 | T50: 338.47624 | U50: 2511.5369 | V50: 2167.0134 | W50: 2.1691536 | X50: 0.084735456 | Y50: 0.0003748476 | Z50: 0.15035486 | AA50: 0 | AB50: 0
B51: ='DB_Aspen simulation_previous'!B123 -> C2H2 | C51: ='DB_Aspen simulation_previous'!C123 -> kmol/hr | D51: ='DB_Aspen simulation_previous'!D123 -> 0 | E51: ='DB_Aspen simulation_previous'!E123 -> 0 | F51: ='DB_Aspen simulation_previous'!F123 -> 66.628656 | G51: ='DB_Aspen simulation_previous'!G123 -> 2624.5266 | H51: ='DB_Aspen simulation_previous'!H123 -> 2.6065817 | I51: ='DB_Aspen simulation_previous'!I123 -> 2554.23 | ... N51: ='DB_Aspen simulation_previous'!N123 -> 0 | R51: 0 | S51: 0 | T51: 66.628656 | U51: 2624.5266 | V51: 2.6065817 | W51: 2554.23 | X51: 0.14815622 | Y51: 0.0046312008 | Z51: 0.0032250312 | AA51: 0 | AB51: 0
B52: ='DB_Aspen simulation_previous'!B124 -> C3-C5 | C52: ='DB_Aspen simulation_previous'!C124 -> kmol/hr | D52: ='DB_Aspen simulation_previous'!D124 -> 0 | E52: ='DB_Aspen simulation_previous'!E124 -> 0 | F52: ='DB_Aspen simulation_previous'!F124 -> 0 | G52: ='DB_Aspen simulation_previous'!G124 -> 0 | H52: ='DB_Aspen simulation_previous'!H124 -> 0 | I52: ='DB_Aspen simulation_previous'!I124 -> 0 | ... N52: ='DB_Aspen simulation_previous'!N124 -> 0 | R52: 0 | S52: 0 | T52: 0 | U52: 0 | V52: 0 | W52: 0 | X52: 0 | Y52: 0 | Z52: 0 | AA52: 0 | AB52: 0
B53: ='DB_Aspen simulation_previous'!B125 -> BEN | C53: ='DB_Aspen simulation_previous'!C125 -> kmol/hr | D53: ='DB_Aspen simulation_previous'!D125 -> 0 | E53: ='DB_Aspen simulation_previous'!E125 -> 0 | F53: ='DB_Aspen simulation_previous'!F125 -> 3.5999699e-07 | G53: ='DB_Aspen simulation_previous'!G125 -> 153.98553 | H53: ='DB_Aspen simulation_previous'!H125 -> 5.2571404e-239 | I53: ='DB_Aspen simulation_previous'!I125 -> 7.0036464 | ... N53: ='DB_Aspen simulation_previous'!N125 -> 0 | R53: 0 | S53: 0 | T53: 3.5999699e-07 | U53: 153.98553 | V53: 5.2571404e-239 | W53: 7.0036464 | X53: 2.2504466 | Y53: 144.71826 | Z53: 6.6589645e-18 | AA53: 0 | AB53: 0
B54: ='DB_Aspen simulation_previous'!B126 -> NAP | C54: ='DB_Aspen simulation_previous'!C126 -> kmol/hr | D54: ='DB_Aspen simulation_previous'!D126 -> 0 | E54: ='DB_Aspen simulation_previous'!E126 -> 0 | F54: ='DB_Aspen simulation_previous'!F126 -> 1.8118093e-56 | G54: ='DB_Aspen simulation_previous'!G126 -> 33.068929 | H54: ='DB_Aspen simulation_previous'!H126 -> 0 | I54: ='DB_Aspen simulation_previous'!I126 -> 7.4870779e-06 | ... N54: ='DB_Aspen simulation_previous'!N126 -> 0 | R54: 0 | S54: 0 | T54: 1.8118093e-56 | U54: 33.068929 | V54: 0 | W54: 7.4870779e-06 | X54: 32.199125 | Y54: 0.86903727 | Z54: 0 | AA54: 0 | AB54: 0
B55: ='DB_Aspen simulation_previous'!B127 -> C | C55: ='DB_Aspen simulation_previous'!C127 -> kmol/hr | D55: ='DB_Aspen simulation_previous'!D127 -> 0 | E55: ='DB_Aspen simulation_previous'!E127 -> 0 | F55: ='DB_Aspen simulation_previous'!F127 -> 0 | G55: ='DB_Aspen simulation_previous'!G127 -> 0 | H55: ='DB_Aspen simulation_previous'!H127 -> 0 | I55: ='DB_Aspen simulation_previous'!I127 -> 0 | ... N55: ='DB_Aspen simulation_previous'!N127 -> 1392.0025 | R55: 0 | S55: 0 | T55: 0 | U55: 0 | V55: 0 | W55: 0 | X55: 0 | Y55: 0 | Z55: 0 | AA55: 0 | AB55: 1392.0025
B56: ='DB_Aspen simulation_previous'!B128 -> WATER | C56: ='DB_Aspen simulation_previous'!C128 -> kmol/hr | D56: ='DB_Aspen simulation_previous'!D128 -> 0 | E56: ='DB_Aspen simulation_previous'!E128 -> 0 | F56: ='DB_Aspen simulation_previous'!F128 -> 0 | G56: ='DB_Aspen simulation_previous'!G128 -> 0 | H56: ='DB_Aspen simulation_previous'!H128 -> 0 | I56: ='DB_Aspen simulation_previous'!I128 -> 0 | ... N56: ='DB_Aspen simulation_previous'!N128 -> 0 | R56: 0 | S56: 0 | T56: 0 | U56: 0 | V56: 0 | W56: 0 | X56: 0 | Y56: 0 | Z56: 0 | AA56: 0 | AB56: 0
B57: ='DB_Aspen simulation_previous'!B129 -> O2 | C57: ='DB_Aspen simulation_previous'!C129 -> kmol/hr | D57: ='DB_Aspen simulation_previous'!D129 -> 0 | E57: ='DB_Aspen simulation_previous'!E129 -> 1400 | F57: ='DB_Aspen simulation_previous'!F129 -> 0 | G57: ='DB_Aspen simulation_previous'!G129 -> 0 | H57: ='DB_Aspen simulation_previous'!H129 -> 0 | I57: ='DB_Aspen simulation_previous'!I129 -> 0 | ... N57: ='DB_Aspen simulation_previous'!N129 -> 0 | R57: 0 | S57: 1400 | T57: 0 | U57: 0 | V57: 0 | W57: 0 | X57: 0 | Y57: 0 | Z57: 0 | AA57: 7.9975 | AB57: 0
B58: ='DB_Aspen simulation_previous'!B130 -> CO2 | C58: ='DB_Aspen simulation_previous'!C130 -> kmol/hr | D58: ='DB_Aspen simulation_previous'!D130 -> 0 | E58: ='DB_Aspen simulation_previous'!E130 -> 0 | F58: ='DB_Aspen simulation_previous'!F130 -> 0 | G58: ='DB_Aspen simulation_previous'!G130 -> 0 | H58: ='DB_Aspen simulation_previous'!H130 -> 0 | I58: ='DB_Aspen simulation_previous'!I130 -> 0 | ... N58: ='DB_Aspen simulation_previous'!N130 -> 0 | R58: 0 | S58: 0 | T58: 0 | U58: 0 | V58: 0 | W58: 0 | X58: 0 | Y58: 0 | Z58: 0 | AA58: 1392.0025 | AB58: 0
B59: ='DB_Aspen simulation_previous'!B144 -> Mass Flows | C59: ='DB_Aspen simulation_previous'!C144 -> kg/hr | D59: ='DB_Aspen simulation_previous'!D144 -> 211552.67 | E59: ='DB_Aspen simulation_previous'!E144 -> 44798.32 | F59: ='DB_Aspen simulation_previous'!F144 -> 1028831.7 | G59: ='DB_Aspen simulation_previous'!G144 -> 1012012.5 | H59: ='DB_Aspen simulation_previous'!H144 -> 60867.667 | I59: ='DB_Aspen simulation_previous'!I144 -> 70796.472 | ... N59: ='DB_Aspen simulation_previous'!N144 -> 16719.342
B60: ='DB_Aspen simulation_previous'!B145 -> H2 | C60: ='DB_Aspen simulation_previous'!C145 -> kg/hr | D60: ='DB_Aspen simulation_previous'!D145 -> 0 | E60: ='DB_Aspen simulation_previous'!E145 -> 0 | F60: ='DB_Aspen simulation_previous'!F145 -> 364610.22 | G60: ='DB_Aspen simulation_previous'!G145 -> 398426.26 | H60: ='DB_Aspen simulation_previous'!H145 -> 2.1245063e-09 | I60: ='DB_Aspen simulation_previous'!I145 -> 4.3749578e-39 | ... N60: ='DB_Aspen simulation_previous'!N145 -> 0
B61: ='DB_Aspen simulation_previous'!B146 -> CH4 | C61: ='DB_Aspen simulation_previous'!C146 -> kg/hr | D61: ='DB_Aspen simulation_previous'!D146 -> 211552.67 | E61: ='DB_Aspen simulation_previous'!E146 -> 0 | F61: ='DB_Aspen simulation_previous'!F146 -> 652875.12 | G61: ='DB_Aspen simulation_previous'!G146 -> 454724.6 | H61: ='DB_Aspen simulation_previous'!H146 -> 6.9218306 | I61: ='DB_Aspen simulation_previous'!I146 -> 1.8120331e-13 | ... N61: ='DB_Aspen simulation_previous'!N146 -> 0
B62: ='DB_Aspen simulation_previous'!B147 -> C2H6 | C62: ='DB_Aspen simulation_previous'!C147 -> kg/hr | D62: ='DB_Aspen simulation_previous'!D147 -> 0 | E62: ='DB_Aspen simulation_previous'!E147 -> 0 | F62: ='DB_Aspen simulation_previous'!F147 -> 115.9964 | G62: ='DB_Aspen simulation_previous'!G147 -> 3799.5111 | H62: ='DB_Aspen simulation_previous'!H147 -> 2.839122e-11 | I62: ='DB_Aspen simulation_previous'!I147 -> 3681.8027 | ... N62: ='DB_Aspen simulation_previous'!N147 -> 0
B63: ='DB_Aspen simulation_previous'!B148 -> C2H4 | C63: ='DB_Aspen simulation_previous'!C148 -> kg/hr | D63: ='DB_Aspen simulation_previous'!D148 -> 0 | E63: ='DB_Aspen simulation_previous'!E148 -> 0 | F63: ='DB_Aspen simulation_previous'!F148 -> 9495.5312 | G63: ='DB_Aspen simulation_previous'!G148 -> 70458.053 | H63: ='DB_Aspen simulation_previous'!H148 -> 60792.875 | I63: ='DB_Aspen simulation_previous'!I148 -> 60.852914 | ... N63: ='DB_Aspen simulation_previous'!N148 -> 0
B64: ='DB_Aspen simulation_previous'!B149 -> C2H2 | C64: ='DB_Aspen simulation_previous'!C149 -> kg/hr | D64: ='DB_Aspen simulation_previous'!D149 -> 0 | E64: ='DB_Aspen simulation_previous'!E149 -> 0 | F64: ='DB_Aspen simulation_previous'!F149 -> 1734.869 | G64: ='DB_Aspen simulation_previous'!G149 -> 68337.109 | H64: ='DB_Aspen simulation_previous'!H149 -> 67.869862 | I64: ='DB_Aspen simulation_previous'!I149 -> 66506.735 | ... N64: ='DB_Aspen simulation_previous'!N149 -> 0
B65: ='DB_Aspen simulation_previous'!B150 -> C3-C5 | C65: ='DB_Aspen simulation_previous'!C150 -> kg/hr | D65: ='DB_Aspen simulation_previous'!D150 -> 0 | E65: ='DB_Aspen simulation_previous'!E150 -> 0 | F65: ='DB_Aspen simulation_previous'!F150 -> 0 | G65: ='DB_Aspen simulation_previous'!G150 -> 0 | H65: ='DB_Aspen simulation_previous'!H150 -> 0 | I65: ='DB_Aspen simulation_previous'!I150 -> 0 | ... N65: ='DB_Aspen simulation_previous'!N150 -> 0
B66: ='DB_Aspen simulation_previous'!B151 -> BEN | C66: ='DB_Aspen simulation_previous'!C151 -> kg/hr | D66: ='DB_Aspen simulation_previous'!D151 -> 0 | E66: ='DB_Aspen simulation_previous'!E151 -> 0 | F66: ='DB_Aspen simulation_previous'!F151 -> 2.8120675e-05 | G66: ='DB_Aspen simulation_previous'!G151 -> 12028.371 | H66: ='DB_Aspen simulation_previous'!H151 -> 4.1065437e-237 | I66: ='DB_Aspen simulation_previous'!I151 -> 547.08032 | ... N66: ='DB_Aspen simulation_previous'!N151 -> 0
B67: ='DB_Aspen simulation_previous'!B152 -> NAP | C67: ='DB_Aspen simulation_previous'!C152 -> kg/hr | D67: ='DB_Aspen simulation_previous'!D152 -> 0 | E67: ='DB_Aspen simulation_previous'!E152 -> 0 | F67: ='DB_Aspen simulation_previous'!F152 -> 2.3222597e-54 | G67: ='DB_Aspen simulation_previous'!G152 -> 4238.5611 | H67: ='DB_Aspen simulation_previous'!H152 -> 0 | I67: ='DB_Aspen simulation_previous'!I152 -> 0.00095964512 | ... N67: ='DB_Aspen simulation_previous'!N152 -> 0
B68: ='DB_Aspen simulation_previous'!B153 -> C | C68: ='DB_Aspen simulation_previous'!C153 -> kg/hr | D68: ='DB_Aspen simulation_previous'!D153 -> 0 | E68: ='DB_Aspen simulation_previous'!E153 -> 0 | F68: ='DB_Aspen simulation_previous'!F153 -> 0 | G68: ='DB_Aspen simulation_previous'!G153 -> 0 | H68: ='DB_Aspen simulation_previous'!H153 -> 0 | I68: ='DB_Aspen simulation_previous'!I153 -> 0 | ... N68: ='DB_Aspen simulation_previous'!N153 -> 16719.342
B69: ='DB_Aspen simulation_previous'!B154 -> WATER | C69: ='DB_Aspen simulation_previous'!C154 -> kg/hr | D69: ='DB_Aspen simulation_previous'!D154 -> 0 | E69: ='DB_Aspen simulation_previous'!E154 -> 0 | F69: ='DB_Aspen simulation_previous'!F154 -> 0 | G69: ='DB_Aspen simulation_previous'!G154 -> 0 | H69: ='DB_Aspen simulation_previous'!H154 -> 0 | I69: ='DB_Aspen simulation_previous'!I154 -> 0 | ... N69: ='DB_Aspen simulation_previous'!N154 -> 0
B70: ='DB_Aspen simulation_previous'!B155 -> O2 | C70: ='DB_Aspen simulation_previous'!C155 -> kg/hr | D70: ='DB_Aspen simulation_previous'!D155 -> 0 | E70: ='DB_Aspen simulation_previous'!E155 -> 44798.32 | F70: ='DB_Aspen simulation_previous'!F155 -> 0 | G70: ='DB_Aspen simulation_previous'!G155 -> 0 | H70: ='DB_Aspen simulation_previous'!H155 -> 0 | I70: ='DB_Aspen simulation_previous'!I155 -> 0 | ... N70: ='DB_Aspen simulation_previous'!N155 -> 0
B71: ='DB_Aspen simulation_previous'!B156 -> CO2 | C71: ='DB_Aspen simulation_previous'!C156 -> kg/hr | D71: ='DB_Aspen simulation_previous'!D156 -> 0 | E71: ='DB_Aspen simulation_previous'!E156 -> 0 | F71: ='DB_Aspen simulation_previous'!F156 -> 0 | G71: ='DB_Aspen simulation_previous'!G156 -> 0 | H71: ='DB_Aspen simulation_previous'!H156 -> 0 | I71: ='DB_Aspen simulation_previous'!I156 -> 0 | ... N71: ='DB_Aspen simulation_previous'!N156 -> 0
B72: ='DB_Aspen simulation_previous'!B170 -> Volume Flow | C72: ='DB_Aspen simulation_previous'!C170 -> cum/hr | D72: ='DB_Aspen simulation_previous'!D170 -> 327437.65 | E72: ='DB_Aspen simulation_previous'!E170 -> 3502.9029 | F72: ='DB_Aspen simulation_previous'!F170 -> 27389526 | G72: ='DB_Aspen simulation_previous'!G170 -> 28557235 | H72: ='DB_Aspen simulation_previous'!H170 -> 98.383621 | I72: ='DB_Aspen simulation_previous'!I170 -> 109.68343 | ... N72: ='DB_Aspen simulation_previous'!N170 -> 28.555045
B74: CARBON EFFICIENCY
B75: One-pass conversion (%) | F75: =(F48-G48)/F48 -> 0.30350448
B76: Overall conversion (%)_Ethylene | F76: =H46*2/D46 -> 0.3291248
B77: Overall conversion (%)_Hydrocarbon | F77: =(SUM(H49:I51)*2+J54*10+J53*6+K53*6+K54*10)/D48 -> 0.82729831
B79: ENERGY EFFICIENCY | H79: HHV | I79: (MJ/kg) | J79: (kWh/kg)
B80: Energy efficiency (%)_For only Ethylene | F80: =F88/(F84+F94) -> 0.1452582 | H80: CH4 | I80: 55.5 | J80: =I80/3.6 -> 15.416667 | M80: 169696.1 | N80: =M80*I80 -> 9418133.6 | O80: MJ
B81: Energy efficiency (%)_For all Hydrocarbon | F81: =F87/(F84+F94) -> 0.59750678 | H81: H2 | I81: 141.7 | J81: =I81/3.6 -> 39.361111 | N81: 2250 | O81: Gcal
B82: Improve by burning coke_Hydrocarbon | F82: =F81-(F87/(F84+F94+F100)) -> 0.016735927 | H82: C2H6 | I82: 51.9 | J82: =I82/3.6 -> 14.416667
H83: C2H4 | I83: 50.3 | J83: =I83/3.6 -> 13.972222
B84: Heat flow in raw material (MJ/h) | F84: =F85 -> 11741173 | H84: C2H2 | I84: 49.9 | J84: =I84/3.6 -> 13.861111
C85: Methane | F85: =D61*I80 -> 11741173 | H85: BEN | I85: 41.8 | J85: =I85/3.6 -> 11.611111
H86: NAP | I86: =17303*2.326/1000 -> 40.246778 | J86: =I86/3.6 -> 11.179661
B87: Heat flow in production (MJ/h) | F87: =SUM(F88:F92) -> 12592257 | H87: C | I87: 32.8 | J87: =I87/3.6 -> 9.1111111
C88: Ethylene | F88: =H63*I83+H64*I84 -> 3061268.3 | H88: C2-C5 | I88: 45.75 | J88: =I88/3.6 -> 12.708333
C89: C2 (Ethane, Acethylene) | F89: =I62*I82+I63*I83+I64*I84+I66*I85 -> 3535700.5 | H89: TOL | I89: 40.589 | J89: =I89/3.6 -> 11.274722
C90: Benzene | F90: =K66*I85+K67*I86 -> 477009.85
C91: Napthalene | F91: =J61*I80+J62*I82+J63*I83+J64*I84+J66*I85+J67*I86 -> 173952.38
C92: Hydrogen | F92: =L60*I81+L61*I80+L63*I83+L64*I84 -> 5344325.6
B94: Utility consumption (MJ/h) | F94: =SUM(F95:F99) -> 9333494.4 | H94: =F94/3.6 -> 2592637.3
C95: Refrigeration | F95: ='DB_Aspen simulation_previous'!L173 -> 1106743 | G95: =F95/3.6 -> 307428.6
C96: Electicity | F96: ='DB_Aspen simulation_previous'!L182 -> 3447411 | G96: =F96/3.6 -> 957614.17
C97: Fired heat | F97: ='DB_Aspen simulation_previous'!L195 -> 4484990 | G97: =F97/3.6 -> 1245830.6
C98: High pressure steam | F98: ='DB_Aspen simulation_previous'!L200 -> 7114.45 | G98: =F98/3.6 -> 1976.2361
C99: Low pressure steam | F99: ='DB_Aspen simulation_previous'!L205 -> 287236 | G99: =F99/3.6 -> 79787.778
B100: Heat recovery by burning coke (included) (MJ) | F100: 607303.38

Sheet 2-2. Equipment cost
D1: Case 1 (BASE) | E1: Case 2 (BASE) | F1: Case 3 (BASE) | G1: Case 4 (BASE) | H1: Case 1 (Base w CCS) | I1: Case 2 (Base w CCS) | J1: Case 3 (Base w CCS) | K1: Case 4 (Base w CCS) | L1: Case 1 (E-furnace) | M1: Case 2 (E-furnace) | N1: Case 3 (E-furnace) | O1: Case 4 (E-furnace) | P1: Case 1 (E-furnace w CCS) | Q1: Case 2 (E-furnace w CCS) | R1: Case 3 (E-furnace w CCS) | S1: Case 4 (E-furnace w CCS)
D2: =G119 -> 7.3276691e+08 | E2: =L119 -> 6.0259787e+08 | F2: =Q119 -> 5.5078726e+08 | G2: =V119 -> 4.9861922e+08 | H2: =Z120 -> 7.9711511e+08 | I2: =AD120 -> 6.6510464e+08 | J2: =AH119 -> 6.0571022e+08 | K2: =AL119 -> 5.5274033e+08 | L2: =AP119 -> 7.704561e+08 | M2: =AT119 -> 6.1413499e+08 | N2: =AZ119 -> 5.4529036e+08 | O2: =BE119 -> 4.849435e+08 | P2: =BJ121 -> 7.739789e+08 | Q2: =BP119 -> 6.2147289e+08 | R2: =BW119 -> 5.5307236e+08 | S2: =CC119 -> 4.99026e+08
C3: Previous | D3: Case 1 (BASE) | E3: Case 2 (BASE) | F3: Case 3 (BASE) | G3: Case 4 (BASE) | H3: Case 1 (Base w CCS) | I3: Case 2 (Base w CCS) | J3: Case 3 (Base w CCS) | K3: Case 4 (Base w CCS) | L3: Case 1 (E-furnace) | M3: Case 2 (E-furnace) | N3: Case 3 (E-furnace) | O3: Case 4 (E-furnace) | P3: Case 1 (E-furnace w CCS) | Q3: Case 2 (E-furnace w CCS) | R3: Case 3 (E-furnace w CCS) | S3: Case 4 (E-furnace w CCS)
B4: Catalytic conversion | C4: =C67 -> 1.850693e+08 | D4: =G68 -> 2.885489e+08 | E4: =L68 -> 2.4211367e+08 | F4: =Q68 -> 2.134096e+08 | G4: =V68 -> 1.9406461e+08 | H4: =G196 -> 0 | I4: =L196 -> 0 | J4: =Q196 -> 0 | K4: =V196 -> 0
B5: Compressor | C5: =SUM(C69:C70) -> 2.5748423e+08 | D5: =SUM(G70:G71) -> 3.1005685e+08 | E5: =SUM(L70:L71) -> 2.4211828e+08 | F5: =SUM(Q70:Q71) -> 2.1963294e+08 | G5: =SUM(V70:V71) -> 1.8140426e+08 | H5: =SUM(G198:G199) -> 0 | I5: =SUM(L198:L199) -> 0 | J5: =SUM(Q198:Q199) -> 0 | K5: =SUM(V198:V199) -> 0
B6: Flash tank & column | C6: =SUM(C72:C80) -> 9109200 | D6: =SUM(G73:G81) -> 15300600 | E6: =SUM(L73:L81) -> 11359600 | F6: =SUM(Q73:Q81) -> 12226000 | G6: =SUM(V73:V81) -> 13574200 | H6: =SUM(G201:G209) -> 5.1538781e+08 | I6: =SUM(L201:L209) -> 4.3210251e+08 | J6: =SUM(Q201:Q209) -> 3.6418467e+08 | K6: =SUM(V201:V209) -> 3.0867973e+08
B7: Heat exchanger, heater, cooler | C7: =SUM(C82:C90) -> 29679386 | D7: =SUM(G83:G90) -> 20612436 | E7: =SUM(L83:L90) -> 13869518 | F7: =SUM(Q83:Q90) -> 12835182 | G7: =SUM(V83:V90) -> 17577886 | H7: =SUM(G211:G218) -> 41309000 | I7: =SUM(L211:L218) -> 28807400 | J7: =SUM(Q211:Q218) -> 17011500 | K7: =SUM(V211:V234) -> 1.4902991e+08
B8: H2PSA | C8: =C96 -> 60444580 | D8: =G97 -> 51057361 | E8: =L96 -> 0 | F8: =Q96 -> 54590487 | G8: =V96 -> 56885626 | H8: =G224 -> 42649769 | I8: =L224 -> 39075310 | J8: =Q224 -> 37937767 | K8: =V224 -> 35480933
B9: CCS | D9: =SUM(G99:G118) -> 0 | E9: =SUM(L98:L118) -> 0 | F9: =SUM(Q98:Q118) -> 0 | G9: =SUM(V98:V118) -> 0 | H9: =SUM(G226:G241) -> 71827105 | I9: =SUM(L226:L241) -> 70587561 | J9: =SUM(Q226:Q241) -> 71144212 | K9: =SUM(V226:V241) -> 71508976
B10: Storage | C10: =SUM(C92:C94) -> 20608098 | D10: =SUM(G93:G95) -> 931227.12 | E10: =SUM(L92:L94) -> 38881494 | F10: =SUM(Q92:Q94) -> 38093061 | G10: =SUM(V92:V94) -> 35112639 | H10: =SUM(G220:G222) -> 1594200 | I10: =SUM(L220:L222) -> 1236400 | J10: =SUM(Q220:Q222) -> 1736800 | K10: =SUM(V92:V94) -> 35112639
B11: TOTAL | C11: =SUM(C4:C10) -> 5.6239479e+08 | D11: =SUM(D4:D10) -> 6.8650738e+08 | E11: =SUM(E4:E10) -> 5.4834256e+08 | F11: =SUM(F4:F10) -> 5.5078726e+08 | G11: =SUM(G4:G10) -> 4.9861922e+08 | H11: =SUM(H4:H10) -> 6.7276788e+08 | I11: =SUM(I4:I10) -> 5.7180918e+08 | J11: =SUM(J4:J10) -> 4.9201495e+08 | K11: =SUM(K4:K10) -> 5.9981219e+08
K12: =K11-K8 -> 5.6433126e+08
B13: Catalytic conversion | C13: =C4/C$11 -> 0.32907363 | D13: =D4/D$11 -> 0.42031435 | E13: =E4/E$11 -> 0.44153726 | F13: =F4/F$11 -> 0.38746284 | G13: =G4/G$11 -> 0.38920403
B14: Compressor | C14: =C5/C$11 -> 0.45783537 | D14: =D5/D$11 -> 0.45164387 | E14: =E5/E$11 -> 0.44154566 | F14: =F5/F$11 -> 0.39876183 | G14: =G5/G$11 -> 0.36381321
B15: Flash tank & column | C15: =C6/C$11 -> 0.016197163 | D15: =D6/D$11 -> 0.022287597 | E15: =E6/E$11 -> 0.020716247 | F15: =F6/F$11 -> 0.022197318 | G15: =G6/G$11 -> 0.02722358
B16: Heat exchanger, heater, cooler | C16: =C7/C$11 -> 0.052773223 | D16: =D7/D$11 -> 0.030025075 | E16: =E7/E$11 -> 0.025293529 | F16: =F7/F$11 -> 0.023303339 | G16: =G7/G$11 -> 0.035253125
B17: H2PSA | C17: =C8/C$11 -> 0.10747713 | D17: =D8/D$11 -> 0.074372633 | E17: =E8/E$11 -> 0 | F17: =F8/F$11 -> 0.099113561 | G17: =G8/G$11 -> 0.11408631
B18: CCS
B19: Storage | C19: =C10/C$11 -> 0.036643473 | D19: =D10/D$11 -> 0.0013564707 | E19: =E10/E$11 -> 0.070907306 | F19: =F10/F$11 -> 0.069161114 | G19: =G10/G$11 -> 0.070419747
C20: Previous | D20: Case 1 | E20: Case 2 | F20: Case 3 | G20: Conventional
B21: Catalytic conversion | C21: =C4*(C$27/C$11) -> 8.3250004e+08 | D21: =D4*(D$27/D$11) -> 1.301264e+09 | E21: =E4*(E$27/E$11) -> 1.0040125e+09 | F21: =F4*(F$27/F$11) -> 7.6528896e+08 | G21: =G4*(G$27/G$11) -> 6.974959e+08
B22: Compressor | C22: =C5*(C$27/C$11) -> 1.1582452e+09 | D22: =D5*(D$27/D$11) -> 1.398258e+09 | E22: =E5*(E$27/E$11) -> 1.0040316e+09 | F22: =F5*(F$27/F$11) -> 7.8760592e+08 | G22: =G5*(G$27/G$11) -> 6.5199281e+08
B23: Flash tank & column | C23: =C6*(C$27/C$11) -> 40976053 | D23: =D6*(D$27/D$11) -> 69000853 | E23: =E6*(E$27/E$11) -> 47106719 | F23: =F6*(F$27/F$11) -> 43842559 | G23: =G6*(G$27/G$11) -> 48787613
B24: Heat exchanger, heater, cooler | C24: =C7*(C$27/C$11) -> 1.3350723e+08 | D24: =D7*(D$27/D$11) -> 92955547 | E24: =E7*(E$27/E$11) -> 57515010 | F24: =F7*(F$27/F$11) -> 46027093 | G24: =G7*(G$27/G$11) -> 63177431
B25: H2PSA | C25: =C8*(C$27/C$11) -> 2.7189878e+08 | D25: =D8*(D$27/D$11) -> 2.302525e+08 | E25: =E8*(E$27/E$11) -> 0 | F25: =F8*(F$27/F$11) -> 1.9576204e+08 | G25: =G8*(G$27/G$11) -> 2.0445506e+08
B26: Storage | C26: =C10*(C$27/C$11) -> 92701723 | D26: =D10*(D$27/D$11) -> 4199538.9 | E26: =E10*(E$27/E$11) -> 1.6123628e+08 | F26: =F10*(F$27/F$11) -> 1.366021e+08 | G26: =G10*(G$27/G$11) -> 1.2619984e+08
B27: CAPEX | C27: 2.5298291e+09 | D27: 3.0959305e+09 | E27: 2.2739022e+09 | F27: 1.9751287e+09 | G27: 1.7921087e+09
BO31: ft2 | BP31: M2
AC32: ft2 | AD32: M2 | AK32: ft2 | AL32: M2 | AY32: ft2 | AZ32: M2 | BO32: 43608.102 | BP32: =BO32/10.764 -> 4051.2915 | CY32: ft2 | CZ32: M2
F33: Deethanizer | G33: 1426 | H33: kmol/h | I33: C2-C3 | J33: 1.2226001 | K33: =693100*(J33/G33)^(0.67) -> 6109.6507 | AC33: 592959.46 | AD33: =AC33/10.764 -> 55087.278 | AK33: 38603.066 | AL33: =AK33/10.764 -> 3586.3123 | AY33: 1233624.4 | AZ33: =AY33/10.764 -> 114606.5 | CY33: 0.138566 | CZ33: =CY33/10.764 -> 0.012873096
F35: ft2 | G35: M2
F36: 968555.43 | G36: =F36/10.764 -> 89980.995 | BO36: Heat exchanger | BP36: 2 | BQ36: m2 | BR36: area | BS36: 4051.2915 | BT36: =15500*(BS36/BP36)^0.59 -> 1384216.9
AC37: Heat exchanger | AD37: 2 | AE37: m2 | AF37: area | AG37: 55087.278 | AH37: =15500*(AG37/AD37)^0.59 -> 6455713.9 | AK37: Heat exchanger | AL37: 2 | AM37: m2 | AN37: area | AO37: 3586.3123 | AP37: =15500*(AO37/AL37)^0.59 -> 1288149.8 | AY37: Heat exchanger | AZ37: 2 | BA37: m2 | BB37: area | BC37: 114606.5 | BD37: =15500*(BC37/AZ37)^0.59 -> 9946206.2 | CY37: Heat exchanger | CZ37: 2 | DA37: m2 | DB37: area | DC37: 0.012873096 | DD37: =15500*(DC37/CZ37)^0.59 -> 789.65423
F40: Heat exchanger | G40: 2 | H40: m2 | I40: area | J40: 89980.995 | K40: =15500*(J40/G40)^0.59 -> 8623289.5
F46: Tower | G46: 0 | K46: Tower | L46: 0 | P46: Tower | Q46: 0 | U46: Tower | V46: 0 | Y46: Tower | Z46: 0 | AC46: Tower | AD46: 0 | AG46: Tower | AH46: 0 | AK46: Tower | AL46: 0 | AO46: Tower | AP46: 0 | AS46: Tower | AT46: 0 | AY46: Tower | AZ46: 0 | BD46: Tower | BE46: 0 | BI46: Tower | BJ46: 0 | BO46: Tower | BP46: 0 | BV46: Tower | BW46: 0 | CB46: Tower | CC46: 0 | CH46: Tower | CI46: 0 | CM46: Tower | CN46: 0 | CQ46: Tower | CR46: 0 | CU46: Tower | CV46: 0 | CY46: Tower | CZ46: 0 | DC46: Tower | DD46: 0 | DG46: Tower | DH46: 0 | DK46: Tower | DL46: 0 | DO46: Tower | DP46: 0
G47: 705400 | L47: 28900 | Q47: 177800 | V47: 99700 | Z47: 39600 | AD47: 28900 | AH47: 177800 | AP47: 42500 | AT47: 29200 | AZ47: 200800 | BE47: 8800 | BJ47: 39200 | BP47: 32900 | BW47: 353400 | CC47: 9400 | CI47: 11700 | CN47: 12500 | CR47: 723000 | CV47: 11600 | CZ47: 702700 | DD47: 698200 | DH47: 595900 | DL47: 610000 | DP47: 601300
G48: 51700 | L48: 21600 | Q48: 65300 | V48: 59300 | Z48: 26000 | AD48: 21600 | AH48: 65300 | AL48: 18600 | AP48: 26400 | AT48: 22000 | AZ48: 99000 | BE48: 18600 | BJ48: 26400 | BP48: 22000 | BW48: 146900 | CC48: 18600 | CI48: 18600 | CN48: 18600 | CR48: 54100 | CV48: 18600 | CZ48: 51700 | DD48: 51700 | DH48: 77500 | DL48: 78000 | DP48: 78000
G49: 0 | L49: 0 | Q49: 0 | V49: 0 | Z49: 0 | AD49: 0 | AH49: 0 | AL49: 0 | AP49: 0 | AT49: 0 | AZ49: 0 | BE49: 0 | BJ49: 0 | BP49: 0 | BW49: 0 | CC49: 0 | CI49: 0 | CN49: 0 | CR49: 0 | CV49: 0 | CZ49: 0 | DD49: 0 | DH49: 0 | DL49: 0 | DP49: 0
G50: 672500 | L50: 75200 | Q50: 240400 | V50: 329800 | Z50: 112300 | AD50: 75400 | AH50: 240100 | AL50: 127900 | AP50: 126900 | AT50: 78000 | AZ50: 480500 | BE50: 131600 | BJ50: 123500 | BP50: 115200 | BW50: 733900 | CC50: 138400 | CI50: 23000 | CN50: 30700 | CR50: 719900 | CV50: 23200 | CZ50: 688300 | DD50: 675800 | DH50: 2546900 | DL50: 2422600 | DP50: 3408200
G51: 30100 | L51: 6300 | Q51: 13600 | V51: 12300 | Z51: 7000 | AD51: 6300 | AH51: 13500 | AL51: 5000 | AP51: 7200 | AT51: 6300 | AZ51: 19200 | BE51: 5000 | BJ51: 7000 | BP51: 6400 | BW51: 32900 | CC51: 5000 | CI51: 5000 | CN51: 5000 | CR51: 30300 | CV51: 5000 | CZ51: 30000 | DD51: 29900 | DH51: 25800 | DL51: 28300 | DP51: 28200
G52: 3612600 | L52: 101200 | Q52: 281500 | V52: 231700 | Z52: 122600 | AD52: 101200 | AH52: 281500 | AL52: 148100 | AP52: 133800 | AT52: 101200 | AZ52: 328000 | BE52: 148100 | BJ52: 133800 | BP52: 122600 | BW52: 432200 | CC52: 169500 | CI52: 35600 | CN52: 56000 | CR52: 4628300 | CV52: 56000 | CZ52: 4195400 | DD52: 4102000 | DH52: 980700 | DL52: 948300 | DP52: 1233100
G53: =SUM(G46:G52) -> 5072300 | L53: =SUM(L46:L52) -> 233200 | Q53: =SUM(Q46:Q52) -> 778600 | V53: =SUM(V46:V52) -> 732800 | Z53: =SUM(Z46:Z52) -> 307500 | AD53: =SUM(AD46:AD52) -> 233400 | AH53: =SUM(AH46:AH52) -> 778200 | AL53: =SUM(AL46:AL52) -> 299600 | AP53: =SUM(AP46:AP52) -> 336800 | AT53: =SUM(AT46:AT52) -> 236700 | AZ53: =SUM(AZ46:AZ52) -> 1127500 | BE53: =SUM(BE46:BE52) -> 312100 | BJ53: =SUM(BJ46:BJ52) -> 329900 | BP53: =SUM(BP46:BP52) -> 299100 | BW53: =SUM(BW46:BW52) -> 1699300 | CC53: =SUM(CC46:CC52) -> 340900 | CI53: =SUM(CI46:CI52) -> 93900 | CN53: =SUM(CN46:CN52) -> 122800 | CR53: =SUM(CR46:CR52) -> 6155600 | CV53: =SUM(CV46:CV52) -> 114400 | CZ53: =SUM(CZ46:CZ52) -> 5668100 | DD53: =SUM(DD46:DD52) -> 5557600 | DH53: =SUM(DH46:DH52) -> 4226800 | DL53: =SUM(DL46:DL52) -> 4087200 | DP53: =SUM(DP46:DP52) -> 5348800
F56: Gcal/hr | G56: -1651.3768 | K56: Gcal/hr | L56: -1225.3657 | P56: Gcal/hr | Q56: -1012.5287 | U56: Gcal/hr | V56: -881.10761 | Y56: Gcal/hr | Z56: -2080.2571 | AC56: Gcal/hr | AD56: -1600.9785 | AG56: Gcal/hr | AH56: -1326.131 | AK56: Gcal/hr | AL56: -1150.7818 | AO56: Gcal/hr | AP56: -2013.7847 | AS56: Gcal/hr | AT56: -1552.1266 | AY56: Gcal/hr | AZ56: -1288.0554 | BD56: Gcal/hr | BE56: -1119.0481 | BI56: Gcal/hr | BJ56: -2069.4042 | BO56: Gcal/hr | BP56: -1594.533 | BV56: Gcal/hr | BW56: -1329.8904 | CB56: Gcal/hr | CC56: -1130.3239 | CH56: Gcal/hr | CI56: -1932.856 | CM56: Gcal/hr | CN56: -1481.1592 | CQ56: Gcal/hr | CR56: -1759.2093 | CU56: Gcal/hr | CV56: -1982.745 | CY56: Gcal/hr | CZ56: -3693.0526 | DC56: Gcal/hr | DD56: -4292.2671 | DG56: Gcal/hr | DH56: -4843.9261 | DK56: Gcal/hr | DL56: -5818.3507 | DO56: Gcal/hr | DP56: -4597.2061
F57: MW | G57: =G56*1000*4.184/3600 -> -1919.2668 | K57: MW | L57: =L56*1000*4.184/3600 -> -1424.1473 | P57: MW | Q57: =Q56*1000*4.184/3600 -> -1176.7833 | U57: MW | V57: =V56*1000*4.184/3600 -> -1024.0428 | Y57: MW | Z57: =Z56*1000*4.184/3600 -> -2417.721 | AC57: MW | AD57: =AD56*1000*4.184/3600 -> -1860.6927 | AG57: MW | AH57: =AH56*1000*4.184/3600 -> -1541.2589 | AK57: MW | AL57: =AL56*1000*4.184/3600 -> -1337.4642 | AO57: MW | AP57: =AP56*1000*4.184/3600 -> -2340.4654 | AS57: MW | AT57: =AT56*1000*4.184/3600 -> -1803.916 | AY57: MW | AZ57: =AZ56*1000*4.184/3600 -> -1497.0066 | BD57: MW | BE57: =BE56*1000*4.184/3600 -> -1300.5825 | BI57: MW | BJ57: =BJ56*1000*4.184/3600 -> -2405.1075 | BO57: MW | BP57: =BP56*1000*4.184/3600 -> -1853.2017 | BV57: MW | BW57: =BW56*1000*4.184/3600 -> -1545.6281 | CB57: MW | CC57: =CC56*1000*4.184/3600 -> -1313.6876 | CH57: MW | CI57: =CI56*1000*4.184/3600 -> -2246.4082 | CM57: MW | CN57: =CN56*1000*4.184/3600 -> -1721.4362 | CQ57: MW | CR57: =CR56*1000*4.184/3600 -> -2044.5921 | CU57: MW | CV57: =CV56*1000*4.184/3600 -> -2304.3903 | CY57: MW | CZ57: =CZ56*1000*4.184/3600 -> -4292.1478 | DC57: MW | DD57: =DD56*1000*4.184/3600 -> -4988.5683 | DG57: MW | DH57: =DH56*1000*4.184/3600 -> -5629.7185 | DK57: MW | DL57: =DL56*1000*4.184/3600 -> -6762.2164 | DO57: MW | DP57: =DP56*1000*4.184/3600 -> -5342.9751
G58: -1919.2668 | L58: -1424.1473 | Q58: -1176.7833 | V58: -1024.0428 | Z58: -2417.721 | AD58: -1860.6927 | AH58: -1541.2589 | AL58: -1337.4642 | AP58: -2340.4654 | AT58: -1803.916 | AZ58: -1497.0066 | BE58: -1300.5825 | BJ58: -2405.1075 | BP58: -1853.2017 | BW58: -1545.6281 | CC58: -1313.6876 | CI58: -2246.4082 | CN58: -1721.4362 | CR58: -2044.5921 | CV58: -2304.3903 | CZ58: -4292.1478 | DD58: -4988.5683 | DH58: -5629.7185 | DL58: -6762.2164 | DP58: -5342.9751
F61: MCOMP2 | G61: 61512900 | H61: 108141.03 | I61: kWh | K61: MCOMP2 | L61: 61512900 | M61: 108141.03 | N61: kWh | P61: MCOMP2 | Q61: 61512900 | R61: 108141.03 | S61: kWh | U61: MCOMP2 | V61: 61512900 | W61: 108141.03 | X61: kWh | Y61: MCOMP2 | Z61: 61512900 | AA61: 108141.03 | AB61: kWh | AC61: MCOMP2 | AD61: 61512900 | AE61: 108141.03 | AF61: kWh | AG61: MCOMP2 | AH61: 61512900 | AI61: 108141.03 | AJ61: kWh | AK61: MCOMP2 | AL61: 61512900 | AM61: 108141.03 | AN61: kWh | AO61: MCOMP2 | AP61: 61512900 | AQ61: 108141.03 | AR61: kWh | AS61: MCOMP2 | AT61: 61512900 | AU61: 108141.03 | AV61: kWh | AY61: MCOMP2 | AZ61: 61512900 | BA61: 108141.03 | BB61: kWh | BD61: MCOMP2 | BE61: 61512900 | BF61: 108141.03 | BG61: kWh | BI61: MCOMP2 | BJ61: 61512900 | BK61: 108141.03 | BL61: kWh | BO61: MCOMP2 | BP61: 61512900 | BQ61: 108141.03 | BR61: kWh | BV61: MCOMP2 | BW61: 61512900 | BX61: 108141.03 | BY61: kWh | CB61: MCOMP2 | CC61: 61512900 | CD61: 108141.03 | CE61: kWh | CH61: MCOMP2 | CI61: 61512900 | CJ61: 108141.03 | CK61: kWh | CM61: MCOMP2 | CN61: 61512900 | CO61: 108141.03 | CP61: kWh | CQ61: MCOMP2 | CR61: 61512900 | CS61: 108141.03 | CT61: kWh | CU61: MCOMP2 | CV61: 61512900 | CW61: 108141.03 | CX61: kWh | CY61: MCOMP2 | CZ61: 61512900 | DA61: 108141.03 | DB61: kWh | DC61: MCOMP2 | DD61: 61512900 | DE61: 108141.03 | DF61: kWh | DG61: MCOMP2 | DH61: 61512900 | DI61: 108141.03 | DJ61: kWh | DK61: MCOMP2 | DL61: 61512900 | DM61: 108141.03 | DN61: kWh | DO61: MCOMP2 | DP61: 61512900 | DQ61: 108141.03 | DR61: kWh
B65: PURCHASED EQUIPMENT COST ($) | F65: Case 1 (Base) | K65: Case 2 (Base) | P65: Case 3 (Base) | U65: Case 4 (Base) | Y65: Case 1 (Base w CCS) | AC65: Case 2 (Base w CCS) | AG65: Case 3 (Base w CCS) | AK65: Case 4 (Base w CCS) | AO65: Case 1 (E-furnace) | AS65: Case 2 (E-furnace) | AY65: Case 3 (E-furnace) | BD65: Case 4 (E-furnace) | BI65: Case 1 (E-furnace w CCS) | BO65: Case 2 (E-furnace w CCS) | BV65: Case 3 (E-furnace w CCS) | CB65: Case 4 (E-furnace w CCS) | CH65: Case 17: FH_H2/CH4 1.22 at 1230 | CM65: Case 18: FH_H2/CH4 1.22 at 1230 | CQ65: Case 19: FH_H2/CH4 1.22 at 1230 | CU65: Case 20: FH_H2/CH4 1.22 at 1230 | CY65: Case 21: FH_H2/CH4 1.22 at 1230 | DC65: Case 22: FH_H2/CH4 1.22 at 1230 | DG65: Case 23: FH_H2/CH4 1.22 at 1230 | DK65: Case 24: FH_H2/CH4 1.22 at 1230 | DO65: Case 25: FH_H2/CH4 1.22 at 1230
C66: Purchased equipment cost ($) | G66: Purchased equipment cost ($) | L66: Purchased equipment cost ($) | Q66: Purchased equipment cost ($) | V66: Purchased equipment cost ($) | Z66: Purchased equipment cost ($) | AD66: Purchased equipment cost ($) | AH66: Purchased equipment cost ($) | AL66: Purchased equipment cost ($) | AP66: Purchased equipment cost ($) | AT66: Purchased equipment cost ($) | AZ66: Purchased equipment cost ($) | BE66: Purchased equipment cost ($) | BJ66: Purchased equipment cost ($) | BP66: Purchased equipment cost ($) | BW66: Purchased equipment cost ($) | CC66: Purchased equipment cost ($) | CI66: Purchased equipment cost ($) | CN66: Purchased equipment cost ($) | CR66: Purchased equipment cost ($) | CV66: Purchased equipment cost ($) | CZ66: Purchased equipment cost ($) | DD66: Purchased equipment cost ($) | DH66: Purchased equipment cost ($) | DL66: Purchased equipment cost ($) | DP66: Purchased equipment cost ($)
B67: Reactor (R1+E1)_1245MW | C67: 1.850693e+08 | F67: Reactor | K67: Reactor | P67: Reactor | U67: Reactor | Y67: Reactor | AC67: Reactor | AG67: Reactor | AK67: Reactor | AO67: Reactor | AS67: Reactor | AY67: Reactor | BD67: Reactor | BI67: Reactor | BO67: Reactor | BV67: Reactor | CB67: Reactor | CH67: Reactor | CM67: Reactor | CQ67: Reactor | CU67: Reactor | CY67: Reactor | DC67: Reactor | DG67: Reactor | DK67: Reactor | DO67: Reactor
B68: Compressor | D68: 875439.42 | E68: kW | F68: R1 (-2418MW) | G68: =100.38*10^6*(2417.72099468889/500)^0.67 -> 2.885489e+08 | K68: R1 (-1880 MW) | L68: 2.4211367e+08 | P68: R1 (-1541 MW) | Q68: 2.134096e+08 | U68: R1 (-1337 MW) | V68: 1.9406461e+08 | Y68: R1 (-2418MW) | Z68: 2.885489e+08 | AC68: R1 (-1880 MW) | AD68: 2.4211367e+08 | AG68: R1 (-1541 MW) | AH68: 2.134096e+08 | AK68: R1 (-1337 MW) | AL68: 1.9406461e+08 | AO68: R1 (-2418MW) | AP68: =(2418/3*1.7/5.04)*10^6*1.2 -> 3.262381e+08 | AS68: R1 (-1880 MW) | AT68: =(1880/3*1.7/5.04)*10^6*1.2 -> 2.5365079e+08 | AY68: R1 (-1541 MW) | AZ68: =(1541/3*1.7/5.04)*10^6*1.2 -> 2.079127e+08 | BD68: R1 (-1337 MW) | BE68: =(1337/3*1.7/5.04)*10^6*1.2 -> 1.8038889e+08 | BI68: R1 (-2418MW) | BJ68: 3.262381e+08 | BO68: R1 (-1880 MW) | BP68: 2.5365079e+08 | BV68: R1 (-1541 MW) | BW68: 2.079127e+08 | CB68: R1 (-1337 MW) | CC68: 1.8038889e+08 | CH68: R1 (-2246 MW) | CI68: =100.38*10^6*(2246.40816068889/500)^0.67 -> 2.7468484e+08 | CM68: R1 (-1721 MW) | CN68: =100.38*10^6*(1721.436195/500)^0.67 -> 2.2981809e+08 | CQ68: R1 (-2045 MW) | CR68: =100.38*10^6*(2044.59211875556/500)^0.67 -> 2.578955e+08 | CU68: R1 (-2304 MW) | CV68: =100.38*10^6*(2304.3903/500)^0.67 -> 2.7941508e+08 | CY68: R1 (-4292 MW) | CZ68: =100.38*10^6*(4292.1478228/500)^0.67 -> 4.2386672e+08 | DC68: R1 (-4989 MW) | DD68: =100.38*10^6*(4988.56826544444/500)^0.67 -> 4.6879304e+08 | DG68: R1 (-5630 MW) | DH68: =100.38*10^6*(5629.7185446/500)^0.67 -> 5.0835063e+08 | DK68: R1 (-6762 MW) | DL68: =100.38*10^6*(6762.21644535556/500)^0.67 -> 5.747738e+08 | DO68: R1 (-5343 MW) | DP68: =100.38*10^6*(5342.97513604445/500)^0.67 -> 4.9085362e+08
B69: MCOMP1 | C69: =C70*(D68/D69)^0.67 -> 2.1369083e+08 | D69: 82185.917 | E69: kW | F69: Compressor | K69: Compressor | P69: Compressor | U69: Compressor | Y69: Compressor | AC69: Compressor | AG69: Compressor | AK69: Compressor | AO69: Compressor | AS69: Compressor | AY69: Compressor | BD69: Compressor | BI69: Compressor | BO69: Compressor | BV69: Compressor | CB69: Compressor | CH69: Compressor | CM69: Compressor | CQ69: Compressor | CU69: Compressor | CY69: Compressor | DC69: Compressor | DG69: Compressor | DK69: Compressor | DO69: Compressor
B70: MCOMP2 | C70: 43793400 | F70: MCOMP1 | G70: 2.4651445e+08 | H70: 858988.46 | I70: kWh | K70: MCOMP1 | L70: 1.7857748e+08 | M70: 525710.9 | N70: kWh | P70: MCOMP1 | Q70: 1.1379208e+08 | R70: 274593.02 | S70: kWh | U70: MCOMP1 | V70: 73204042 | W70: 139977.95 | X70: kWh | Y70: MCOMP1 | Z70: 2.4651445e+08 | AA70: 858988.46 | AC70: MCOMP1 | AD70: 1.7857748e+08 | AE70: 525710.9 | AG70: MCOMP1 | AH70: 1.1379208e+08 | AI70: 274593.02 | AK70: MCOMP1 | AL70: 73204042 | AM70: 139977.95 | AO70: MCOMP1 | AP70: 2.4651445e+08 | AQ70: 858988.46 | AS70: MCOMP1 | AT70: 1.7857748e+08 | AU70: 525710.9 | AY70: MCOMP1 | AZ70: 1.1379208e+08 | BA70: 274593.02 | BD70: MCOMP1 | BE70: 73204042 | BF70: 139977.95 | BI70: MCOMP1 | BJ70: 2.4651445e+08 | BK70: 858988.46 | BO70: MCOMP1 | BP70: 1.7857748e+08 | BQ70: 525710.9 | BV70: MCOMP1 | BW70: 1.1379208e+08 | BX70: 274593.02 | CB70: MCOMP1 | CC70: 73204042 | CD70: 139977.95 | CH70: MCOMP1 | CI70: =CI61*(CJ70/CJ61)^(0.67) -> 2.9476903e+08 | CJ70: 1121206.2 | CM70: MCOMP1 | CN70: =CN61*(CO70/CO61)^(0.67) -> 2.4702652e+08 | CO70: 861292.68 | CQ70: MCOMP1 | CR70: =CR61*(CS70/CS61)^(0.67) -> 2.7246406e+08 | CS70: 996968.8 | CU70: MCOMP1 | CV70: =CV61*(CW70/CW61)^(0.67) -> 2.9735143e+08 | CW70: 1135898.4 | CY70: MCOMP1 | CZ70: =CZ61*(DA70/DA61)^(0.67) -> 4.8273513e+08 | DA70: 2341139.8 | DC70: MCOMP1 | DD70: =DD61*(DE70/DE61)^(0.67) -> 5.3919762e+08 | DE70: 2761388.1 | DG70: MCOMP1 | DH70: =DH61*(DI70/DI61)^(0.67) -> 5.8436123e+08 | DI70: 3113629.2 | DK70: MCOMP1 | DL70: =DL61*(DM70/DM61)^(0.67) -> 6.891753e+08 | DM70: 3982948.3 | DO70: MCOMP1 | DP70: =DP61*(DQ70/DQ61)^(0.67) -> 5.8445933e+08 | DQ70: 3114409.4
B71: Flash tank | F71: MCOMP2 | G71: 63542400 | H71: 150168.72 | I71: kWh | K71: MCOMP2 | L71: 63540800 | M71: 250558.13 | N71: kWh | P71: MCOMP2 | Q71: 1.0584086e+08 | R71: 243677.03 | S71: kWh | U71: MCOMP2 | V71: 1.0820022e+08 | W71: 250761.09 | X71: kWh | Y71: MCOMP2 | Z71: 63542400 | AA71: 150168.72 | AC71: MCOMP2 | AD71: 63540800 | AE71: 250558.13 | AG71: MCOMP2 | AH71: 1.0584086e+08 | AI71: 243677.03 | AK71: MCOMP2 | AL71: 1.0820022e+08 | AM71: 250761.09 | AO71: MCOMP2 | AP71: 63542400 | AQ71: 150168.72 | AS71: MCOMP2 | AT71: 63540800 | AU71: 250558.13 | AY71: MCOMP2 | AZ71: 1.0584086e+08 | BA71: 243677.03 | BD71: MCOMP2 | BE71: 1.0820022e+08 | BF71: 250761.09 | BI71: MCOMP2 | BJ71: 63542400 | BK71: 150168.72 | BO71: MCOMP2 | BP71: 63540800 | BQ71: 250558.13 | BV71: MCOMP2 | BW71: 1.0584086e+08 | BX71: 243677.03 | CB71: MCOMP2 | CC71: 1.0820022e+08 | CD71: 250761.09 | CH71: MCOMP2 | CI71: 63543600 | CJ71: 145401.12 | CM71: MCOMP2 | CN71: 57812200 | CO71: 111662.07 | CQ71: MCOMP2 | CR71: 57812200 | CS71: 129245.99 | CU71: MCOMP2 | CV71: 57812600 | CW71: 147252.26 | CY71: MCOMP2 | CZ71: =CZ61*(DA71/DA61)^(0.67) -> 1.2283332e+08 | DA71: 303580.63 | DC71: MCOMP2 | DD71: =DD61*(DE71/DE61)^(0.67) -> 1.3719935e+08 | DE71: 358071.17 | DG71: MCOMP2 | DH71: =DH61*(DI71/DI61)^(0.67) -> 1.4868529e+08 | DI71: 403722.3 | DK71: MCOMP2 | DL71: =DL61*(DM71/DM61)^(0.67) -> 1.7536109e+08 | DM71: 516470.8 | DO71: MCOMP2 | DP71: =DP61*(DQ71/DQ61)^(0.67) -> 1.4869598e+08 | DQ71: 403765.61
B72: V1 | C72: 1476700 | F72: Flash tank | K72: Flash tank | P72: Flash tank | U72: Flash tank | Y72: Flash tank | AC72: Flash tank | AG72: Flash tank | AK72: Flash tank | AO72: Flash tank | AS72: Flash tank | AY72: Flash tank | BD72: Flash tank | BI72: Flash tank | BO72: Flash tank | BV72: Flash tank | CB72: Flash tank | CH72: Flash tank | CM72: Flash tank | CQ72: Flash tank | CU72: Flash tank | CY72: Flash tank | DC72: Flash tank | DG72: Flash tank | DK72: Flash tank | DO72: Flash tank
B73: V2 | C73: 1090800 | F73: V5-flash vessel | G73: 630000 | K73: V1 | L73: 460200 | P73: V1 | Q73: 301300 | U73: V5-flash vessel | V73: 178900 | Y73: V5-flash vessel | Z73: 630000 | AC73: V1 | AD73: 460200 | AG73: V1 | AH73: 301300 | AK73: V5-flash vessel | AL73: 178900 | AO73: V5-flash vessel | AP73: 630000 | AS73: V1 | AT73: 460200 | AY73: V1 | AZ73: 301300 | BD73: V5-flash vessel | BE73: 178900 | BI73: V5-flash vessel | BJ73: 630000 | BO73: V1 | BP73: 460200 | BV73: V1 | BW73: 301300 | CB73: V5-flash vessel | CC73: 178900 | CH73: V5-flash vessel | CI73: 913600 | CM73: V5-flash vessel | CN73: 701000 | CQ73: V5-flash vessel | CR73: 835200 | CU73: V5-flash vessel | CV73: 937100 | CY73: V5-flash vessel | CZ73: 2203100 | DC73: V5-flash vessel | DD73: 2614800 | DG73: V5-flash vessel | DH73: 3033200
B74: V3 | C74: 949500 | F74: V4-flash vessel | G74: 788700 | K74: V2 | L74: 588700 | P74: V2 | Q74: 469400 | U74: V4-flash vessel | V74: 472400 | Y74: V4-flash vessel | Z74: 788700 | AC74: V2 | AD74: 588700 | AG74: V2 | AH74: 469400 | AK74: V4-flash vessel | AL74: 472400 | AO74: V4-flash vessel | AP74: 788700 | AS74: V2 | AT74: 588700 | AY74: V2 | AZ74: 469400 | BD74: V4-flash vessel | BE74: 472400 | BI74: V4-flash vessel | BJ74: 788700 | BO74: V2 | BP74: 588700 | BV74: V2 | BW74: 469400 | CB74: V4-flash vessel | CC74: 472400 | CH74: V4-flash vessel | CI74: 1099300 | CM74: V4-flash vessel | CN74: 925800 | CQ74: V4-flash vessel | CR74: 1105500 | CU74: V4-flash vessel | CV74: 1280100 | CY74: V4-flash vessel | CZ74: 3167000 | DC74: V4-flash vessel | DD74: 4007800 | DG74: V4-flash vessel | DH74: 4799400 | DK74: V2 | DL74: =DL75*(DM74/DM75)^0.67 -> 2809442.3 | DM74: -10.010416 | DO74: V5-flash vessel | DP74: 2600600 | DQ74: -25.547288
B75: V4 | C75: 444700 | F75: V3-flash vessel | G75: 1325800 | K75: V3 | L75: 955800 | P75: V3 | Q75: 757100 | U75: V3-flash vessel | V75: 660300 | Y75: V3-flash vessel | Z75: 1325800 | AC75: V3 | AD75: 955800 | AG75: V3 | AH75: 757100 | AK75: V3-flash vessel | AL75: 660300 | AO75: V3-flash vessel | AP75: 1325800 | AS75: V3 | AT75: 955800 | AY75: V3 | AZ75: 757100 | BD75: V3-flash vessel | BE75: 660300 | BI75: V3-flash vessel | BJ75: 1325800 | BO75: V3 | BP75: 955800 | BV75: V3 | BW75: 757100 | CB75: V3-flash vessel | CC75: 660300 | CH75: V3-flash vessel | CI75: 1879700 | CM75: V3-flash vessel | CN75: 1456500 | CQ75: V3-flash vessel | CR75: 1768500 | CU75: V3-flash vessel | CV75: 2090500 | CY75: V3-flash vessel | CZ75: 4302400 | DC75: V3-flash vessel | DD75: 5481000 | DG75: V3-flash vessel | DH75: 6423100 | DK75: V3 | DL75: 8594700 | DM75: -53.118291 | DO75: V4-flash vessel | DP75: 4656900
B76: V5 | C76: 443200 | F76: V2-flash vessel | G76: 1456500 | K76: V4 | L76: 1099300 | P76: V4 | Q76: 900300 | U76: V2-flash vessel | V76: 757100 | Y76: V2-flash vessel | Z76: 1456500 | AC76: V4 | AD76: 1099300 | AG76: V4 | AH76: 900300 | AK76: V2-flash vessel | AL76: 757100 | AO76: V2-flash vessel | AP76: 1456500 | AS76: V4 | AT76: 1099300 | AY76: V4 | AZ76: 900300 | BD76: V2-flash vessel | BE76: 757100 | BI76: V2-flash vessel | BJ76: 1456500 | BO76: V4 | BP76: 1099300 | BV76: V4 | BW76: 900300 | CB76: V2-flash vessel | CC76: 757100 | CH76: V2-flash vessel | CI76: 1989700 | CM76: V2-flash vessel | CN76: 1596600 | CQ76: V2-flash vessel | CR76: 1924300 | CU76: V2-flash vessel | CV76: 2225900 | CY76: V2-flash vessel | CZ76: 5068700 | DC76: V2-flash vessel | DD76: 6305900 | DG76: V2-flash vessel | DH76: 7518400 | DK76: V4 | DL76: 7039000 | DO76: V3-flash vessel | DP76: 6742500
B77: Columns | F77: V1-flash vessel | G77: 1989700 | K77: V5 | L77: 1989700 | P77: V5 | Q77: 2297400 | U77: V1-flash vessel | V77: 2679100 | Y77: V1-flash vessel | Z77: 1989700 | AC77: V5 | AD77: 1989700 | AG77: V5 | AH77: 2297400 | AK77: V1-flash vessel | AL77: 2679100 | AO77: V1-flash vessel | AP77: 1989700 | AS77: V5 | AT77: 1989700 | AY77: V5 | AZ77: 2297400 | BD77: V1-flash vessel | BE77: 2679100 | BI77: V1-flash vessel | BJ77: 1989700 | BO77: V5 | BP77: 1989700 | BV77: V5 | BW77: 2297400 | CB77: V1-flash vessel | CC77: 2679100 | CH77: V1-flash vessel | CI77: 2775100 | CM77: V1-flash vessel | CN77: 2173100 | CQ77: V1-flash vessel | CR77: 2679100 | CU77: V1-flash vessel | CV77: 3090200 | CY77: V1-flash vessel | CZ77: 7039000 | DC77: V1-flash vessel | DD77: 8818500 | DK77: V5 | DL77: 4158400 | DM77: -326.65199 | DO77: V2-flash vessel | DP77: 7770100
B78: T1 | C78: 125300 | F78: Columns | K78: Columns | P78: Columns | U78: Columns | Y78: Columns | AC78: Columns | AG78: Columns | AK78: Columns | AO78: Columns | AS78: Columns | AY78: Columns | BD78: Columns | BI78: Columns | BO78: Columns | BV78: Columns | CB78: Columns | CH78: Columns | CM78: Columns | CQ78: Columns | CU78: Columns | CY78: Columns | DC78: Columns | DG78: Columns | DK78: Columns | DO78: Columns
B79: T2 | C79: 1031800 | F79: T1 | G79: 307500 | K79: T1 | L79: 233400 | P79: T1 | Q79: 778200 | U79: T1 | V79: 299600 | Y79: T1 | Z79: 307500 | AC79: T1 | AD79: 233400 | AG79: T1 | AH79: 778200 | AK79: T1 | AL79: 299600 | AO79: T1 | AP79: 307500 | AS79: T1 | AT79: 233400 | AY79: T1 | AZ79: 778200 | BD79: T1 | BE79: 299600 | BI79: T1 | BJ79: 307500 | BO79: T1 | BP79: 233400 | BV79: T1 | BW79: 778200 | CB79: T1 | CC79: 299600 | CH79: T1 | CI79: 93900 | CM79: T1 | CN79: 122800 | CQ79: T1 | CR79: 122300 | CU79: T1 | CV79: 114400 | CY79: T1 | CZ79: 73000 | DC79: T1 | DD79: 87600
B80: T3 | C80: 3547200 | F80: T2 | G80: 3715200 | K80: T2 | L80: 1278200 | P80: T2 | Q80: 2108400 | U80: T2 | V80: 3487500 | Y80: T2 | Z80: 3715200 | AC80: T2 | AD80: 1278200 | AG80: T2 | AH80: 2108400 | AK80: T2 | AL80: 3487500 | AO80: T2 | AP80: 3715200 | AS80: T2 | AT80: 1278200 | AY80: T2 | AZ80: 2108400 | BD80: T2 | BE80: 3487500 | BI80: T2 | BJ80: 3715200 | BO80: T2 | BP80: 1278200 | BV80: T2 | BW80: 2108400 | CB80: T2 | CC80: 3487500 | CH80: T2 | CI80: 3446200 | CM80: T2 | CN80: 3540200 | CQ80: T2 | CR80: 3787500 | CU80: T2 | CV80: 4037900 | CY80: T2 | CZ80: 3707500 | DC80: T2 | DD80: 3750900 | DG80: T2 | DH80: 4226800 | DK80: T2 | DL80: 4087200 | DO80: T2 | DP80: 5348800
B81: Heat exchanger, heater, cooler | F81: T3 | G81: 5087200 | K81: T3 | L81: 4754300 | P81: T3 | Q81: 4613900 | U81: T3 | V81: 5039300 | Y81: T3 | Z81: 5087200 | AC81: T3 | AD81: 4754300 | AG81: T3 | AH81: 4613900 | AK81: T3 | AL81: 5039300 | AO81: T3 | AP81: 5087200 | AS81: T3 | AT81: 4754300 | AY81: T3 | AZ81: 4613900 | BD81: T3 | BE81: 5039300 | BI81: T3 | BJ81: 5087200 | BO81: T3 | BP81: 4754300 | BV81: T3 | BW81: 4613900 | CB81: T3 | CC81: 5039300 | CH81: T3 | CI81: 5899000 | CM81: T3 | CN81: 4688900 | CQ81: T3 | CR81: 6155600 | CU81: T3 | CV81: 6155500 | CY81: T3 | CZ81: 5668100 | DC81: T3 | DD81: 5557600 | DG81: T3 | DH81: 5567800 | DK81: T3 | DL81: 5236000 | DO81: T3 | DP81: 5384200
B82: E2 | C82: 12850900 | F82: Heat exchanger, heater, cooler | K82: Heat exchanger, heater, cooler | P82: Heat exchanger, heater, cooler | U82: Heat exchanger, heater, cooler | Y82: Heat exchanger, heater, cooler | AC82: Heat exchanger, heater, cooler | AG82: Heat exchanger, heater, cooler | AK82: Heat exchanger, heater, cooler | AO82: Heat exchanger, heater, cooler | AS82: Heat exchanger, heater, cooler | AY82: Heat exchanger, heater, cooler | BD82: Heat exchanger, heater, cooler | BI82: Heat exchanger, heater, cooler | BO82: Heat exchanger, heater, cooler | BV82: Heat exchanger, heater, cooler | CB82: Heat exchanger, heater, cooler | CH82: Heat exchanger, heater, cooler | CM82: Heat exchanger, heater, cooler | CQ82: Heat exchanger, heater, cooler | CU82: Heat exchanger, heater, cooler | CY82: Heat exchanger, heater, cooler | DC82: Heat exchanger, heater, cooler | DG82: Heat exchanger, heater, cooler | DK82: Heat exchanger, heater, cooler | DO82: Heat exchanger, heater, cooler
B83: E3 | C83: 4429400 | F83: MHX1 | G83: 2093500 | K83: MHX1 | L83: 1932500 | P83: MHX1 | Q83: 1416600 | R83: -53.451566 | S83: kW | U83: MHX1 | V83: 1240100 | W83: -115.87499 | X83: kW | Y83: MHX1 | Z83: 2093500 | AC83: MHX1 | AD83: 1932500 | AG83: MHX1 | AH83: 1416600 | AI83: -53.451566 | AK83: MHX1 | AL83: 1240100 | AM83: -115.87499 | AO83: MHX1 | AP83: 2093500 | AS83: MHX1 | AT83: 1932500 | AY83: MHX1 | AZ83: 1416600 | BA83: -53.451566 | BD83: MHX1 | BE83: 1240100 | BF83: -115.87499 | BI83: MHX1 | BJ83: 2093500 | BO83: MHX1 | BP83: 1932500 | BV83: MHX1 | BW83: 1416600 | BX83: -53.451566 | CB83: MHX1 | CC83: 1240100 | CD83: -115.87499 | CH83: MHX1 | CI83: 4877800 | CM83: MHX1 | CN83: 4134300 | CQ83: MHX1 | CR83: 4958600 | CU83: MHX1 | CV83: 3024800 | CY83: MHX1 | CZ83: 12003700 | DA83: -131.79956 | DC83: MHX1 | DD83: 7421900 | DG83: MHX1 | DH83: 8965000 | DK83: MHX1 | DL83: 11237200 | DO83: MHX1 | DP83: 9891600
B84: E4 | C84: 8613900 | F84: MHX2 | G84: 2635300 | K84: MHX2 | L84: 4146300 | M84: -276.36945 | P84: MHX2 | Q84: 2988800 | R84: -126.70453 | S84: kW | U84: MHX2 | V84: 8424800 | W84: -263.60946 | X84: kW | Y84: MHX2 | Z84: 2635300 | AC84: MHX2 | AD84: 4146300 | AE84: -276.36945 | AG84: MHX2 | AH84: 2988800 | AI84: -126.70453 | AK84: MHX2 | AL84: 8424800 | AM84: -263.60946 | AO84: MHX2 | AP84: 2635300 | AS84: MHX2 | AT84: 4146300 | AU84: -276.36945 | AY84: MHX2 | AZ84: 2988800 | BA84: -126.70453 | BD84: MHX2 | BE84: 8424800 | BF84: -263.60946 | BI84: MHX2 | BJ84: 2635300 | BO84: MHX2 | BP84: 4146300 | BQ84: -276.36945 | BV84: MHX2 | BW84: 2988800 | BX84: -126.70453 | CB84: MHX2 | CC84: 8424800 | CD84: -263.60946 | CH84: MHX2 | CI84: 8697400 | CM84: MHX2 | CN84: 6378400 | CQ84: MHX2 | CR84: 7534200 | CU84: MHX2 | CV84: 2114100 | CY84: MHX2 | CZ84: =CZ83*(DA84/DA83)^0.67 -> 22282987 | DA84: -331.81533 | DC84: MHX2 | DD84: 5531800 | DG84: MHX2 | DH84: 6216000 | DK84: MHX2 | DL84: 8065500 | DO84: MHX2 | DP84: 5991400
B85: HX1 | C85: 122541.25 | F85: MHX3 | G85: 5702000 | K85: MHX3 | L85: 2483300 | M85: -104.1118 | P85: MHX3 | Q85: 2171700 | U85: MHX3 | V85: 1911000 | Y85: MHX3 | Z85: 5702000 | AC85: MHX3 | AD85: 2483300 | AE85: -104.1118 | AG85: MHX3 | AH85: 2171700 | AK85: MHX3 | AL85: 1911000 | AO85: MHX3 | AP85: 5702000 | AS85: MHX3 | AT85: 2483300 | AU85: -104.1118 | AY85: MHX3 | AZ85: 2171700 | BD85: MHX3 | BE85: 1911000 | BI85: MHX3 | BJ85: 5702000 | BO85: MHX3 | BP85: 2483300 | BQ85: -104.1118 | BV85: MHX3 | BW85: 2171700 | CB85: MHX3 | CC85: 1911000 | CH85: MHX3 | CI85: 3603700 | CM85: MHX3 | CN85: 2536600 | CQ85: MHX3 | CR85: 2988200 | CU85: MHX3 | CV85: 4222200 | CY85: MHX3 | CZ85: 7877300 | DC85: MHX3 | DD85: 11337900 | DG85: MHX3 | DH85: 14041000 | DK85: MHX3 | DL85: =DL86*(DM85/DM86)^0.67 -> 11706241 | DM85: -486.16292 | DO85: MHX3 | DP85: 13690200
B86: HX2 | C86: 110944.4 | F86: MHX4 | G86: 3370200 | K86: HX9 | L86: 305000 | P86: HX9 | Q86: 183600 | U86: HX9 | V86: 114300 | Y86: MHX4 | Z86: 3370200 | AC86: HX9 | AD86: 305000 | AG86: HX9 | AH86: 183600 | AK86: HX9 | AL86: 114300 | AO86: MHX4 | AP86: 3370200 | AS86: HX9 | AT86: 305000 | AY86: HX9 | AZ86: 183600 | BD86: HX9 | BE86: 114300 | BI86: MHX4 | BJ86: 3370200 | BO86: HX9 | BP86: 305000 | BV86: HX9 | BW86: 183600 | CB86: HX9 | CC86: 114300 | CH86: HX9 | CI86: 3017000 | CM86: HX9 | CN86: 2043600 | CQ86: HX9 | CR86: 2355700 | CU86: HX9 | CV86: 2453800 | CY86: HX9 | CZ86: 6170800 | DC86: HX9 | DD86: 6526200 | DG86: HX9 | DH86: 7232200 | DK86: HX9 | DL86: 9457500 | DM86: -353.59939 | DO86: HX9 | DP86: 6919200
B87: HX3 | C87: 1865400 | F87: HX1 | G87: 4381735.6 | H87: 1452.739 | I87: Gcal/hr | K87: HX1 | L87: 3536318.4 | M87: 1122.9256 | N87: Gcal/hr | P87: HX1 | Q87: 3964182.1 | R87: 896.35085 | S87: Gcal/hr | U87: HX1 | V87: 3396885.7 | W87: 700.81668 | X87: Gcal/hr | Y87: HX1 | Z87: 4381735.6 | AA87: 1452.739 | AC87: HX1 | AD87: 3536318.4 | AE87: 1122.9256 | AG87: HX1 | AH87: 3964182.1 | AI87: 896.35085 | AK87: HX1 | AL87: 3396885.7 | AM87: 700.81668 | AO87: HX1 | AP87: 4381735.6 | AQ87: 1452.739 | AS87: HX1 | AT87: 3536318.4 | AU87: 1122.9256 | AY87: HX1 | AZ87: 3964182.1 | BA87: 896.35085 | BD87: HX1 | BE87: 3396885.7 | BF87: 700.81668 | BI87: HX1 | BJ87: 4381735.6 | BK87: 1452.739 | BO87: HX1 | BP87: 3536318.4 | BQ87: 1122.9256 | BV87: HX1 | BW87: 3964182.1 | BX87: 896.35085 | CB87: HX1 | CC87: 3396885.7 | CD87: 700.81668 | CH87: HX1 | CI87: =CI88*(CJ87/CJ88)^0.67 -> 6902351.9 | CJ87: 2094.2269 | CM87: HX1 | CN87: =CN88*(CO87/CO88)^0.67 -> 5161560.1 | CO87: 1693.5938 | CQ87: HX1 | CR87: =CR88*(CS87/CS88)^0.67 -> 5478541.2 | CS87: 1898.3671 | CU87: HX1 | CV87: =CV88*(CW87/CW88)^0.67 -> 7115200.9 | CW87: 2127.6864 | CY87: HX1 | CZ87: =CZ88*(DA87/DA88)^0.67 -> 65767125 | DA87: 4586.6105 | DC87: HX1 | DD87: =DD89*(DE87/DE89)^0.67 -> 22073924 | DE87: 4733.6485 | DG87: HX1 | DH87: =DH89*(DI87/DI89)^0.67 -> 24324689 | DI87: 5313.1293 | DK87: HX1 | DL87: =DL89*(DM87/DM89)^0.67 -> 30574565 | DM87: 6357.6216 | DO87: HX1 | DP87: =DP89*(DQ87/DQ89)^0.67 -> 28956783 | DQ87: 5207.9256
B88: HX4 | C88: 409400 | D88: 60867.667 | F88: HX-HPS | G88: 115200 | H88: 3.8330255 | I88: Gcal/hr | K88: HX-HPS | L88: 104200 | M88: 3.356047 | N88: Gcal/hr | P88: HX-HPS | Q88: 329200 | R88: 12.227892 | S88: Gcal/hr | U88: HX-HPS | V88: 152000 | W88: 10.988836 | X88: Gcal/hr | Y88: HX-HPS | Z88: 115200 | AA88: 3.8330255 | AC88: HX-HPS | AD88: 104200 | AE88: 3.356047 | AG88: HX-HPS | AH88: 329200 | AI88: 12.227892 | AK88: HX-HPS | AL88: 152000 | AM88: 10.988836 | AO88: HX-HPS | AP88: 115200 | AQ88: 3.8330255 | AS88: HX-HPS | AT88: 104200 | AU88: 3.356047 | AY88: HX-HPS | AZ88: 329200 | BA88: 12.227892 | BD88: HX-HPS | BE88: 152000 | BF88: 10.988836 | BI88: HX-HPS | BJ88: 115200 | BK88: 3.8330255 | BO88: HX-HPS | BP88: 104200 | BQ88: 3.356047 | BV88: HX-HPS | BW88: 329200 | BX88: 12.227892 | CB88: HX-HPS | CC88: 152000 | CD88: 10.988836 | CH88: HX-HPS | CI88: 21200 | CJ88: 0.37220575 | CM88: HX-HPS | CN88: 27100 | CO88: 0.67004693 | CQ88: HX-HPS | CR88: 24100 | CS88: 0.57676021 | CU88: HX-HPS | CV88: 23300 | CW88: 0.41610627 | CY88: HX-HPS | CZ88: 11300 | DA88: 0.011020283 | DC88: HX-HPS | DD88: 10400 | DG88: HX-HPS | DI88: 1822.6855 | DK88: HX-HPS | DM88: 1822.6855 | DO88: HX-HPS | DQ88: 1822.6855
B89: HX5 | C89: 475200 | D89: 4312.9738 | F89: HX-LPS1 | G89: 911500 | K89: HX-LPS1 | L89: 756900 | P89: HX-LPS1 | Q89: 796500 | U89: HX-LPS1 | V89: 803700 | Y89: HX-LPS1 | Z89: 911500 | AC89: HX-LPS1 | AD89: 756900 | AG89: HX-LPS1 | AH89: 796500 | AK89: HX-LPS1 | AL89: 803700 | AO89: HX-LPS1 | AP89: 911500 | AS89: HX-LPS1 | AT89: 756900 | AY89: HX-LPS1 | AZ89: 796500 | BD89: HX-LPS1 | BE89: 803700 | BI89: HX-LPS1 | BJ89: 911500 | BO89: HX-LPS1 | BP89: 756900 | BV89: HX-LPS1 | BW89: 796500 | CB89: HX-LPS1 | CC89: 803700 | CH89: HX-LPS1 | CI89: 900700 | CM89: HX-LPS1 | CN89: 964600 | CQ89: HX-LPS1 | CR89: 1047600 | CU89: HX-LPS1 | CV89: 1207500 | CY89: HX-LPS1 | CZ89: 1289400 | DC89: HX-LPS1 | DD89: 1149800 | DE89: 57.528982 | DG89: HX-LPS1 | DH89: 1301800 | DI89: 67.233339 | DK89: HX-LPS1 | DL89: 1392900 | DM89: 63.262287 | DO89: HX-LPS1 | DP89: 1908900 | DQ89: 89.955402
B90: HX6 | C90: 801700 | D90: 11415.992 | F90: HX-LPS2 | G90: 1403000 | K90: HX-LPS2 | L90: 605000 | P90: HX-LPS2 | Q90: 984600 | U90: HX-LPS2 | V90: 1535100 | Y90: HX-LPS2 | Z90: 1403000 | AC90: HX-LPS2 | AD90: 605000 | AG90: HX-LPS2 | AH90: 984600 | AK90: HX-LPS2 | AL90: 1535100 | AO90: HX-LPS2 | AP90: 1403000 | AS90: HX-LPS2 | AT90: 605000 | AY90: HX-LPS2 | AZ90: 984600 | BD90: HX-LPS2 | BE90: 1535100 | BI90: HX-LPS2 | BJ90: 1403000 | BO90: HX-LPS2 | BP90: 605000 | BV90: HX-LPS2 | BW90: 984600 | CB90: HX-LPS2 | CC90: 1535100 | CH90: HX-LPS2 | CI90: 559800 | CM90: HX-LPS2 | CN90: 475500 | CQ90: HX-LPS2 | CR90: 573700 | CU90: HX-LPS2 | CV90: 572000 | CY90: HX-LPS2 | CZ90: 608700 | DC90: HX-LPS2 | DD90: 553900 | DG90: HX-LPS2 | DH90: 557900 | DK90: HX-LPS2 | DL90: 590200 | DO90: HX-LPS2 | DP90: 552700
B91: Storage | K91: E2 | P91: Storage | U91: Storage | AC91: E2 | AG91: Storage | AK91: Storage | AS91: E2 | AY91: Storage | BD91: Storage | BO91: E2 | BV91: Storage | CB91: Storage | CH91: Storage | CM91: Storage | CQ91: Storage | CU91: Storage | CY91: Storage | DC91: Storage | DG91: Storage | DK91: Storage | DO91: Storage
B92: Ethylene | C92: =(7.54*10^6)*(D88/(5.7*3600))^0.87 -> 19417505 | F92: Storage | G92: 41348428 | K92: Storage | M92: 133442.96 | N92: kg/h | P92: Ethylene | Q92: 36398964 | R92: 125323.78 | S92: kg/h | U92: Ethylene | V92: 32975123 | W92: 113604.93 | X92: kg/h | Y92: Storage | Z92: 41348428 | AC92: Storage | AE92: 133442.96 | AG92: Ethylene | AH92: 36398964 | AI92: 125323.78 | AK92: Ethylene | AL92: 32975123 | AM92: 113604.93 | AO92: Storage | AP92: 41348428 | AS92: Storage | AU92: 133442.96 | AY92: Ethylene | AZ92: 36398964 | BA92: 125323.78 | BD92: Ethylene | BE92: 32975123 | BF92: 113604.93 | BI92: Storage | BJ92: 41348428 | BO92: Storage | BQ92: 133442.96 | BV92: Ethylene | BW92: 36398964 | BX92: 125323.78 | CB92: Ethylene | CC92: 32975123 | CD92: 113604.93 | CH92: Ethylene | CI92: =(7.54*10^6)*(CJ92/(5.7*3600))^0.87 -> 41421662 | CJ92: 145407.48 | CM92: Ethylene | CN92: =(7.54*10^6)*(CO92/(5.7*3600))^0.87 -> 39613694 | CO92: 138136.48 | CQ92: Ethylene | CR92: =(7.54*10^6)*(CS92/(5.7*3600))^0.87 -> 41193061 | CS92: 144485.46 | CU92: Ethylene | CV92: =(7.54*10^6)*(CW92/(5.7*3600))^0.87 -> 41496233 | CW92: 145708.41 | CY92: Ethylene | CZ92: =(7.54*10^6)*(DA92/(5.7*3600))^0.87 -> 40665056 | DA92: 142358.79 | DC92: Ethylene | DD92: =(7.54*10^6)*(DE92/(5.7*3600))^0.87 -> 40132213 | DE92: 140216.81 | DG92: Ethylene | DH92: =(7.54*10^6)*(DI92/(5.7*3600))^0.87 -> 40189889 | DI92: 140448.45 | DK92: Ethylene | DL92: =(7.54*10^6)*(DM92/(5.7*3600))^0.87 -> 40418487 | DM92: 141367.08 | DO92: Ethylene | DP92: =(7.54*10^6)*(DQ92/(5.7*3600))^0.87 -> 37668468 | DQ92: 130368.74
B93: Naphthalene | C93: =(5.01*10^6)*(D89/(14.17*3600))^0.84 -> 628934.59 | F93: Ethylene | G93: 279127.93 | H93: 145100.57 | I93: kg/h | K93: Ethylene | L93: 38451262 | M93: 2743.1846 | N93: kg/h | P93: Naphthalene | Q93: 624853.43 | R93: 4278.3967 | S93: kg/h | U93: Naphthalene | V93: 839350.27 | W93: 6081.5511 | X93: kg/h | Y93: Ethylene | Z93: 279127.93 | AA93: 145100.57 | AC93: Ethylene | AD93: 38451262 | AE93: 2743.1846 | AG93: Naphthalene | AH93: 624853.43 | AI93: 4278.3967 | AK93: Naphthalene | AL93: 839350.27 | AM93: 6081.5511 | AO93: Ethylene | AP93: 279127.93 | AQ93: 145100.57 | AS93: Ethylene | AT93: 38451262 | AU93: 2743.1846 | AY93: Naphthalene | AZ93: 624853.43 | BA93: 4278.3967 | BD93: Naphthalene | BE93: 839350.27 | BF93: 6081.5511 | BI93: Ethylene | BJ93: 279127.93 | BK93: 145100.57 | BO93: Ethylene | BP93: 38451262 | BQ93: 2743.1846 | BV93: Naphthalene | BW93: 624853.43 | BX93: 4278.3967 | CB93: Naphthalene | CC93: 839350.27 | CD93: 6081.5511 | CH93: Naphthalene | CI93: =(5.01*10^6)*(CJ93/(14.17*3600))^0.84 -> 0 | CJ93: 0 | CM93: Naphthalene | CN93: =(5.01*10^6)*(CO93/(14.17*3600))^0.84 -> 0 | CO93: 0 | CQ93: Naphthalene | CR93: =(5.01*10^6)*(CS93/(14.17*3600))^0.84 -> 0 | CS93: 0 | CU93: Naphthalene | CV93: =(5.01*10^6)*(CW93/(14.17*3600))^0.84 -> 0 | CW93: 0 | CY93: Naphthalene | CZ93: =(5.01*10^6)*(DA93/(14.17*3600))^0.84 -> 0 | DA93: 0 | DC93: Naphthalene | DD93: =(5.01*10^6)*(DE93/(14.17*3600))^0.84 -> 0 | DE93: 0 | DG93: Naphthalene | DH93: =(5.01*10^6)*(DI93/(14.17*3600))^0.84 -> 0 | DI93: 0 | DK93: Naphthalene | DL93: =(5.01*10^6)*(DM93/(14.17*3600))^0.84 -> 0 | DM93: 0 | DO93: Naphthalene | DP93: =(5.01*10^6)*(DQ93/(14.17*3600))^0.84 -> 0 | DQ93: 0
B94: Benzene | C94: =(0.93*10^6)*(D90/(5.7*3600))^0.86 -> 561658.3 | F94: Naphthalene | G94: 652099.19 | H94: 1639.5145 | I94: kg/h | K94: Naphthalene | L94: 430232.17 | M94: 18915.199 | N94: kg/h | P94: Benzene | Q94: 1069243.5 | R94: 24132.566 | S94: kg/h | U94: Benzene | V94: 1298165.4 | W94: 30380.708 | X94: kg/h | Y94: Naphthalene | Z94: 652099.19 | AA94: 1639.5145 | AC94: Naphthalene | AD94: 430232.17 | AE94: 18915.199 | AG94: Benzene | AH94: 1069243.5 | AI94: 24132.566 | AK94: Benzene | AL94: 1298165.4 | AM94: 30380.708 | AO94: Naphthalene | AP94: 652099.19 | AQ94: 1639.5145 | AS94: Naphthalene | AT94: 430232.17 | AU94: 18915.199 | AY94: Benzene | AZ94: 1069243.5 | BA94: 24132.566 | BD94: Benzene | BE94: 1298165.4 | BF94: 30380.708 | BI94: Naphthalene | BJ94: 652099.19 | BK94: 1639.5145 | BO94: Naphthalene | BP94: 430232.17 | BQ94: 18915.199 | BV94: Benzene | BW94: 1069243.5 | BX94: 24132.566 | CB94: Benzene | CC94: 1298165.4 | CD94: 30380.708 | CH94: Benzene | CI94: =(0.93*10^6)*(CJ94/(5.7*3600))^0.86 -> 104619.37 | CJ94: 1617.481 | CM94: Benzene | CN94: =(0.93*10^6)*(CO94/(5.7*3600))^0.86 -> 182190.33 | CO94: 3082.9808 | CQ94: Benzene | CR94: =(0.93*10^6)*(CS94/(5.7*3600))^0.86 -> 160546.34 | CS94: 2661.3663 | CU94: Benzene | CV94: =(0.93*10^6)*(CW94/(5.7*3600))^0.86 -> 128177.28 | CW94: 2048.312 | CY94: Benzene | CZ94: =(0.93*10^6)*(DA94/(5.7*3600))^0.86 -> 2604.1106 | DA94: 22.068759 | DC94: Benzene | DD94: =(0.93*10^6)*(DE94/(5.7*3600))^0.86 -> 2847.849 | DE94: 24.488439 | DG94: Benzene | DH94: =(0.93*10^6)*(DI94/(5.7*3600))^0.86 -> 0 | DI94: 0 | DK94: Benzene | DL94: =(0.93*10^6)*(DM94/(5.7*3600))^0.86 -> 0 | DM94: 0 | DO94: Benzene | DP94: =(0.93*10^6)*(DQ94/(5.7*3600))^0.86 -> 0 | DQ94: 0
B95: H2PSA | F95: Benzene | H95: 13579.035 | I95: kg/h | K95: Benzene | L95: 867429.02 | P95: H2PSA | U95: H2PSA | Y95: Benzene | AA95: 13579.035 | AC95: Benzene | AD95: 867429.02 | AG95: H2PSA | AK95: H2PSA | AO95: Benzene | AQ95: 13579.035 | AS95: Benzene | AT95: 867429.02 | AY95: H2PSA | BD95: H2PSA | BI95: Benzene | BK95: 13579.035 | BO95: Benzene | BP95: 867429.02 | BV95: H2PSA | CB95: H2PSA | CH95: H2PSA | CM95: H2PSA | CQ95: H2PSA | CU95: H2PSA | CY95: H2PSA | DC95: H2PSA | DG95: H2PSA | DK95: H2PSA | DO95: H2PSA
B96: Columns + sorbent | C96: =603.1/392.6*1510000*(D96/500)^0.6+D97/0.01*6.11*4 -> 60444580 | D96: 17375.952 | E96: kmoll gas in | F96: H2PSA | K96: H2PSA | M96: 16760.111 | N96: kmoll gas in | P96: Columns + sorbent | Q96: 54590487 | R96: 16760.111 | S96: kmoll gas in | U96: Columns + sorbent | V96: 56885626 | W96: 17273.892 | X96: kmoll gas in | Y96: H2PSA | AC96: H2PSA | AE96: 16760.111 | AG96: Columns + sorbent | AH96: 54590487 | AI96: 16760.111 | AK96: Columns + sorbent | AL96: 56885626 | AM96: 17273.892 | AO96: H2PSA | AS96: H2PSA | AU96: 16760.111 | AY96: Columns + sorbent | AZ96: 54590487 | BA96: 16760.111 | BD96: Columns + sorbent | BE96: 56885626 | BF96: 17273.892 | BI96: H2PSA | BO96: H2PSA | BQ96: 16760.111 | BV96: Columns + sorbent | BW96: 54590487 | BX96: 16760.111 | CB96: Columns + sorbent | CC96: 56885626 | CD96: 17273.892 | CH96: Columns + sorbent | CI96: =603.1/392.6*1510000*(CJ96/500)^0.6+CJ97/0.01*6.11*4 -> 58461763 | CJ96: 16724.808 | CM96: Columns + sorbent | CN96: =603.1/392.6*1510000*(CO96/500)^0.6+CO97/0.01*6.11*4 -> 60041263 | CO96: 17248.576 | CQ96: Columns + sorbent | CR96: =603.1/392.6*1510000*(CS96/500)^0.6+CS97/0.01*6.11*4 -> 58181302 | CS96: 16636.6 | CU96: Columns + sorbent | CV96: =603.1/392.6*1510000*(CW96/500)^0.6+CW97/0.01*6.11*4 -> 57544076 | CW96: 16427.746 | CY96: Columns + sorbent | CZ96: =603.1/392.6*1510000*(DA96/500)^0.6+DA97/0.01*6.11*4 -> 56992782 | DA96: 16245.759 | DC96: Columns + sorbent | DD96: =603.1/392.6*1510000*(DE96/500)^0.6+DE97/0.01*6.11*4 -> 56662738 | DE96: 16138.002 | DG96: Columns + sorbent | DH96: =603.1/392.6*1510000*(DI96/500)^0.6+DI97/0.01*6.11*4 -> 55561930 | DI96: 15778.341 | DK96: Columns + sorbent | DL96: =603.1/392.6*1510000*(DM96/500)^0.6+DM97/0.01*6.11*4 -> 53599544 | DM96: 15136.768 | DO96: Columns + sorbent | DP96: =603.1/392.6*1510000*(DQ96/500)^0.6+DQ97/0.01*6.11*4 -> 57146798 | DQ96: 16299.391
D97: 16753.68 | E97: kmol H2 | F97: Columns + sorbent | G97: 51057361 | H97: 15286.359 | I97: kmoll gas in | K97: Columns + sorbent | L97: 53387879 | M97: 14996.606 | N97: kmol H2 | R97: 14996.606 | S97: kmol H2 | W97: 15451.253 | X97: kmol H2 | Y97: Columns + sorbent | Z97: 51057361 | AA97: 15286.359 | AC97: Columns + sorbent | AD97: 53387879 | AE97: 14996.606 | AI97: 14996.606 | AM97: 15451.253 | AO97: Columns + sorbent | AP97: 51057361 | AQ97: 15286.359 | AS97: Columns + sorbent | AT97: 53387879 | AU97: 14996.606 | BA97: 14996.606 | BF97: 15451.253 | BI97: Columns + sorbent | BJ97: 51057361 | BK97: 15286.359 | BO97: Columns + sorbent | BP97: 53387879 | BQ97: 14996.606 | BX97: 14996.606 | CD97: 15451.253 | CJ97: 16123.131 | CO97: 16623.799 | CS97: 16033.077 | CW97: 15831.041 | DA97: 15656.858 | DE97: 15552.351 | DI97: 15204.454 | DM97: 14586.736 | DQ97: 15704.708
F98: E2 | G98: 4911100 | H98: 13684.157 | I98: kmol H2 | K98: CCS | P98: CCS | U98: CCS | Y98: E2 | Z98: 4911100 | AA98: 13684.157 | AG98: CCS | AK98: CCS | AO98: E2 | AP98: 4911100 | AQ98: 13684.157 | AS98: CCS | AY98: CCS | BD98: CCS | BI98: E2 | BJ98: 4911100 | BK98: 13684.157 | BO98: CCS | BV98: CCS | CB98: CCS | CH98: CCS | CM98: CCS | CQ98: CCS | CU98: CCS | CY98: CCS | DC98: CCS | DG98: CCS | DK98: CCS | DO98: CCS
F99: REG-bottoms split | K99: REG-bottoms split | P99: REG-bottoms split | U99: REG-bottoms split | Y99: CCS | AC99: CCS | AG99: REG-bottoms split | AH99: 0 | AK99: REG-bottoms split | AL99: 0 | AS99: REG-bottoms split | AY99: REG-bottoms split | BD99: REG-bottoms split | BO99: REG-bottoms split | BP99: 0 | BV99: REG-bottoms split | BW99: 0 | CB99: REG-bottoms split | CC99: 0 | CH99: REG-bottoms split | CM99: REG-bottoms split | CQ99: REG-bottoms split | CU99: REG-bottoms split | CY99: REG-bottoms split | DC99: REG-bottoms split | DG99: REG-bottoms split | DK99: REG-bottoms split | DO99: REG-bottoms split
F100: REG-cond | K100: REG-cond | P100: REG-cond | U100: REG-cond | Y100: REG-bottoms split | Z100: 0 | AC100: REG-bottoms split | AD100: 0 | AG100: REG-cond | AH100: 112900 | AK100: REG-cond | AL100: 113800 | AO100: CCS | AS100: REG-cond | AY100: REG-cond | BD100: REG-cond | BI100: CCS | BO100: REG-cond | BP100: 28400 | BV100: REG-cond | BW100: 28300 | CB100: REG-cond | CC100: 39300 | CH100: REG-cond | CM100: REG-cond | CQ100: REG-cond | CU100: REG-cond | CY100: REG-cond | DC100: REG-cond | DG100: REG-cond | DK100: REG-cond | DO100: REG-cond
F101: REG-cond acc | K101: REG-cond acc | P101: REG-cond acc | U101: REG-cond acc | Y101: REG-cond | Z101: 154600 | AC101: REG-cond | AD101: 137600 | AG101: REG-cond acc | AH101: 100100 | AK101: REG-cond acc | AL101: 84700 | AO101: REG-bottoms split | AS101: REG-cond acc | AY101: REG-cond acc | BD101: REG-cond acc | BI101: REG-bottoms split | BJ101: 0 | BO101: REG-cond acc | BP101: 15900 | BV101: REG-cond acc | BW101: 17600 | CB101: REG-cond acc | CC101: 24200 | CH101: REG-cond acc | CM101: REG-cond acc | CQ101: REG-cond acc | CU101: REG-cond acc | CY101: REG-cond acc | DC101: REG-cond acc | DG101: REG-cond acc | DK101: REG-cond acc | DO101: REG-cond acc
